Workbook

Sheet Portada
B2: Modelo financiero de la quesería
B3: Lácteos Fúquene · Oferta de IntegraMotion S.A.S.
B5: Documento
B6: Elaboró | C6: IntegraMotion S.A.S. · Producción y evaluación económica
B7: Curso | C7: Automatización de Procesos de Manufactura · 2026-2S · Universidad Nacional de Colombia
B8: Unidades | C8: Millones de pesos constantes de 2026, salvo donde se indique
B9: Estado de los chequeos | C9: =Chequeos!$C$43 -> OK
B10: Chequeos en OK | C10: =Chequeos!$B$43 -> 36 de 36
B12: Resultados de la oferta
B13: Costo de capital del proyecto | C13: =Quesería!B178 -> 0.1470725 | D13: Crédito de fomento más garantía, después de impuestos, y capital propio al 25 %.
B14: TIR del proyecto en pesos corrientes | C14: =Quesería!B179 -> 0.24327136 | D14: Se compara con el costo de capital.
B15: TIR del proyecto en pesos constantes | C15: =Quesería!B180 -> 0.19238125 | D15: Se compara con la tasa real equivalente.
B16: Tasa real equivalente | C16: =Quesería!B181 -> 0.099609054 | D16: Costo de capital sin la inflación promedio de 2027 a 2037 (hoja Entorno).
B17: VPN a 10 años al costo de capital ($ M de 2026) | C17: =Quesería!B182 -> 639.5567 | D17: Valor que crea el proyecto después de pagar el capital.
B18: Recuperación simple (años) | C18: =Quesería!B183 -> 4.6824017 | D18: Años hasta recuperar la inversión con los flujos sin descontar.
B19: Recuperación descontada (años) | C19: =Quesería!B184 -> 6.4410043 | D19: Lo mismo, con los flujos descontados al costo de capital.
B20: TIR del inversionista en pesos corrientes | C20: =Quesería!B186 -> 0.42102438 | D20: Se compara con el 25 % que exige el socio.
B21: Cobertura mínima del servicio de la deuda | C21: =Quesería!B189 -> 1.3435688 | D21: Del proyecto solo, con el prepago de 10 % del saldo en 2029; la empresa completa en la hoja Empresa.
B22: VPN si no se obtiene el crédito fiscal por innovación ($ M) | C22: =Escenarios!$T$37 -> 402.88946 | D22: La oferta incluye la gestión del crédito. Sin la certificación el proyecto todavía crea valor, aunque poco, y el dueño gana menos del 25 % que pide: la gestión es parte de la oferta, no un extra.
B23: VPN si la primera compuerta no se supera ($ M) | C23: =Herramientas!B80 -> -48.867085 | D23: Se paga el contrato principal completo y las herramientas de la etapa 0, sin comprar equipos. Es la pérdida que se acepta con los ahorros conservadores de la etapa 0; sensibilidad en la hoja Herramientas.
B24: Deuda total / EBITDA más alta de la empresa | C24: =Empresa!$B$41 -> 1.2478296 | D24: Con el crédito del proyecto.
B25: Inversión total ($ M de 2026) | C25: =Quesería!$F$97 -> 1589.2693 | D25: Con imprevistos, sin IVA.
B26: Beneficio anual pleno ($ M de 2026) | C26: =Quesería!$E$128 -> 568.06498 | D26: A salarios de 2026; los ahorros de mano de obra crecen con el salario mínimo real.
B28: Contenido
B29: Resumen | C29: Los cuadros que se presentan: costo total, costo de ingeniería, cronograma, BOM, beneficios, flujo, indicadores y escenarios.
B30: Quesería | C30: Supuestos, inversión, beneficios, flujo de caja, crédito y resultados de la oferta.
B31: Entorno | C31: Inflación y salario mínimo de 2027 a 2037 y lectura política y económica, con fuentes.
B32: Beneficios y costos | C32: Balance de masa de los quesos, cálculo de cada beneficio, cómo se mide cada uno (matriz de trazabilidad) y costos operativos nuevos (energía, vapor y calibración).
B33: Cotizaciones | C33: Precios de referencia de los equipos y tasas de cambio.
B34: BOM | C34: Lista de materiales del diseño técnico, valorada ítem por ítem y enlazada a la inversión.
B35: Escenarios | C35: La evaluación completa con los supuestos que más mueven el resultado.
B36: Riesgo | C36: Punto de equilibrio, gráfico de tornado, escenarios clave y plan de respuesta a los riesgos (señal, estrategia, responsable y recursos).
B37: Herramientas | C37: Herramientas económicas una sobre otra, beneficios tributarios y qué pasa si no se aprueban, valor de cada etapa y protecciones en los contratos.
B38: Empresa | C38: Efecto en el estado de resultados y el endeudamiento de Lácteos Fúquene.
B39: IntegraMotion | C39: Horas y precio del contrato principal y los dos otrosíes por paquete de la EDT, control del contrato principal por valor ganado (curva S), gastos de funcionamiento, entregables y plan de negocio.
B40: APU | C40: Análisis de precios unitarios de la ingeniería.
B41: Chequeos | C41: Diferencias que deben dar cero.
B43: Cómo se lee
B44: Texto azul | C44: Dato de entrada: se puede cambiar.
B45: Texto negro | C45: Fórmula: no se escribe encima.
B46: Fondo amarillo | C46: Cifra clave o supuesto que más mueve el resultado.

Sheet Resumen
A1: Resumen del proyecto: automatización de la quesería de Lácteos Fúquene
A2: Oferta de IntegraMotion S.A.S. Millones de pesos constantes de 2026, sin IVA, salvo donde se indique. Todas las cifras salen de las demás hojas del modelo.
A4: Las tres cifras que hay que saber
A5: Costo total del proyecto | E5: Costo de ingeniería | I5: Cronograma
A6: =Quesería!$B$191 -> 1589.2693 | E6: =IntegraMotion!$I$149 -> 376.01435 | I6: 16 semanas
A7: Inversión del año 0 (semestre 2026-2 y 2027) y de 2028, con imprevistos: equipos del BOM, ingeniería, ERP, formación y aval. | E7: Lo que Lácteos Fúquene le paga a IntegraMotion: contrato principal y dos otrosíes. | I7: Contrato principal en el semestre 2026-2; otrosí 1 en marzo y abril de 2027 y otrosí 2 en 2028, si se superan las compuertas.
A9: Presupuesto del proyecto (costo para Lácteos Fúquene)
A10: Rubro ($ M constantes de 2026) | B10: Año 0: 2026-2 y 2027 (etapas 0 y 1) | C10: 2028 (etapa 2) | D10: Total
A11: Equipos, instrumentos, control y herramientas (del BOM) | B11: =Quesería!$F$70*(Quesería!$C$70=0)+Quesería!$F$71*(Quesería!$C$71=0)+Quesería!$F$72*(Quesería!$C$72=0)+Quesería!$F$73*(Quesería!$C$73=0)+Quesería!$F$74*(Quesería!$C$74=0)+Quesería!$F$75*(Quesería!$C$75=0)+Quesería!$F$84*(Quesería!$C$84=0)+Quesería!$F$85*(Quesería!$C$85=0)+Quesería!$F$86*(Quesería!$C$86=0)+Quesería!$F$87*(Quesería!$C$87=0) -> 484.36567 | C11: =Quesería!$F$70*(Quesería!$C$70=1)+Quesería!$F$71*(Quesería!$C$71=1)+Quesería!$F$72*(Quesería!$C$72=1)+Quesería!$F$73*(Quesería!$C$73=1)+Quesería!$F$74*(Quesería!$C$74=1)+Quesería!$F$75*(Quesería!$C$75=1)+Quesería!$F$84*(Quesería!$C$84=1)+Quesería!$F$85*(Quesería!$C$85=1)+Quesería!$F$86*(Quesería!$C$86=1)+Quesería!$F$87*(Quesería!$C$87=1) -> 488.78187 | D11: =B11+C11 -> 973.14753
A12: Ingeniería de IntegraMotion | B12: =Quesería!$F$76*(Quesería!$C$76=0)+Quesería!$F$77*(Quesería!$C$77=0)+Quesería!$F$78*(Quesería!$C$78=0)+Quesería!$F$79*(Quesería!$C$79=0)+Quesería!$F$88*(Quesería!$C$88=0) -> 289.95616 | C12: =Quesería!$F$76*(Quesería!$C$76=1)+Quesería!$F$77*(Quesería!$C$77=1)+Quesería!$F$78*(Quesería!$C$78=1)+Quesería!$F$79*(Quesería!$C$79=1)+Quesería!$F$88*(Quesería!$C$88=1) -> 90.106032 | D12: =B12+C12 -> 380.06219
A13: Parametrización del ERP por su proveedor, formación con el SENA y aval del proyecto de innovación | B13: =Quesería!$F$80*(Quesería!$C$80=0)+Quesería!$F$81*(Quesería!$C$81=0)+Quesería!$F$82*(Quesería!$C$82=0) -> 46.666667 | C13: =Quesería!$F$80*(Quesería!$C$80=1)+Quesería!$F$81*(Quesería!$C$81=1)+Quesería!$F$82*(Quesería!$C$82=1) -> 0 | D13: =B13+C13 -> 46.666667
A14: Imprevistos según la madurez de cada precio | B14: =Quesería!$F$83*(Quesería!$C$83=0)+Quesería!$F$89*(Quesería!$C$89=0) -> 109.81175 | C14: =Quesería!$F$83*(Quesería!$C$83=1)+Quesería!$F$89*(Quesería!$C$89=1) -> 79.581168 | D14: =B14+C14 -> 189.39292
A15: Costo total del proyecto | B15: =SUM(B11:B14) -> 930.80024 | C15: =SUM(C11:C14) -> 658.46907 | D15: =SUM(D11:D14) -> 1589.2693
A16: Comprobación: total − inversión de la hoja Quesería | D16: =D15-Quesería!$B$191 -> 0
A18: Costo de ingeniería por contrato
A19: Contrato ($ M de 2026, sin reajuste) | B19: Plazo | C19: Horas | D19: Costo para IntegraMotion | E19: Costo de ingeniería del proyecto | F19: Con IVA
A20: Contrato principal: los 19 paquetes de la EDT | B20: 16 semanas | C20: =IntegraMotion!$H$139 -> 2680.5912 | D20: =IntegraMotion!$H$145 -> 160.71471 | E20: =IntegraMotion!$H$149 -> 223.39345 | F20: =IntegraMotion!$H$151 -> 265.8382
A21: Otrosí 1: implementación de la etapa 1 | B21: 2 meses | C21: =IntegraMotion!$F$139 -> 611.6 | D21: =IntegraMotion!$F$145 -> 46.783459 | E21: =IntegraMotion!$F$149 -> 65.029008 | F21: =IntegraMotion!$F$151 -> 77.38452
A22: Otrosí 2: detalle e implementación de la etapa 2 | B22: 2 meses | C22: =IntegraMotion!$G$139 -> 1004.8425 | D22: =IntegraMotion!$G$145 -> 63.015753 | E22: =IntegraMotion!$G$149 -> 87.591896 | F22: =IntegraMotion!$G$151 -> 104.23436
A23: Total | C23: =SUM(C20:C22) -> 4297.0337 | D23: =SUM(D20:D22) -> 270.51392 | E23: =SUM(E20:E22) -> 376.01435 | F23: =SUM(F20:F22) -> 447.45708
A24: Reajuste real de los otrosíes: se liquidan con el salario mínimo del año en que se ejecutan, que sube más que la inflación | E24: =D12-E23 -> 4.0478383
A25: Ingeniería en el presupuesto del proyecto, en pesos constantes de 2026 | E25: =D12 -> 380.06219
A26: Para IntegraMotion, el costo es lo que gasta (honorarios, conocimiento certificado, viajes e instrumentos) y el precio es lo que cobra: costo más administración, imprevistos y utilidad (AIU). Ese precio es el costo de ingeniería del proyecto para Lácteos Fúquene y entra a la inversión.
A28: Equipos del BOM por rubro
A29: Rubro | B29: Etapa | C29: Ítems | D29: Valor del BOM | E29: Parte de la quesería | F29: A la inversión
A30: =BOM!A72 -> Etapa 0: herramientas de mantenimiento y medición | B30: =BOM!C72 -> 0 | C30: =BOM!E72 -> 6 | D30: =BOM!F72 -> 56.872528 | E30: =BOM!H72 -> 0.36 | F30: =BOM!I72 -> 20.47411
A31: =BOM!A73 -> Tinas TQ-301 y TQ-303, control y tablero | B31: =BOM!C73 -> 1 | C31: =BOM!E73 -> 19 | D31: =BOM!F73 -> 267.50965 | E31: =BOM!H73 -> 1 | F31: =BOM!I73 -> 267.50965
A32: =BOM!A74 -> Tina TQ-302 del doble crema | B32: =BOM!C74 -> 1 | C32: =BOM!E74 -> 6 | D32: =BOM!F74 -> 47.746861 | E32: =BOM!H74 -> 1 | F32: =BOM!I74 -> 47.746861
A33: =BOM!A75 -> Estación E18 de inspección | B33: =BOM!C75 -> 1 | C33: =BOM!E75 -> 1 | D33: =BOM!F75 -> 33.178864 | E33: =BOM!H75 -> 1 | F33: =BOM!I75 -> 33.178864
A34: =BOM!A76 -> Estandarización de grasa (recepción) | B34: =BOM!C76 -> 1 | C34: =BOM!E76 -> 2 | D34: =BOM!F76 -> 129.98093 | E34: =BOM!H76 -> 0.36 | F34: =BOM!I76 -> 46.793136
A35: =BOM!A77 -> SCADA, historiador y MES | B35: =BOM!C77 -> 1 | C35: =BOM!E77 -> 11 | D35: =BOM!F77 -> 130.79213 | E35: =BOM!H77 -> 0.5249784 | F35: =BOM!I77 -> 68.663043
A36: =BOM!A78 -> Hiladora E13 | B36: =BOM!C78 -> 2 | C36: =BOM!E78 -> 1 | D36: =BOM!F78 -> 322.6 | E36: =BOM!H78 -> 1 | F36: =BOM!I78 -> 322.6
A37: =BOM!A79 -> CIP del circuito de quesos | B37: =BOM!C79 -> 2 | C37: =BOM!E79 -> 1 | D37: =BOM!F79 -> 106.66667 | E37: =BOM!H79 -> 1 | F37: =BOM!I79 -> 106.66667
A38: =BOM!A80 -> Suero | B38: =BOM!C80 -> 2 | C38: =BOM!E80 -> 1 | D38: =BOM!F80 -> 80 | E38: =BOM!H80 -> 0 | F38: =BOM!I80 -> 0
A39: =BOM!A81 -> Instrumentación y control de la etapa 2 | B39: =BOM!C81 -> 2 | C39: =BOM!E81 -> 4 | D39: =BOM!F81 -> 59.5152 | E39: =BOM!H81 -> 1 | F39: =BOM!I81 -> 59.5152
A40: Total que entra a la inversión, sin imprevistos | C40: =SUM(C30:C39) -> 52 | F40: =SUM(F30:F39) -> 973.14753
A41: Celda de paletizado (se diseña en el contrato principal; su compra es una etapa 3 fuera de la evaluación) | D41: =BOM!F82 -> 521.38215
A43: Beneficios anuales en régimen
A44: Medida | B44: Etapa | C44: Beneficio | D44: Respaldo (1 a 5)
A45: =Quesería!A104 -> Horas extra del hilado evitadas con el orden del hilado (0,5 h/día) | B45: =Quesería!B104 -> 1 | C45: =Quesería!E104 -> 11.76 | D45: =Quesería!H104 -> 3
A46: =Quesería!A105 -> Mayor rendimiento del campesino y la mozzarella (sensor de coagulación) | B46: =Quesería!B105 -> 1 | C46: =Quesería!E105 -> 52.798395 | D46: =Quesería!H105 -> 3
A47: =Quesería!A106 -> Estandarización de grasa en línea | B47: =Quesería!B106 -> 1 | C47: =Quesería!E106 -> 18.721498 | D47: =Quesería!H106 -> 3
A48: =Quesería!A107 -> Menor merma (de 2,0 a 1,5 % de las ventas) | B48: =Quesería!B107 -> 1 | C48: =Quesería!E107 -> 33.86 | D48: =Quesería!H107 -> 4
A49: =Quesería!A108 -> Mantenimiento preventivo (ahorro neto de 20 % del gasto) | B49: =Quesería!B108 -> 1 | C49: =Quesería!E108 -> 32.904 | D49: =Quesería!H108 -> 3
A50: =Quesería!A109 -> Menor sobrepeso de los tres quesos (de 1,0 a 0,5 %) | B50: =Quesería!B109 -> 1 | C50: =Quesería!E109 -> 32.5056 | D50: =Quesería!H109 -> 4
A51: =Quesería!A110 -> Programación con el estado real de la planta: MES con estado de máquinas, paros y OEE enlazado al ERP (hallazgo H9) | B51: =Quesería!B110 -> 1 | C51: =Quesería!E110 -> 26.333 | D51: =Quesería!H110 -> 3
A52: =Quesería!A111 -> Balance de sólidos y humedad por lote en el MES (hallazgo H11) | B52: =Quesería!B111 -> 1 | C52: =Quesería!E111 -> 32.551052 | D52: =Quesería!H111 -> 4
A53: =Quesería!A112 -> Hiladora-moldeadora: más doble crema y mozzarella | B53: =Quesería!B112 -> 2 | C53: =Quesería!E112 -> 70.703173 | D53: =Quesería!H112 -> 3
A54: =Quesería!A113 -> Horas extra restantes que elimina la hiladora (0,5 h/día) | B54: =Quesería!B113 -> 2 | C54: =Quesería!E113 -> 11.76 | D54: =Quesería!H113 -> 3
A55: =Quesería!A114 -> Limpieza CIP automática del circuito de quesos | B55: =Quesería!B114 -> 2 | C55: =Quesería!E114 -> 40.6 | D55: =Quesería!H114 -> 4
A56: =Quesería!A115 -> Contrato de venta del suero enfriado (opción, fuera de la oferta: solo con contrato a $49/kg o más) | B56: =Quesería!B115 -> 2 | C56: =Quesería!E115 -> 0 | D56: =Quesería!H115 -> 1
... A60: =Quesería!A119 -> Reubicación por competencias (H10): el otro operario cubre el mantenimiento autónomo del plan preventivo | B60: =Quesería!B119 -> 2 | C60: =Quesería!E119 -> 36 | D60: =Quesería!H119 -> 3
A61: Beneficio anual pleno | C61: =SUM(C45:C60) -> 568.06498
A62: Costos operativos nuevos al año (energía, vapor, mantenimiento, suscripciones y póliza) | C62: =Quesería!$B$193 -> 76.496482
A63: Respaldo: 1 contratado, 2 medido, 3 técnicamente justificado, 4 por medir en la etapa 0, 5 hipotético.
A65: Los doce hallazgos del diagnóstico y dónde se cobra cada uno
A66: Hallazgo | B66: Etapa | C66: Valor para la planta | D66: A la quesería
A67: ='Beneficios y costos'!A176 -> H1. Grasa estandarizada a mano | B67: ='Beneficios y costos'!C176&"" -> 1 | C67: ='Beneficios y costos'!D176 -> 52.00416 | D67: ='Beneficios y costos'!E176 -> 18.721498
A68: ='Beneficios y costos'!A177 -> H2. Yogur incubado de noche sin vigilancia | B68: ='Beneficios y costos'!C177&"" -> 2 | C68: ='Beneficios y costos'!D177 -> 67.77488 | D68: ='Beneficios y costos'!E177 -> 67.77488
A69: ='Beneficios y costos'!A178 -> H2. Lo que queda del yogur sobreacidificado | B69: ='Beneficios y costos'!C178&"" -> — | C69: ='Beneficios y costos'!D178 -> 98.51 | D69: ='Beneficios y costos'!E178 -> 0
A70: ='Beneficios y costos'!A179 -> H3. Producto regalado en el llenado: quesos | B70: ='Beneficios y costos'!C179&"" -> 1 | C70: ='Beneficios y costos'!D179 -> 32.5056 | D70: ='Beneficios y costos'!E179 -> 32.5056
A71: ='Beneficios y costos'!A180 -> H3. Producto regalado en el llenado: yogur y UHT | B71: ='Beneficios y costos'!C180&"" -> — | C71: ='Beneficios y costos'!D180 -> 307.3632 | D71: ='Beneficios y costos'!E180 -> 0
A72: ='Beneficios y costos'!A181 -> H4. Pérdidas del UHT en arranques y cambios | B72: ='Beneficios y costos'!C181&"" -> — | C72: ='Beneficios y costos'!D181 -> 123.15 | D72: ='Beneficios y costos'!E181 -> 0
A73: ='Beneficios y costos'!A182 -> H5. Hilado manual, cuello de botella | B73: ='Beneficios y costos'!C182&"" -> 0 y 2 | C73: ='Beneficios y costos'!D182 -> 94.223173 | D73: ='Beneficios y costos'!E182 -> 94.223173
A74: ='Beneficios y costos'!A183 -> H6. Registros críticos en papel | B74: ='Beneficios y costos'!C183&"" -> 1 | C74: ='Beneficios y costos'!D183 -> 152.285 | D74: ='Beneficios y costos'!E183 -> 33.86
A75: ='Beneficios y costos'!A184 -> H7. Limpieza y mantenimiento manuales y correctivos | B75: ='Beneficios y costos'!C184&"" -> 0 y 2 | C75: ='Beneficios y costos'!D184 -> 213.2 | D75: ='Beneficios y costos'!E184 -> 73.504
A76: ='Beneficios y costos'!A185 -> H8. Suero vendido barato | B76: ='Beneficios y costos'!C185&"" -> Opción | C76: ='Beneficios y costos'!D185 -> 36.110821 | D76: ='Beneficios y costos'!E185 -> 0
A77: ='Beneficios y costos'!A186 -> H9. Información en islas | B77: ='Beneficios y costos'!C186&"" -> 1 | C77: ='Beneficios y costos'!D186 -> 26.333 | D77: ='Beneficios y costos'!E186 -> 26.333
A78: ='Beneficios y costos'!A187 -> H10. Puestos asignados por costumbre, no por competencias | B78: ='Beneficios y costos'!C187&"" -> 0 y 2 | C78: ='Beneficios y costos'!D187 -> 36 | D78: ='Beneficios y costos'!E187 -> 36
... A84: ='Beneficios y costos'!A193 -> Pérdidas de yogur y UHT que quedan para la ampliación | B84: ='Beneficios y costos'!C193&"" | C84: ='Beneficios y costos'!D193 -> 529.0232 | D84: ='Beneficios y costos'!E193 -> 0
A85: Los hallazgos de yogur y UHT (H2 a H4) no entran en esta oferta: su pérdida de hoy, a precio de venta, es la base de la ampliación a esas líneas con la misma plataforma.
A87: Flujo de caja (año 0 = semestre 2026-2 y 2027; años 1 a 10 = 2028 a 2037)
A88: $ M | B88: 2026-27 | C88: 2028 | D88: 2029 | E88: 2030 | F88: 2031 | G88: 2032 | H88: 2033 | I88: 2034 | J88: 2035 | K88: 2036 | L88: 2037
A89: Beneficios | B89: =Quesería!B143 -> 120.71677 | C89: =Quesería!C143 -> 181.32832 | D89: =Quesería!D143 -> 499.18307 | E89: =Quesería!E143 -> 570.38719 | F89: =Quesería!F143 -> 570.6964 | G89: =Quesería!G143 -> 571.00716 | H89: =Quesería!H143 -> 571.31947 | I89: =Quesería!I143 -> 571.63334 | ... L89: =Quesería!L143 -> 572.5844
A90: − Costos operativos nuevos y transición del personal | B90: =-(Quesería!B144+Quesería!B145+Quesería!B146) -> -4.3196636 | C90: =-(Quesería!C144+Quesería!C145+Quesería!C146) -> -63.988058 | D90: =-(Quesería!D144+Quesería!D145+Quesería!D146) -> -76.802468 | E90: =-(Quesería!E144+Quesería!E145+Quesería!E146) -> -76.802468 | F90: =-(Quesería!F144+Quesería!F145+Quesería!F146) -> -76.802468 | G90: =-(Quesería!G144+Quesería!G145+Quesería!G146) -> -76.933202 | H90: =-(Quesería!H144+Quesería!H145+Quesería!H146) -> -77.02328 | I90: =-(Quesería!I144+Quesería!I145+Quesería!I146) -> -76.802468 | ... L90: =-(Quesería!L144+Quesería!L145+Quesería!L146) -> -76.802468
A91: − Impuesto de renta (positivo: descuentos que recibe la empresa) | B91: =-Quesería!B151 -> 9.5983912 | C91: =-Quesería!C151 -> 267.27575 | D91: =-Quesería!D151 -> 153.62175 | E91: =-Quesería!E151 -> -125.10984 | F91: =-Quesería!F151 -> -127.05261 | G91: =-Quesería!G151 -> -128.90249 | H91: =-Quesería!H151 -> -128.13102 | I91: =-Quesería!I151 -> -123.23634 | ... L91: =-Quesería!L151 -> -136.65448
A92: − Inversión, reposiciones e IVA | B92: =-(Quesería!B138+Quesería!B139+Quesería!B140) -> -1079.9159 | C92: =-(Quesería!C138+Quesería!C139+Quesería!C140) -> -783.57819 | D92: =-(Quesería!D138+Quesería!D139+Quesería!D140) -> 0 | E92: =-(Quesería!E138+Quesería!E139+Quesería!E140) -> 0 | F92: =-(Quesería!F138+Quesería!F139+Quesería!F140) -> 0 | G92: =-(Quesería!G138+Quesería!G139+Quesería!G140) -> -32.683609 | H92: =-(Quesería!H138+Quesería!H139+Quesería!H140) -> -55.203095 | I92: =-(Quesería!I138+Quesería!I139+Quesería!I140) -> 0 | ... L92: =-(Quesería!L138+Quesería!L139+Quesería!L140) -> 0
A93: ± Capital de trabajo y valor final de los equipos | B93: =-Quesería!B153+Quesería!B154 -> -7.231469 | C93: =-Quesería!C153+Quesería!C154 -> -1.4228785 | D93: =-Quesería!D153+Quesería!D154 -> -121.06797 | E93: =-Quesería!E153+Quesería!E154 -> -44.684953 | F93: =-Quesería!F153+Quesería!F154 -> -6.490106 | G93: =-Quesería!G153+Quesería!G154 -> -6.490106 | H93: =-Quesería!H153+Quesería!H154 -> -6.490106 | I93: =-Quesería!I153+Quesería!I154 -> -6.490106 | ... L93: =-Quesería!L153+Quesería!L154 -> 224.17642
A94: Flujo de caja libre del proyecto | B94: =Quesería!B155 -> -961.15188 | C94: =Quesería!C155 -> -400.38506 | D94: =Quesería!D155 -> 454.93438 | E94: =Quesería!E155 -> 323.78993 | F94: =Quesería!F155 -> 360.35121 | G94: =Quesería!G155 -> 325.99775 | H94: =Quesería!H155 -> 304.47197 | I94: =Quesería!I155 -> 365.10443 | ... L94: =Quesería!L155 -> 583.30388
A95: Flujo del inversionista (con el crédito) | B95: =Quesería!B170 -> -358.74492 | C95: =Quesería!C170 -> -25.457892 | D95: =Quesería!D170 -> 274.21152 | E95: =Quesería!E170 -> 92.304239 | F95: =Quesería!F170 -> 151.40912 | G95: =Quesería!G170 -> 138.20757 | H95: =Quesería!H170 -> 136.51572 | I95: =Quesería!I170 -> 215.73421 | ... L95: =Quesería!L170 -> 583.30388
A96: Cobertura del servicio de la deuda (veces) | B96: =Quesería!B174 | C96: =Quesería!C174 -> 5.0671807 | D96: =Quesería!D174 -> 2.2098747 | E96: =Quesería!E174 -> 1.3435688 | F96: =Quesería!F174 -> 1.6335761 | G96: =Quesería!G174 -> 1.6832032 | H96: =Quesería!H174 -> 1.7949431 | I96: =Quesería!I174 -> 2.3684236 | ... L96: =Quesería!L174
A97: Comprobación: suma de las líneas − flujo de caja libre | L97: =ABS(SUM(B89:B93)-B94)+ABS(SUM(C89:C93)-C94)+ABS(SUM(D89:D93)-D94)+ABS(SUM(E89:E93)-E94)+ABS(SUM(F89:F93)-F94)+ABS(SUM(G89:G93)-G94)+ABS(SUM(H89:H93)-H94)+ABS(SUM(I89:I93)-I94)+ABS(SUM(J89:J93)-J94)+ABS(SUM(K89:K93)-K94)+ABS(SUM(L89:L93)-L94) -> 0
A99: Indicadores de la oferta
A100: Indicador | B100: Oferta | C100: Se compara con
A101: VPN a 10 años al costo de capital | B101: =Quesería!$B$182 -> 639.5567 | C101: mayor que 0
A102: TIR del proyecto en pesos corrientes | B102: =Quesería!$B$179 -> 0.24327136 | C102: =Quesería!$B$178 -> 0.1470725
A103: TIR del proyecto en pesos constantes | B103: =Quesería!$B$180 -> 0.19238125 | C103: =Quesería!$B$181 -> 0.099609054
A104: TIR del inversionista con el crédito | B104: =Quesería!$B$186 -> 0.42102438 | C104: =Quesería!$B$11 -> 0.25
A105: Recuperación (años) | B105: =Quesería!$B$183 -> 4.6824017 | C105: 10 años de vida
A106: Recuperación descontada (años) | B106: =Quesería!$B$184 -> 6.4410043 | C106: 10 años de vida
A107: ROI a 10 años | B107: =Quesería!$B$185 -> 1.2996922
A108: Cobertura mínima del servicio de la deuda | B108: =Quesería!$B$189 -> 1.3435688 | C108: 1.2
A109: Aporte del dueño en el año 0 y en 2028 | B109: =Quesería!$B$190 -> 384.20282
A111: Escenarios clave
A112: Escenario | B112: VPN | C112: TIR del proyecto | D112: TIR del inversionista | E112: Cobertura
A113: Oferta | B113: =Escenarios!B37 -> 639.5567 | C113: =Escenarios!B35 -> 0.24327136 | D113: =Escenarios!B41 -> 0.42102438 | E113: =Escenarios!B43 -> 1.3435688
A114: Sin crédito fiscal por innovación | B114: =Escenarios!T37 -> 402.88946 | C114: =Escenarios!T35 -> 0.20291645 | D114: =Escenarios!T41 -> 0.3012011 | E114: =Escenarios!T43 -> 1.3435688
A115: Sin reubicación del personal | B115: =Escenarios!F37 -> 288.29355 | C115: =Escenarios!F35 -> 0.19286058 | D115: =Escenarios!F41 -> 0.30861776 | E115: =Escenarios!F43 -> 1.0920617
A116: Beneficios −20 % | B116: =Escenarios!G37 -> 242.43744 | C116: =Escenarios!G35 -> 0.18563795 | D116: =Escenarios!G41 -> 0.2898649 | E116: =Escenarios!G43 -> 1.1037925
A117: Inversión +20 % | B117: =Escenarios!I37 -> 406.56306 | C117: =Escenarios!I35 -> 0.20028755 | D117: =Escenarios!I41 -> 0.32339577 | E117: =Escenarios!I43 -> 1.1619298
...

Sheet Quesería
A1: Modelo financiero de la quesería — Lácteos Fúquene
A2: Oferta de IntegraMotion S.A.S. Millones de pesos constantes de 2026. Texto azul: datos de entrada; negro: fórmulas; fondo amarillo: cifras clave.
A4: Supuestos
A5: Supuesto | B5: Valor | C5: Unidad | D5: Fuente o criterio
A6: Tasas e inflación
A7: Ruta de inflación (1 base, 2 consenso de los analistas, 3 persistente) | B7: 1 | C7: ruta | D7: Hoja Entorno: inflación de cada año de 2027 a 2037.
A8: Costo de capital de la empresa con su deuda actual | B8: 0.16 | C8: % | D8: 70 % deuda al 18 % (intereses / deuda de 2026: 252 / 1.400) y 30 % capital propio al 25 %. Es la referencia de la primera entrega.
A9: Costo de capital del proyecto en pesos corrientes | B9: =$B$44*($B$45+$B$49*$B$51*1.19)*(1-$B$54)+(1-$B$44)*$B$11 -> 0.1470725 | C9: % | D9: Con la deuda que de verdad financia el proyecto: crédito de fomento más la comisión de la garantía, después de impuestos (70 %), y capital propio al 25 % (30 %). Con él se descuentan los flujos.
A10: Tasa real equivalente | B10: =(1+$B$9)/(1+CHOOSE($B$7,Entorno!$M$7,Entorno!$M$8,Entorno!$M$9))-1 -> 0.099609054 | C10: % | D10: El costo de capital sin la inflación promedio de la ruta; con ella se compara la TIR en pesos constantes.
A11: Rentabilidad que exige el inversionista en pesos corrientes | B11: 0.25 | C11: % | D11: Lo que espera ganar el socio por arriesgar su capital.
A12: Rentabilidad exigida real equivalente | B12: =(1+$B$11)/(1+CHOOSE($B$7,Entorno!$M$7,Entorno!$M$8,Entorno!$M$9))-1 -> 0.19827763 | C12: % | D12: Misma conversión de la tasa de descuento.
A13: Operación de la planta y reparto
A14: Leche de la quesería | B14: 9000 | C14: L/día | D14: Reparto de la leche de la planta.
A15: Leche de la planta | B15: 25000 | C15: L/día | D15: Caso de estudio.
A16: Parte de la quesería en la leche | B16: =$B$14/$B$15 -> 0.36 | C16: % | D16: Reparte la grasa en línea, el mantenimiento y la etapa 0.
A17: Ventas de la quesería | B17: 6772 | C17: $ M/año | D17: Caso de estudio (294 días de operación).
A18: Ventas de la planta | B18: 30457 | C18: $ M/año | D18: Caso de estudio.
A19: Parte de la quesería en las ventas | B19: =$B$17/$B$18 -> 0.22234626 | C19: % | D19: Reparte la reducción de merma.
A20: Beneficio del primer año de cada etapa | B20: 0.75 | C20: % del pleno | D20: Arranque, ajuste de recetas y formación.
A21: Meses de operación de la etapa 1 en 2027 | B21: 8 | C21: meses | D21: El contrato principal son las 16 semanas del semestre 2026-2 y cierra con la primera compuerta en diciembre de 2026. Los equipos se compran en enero y el otrosí 1 (montaje y puesta en marcha) va en marzo y abril: la etapa 1 opera desde mayo de 2027. Se cuentan 8 meses con el beneficio de arranque; la compuerta de diciembre de 2027 usa esos datos medidos.
A22: Costo anual de un operario | B22: 36 | C22: $ M/año | D22: Salario, prestaciones y aportes.
A23: Meses de traslape mientras se forman los operarios de la hiladora | B23: 3 | C23: meses | D23: Los 2 operarios que se reubican siguen en el hilado hasta que la hiladora opera sola, mientras se forman para su nuevo puesto; la producción no cae en ese tiempo.
A24: Costo de reemplazar a un operario con alguien de afuera | B24: 0.3 | C24: % del costo anual | D24: Reclutamiento, vacante y curva de aprendizaje: 30 a 50 % del salario anual (Semana, febrero de 2026). Se evita al cubrir el puesto con personal de la planta.
A25: Inversión, imprevistos y reposición
A26: Imprevistos: precio cerrado (contratos y SENA) | B26: 0.05 | C26: % del rubro | D26: Clasificación de estimados AACE 18R-97: la contingencia baja a medida que el precio madura. Solo cubre cambios de alcance.
A27: Imprevistos: precio publicado de catálogo | B27: 0.1 | C27: % del rubro | D27: Falta la cotización formal y el flete real.
A28: Imprevistos: estimado con referencias de mercado | B28: 0.15 | C28: % del rubro | D28: Equipos con precios de referencia de máquinas parecidas (hoja Cotizaciones).
A29: Imprevistos: estimado sin cotización | B29: 0.25 | C29: % del rubro | D29: Estimado de orden de magnitud (clase 4 a 5 de AACE).
A30: Vida fiscal de maquinaria y equipo | B30: 10 | C30: años | D30: Línea recta, 10 % anual (art. 137 ET). La de cada rubro está en la tabla de inversión.
A31: Mantenimiento de equipos nuevos | B31: 0.03 | C31: % equipos/año | D31: Práctica de la industria para equipos de proceso.
A32: Suscripciones de software del SCADA de la quesería | B32: 13.6 | C32: $ M/año | D32: Licencias de SCADA, historiador y analítica dimensionadas para una línea (12,0) y renovación de la protección del firewall (unos US$1.435 al año, 36 % a la quesería: 1,6).
A33: Póliza todo riesgo de los equipos nuevos | B33: 0.0025 | C33: % equipos/año | D33: El banco la pide endosada a su favor. Supuesto; se cotiza.
A34: Reposición del hardware del SCADA en el año 5 | B34: 0.4 | C34: % del rubro SCADA | D34: Servidor, red y estaciones (vida fiscal de 5 años); las licencias siguen en las suscripciones.
A35: Reposición parcial de instrumentación en el año 6 | B35: 0.1 | C35: % de los equipos de la etapa 1 | D35: Sensores, celdas de carga y sondas en ambiente húmedo y con lavados.
A36: Valor de los equipos al año 10 | B36: 0.1 | C36: % de su costo | D36: Se vende o se toma como parte de pago; se grava completo.
A37: Capital de trabajo
A38: Días de cartera sobre las ventas adicionales | B38: 30 | C38: días | D38: Política comercial de la planta. El capital de trabajo suma cartera e inventario al costo y resta las cuentas por pagar; se recupera al final del horizonte.
A39: Días de inventario del queso adicional | B39: 5 | C39: días | D39: Queso fresco: se despacha en la semana. Se valora al costo, no al precio.
A40: Costo de ventas sobre ventas | B40: 0.82 | C40: % | D40: Estado de resultados del caso: leche, insumos, nómina, energía y mantenimiento sobre las ventas.
A41: Costo variable sobre ventas (lo que se evita al no perder producto) | B41: 0.688 | C41: % | D41: Estado de resultados del caso: leche (47,8 %), insumos y empaques (17,0 %) y energía, agua, gas y químicos (4,0 %). La nómina y el mantenimiento no cambian si se pierde menos producto.
A42: Días de cuentas por pagar sobre los costos operativos nuevos | B42: 22 | C42: días | D42: Balance del caso: cuentas por pagar de 1.206 sobre compras de leche e insumos.
A43: Financiación
A44: Parte de la inversión financiada con crédito | B44: 0.65 | C44: % | D44: Líneas Bancóldex Impulso a la Productividad y Transformación Digital, a través del banco de la empresa. Con 65 % la cobertura del servicio de la deuda no baja de 1,2.
A45: Tasa del crédito de fomento (efectiva anual, pesos corrientes) | B45: 0.141 | C45: % | D45: Superfinanciera, datos abiertos: créditos con recursos de redescuento a medianas empresas, 3 a 5 años, mayo a julio de 2026. El crédito se pacta en pesos corrientes; cada pago se pasa a pesos constantes con el factor del flujo.
A46: Plazo del crédito, incluida la gracia | B46: 7 | C46: años | D46: Bancóldex Impulso a la Productividad: hasta 7 años con 12 meses de gracia.
A47: Gracia a capital | B47: 1 | C47: años | D47: Se pagan solo intereses.
A48: Prepago del crédito en el año 2, % del saldo | B48: 0 | C48: % | D48: Respuesta preparada al riesgo de cobertura (hoja Riesgo): si la proyección de 2029 muestra menos de 1,2 para 2030, cuando se pagan completas las cuotas de los dos tramos, la empresa prepaga parte del saldo con el IVA recuperado y la segunda mitad del crédito fiscal, que llegan ese año. En la oferta la cobertura ya pasa de 1,2, así que queda en reserva; con 10 % la cobertura subiría a cerca de 1,44. Los créditos comerciales admiten prepago; se pacta sin penalidad.
A49: Garantía del crédito (0 = prenda sobre los equipos; 1 = FNG) | B49: 0 | C49: 0 / 1 | D49: IntegraMotion negocia la prenda con el banco.
A50: Avalúo y registro de la garantía mobiliaria (prenda) | B50: 4 | C50: $ M | D50: Ley 1676 de 2013: avalúo de los equipos e inscripción en el registro de garantías mobiliarias de Confecámaras. Supuesto; se cotiza.
A51: Comisión de la garantía del Fondo Nacional de Garantías | B51: 0.0199 | C51: % anual del saldo | D51: Garantía Preferente del FNG, 1,99 % anual (La República), con IVA, sobre el saldo. La oferta la reemplaza por prenda sobre los equipos; se usa en el escenario Garantía del FNG.
A52: Gravamen a los movimientos financieros (cuatro por mil) | B52: 0.004 | C52: % de cada pago | D52: Se aplica a los pagos del proyecto y del crédito; la mitad es deducible de renta (art. 115 ET).
A53: Impuestos y beneficios tributarios
A54: Impuesto de renta | B54: 0.35 | C54: % | D54: Tarifa general de personas jurídicas.
A55: IVA de equipos y contratos de integración | B55: 0.19 | C55: % | D55: Se paga al comprar y se recupera como descuento en la declaración de renta del año, que se presenta al año siguiente (art. 258-1 ET: activos fijos productivos y servicios para ponerlos en uso). El IVA del diagnóstico y del aval se descuenta en la declaración de IVA. Los valores de la inversión van sin IVA.
A56: Descuento tributario por inversión ambiental (art. 255 ET) | B56: 0.25 | C56: % inversión | D56: Sobre el enfriador y el tanque del suero, que evitan verterlo; solo si se ejerce la opción del suero. Requiere certificado de la CAR; IntegraMotion lo tramita.
A57: Tope del descuento del art. 255 sobre el impuesto de la empresa | B57: 0.25 | C57: % del impuesto | D57: Art. 258 ET.
A58: Impuesto de renta a cargo de la empresa | B58: 334 | C58: $ M/año | D58: Estado de resultados del caso (2026).
A59: Crédito fiscal por innovación en la oferta (1 = se incluye; 0 = no) | B59: 1 | C59: 0 / 1 | D59: Gestión que IntegraMotion se compromete a hacer: postular el proyecto ante Minciencias. Queda condicionado a la certificación del CNBT; el escenario Sin crédito fiscal muestra el resultado sin él.
A60: Crédito fiscal por inversión en innovación (art. 256-1 ET) | B60: 0.5 | C60: % inversión | D60: Para micro, pequeñas y medianas empresas: Lácteos Fúquene es mediana. IntegraMotion postula el proyecto ante Minciencias con el aval de un actor reconocido; el CNBT certifica la inversión y el crédito se compensa con impuestos nacionales en los dos años siguientes. La inversión se sigue depreciando (DIAN, concepto 012495 de 2026).
A61: Caso conservador: cuánto se cuenta de cada beneficio según su respaldo
A62: Caso conservador: beneficio contratado | B62: 1 | C62: % del beneficio | D62: Respaldo 1: beneficio con contrato firmado.
A63: Caso conservador: beneficio medido en la planta | B63: 1 | C63: % del beneficio | D63: Respaldo 2. Medido en la etapa 0 con el protocolo de medida y verificación.
A64: Caso conservador: beneficio técnicamente justificado | B64: 0.75 | C64: % del beneficio | D64: Respaldo 3. Balance de masa, VSM, literatura o datos de la planta.
A65: Caso conservador: beneficio por medir en la etapa 0 | B65: 0.5 | C65: % del beneficio | D65: Respaldo 4. Supuesto razonable que todavía no tiene medición.
A66: Caso conservador: beneficio hipotético | B66: 0 | C66: % del beneficio | D66: Respaldo 5.
A68: Inversión
A69: Componente | B69: Etapa | C69: Año | D69: Planta | E69: Reparto | F69: Quesería | G69: ¿Equipo? | H69: Madurez del precio (1 a 4) | I69: % imprevistos | J69: Vida fiscal (años; 0 = gasto) | K69: Innovación (1 = sí)
A70: Diagnóstico de la planta, plan de mantenimiento y orden de la operación | B70: 0 | C70: 0 | D70: =BOM!$F$72 -> 56.872528 | E70: =BOM!$H$72 -> 0.36 | F70: =D70*E70 -> 20.47411 | G70: 0 | H70: =ROUND(BOM!$G$72,0) -> 4 | I70: =BOM!$J$72 -> 0.21827576 | J70: 0 | K70: 0
A71: Automatización de 2 tinas: liras con variador, sensor de coagulación, dosificación | B71: 1 | C71: 0 | D71: =BOM!$F$73 -> 267.50965 | E71: =BOM!$H$73 -> 1 | F71: =D71*E71 -> 267.50965 | G71: 1 | H71: =ROUND(BOM!$G$73,0) -> 3 | I71: =BOM!$J$73 -> 0.18229324 | J71: 10 | K71: 1
A72: Tina del doble crema: medición y mando básicos (caudal, nivel, temperatura, válvula y bomba) | B72: 1 | C72: 0 | D72: =BOM!$F$74 -> 47.746861 | E72: =BOM!$H$74 -> 1 | F72: =D72*E72 -> 47.746861 | G72: 1 | H72: =ROUND(BOM!$G$74,0) -> 2 | I72: =BOM!$J$74 -> 0.13503854 | J72: 10 | K72: 0
A73: Controladora de peso y detector de metales en la salida del empaque | B73: 1 | C73: 0 | D73: =BOM!$F$75 -> 33.178864 | E73: =BOM!$H$75 -> 1 | F73: =D73*E73 -> 33.178864 | G73: 1 | H73: =ROUND(BOM!$G$75,0) -> 2 | I73: =BOM!$J$75 -> 0.1 | J73: 10 | K73: 0
A74: Medidor de grasa en línea en la estandarización | B74: 1 | C74: 0 | D74: =BOM!$F$76 -> 129.98093 | E74: =BOM!$H$76 -> 0.36 | F74: =D74*E74 -> 46.793136 | G74: 1 | H74: =ROUND(BOM!$G$76,0) -> 4 | I74: =BOM!$J$76 -> 0.25 | J74: 10 | K74: 0
A75: SCADA, historiador y MES ligero de la quesería (red, servidor, licencias e instrumentación) | B75: 1 | C75: 0 | D75: =BOM!$F$77 -> 130.79213 | E75: =BOM!$H$77 -> 0.5249784 | F75: =D75*E75 -> 68.663043 | G75: 1 | H75: =ROUND(BOM!$G$77,0) -> 3 | I75: =BOM!$J$77 -> 0.14975401 | J75: 5 | K75: 1
A76: Contrato principal con IntegraMotion (semestre 2026-2): ingeniería de la etapa 1 (diseño, programación y validación virtual) | B76: 1 | C76: 0 | D76: =IntegraMotion!$C$149 -> 162.40506 | E76: 1 | F76: =D76*E76 -> 162.40506 | G76: 0 | H76: 1 | I76: =CHOOSE(H76,$B$26,$B$27,$B$28,$B$29) -> 0.05 | J76: 10 | K76: 1
A77: Contrato principal con IntegraMotion (semestre 2026-2): etapa 0 (diagnóstico, línea base y gestión) | B77: 1 | C77: 0 | D77: =IntegraMotion!$B$149 -> 37.147218 | E77: 1 | F77: =D77*E77 -> 37.147218 | G77: 0 | H77: 1 | I77: =CHOOSE(H77,$B$26,$B$27,$B$28,$B$29) -> 0.05 | J77: 0 | K77: 0
A78: Contrato principal con IntegraMotion (semestre 2026-2): ingeniería básica de la etapa 2 y diseño de la celda de paletizado | B78: 1 | C78: 0 | D78: =(IntegraMotion!$D$149+IntegraMotion!$E$149) -> 23.841166 | E78: 1 | F78: =D78*E78 -> 23.841166 | G78: 0 | H78: 1 | I78: =CHOOSE(H78,$B$26,$B$27,$B$28,$B$29) -> 0.05 | J78: 0 | K78: 0
A79: Otrosí 1 con IntegraMotion: implementación de la etapa 1 (montaje supervisado, puesta en marcha, capacitación y soporte) | B79: 1 | C79: 0 | D79: =IntegraMotion!$D$235*Entorno!$B$14 -> 66.562711 | E79: 1 | F79: =D79*E79 -> 66.562711 | G79: 0 | H79: 1 | I79: =CHOOSE(H79,$B$26,$B$27,$B$28,$B$29) -> 0.05 | J79: 10 | K79: 1
A80: Parametrización de SAP Business One para la quesería, por el proveedor del ERP | B80: 1 | C80: 0 | D80: 25 | E80: 1 | F80: =D80*E80 -> 25 | G80: 0 | H80: 4 | I80: =CHOOSE(H80,$B$26,$B$27,$B$28,$B$29) -> 0.25 | J80: 0 | K80: 0
A81: Formación de los operarios con el SENA | B81: 1 | C81: 0 | D81: =20/3 -> 6.6666667 | E81: 1 | F81: =D81*E81 -> 6.6666667 | G81: 0 | H81: 1 | I81: =CHOOSE(H81,$B$26,$B$27,$B$28,$B$29) -> 0.05 | J81: 0 | K81: 0
A82: Aval y seguimiento del proyecto de innovación por un actor reconocido por Minciencias | B82: 1 | C82: 0 | D82: 15 | E82: 1 | F82: =D82*E82 -> 15 | G82: 0 | H82: 4 | I82: =CHOOSE(H82,$B$26,$B$27,$B$28,$B$29) -> 0.25 | J82: 0 | K82: 1
A83: Imprevistos de las etapas 0 y 1 | B83: 1 | C83: 0 | D83: =SUMPRODUCT(F70:F82,I70:I82) -> 109.81175 | E83: 1 | F83: =D83*E83 -> 109.81175 | G83: 0 | K83: 0
A84: Hiladora-moldeadora continua para doble crema y mozzarella | B84: 2 | C84: 1 | D84: =BOM!$F$78 -> 322.6 | E84: =BOM!$H$78 -> 1 | F84: =D84*E84 -> 322.6 | G84: 1 | H84: =ROUND(BOM!$G$78,0) -> 3 | I84: =BOM!$J$78 -> 0.15 | J84: 10 | K84: 0
A85: CIP automático del circuito de quesos | B85: 2 | C85: 1 | D85: =BOM!$F$79 -> 106.66667 | E85: =BOM!$H$79 -> 1 | F85: =D85*E85 -> 106.66667 | G85: 1 | H85: =ROUND(BOM!$G$79,0) -> 3 | I85: =BOM!$J$79 -> 0.15 | J85: 10 | K85: 0
A86: Enfriador de placas y tanque pulmón del suero (opción, fuera de la oferta) | B86: 2 | C86: 1 | D86: =BOM!$F$80 -> 80 | E86: 0 | F86: =D86*E86 -> 0 | G86: 1 | H86: =ROUND(BOM!$G$80,0) -> 4 | I86: =BOM!$J$80 -> 0.25 | J86: 10 | K86: 0
A87: Instrumentación y control de la etapa 2: E/S del PLC, ampliación del tablero, salmuera y suero | B87: 2 | C87: 1 | D87: =BOM!$F$81 -> 59.5152 | E87: =BOM!$H$81 -> 1 | F87: =D87*E87 -> 59.5152 | G87: 1 | H87: =ROUND(BOM!$G$81,0) -> 3 | I87: =BOM!$J$81 -> 0.17954853 | J87: 10 | K87: 0
A88: Otrosí 2 con IntegraMotion: ingeniería de detalle e implementación de la etapa 2 | B88: 2 | C88: 1 | D88: =IntegraMotion!$D$255*Entorno!$B$15 -> 90.106032 | E88: 1 | F88: =D88*E88 -> 90.106032 | G88: 0 | H88: 1 | I88: =CHOOSE(H88,$B$26,$B$27,$B$28,$B$29) -> 0.05 | J88: 10 | K88: 0
A89: Imprevistos de la etapa 2 | B89: 2 | C89: 1 | D89: =SUMPRODUCT(F84:F88,I84:I88) -> 79.581168 | E89: 1 | F89: =D89*E89 -> 79.581168 | G89: 0 | K89: 0
A90: Todo se dimensiona para la quesería. Equipos: hoja BOM, que valora cada ítem del diseño técnico (instrumentos, actuadores, control, SCADA y equipos de proceso) y lo suma por rubro. CIP y formación: un tercio del costo estimado para toda la planta. Diagnóstico, grasa en línea y la plataforma del SCADA (licencias, servidor y red) son comunes a la planta: se carga la parte de la leche de quesos. Contratos con IntegraMotion: hoja IntegraMotion, sin IVA. El contrato principal se ejecuta en el semestre 2026-2, en pesos de 2026, y se lleva al año 0, el arranque de la evaluación; los otrosíes se reajustan con el salario mínimo real del año en que se ejecutan (hoja Entorno). La tina del doble crema lleva solo medición y mando básicos porque no usa sensor de coagulación.
A91: Madurez del precio: 1 precio cerrado, 2 precio publicado, 3 estimado con referencias, 4 estimado sin cotización. Los imprevistos de cada etapa suman cada rubro por su porcentaje (supuestos de arriba). Vida fiscal: art. 137 ET (maquinaria 10 años; equipo de cómputo y redes 5 años); el diagnóstico, la formación y el aval son gastos deducibles del año. Los imprevistos se deducen y llevan IVA según el rubro al que pertenecen. Innovación: rubros del proyecto que se postula ante Minciencias (control del corte por coagulación, SCADA y MES, la ingeniería que los desarrolla y el aval); la compra de equipos estándar no califica.
A92: Inversión del año 0 (etapas 0 y 1) | F92: =SUMIFS(F70:F89,C70:C89,0) -> 930.80024
A93: Inversión del año 1 (etapa 2) | F93: =SUMIFS(F70:F89,C70:C89,1) -> 658.46907
A94: Equipos del año 0 | F94: =SUMIFS(F70:F89,C70:C89,0,G70:G89,1) -> 463.89156
A95: Equipos del año 1 | F95: =SUMIFS(F70:F89,C70:C89,1,G70:G89,1) -> 488.78187
A96: Imprevistos sobre la inversión sin imprevistos | F96: =(F83+F89)/(SUM(F70:F89)-F83-F89) -> 0.1352926
A97: Inversión total | F97: =$F$92+$F$93 -> 1589.2693
A98: Inversión del proyecto de innovación (base del crédito fiscal) | F98: =SUMPRODUCT(F70:F89,K70:K89) -> 580.14047
A99: Reposición del año 5 (hardware del SCADA) | F99: =$B$34*F75 -> 27.465217
A100: Reposición del año 6 (instrumentación) | F100: =$B$35*$F$94 -> 46.389156
A102: Beneficios anuales en régimen
A103: Medida | B103: Etapa | C103: Planta | D103: Reparto | E103: Quesería | F103: Δ ventas planta | G103: Δ ventas quesería | H103: Respaldo (1 a 5) | I103: Factor conservador | J103: Quesería, caso conservador
...

Sheet Entorno
A1: Entorno económico y político del proyecto
A2: La quesería se ejecuta en 2027 y 2028 y opera hasta 2037. Precios en pesos de 2026; esta hoja dice cuánto cambian año por año la inflación y el salario mínimo.
A4: Inflación y salario mínimo, año por año
B5: Año 0 | C5: Año 1 | D5: Año 2 | E5: Año 3 | F5: Año 4 | G5: Año 5 | H5: Año 6 | I5: Año 7 | J5: Año 8 | K5: Año 9 | L5: Año 10 | M5: Promedio
A6: Año calendario | B6: 2027 | C6: 2028 | D6: 2029 | E6: 2030 | F6: 2031 | G6: 2032 | H6: 2033 | I6: 2034 | J6: 2035 | K6: 2036 | L6: 2037
A7: Ruta 1 · base: inflación de cada año | B7: 0.06 | C7: 0.05 | D7: 0.045 | E7: 0.04 | F7: 0.04 | G7: 0.04 | H7: 0.04 | I7: 0.04 | J7: 0.04 | K7: 0.04 | L7: 0.04 | M7: =EXP(SUMPRODUCT(LN(1+B7:L7))/11)-1 -> 0.043163928
A8: Ruta 2 · consenso de los analistas | B8: 0.059 | C8: 0.045 | D8: 0.037 | E8: 0.034 | F8: 0.034 | G8: 0.034 | H8: 0.034 | I8: 0.034 | J8: 0.034 | K8: 0.034 | L8: 0.034 | M8: =EXP(SUMPRODUCT(LN(1+B8:L8))/11)-1 -> 0.037518712
A9: Ruta 3 · inflación persistente | B9: 0.065 | C9: 0.065 | D9: 0.065 | E9: 0.065 | F9: 0.065 | G9: 0.065 | H9: 0.065 | I9: 0.065 | J9: 0.065 | K9: 0.065 | L9: 0.065 | M9: =EXP(SUMPRODUCT(LN(1+B9:L9))/11)-1 -> 0.065
A10: Promedio geométrico de 2027 a 2037. La ruta que usa el modelo se elige en los supuestos de la hoja Quesería.
A12: Incremento del salario mínimo para 2027 | B12: 0.085 | D12: Davivienda: inflación de 2026 (6,91 %) − productividad (0,32 %) + «sorpresa política» (1,91 %). Gremios: 8 % a 9,5 %; Credicorp: 9 % a 10 %.
A13: Aumento real del salario mínimo desde 2028 | B13: 0.005 | D13: El Gobierno plantea volver a ajustarlo por inflación y productividad; la productividad del trabajo ha estado cerca de cero.
A14: Salario mínimo real de 2027 con la ruta base (2026 = 1) | B14: =(1+B12)/(1+B7) -> 1.0235849 | D14: Cuánto sube por encima de la inflación.
A15: Salario mínimo real de 2028 con la ruta base (2026 = 1) | B15: =B14*(1+B13) -> 1.0287028 | D15: Reajusta los contratos de IntegraMotion: la etapa 2 se ejecuta en 2028.
A16: Salario mínimo de 2027 en pesos | B16: =1750905*(1+B12) -> 1899731.9 | D16: Decreto de 2026: $1.750.905.
A17: Afecta lo que depende del salario: horas extra y reubicación de operarios (beneficios), traslape del personal y honorarios de IntegraMotion.
A19: Cómo se armaron las rutas
A20: • Encuesta de analistas del Banco de la República (septiembre de 2026): 6,8 % al cierre de 2026, 5,1 % al cierre de 2027, 4,0 % en agosto de 2028 y 3,4 % a cinco años. Los analistas han subido su pronóstico casi todos los meses de 2026.
A21: • Inflación de septiembre de 2026: 6,29 % anual (DANE), la más alta desde julio de 2024. Tasa del Banco de la República: 12,25 % desde el 1 de octubre, con una subida de 25 puntos básicos y la junta dividida.
A22: • Rutas en promedio de cada año. Consenso: de 6,8 % en diciembre de 2026 a 5,1 % en diciembre de 2027 da 5,9 % para 2027; luego 4,5 %, 3,7 % y 3,4 %. Ruta base: por encima del consenso cada año, con más margen desde 2028, y 4 % desde 2030, el techo del rango de la meta (2 % a 4 %). Ruta persistente: la inflación se queda cerca del dato de septiembre todo el horizonte.
A24: Lectura política y económica (octubre de 2026)
A25: • Salario mínimo: en 2026 subió 23,7 %, muy por encima de la inflación. El Gobierno de Abelardo de la Espriella y su ministro de Hacienda piden volver a un ajuste técnico (inflación más productividad); los analistas esperan 8 % a 10 % para 2027 por una prima política. La decisión se toma a más tardar el 30 de diciembre.
A26: • Presupuesto General de 2027: el Congreso lo aprobó el 20 de octubre por $634,9 billones, pero quedó en vilo por un presunto vicio de trámite en el artículo 65 (Senado y Cámara habrían aprobado textos distintos); si se confirma, el Gobierno lo expide por decreto. Suma incertidumbre fiscal: hace menos probable que las tasas de interés bajen rápido.
A27: • Política monetaria: el Banco de la República volvió a subir la tasa en septiembre. Davivienda espera bajadas graduales hasta 11 % al cierre de 2027. El crédito de fomento se pacta sobre la IBR más un margen, así que sigue esa tendencia.
A28: • Impuestos: el Gobierno anunció una reforma para bajar la carga de las empresas, sin tarifa definida todavía. El modelo deja la renta en 35 % y prueba 30 % en la hoja Escenarios.
A29: • Energía: el gas para la industria depende cada vez más de importaciones y El Niño presiona las tarifas. La hoja Escenarios prueba costos operativos 30 % más altos.
A31: Cómo entra al modelo
... A43: • Presupuesto de 2027 aprobado y en vilo: portafolio.co/economia/gobierno/presupuesto-de-2027-recien-aprobado-en-vilo-por-inminente-hundimiento-por-vicio-de-tramite-en-el-congreso-504829

Sheet Beneficios y costos
A1: Beneficios y costos operativos de la quesería
A2: Cada beneficio sale del balance de masa, de los precios y de la mejora que se espera; cada costo nuevo, del consumo de los equipos. $ M constantes de 2026. Las cifras en azul se miden en la etapa 0.
A4: Datos de la operación
A5: Dato | B5: Valor | C5: Unidad | D5: Fuente o criterio
A6: Días de operación al año | B6: 294 | C6: días | D6: Caso: lunes a sábado menos festivos.
A7: Densidad de la leche | B7: 1.03 | C7: kg/L | D7: Valor típico.
A8: Grasa de la leche cruda | B8: 0.036 | C8: % m/m | D8: Hato Holstein de la sabana de Ubaté.
A9: Grasa de la crema | B9: 0.4 | C9: % m/m | D9: Descremadora centrífuga.
A10: Grasa de más que se deja hoy al estandarizar a mano | B10: 0.0008 | C10: puntos | D10: Cuadro de Pearson y muestreo: el operario deja margen para no quedar por debajo del mínimo.
A11: Grasa de más con el medidor en línea | B11: 0.0003 | C11: puntos | D11: Medidor de grasa y densidad con válvula de remezcla.
A12: Crema añadida al fundido del doble crema | B12: 30 | C12: kg/día | D12: Sale de la crema de la estandarización.
A13: Agua de lavado del grano del campesino | B13: 0.03 | C13: kg/kg leche | D13: Sale con el suero.
A14: Queso adicional por el corte con sensor de coagulación | B14: 0.0015 | C14: kg/kg leche | D14: Menos finos al suero en el campesino y la mozzarella (0,15 puntos de rendimiento).
A15: Queso adicional con la hiladora-moldeadora | B15: 0.02 | C15: % del queso hilado | D15: Menos grasa y finos al agua de hilado que en la marmita a mano.
A16: Sobrepeso de los quesos hoy | B16: 0.01 | C16: % del peso | D16: Igual al de las bolsas UHT del caso.
A17: Sobrepeso con la controladora de peso | B17: 0.005 | C17: % del peso | D17: La controladora rechaza y ajusta el corte.
... A24: Ahorro con limpieza CIP automática | B24: 0.1 | C24: % de ese gasto | D24: Recuperación de soluciones y ciclos medidos en lugar de lavado a mano.
A25: Parte del circuito de quesos en la limpieza | B25: =1/3 -> 0.33333333 | C25: % | D25: Uno de los tres circuitos (quesos, yogur y UHT).
A26: Horas extra diarias del hilado que se evitan en cada etapa | B26: 0.5 | C26: h/día | D26: VSM: el hilado a mano necesita 8,4 h en una ventana de 7,4 h.
A27: Operarios del hilado | B27: 4 | C27: personas | D27: Dos parejas.
A28: Costo de la hora extra | B28: 20000 | C28: $/h | D28: Costo de la hora de un salario mínimo más el recargo de 25 %.
A29: Precio de la crema vendida | B29: 9000 | C29: $/kg | D29: Crema al 40 % a granel.
A30: Precio de la leche entera UHT | B30: 3100 | C30: $/L | D30: Precio a distribuidor del caso.
A31: Precio del suero hoy, sin enfriar | B31: 30 | C31: $/kg | D31: Caso de estudio.
A32: Precio del suero enfriado con contrato | B32: 45 | C32: $/kg | D32: Contrato anual con una fábrica de alimento balanceado; se valida en la etapa 0 con dos cotizaciones.
A33: Ventas de la quesería que hoy salen incompletas o tarde por paros que Ventas no conoce | B33: 0.01 | C33: % ventas de quesos | D33: Caso de estudio, hallazgo H9 (registro de despachos de 2026): Ventas promete sin saber qué máquinas están en falla.
A34: Descuento con que se coloca ese queso en otro cliente o canal | B34: 0.3 | C34: % del precio | D34: Caso de estudio: el queso fresco que no sale a tiempo se coloca en mayoristas con descuento.
A35: Parte de esos incumplimientos que se evita con el estado de la planta en el ERP | B35: =2/3 -> 0.66666667 | C35: % | D35: Estimado: los paros siguen ocurriendo, pero Ventas los ve en el ERP y promete con la capacidad real.
A36: Horas al día de supervisores y planeador conciliando registros de papel y Excel | B36: 1.5 | C36: h/día | D36: Caso de estudio, hallazgo H9: planeación semanal en Excel y registros en papel. El MES los registra solos; el tiempo liberado se usa en mejora.
A37: Costo de una hora de supervisor | B37: 29000 | C37: $/h | D37: Salario de unos $3,5 M al mes con factor prestacional de 1,52, entre 182 horas.
A38: Ventas del yogur | B38: 9851 | C38: $ M/año | D38: Caso de estudio.
A39: Ventas del UHT | B39: 12315 | C39: $ M/año | D39: Caso de estudio.
A40: Yogur que se sobreacidifica o se reprocesa (H2) | B40: 0.02 | C40: % de la producción | D40: Caso de estudio.
A41: Sobrellenado de los vasos de yogur (H3) | B41: 0.02 | C41: % del peso | D41: Caso de estudio.
A42: Sobrellenado de las bolsas de UHT (H3) | B42: 0.01 | C42: % del volumen | D42: Caso de estudio.
A43: Producto perdido en las interfases del UHT (H4) | B43: 0.01 | C43: % del volumen | D43: Caso de estudio.
A44: Operarios liberados que cubren un puesto que la planta tendría que contratar | B44: 1 | C44: personas | D44: Hallazgo H10 de la etapa 0: el plan preventivo necesita un puesto de mantenimiento autónomo (inspección, lubricación y limpieza técnica) que hoy no existe. La asignación por competencias pone ahí a uno de los operarios que libera la hiladora.
A45: Queso adicional con el balance de sólidos y la humedad controlados por lote | B45: 0.005 | C45: % del queso | D45: Hallazgo H11 de la etapa 0. Por la fórmula de Van Slyke el rendimiento va con 1/(1 − humedad): subir la humedad promedio 0,25 puntos dentro de la norma del queso (de 50,00 a 50,25 %) da 0,5 % más queso; también sale de llevar a la mediana los lotes que hoy pierden más grasa y proteína al suero. La etapa 0 mide la dispersión real con un mes de lotes. No incluye el sensor ni la hiladora.
A46: Lo que puede bajar la leche de cada queso frente a hoy | B46: 0.15 | C46: % de su leche | D46: Hallazgo H12. Bajar la producción de un queso no tiene límite de mercado; se limita para no perder clientes del campesino.
A47: Lo que el mercado absorbe de más de campesino | B47: 0.05 | C47: % de su producción | D47: Estudio de mercado de la empresa (tabla de esta hoja): el campesino no sube en la mezcla óptima porque es el que menos deja por litro.
... A63: OEE de la termoformadora con el MES y el mantenimiento preventivo | B63: 0.68 | C63: % | D63: Mitad del rango de 66 a 70 % del documento de OEE.
A65: Quesos
A66: Referencia | B66: Leche (L/día) | C66: Grasa objetivo | D66: Rendimiento (kg/kg) | E66: Precio ($/kg) | F66: Insumos y empaque ($/kg)
A67: Q1 campesino | B67: 4500 | C67: 0.026 | D67: 0.12 | E67: 19500 | F67: 750
A68: Q2 doble crema (leche entera, sin estandarizar) | B68: 3000 | C68: =$B$8 -> 0.036 | D68: 0.13 | E68: 22000 | F68: 900
A69: Q3 mozzarella | B69: 1500 | C69: 0.026 | D69: 0.1 | E69: 24000 | F69: 800
A70: Rendimiento del campesino y la mozzarella sobre leche estandarizada; el del doble crema, sobre leche entera e incluye la crema del fundido. Precios: Corabastos y mercado mayorista, 2026.
A72: Estandarización de grasa de toda la recepción (kg/día)
A73: Referencia | B73: Leche (L/día) | C73: Grasa objetivo | D73: Crema retirada hoy | E73: Crema con medidor | F73: Crema adicional
A74: L1 leche entera UHT | B74: 6500 | C74: 0.03 | D74: =MAX(0,B74*$B$7*($B$8-(C74+$B$10))/($B$9-(C74+$B$10))) -> 94.295775 | E74: =MAX(0,B74*$B$7*($B$8-(C74+$B$11))/($B$9-(C74+$B$11))) -> 103.22288 | F74: =E74-D74 -> 8.9271088
A75: L2 deslactosada | B75: 3500 | C75: 0.015 | D75: =MAX(0,B75*$B$7*($B$8-(C75+$B$10))/($B$9-(C75+$B$10))) -> 189.5393 | E75: =MAX(0,B75*$B$7*($B$8-(C75+$B$11))/($B$9-(C75+$B$11))) -> 193.97842 | F75: =E75-D75 -> 4.4391223
A76: L3 bebida láctea | B76: 2000 | C76: 0.02 | D76: =MAX(0,B76*$B$7*($B$8-(C76+$B$10))/($B$9-(C76+$B$10))) -> 82.57384 | E76: =MAX(0,B76*$B$7*($B$8-(C76+$B$11))/($B$9-(C76+$B$11))) -> 85.177772 | F76: =E76-D76 -> 2.6039323
A77: Q1 campesino | B77: =B67 -> 4500 | C77: =C67 -> 0.026 | D77: =MAX(0,B77*$B$7*($B$8-(C77+$B$10))/($B$9-(C77+$B$10))) -> 114.26045 | E77: =MAX(0,B77*$B$7*($B$8-(C77+$B$11))/($B$9-(C77+$B$11))) -> 120.30907 | F77: =E77-D77 -> 6.0486213
A78: Q3 mozzarella | B78: =B69 -> 1500 | C78: =C69 -> 0.026 | D78: =MAX(0,B78*$B$7*($B$8-(C78+$B$10))/($B$9-(C78+$B$10))) -> 38.086817 | E78: =MAX(0,B78*$B$7*($B$8-(C78+$B$11))/($B$9-(C78+$B$11))) -> 40.103024 | F78: =E78-D78 -> 2.0162071
A79: Y1 yogur natural | B79: 1400 | C79: 0.03 | D79: =MAX(0,B79*$B$7*($B$8-(C79+$B$10))/($B$9-(C79+$B$10))) -> 20.309859 | E79: =MAX(0,B79*$B$7*($B$8-(C79+$B$11))/($B$9-(C79+$B$11))) -> 22.232621 | F79: =E79-D79 -> 1.9227619
A80: Y2 yogur de fresa | B80: 1400 | C80: 0.03 | D80: =MAX(0,B80*$B$7*($B$8-(C80+$B$10))/($B$9-(C80+$B$10))) -> 20.309859 | E80: =MAX(0,B80*$B$7*($B$8-(C80+$B$11))/($B$9-(C80+$B$11))) -> 22.232621 | F80: =E80-D80 -> 1.9227619
A81: Y3 yogur de mora | B81: 1200 | C81: 0.03 | D81: =MAX(0,B81*$B$7*($B$8-(C81+$B$10))/($B$9-(C81+$B$10))) -> 17.408451 | E81: =MAX(0,B81*$B$7*($B$8-(C81+$B$11))/($B$9-(C81+$B$11))) -> 19.056532 | F81: =E81-D81 -> 1.6480816
A82: Total | B82: =SUM(B74:B81) -> 22000 | D82: =SUM(D74:D81) -> 576.78435 | E82: =SUM(E74:E81) -> 606.31295 | F82: =SUM(F74:F81) -> 29.528597
A83: Balance de grasa: crema = leche × (grasa de la leche − grasa objetivo) / (grasa de la crema − grasa objetivo). Hoy el objetivo lleva la grasa de más del ajuste manual. El doble crema usa leche entera y no se estandariza.
A85: Balance de masa de los quesos (kg/día)
A86: Corriente | B86: Q1 campesino | C86: Q2 doble crema | D86: Q3 mozzarella | E86: Total
A87: Leche | B87: =B67*$B$7 -> 4635 | C87: =B68*$B$7 -> 3090 | D87: =B69*$B$7 -> 1545 | E87: =SUM(B87:D87) -> 9270
A88: Crema retirada en la estandarización | B88: =D77 -> 114.26045 | C88: =0 -> 0 | D88: =D78 -> 38.086817 | E88: =SUM(B88:D88) -> 152.34727
A89: Crema añadida al fundido | B89: =0 -> 0 | C89: =$B$12 -> 30 | D89: =0 -> 0 | E89: =SUM(B89:D89) -> 30
A90: Leche para quesería | B90: =B87-B88 -> 4520.7395 | C90: =C87-C88 -> 3090 | D90: =D87-D88 -> 1506.9132 | E90: =SUM(B90:D90) -> 9117.6527
A91: Agua de lavado del grano | B91: =B90*$B$13 -> 135.62219 | C91: =0 -> 0 | D91: =0 -> 0 | E91: =SUM(B91:D91) -> 135.62219
A92: Queso hoy | B92: =B90*D67 -> 542.48875 | C92: =C90*D68 -> 401.7 | D92: =D90*D69 -> 150.69132 | E92: =SUM(B92:D92) -> 1094.8801
A93: Suero | B93: =B90+B89+B91-B92 -> 4113.873 | C93: =C90+C89+C91-C92 -> 2718.3 | D93: =D90+D89+D91-D92 -> 1356.2219 | E93: =SUM(B93:D93) -> 8188.3949
A94: Cierre: entradas − salidas (debe ser 0) | B94: =(B87+B89+B91)-(B88+B92+B93) -> 0 | C94: =(C87+C89+C91)-(C88+C92+C93) -> 0 | D94: =(D87+D89+D91)-(D88+D92+D93) -> 0 | E94: =SUM(B94:D94) -> 0
A95: Queso adicional por el sensor de coagulación (etapa 1) | B95: =B90*$B$14 -> 6.7811093 | C95: =0 -> 0 | D95: =D90*$B$14 -> 2.2603698 | E95: =SUM(B95:D95) -> 9.0414791
A96: Queso adicional por la hiladora (etapa 2) | B96: =0 -> 0 | C96: =(C92+C95)*$B$15 -> 8.034 | D96: =(D92+D95)*$B$15 -> 3.0590338 | E96: =SUM(B96:D96) -> 11.093034
A97: Queso que pasa por el hilado con la hiladora | B97: =0 -> 0 | C97: =C92+C95+C96 -> 409.734 | D97: =D92+D95+D96 -> 156.01072 | E97: =SUM(B97:D97) -> 565.74472
A98: Queso adicional frente a la producción actual | B98: =(E95+E96)/E92 -> 0.018389697 | D98: Se vende a los mismos clientes: es menos del 2 % del queso que ya se despacha.
A99: El suero total coincide con los 8.188 kg/día del caso. El queso adicional usa la misma leche: no se compra más.
A101: Mezcla óptima de los tres quesos (programación lineal, desde la etapa 2)
A102: Los 9.000 L de la quesería se reparten hoy por costumbre. Con el costo real por lote, cada litro va al queso que más deja, dentro de lo que absorbe el mercado según el estudio de mercado de la empresa (más doble crema; poca mozzarella más, porque compite con la importada) y con la capacidad que libera la hiladora. Es un programa lineal con una restricción de leche y cotas por queso; esta tabla lo resuelve ordenando los quesos por margen por litro, que para esa estructura da el óptimo exacto.
A103: Queso | B103: Leche hoy (L/día) | C103: Margen por litro ($/L) | D103: Mínimo (L/día) | E103: Máximo (L/día) | F103: Puesto por margen | G103: Leche óptima (L/día) | H103: Cambio (L/día)
A104: =A67 -> Q1 campesino | B104: =B67 -> 4500 | C104: =(B92*(E67-F67)+(B88-B89)*$B$29)/B67 -> 2488.8907 | D104: =B104*(1-$B$46) -> 3825 | E104: =B104*(1+$B$47) -> 4725 | F104: =RANK(C104,$C$104:$C$106,0) -> 3 | G104: =D104+MIN(E104-D104,MAX(0,(SUM($B$104:$B$106)-SUM($D$104:$D$106))-SUMIF($F$104:$F$106,"<"&F104,$E$104:$E$106)+SUMIF($F$104:$F$106,"<"&F104,$D$104:$D$106))) -> 3975 | H104: =G104-B104 -> -525
A105: =A68 -> Q2 doble crema (leche entera, sin estandarizar) | B105: =B68 -> 3000 | C105: =(C92*(E68-F68)+(C88-C89)*$B$29)/B68 -> 2735.29 | D105: =B105*(1-$B$46) -> 2550 | E105: =B105*(1+$B$48) -> 3450 | F105: =RANK(C105,$C$104:$C$106,0) -> 1 | G105: =D105+MIN(E105-D105,MAX(0,(SUM($B$104:$B$106)-SUM($D$104:$D$106))-SUMIF($F$104:$F$106,"<"&F105,$E$104:$E$106)+SUMIF($F$104:$F$106,"<"&F105,$D$104:$D$106))) -> 3450 | H105: =G105-B105 -> 450
A106: =A69 -> Q3 mozzarella | B106: =B69 -> 1500 | C106: =(D92*(E69-F69)+(D88-D89)*$B$29)/B69 -> 2559.2133 | D106: =B106*(1-$B$46) -> 1275 | E106: =B106*(1+$B$49) -> 1575 | F106: =RANK(C106,$C$104:$C$106,0) -> 2 | G106: =D106+MIN(E106-D106,MAX(0,(SUM($B$104:$B$106)-SUM($D$104:$D$106))-SUMIF($F$104:$F$106,"<"&F106,$E$104:$E$106)+SUMIF($F$104:$F$106,"<"&F106,$D$104:$D$106))) -> 1575 | H106: =G106-B106 -> 75
A107: Margen adicional de la mezcla óptima ($ M/año) | C107: =SUMPRODUCT(H104:H106,C104:C106)*$B$6/1000000 -> 34.149244
A108: Ventas adicionales de la mezcla óptima ($ M/año) | C108: =(H104*B92/B67*E67+H105*C92/B68*E68+H106*D92/B69*E69)*$B$6/1000000 -> 80.049639
A109: Horas de hiladora al día con la mezcla óptima (300 kg/h) | C109: =(G105*C92/B68+G106*D92/B69)/300 -> 2.0672696 | D109: Cabe en un turno: la hiladora libera la capacidad que el hilado a mano no tiene.
A110: Comprobación: leche óptima − leche de hoy (L/día) | C110: =SUM(G104:G106)-SUM(B104:B106) -> 0
A111: Margen por litro: queso por litro × (precio − insumos) más la crema que se retira y se vende, menos la crema que se añade al fundido. La leche cuesta lo mismo en los tres, así que no cambia la decisión. Método: Meneghini et al. (2016), programación lineal de la mezcla en una láctea de Brasil.
A113: Estudio de mercado: ¿la región absorbe la nueva mezcla?
A114: Lácteos Fúquene vende en Bogotá, Cundinamarca y Boyacá. Con fuentes públicas se estima el tamaño del mercado de quesos de esa región y se compara con el queso de más que pide la mezcla óptima. Los límites de la mezcla (supuestos de arriba) salen de este análisis.
A115: Dato | B115: Valor | C115: Unidad | D115: Fuente o cálculo
A116: Población de Bogotá, Cundinamarca y Boyacá en 2026 | B116: 12843121 | C116: personas | D116: DANE, proyecciones con base en el censo de 2018: Bogotá 7.945.996, Cundinamarca 3.601.277, Boyacá 1.295.848.
A117: Consumo de queso por persona (bajo) | B117: 1.2 | C117: kg/año | D117: Cundinamarca, Nielsen 2017 (Portafolio, 26 de septiembre de 2018).
A118: Consumo de queso por persona (alto) | B118: 1.5 | C118: kg/año | D118: Promedio nacional (Portafolio, 13 de agosto de 2024).
A119: Mercado de queso de la región (bajo) | B119: =B116*B117/1000 -> 15411.745 | C119: t/año | D119: Población × consumo por persona.
A120: Mercado de queso de la región (alto) | B120: =B116*B118/1000 -> 19264.681 | C120: t/año | D120: Población × consumo por persona.
A121: Participación de los quesos hilados (doble crema, mozzarella) | B121: 0.28 | C121: % del mercado | D121: Nielsen 2017: frescos 32 %, hilados 28 %, gratinados 6 %, maduros 2 % (Portafolio, 2018).
A122: Mercado de hilados de la región (bajo) | B122: =B119*B121 -> 4315.2887 | C122: t/año | D122: Se toma el bajo para ser prudentes.
A123: Crecimiento del mercado de queso | B123: 0.068 | C123: % al año | D123: Portafolio, 13 de agosto de 2024. Nielsen (Portafolio, 9 de noviembre de 2023) ve a Cundinamarca y Boyacá entre las regiones que más crecen.
A124: Crecimiento anual de los hilados de la región | B124: =B122*B123 -> 293.43963 | C124: t/año | D124: Mercado bajo × crecimiento.
A125: Hilados que produce hoy Lácteos Fúquene | B125: =(C92+D92)*$B$6/1000 -> 162.40305 | C125: t/año | D125: Balance de masa de esta hoja.
A126: Participación de Lácteos Fúquene en los hilados de la región | B126: =B125/B122 -> 0.037634342 | C126: % | D126: Con el mercado bajo.
A127: Hilados de más con la mezcla óptima | B127: =(H105*C92/B68+H106*D92/B69)*$B$6/1000 -> 19.930132 | C127: t/año | D127: Cambio de leche × queso por litro × días.
...

Sheet Cotizaciones
A1: Cotizaciones y precios de referencia de los equipos
A2: Precios publicados en octubre de 2026, convertidos a pesos con la TRM y el euro del día. Sin cotización formal todavía: las cifras en azul se reemplazan cuando lleguen las de los proveedores.
A4: Tasas de cambio y factores
A5: Concepto | B5: Valor | C5: Unidad | D5: Fuente
A6: Tasa representativa del mercado (16 de octubre de 2026) | B6: 3170.46 | C6: $/US$ | D6: Superintendencia Financiera, citada por Noticias Caracol, 16-oct-2026.
A7: Euro en pesos (15 de octubre de 2026) | B7: 3569.9 | C7: $/€ | D7: Investing.com, citado por Portafolio, 15-oct-2026.
A8: Flete, seguro, arancel y nacionalización de un equipo importado | B8: 0.3 | C8: % del precio | D8: Supuesto: flete marítimo e internación desde Asia o Europa; confirmar con el agente de aduanas.
A9: Instalación, integración y puesta en marcha | B9: 0.15 | C9: % del precio | D9: Supuesto: montaje, cableado al PLC y pruebas en sitio.
A11: Equipos de la inversión
A12: Equipo | B12: Precio de referencia | C12: Moneda | D12: Precio en $ M | E12: Con nacionalización e instalación ($ M) | F12: Valor en el modelo ($ M) | G12: Estado | H12: Referencia | I12: Lectura
A13: Controladora de peso y detector de metales (estación E18) | B13: 7000 | C13: US$ | D13: =B13*$B$6/1000000 -> 22.19322 | E13: =D13*(1+$B$8)*(1+$B$9) -> 33.178864 | F13: =E13 -> 33.178864 | G13: Precio publicado | H13: Made-in-China, catálogo de controladoras de peso: equipo combinado con detector de metales, US$6.500–7.000 por unidad (oct-2026). | I13: Equipo de origen chino. Una marca europea puede costar 3 a 4 veces más; se recomienda pedir las dos cotizaciones.
A14: Hiladora-moldeadora continua de 300 kg/h | B14: 39000 | C14: € | D14: =B14*$B$7/1000000 -> 139.2261 | E14: =D14*(1+$B$8)*(1+$B$9) -> 208.14302 | F14: 322.6 | G14: Estimado con referencias | H14: Werktuigen: DIMA 100 Compact usada (2023), 100 kg/h, €39.000. Ullmer's: cocedora-hiladora DIMA usada, US$35.000. Made-in-China: cocedora-hiladora por lotes, US$12.500–18.500. | I14: Las referencias son de máquinas usadas de 100 kg/h o de equipos por lotes. Una continua nueva de 300 kg/h (Milkylab, CMT, Dima) es de precio a solicitud; el estimado equivale a unos US$102.000.
A15: CIP automático del circuito de quesos | B15: 5000 | C15: US$ | D15: =B15*$B$6/1000000 -> 15.8523 | E15: =D15*(1+$B$8)*(1+$B$9) -> 23.699189 | F15: =320/3 -> 106.66667 | G15: Estimado con referencias | H15: Accio: sistemas CIP automáticos de US$4.000–10.000 (estaciones pequeñas) hasta US$80.000 (línea completa de leche). | I15: El estimado (un tercio de una estación de tres circuitos) está dentro del rango publicado.
A16: SCADA, historiador y MES ligero (licencias Ignition) | B16: 9500 | C16: US$ | D16: =B16*$B$6/1000000 -> 30.11937 | E16: =D16*(1+$B$8)*(1+$B$9) -> 45.028458 | F16: =BOM!$F$77 -> 130.79213 | G16: Valorado en el BOM | H16: Detalle ítem por ítem en la hoja BOM. | I16: Las licencias son una parte; el valor del modelo incluye servidor, red e instrumentación de la quesería.
A17: Controlador de las tinas (CompactLogix 1769-L33ER) | B17: 2200 | C17: US$ | D17: =B17*$B$6/1000000 -> 6.975012 | E17: =D17*(1+$B$8)*(1+$B$9) -> 10.427643 | F17: =E17 -> 10.427643 | G17: Precio publicado | H17: NJT Automation: 1769-L33ER nuevo, caja abierta, US$2.199,99. | I17: Componente incluido en la automatización de las tinas; se muestra como referencia del costo del control.
A18: Automatización de 2 tinas (liras con variador, sensor de coagulación, dosificación) | F18: =BOM!$F$73 -> 267.50965 | G18: Valorado en el BOM | H18: Detalle ítem por ítem en la hoja BOM.
A19: Tina del doble crema: medición y mando básicos | F19: =BOM!$F$74 -> 47.746861 | G19: Valorado en el BOM | H19: Detalle ítem por ítem en la hoja BOM.
A20: Medidor de grasa en línea (planta) | F20: =BOM!$F$76 -> 129.98093 | G20: Valorado en el BOM | H20: Detalle ítem por ítem en la hoja BOM.
A21: Enfriador de placas y tanque pulmón del suero | F21: 80 | G21: Estimado | H21: Pendiente de cotización.
A23: Siguiente paso: solicitud formal de cotización a proveedores en Colombia (equipos de proceso lácteo, instrumentación y control) para la hiladora, las tinas, el medidor de grasa, el CIP y la estación E18.

Sheet BOM
A1: BOM: lista de materiales del proyecto, del diseño técnico a la inversión
A2: Cada ítem sale del diseño técnico del proyecto (instrumentación de la sección 7 del README, modelo físico ISA-88, arquitectura ISA-95) y entra a la inversión de la hoja Quesería por su rubro. Lo especifica el paquete de la EDT indicado; el ingeniero de gestión y finanzas lo cotiza (paquete 6.1).
A4: Tasas y factores
A5: Concepto | C5: Valor | D5: Unidad | E5: Fuente
A6: Dólar | C6: =Cotizaciones!$B$6 -> 3170.46 | D6: $/US$ | E6: Hoja Cotizaciones.
A7: Euro | C7: =Cotizaciones!$B$7 -> 3569.9 | D7: $/€ | E7: Hoja Cotizaciones.
A8: Libra esterlina | C8: =C6*1.33 -> 4216.7118 | D8: $/£ | E8: Dólar × 1,33 US$/£ (estimado, octubre de 2026).
A9: Importación directa | C9: =Cotizaciones!$B$8 -> 0.3 | D9: % del precio | E9: Flete, seguro, arancel y aduana de un equipo que se trae del exterior; hoja Cotizaciones.
A10: Instalación | C10: =Cotizaciones!$B$9 -> 0.15 | D10: % del precio | E10: Montaje, cableado al PLC y pruebas; hoja Cotizaciones.
A11: Compra a un distribuidor en Colombia | C11: 0.15 | D11: % del precio | E11: Instrumentos, control y red comprados a distribuidores con stock local (Endress+Hauser, Rockwell, Siemens): el precio local suele ser el de lista más 10 a 20 %. Confirmar con su cotización.
A12: Lista de materiales
A13: Tag | B13: Descripción | C13: Etapa | D13: Rubro de la inversión | E13: Cantidad | F13: Precio unitario | G13: Moneda | H13: Origen (0 nacional, 1 importado, 2 distribuidor) | I13: Instalación (1 = sí) | J13: Valor ($ M) | K13: Parte de la quesería | L13: Paquete de la EDT | M13: Madurez (1 a 4) | N13: % imprevistos | O13: Fuente
A14: IR-01 | B14: Cámara termográfica para mantenimiento predictivo (FLIR E8 Pro) | C14: 0 | D14: Etapa 0: herramientas de mantenimiento y medición | E14: 1 | F14: 3299 | G14: US$ | H14: 2 | I14: 0 | J14: =E14*F14*$C$6/1000000*(1+(H14=1)*$C$9+(H14=2)*$C$11)*(1+I14*$C$10) -> 12.02825 | K14: =Quesería!$B$16 -> 0.36 | L14: 2.1 | M14: 2 | N14: =CHOOSE(M14,Quesería!$B$26,Quesería!$B$27,Quesería!$B$28,Quesería!$B$29) -> 0.1 | O14: FLIR, precio de lista 2026. | P14: D0
A15: VA-01 | B15: Analizador de vibraciones portátil | C15: 0 | D15: Etapa 0: herramientas de mantenimiento y medición | E15: 1 | F15: 1500 | G15: US$ | H15: 2 | I15: 0 | J15: =E15*F15*$C$6/1000000*(1+(H15=1)*$C$9+(H15=2)*$C$11)*(1+I15*$C$10) -> 5.4690435 | K15: =Quesería!$B$16 -> 0.36 | L15: 2.1 | M15: 4 | N15: =CHOOSE(M15,Quesería!$B$26,Quesería!$B$27,Quesería!$B$28,Quesería!$B$29) -> 0.25 | O15: Estimado. | P15: D0
A16: UL-01 | B16: Detector ultrasónico de fugas de aire y vapor | C16: 0 | D16: Etapa 0: herramientas de mantenimiento y medición | E16: 1 | F16: 1200 | G16: US$ | H16: 2 | I16: 0 | J16: =E16*F16*$C$6/1000000*(1+(H16=1)*$C$9+(H16=2)*$C$11)*(1+I16*$C$10) -> 4.3752348 | K16: =Quesería!$B$16 -> 0.36 | L16: 2.1 | M16: 4 | N16: =CHOOSE(M16,Quesería!$B$26,Quesería!$B$27,Quesería!$B$28,Quesería!$B$29) -> 0.25 | O16: Estimado. | P16: D0
A17: CMMS | B17: Software de mantenimiento (CMMS), suscripción del primer año | C17: 0 | D17: Etapa 0: herramientas de mantenimiento y medición | E17: 1 | F17: 6000000 | G17: $ | H17: 0 | I17: 0 | J17: =E17*F17*1/1000000*(1+(H17=1)*$C$9+(H17=2)*$C$11)*(1+I17*$C$10) -> 6 | K17: =Quesería!$B$16 -> 0.36 | L17: 2.1 | M17: 4 | N17: =CHOOSE(M17,Quesería!$B$26,Quesería!$B$27,Quesería!$B$28,Quesería!$B$29) -> 0.25 | O17: Estimado: unos $0,5 M al mes. | P17: D0
A18: BAL-02 | B18: Pesas patrón y calibración de las básculas de la planta | C18: 0 | D18: Etapa 0: herramientas de mantenimiento y medición | E18: 1 | F18: 4000000 | G18: $ | H18: 0 | I18: 0 | J18: =E18*F18*1/1000000*(1+(H18=1)*$C$9+(H18=2)*$C$11)*(1+I18*$C$10) -> 4 | K18: =Quesería!$B$16 -> 0.36 | L18: 2.3 | M18: 4 | N18: =CHOOSE(M18,Quesería!$B$26,Quesería!$B$27,Quesería!$B$28,Quesería!$B$29) -> 0.25 | O18: Estimado. | P18: D0
A19: MANT | B19: Repuestos y reparaciones urgentes que deje el diagnóstico (sellos, rodamientos, trampas de vapor) | C19: 0 | D19: Etapa 0: herramientas de mantenimiento y medición | E19: 1 | F19: 25000000 | G19: $ | H19: 0 | I19: 0 | J19: =E19*F19*1/1000000*(1+(H19=1)*$C$9+(H19=2)*$C$11)*(1+I19*$C$10) -> 25 | K19: =Quesería!$B$16 -> 0.36 | L19: 2.1 | M19: 4 | N19: =CHOOSE(M19,Quesería!$B$26,Quesería!$B$27,Quesería!$B$28,Quesería!$B$29) -> 0.25 | O19: Estimado del diagnóstico; se ajusta con el inventario de fallas. | P19: D0
A20: FT-301/303 | B20: Caudalímetro electromagnético sanitario DN50 (Promag H 100) | C20: 1 | D20: Tinas TQ-301 y TQ-303, control y tablero | E20: 2 | F20: 4816.4 | G20: US$ | H20: 2 | I20: 1 | J20: =E20*F20*$C$6/1000000*(1+(H20=1)*$C$9+(H20=2)*$C$11)*(1+I20*$C$10) -> 40.389688 | K20: 1 | L20: 3.1 | M20: 2 | N20: =CHOOSE(M20,Quesería!$B$26,Quesería!$B$27,Quesería!$B$28,Quesería!$B$29) -> 0.1 | O20: Instrumart, precio de lista (oct-2026). | P20: T13
A21: LT-301/303 | B21: Radar de nivel sanitario (Micropilot FMR43) | C21: 1 | D21: Tinas TQ-301 y TQ-303, control y tablero | E21: 2 | F21: 1936.25 | G21: US$ | H21: 2 | I21: 1 | J21: =E21*F21*$C$6/1000000*(1+(H21=1)*$C$9+(H21=2)*$C$11)*(1+I21*$C$10) -> 16.237134 | K21: 1 | L21: 3.1 | M21: 2 | N21: =CHOOSE(M21,Quesería!$B$26,Quesería!$B$27,Quesería!$B$28,Quesería!$B$29) -> 0.1 | O21: Instrumart, precio de lista. | P21: T13
A22: LSHH-301/303 | B22: Interruptor de nivel alto por vibración (Liquiphant FTL33) | C22: 1 | D22: Tinas TQ-301 y TQ-303, control y tablero | E22: 2 | F22: 436.59 | G22: US$ | H22: 2 | I22: 1 | J22: =E22*F22*$C$6/1000000*(1+(H22=1)*$C$9+(H22=2)*$C$11)*(1+I22*$C$10) -> 3.6611855 | K22: 1 | L22: 3.1 | M22: 2 | N22: =CHOOSE(M22,Quesería!$B$26,Quesería!$B$27,Quesería!$B$28,Quesería!$B$29) -> 0.1 | O22: Instrumart, precio de lista. | P22: T13
A23: TT-301/303 | B23: RTD sanitaria Pt100 con transmisor de 4–20 mA | C23: 1 | D23: Tinas TQ-301 y TQ-303, control y tablero | E23: 2 | F23: 480 | G23: US$ | H23: 2 | I23: 1 | J23: =E23*F23*$C$6/1000000*(1+(H23=1)*$C$9+(H23=2)*$C$11)*(1+I23*$C$10) -> 4.025216 | K23: 1 | L23: 3.1 | M23: 3 | N23: =CHOOSE(M23,Quesería!$B$26,Quesería!$B$27,Quesería!$B$28,Quesería!$B$29) -> 0.15 | O23: Intempco RS80, US$230,50 (Instrumart), más transmisor estimado en US$250. | P23: T13
A24: XV-301/303 | B24: Válvula de mariposa sanitaria DN50 con actuador neumático y posicionador on/off | C24: 1 | D24: Tinas TQ-301 y TQ-303, control y tablero | E24: 2 | F24: 1218.22 | G24: US$ | H24: 2 | I24: 1 | J24: =E24*F24*$C$6/1000000*(1+(H24=1)*$C$9+(H24=2)*$C$11)*(1+I24*$C$10) -> 10.215831 | K24: 1 | L24: 3.1 | M24: 2 | N24: =CHOOSE(M24,Quesería!$B$26,Quesería!$B$27,Quesería!$B$28,Quesería!$B$29) -> 0.1 | O24: Tameson, precio de lista. | P24: T13
A25: TV-301/303 | B25: Válvula de control del agua caliente y fría de la camisa | C25: 1 | D25: Tinas TQ-301 y TQ-303, control y tablero | E25: 2 | F25: 2500 | G25: US$ | H25: 2 | I25: 1 | J25: =E25*F25*$C$6/1000000*(1+(H25=1)*$C$9+(H25=2)*$C$11)*(1+I25*$C$10) -> 20.964667 | K25: 1 | L25: 3.1 | M25: 4 | N25: =CHOOSE(M25,Quesería!$B$26,Quesería!$B$27,Quesería!$B$28,Quesería!$B$29) -> 0.25 | O25: Estimado. | P25: T13
A26: SC-301/303 | B26: Variador de velocidad de las liras de corte y agitación (PowerFlex 525, 7,5 kW) | C26: 1 | D26: Tinas TQ-301 y TQ-303, control y tablero | E26: 2 | F26: 1850 | G26: US$ | H26: 2 | I26: 1 | J26: =E26*F26*$C$6/1000000*(1+(H26=1)*$C$9+(H26=2)*$C$11)*(1+I26*$C$10) -> 15.513853 | K26: 1 | L26: 3.1 | M26: 3 | N26: =CHOOSE(M26,Quesería!$B$26,Quesería!$B$27,Quesería!$B$28,Quesería!$B$29) -> 0.15 | O26: Estimado nuevo; NJT Automation lo publica usado en US$549,99. Las liras y sus motores ya existen. | P26: T13
A27: AT-301/303 | B27: Sensor de coagulación en línea (tipo CoAguLite) con su transmisor | C27: 1 | D27: Tinas TQ-301 y TQ-303, control y tablero | E27: 2 | F27: 6000 | G27: US$ | H27: 1 | I27: 1 | J27: =E27*F27*$C$6/1000000*(1+(H27=1)*$C$9+(H27=2)*$C$11)*(1+I27*$C$10) -> 56.878052 | K27: 1 | L27: 3.1 | M27: 4 | N27: =CHOOSE(M27,Quesería!$B$26,Quesería!$B$27,Quesería!$B$28,Quesería!$B$29) -> 0.25 | O27: Precio a solicitud; usa el PLC y el SCADA de la planta. Estimado. | P27: T13
A28: P-DOS | B28: Bombas dosificadoras de cuajo, cloruro de calcio y cultivo (ProMinent Gamma X) | C28: 1 | D28: Tinas TQ-301 y TQ-303, control y tablero | E28: 3 | F28: 1421 | G28: £ | H28: 2 | I28: 1 | J28: =E28*F28*$C$8/1000000*(1+(H28=1)*$C$9+(H28=2)*$C$11)*(1+I28*$C$10) -> 23.773052 | K28: 1 | L28: 3.1 | M28: 2 | N28: =CHOOSE(M28,Quesería!$B$26,Quesería!$B$27,Quesería!$B$28,Quesería!$B$29) -> 0.1 | O28: TF Pumps, precio de lista. | P28: T13
A29: XV-DOS | B29: Válvulas de destino de la dosificación a cada tina | C29: 1 | D29: Tinas TQ-301 y TQ-303, control y tablero | E29: 6 | F29: 300 | G29: US$ | H29: 2 | I29: 1 | J29: =E29*F29*$C$6/1000000*(1+(H29=1)*$C$9+(H29=2)*$C$11)*(1+I29*$C$10) -> 7.54728 | K29: 1 | L29: 3.1 | M29: 4 | N29: =CHOOSE(M29,Quesería!$B$26,Quesería!$B$27,Quesería!$B$28,Quesería!$B$29) -> 0.25 | O29: Estimado. | P29: T13
A30: BAL-01 | B30: Balanza de ingredientes con salida Ethernet | C30: 1 | D30: Tinas TQ-301 y TQ-303, control y tablero | E30: 1 | F30: 1500 | G30: US$ | H30: 2 | I30: 1 | J30: =E30*F30*$C$6/1000000*(1+(H30=1)*$C$9+(H30=2)*$C$11)*(1+I30*$C$10) -> 6.2894 | K30: 1 | L30: 3.1 | M30: 4 | N30: =CHOOSE(M30,Quesería!$B$26,Quesería!$B$27,Quesería!$B$28,Quesería!$B$29) -> 0.25 | O30: Estimado. | P30: T13
A31: pH-M01 | B31: pHmetro de mesa calibrado para la muestra de cuajada | C31: 1 | D31: Tinas TQ-301 y TQ-303, control y tablero | E31: 1 | F31: 1200 | G31: US$ | H31: 2 | I31: 0 | J31: =E31*F31*$C$6/1000000*(1+(H31=1)*$C$9+(H31=2)*$C$11)*(1+I31*$C$10) -> 4.3752348 | K31: 1 | L31: 3.1 | M31: 4 | N31: =CHOOSE(M31,Quesería!$B$26,Quesería!$B$27,Quesería!$B$28,Quesería!$B$29) -> 0.25 | O31: Estimado. | P31: T13
A32: PLC-300 | B32: Controlador CompactLogix 5380 (5069-L320ER) | C32: 1 | D32: Tinas TQ-301 y TQ-303, control y tablero | E32: 1 | F32: 2199.99 | G32: US$ | H32: 2 | I32: 1 | J32: =E32*F32*$C$6/1000000*(1+(H32=1)*$C$9+(H32=2)*$C$11)*(1+I32*$C$10) -> 9.2244114 | K32: 1 | L32: 3.2 | M32: 3 | N32: =CHOOSE(M32,Quesería!$B$26,Quesería!$B$27,Quesería!$B$28,Quesería!$B$29) -> 0.15 | O32: NJT Automation, reacondicionado; nuevo con el distribuidor. | P32: T13
A33: AI-300 | B33: Módulo de 8 entradas analógicas (5069-IF8) | C33: 1 | D33: Tinas TQ-301 y TQ-303, control y tablero | E33: 3 | F33: 449.99 | G33: US$ | H33: 2 | I33: 1 | J33: =E33*F33*$C$6/1000000*(1+(H33=1)*$C$9+(H33=2)*$C$11)*(1+I33*$C$10) -> 5.6603342 | K33: 1 | L33: 3.2 | M33: 3 | N33: =CHOOSE(M33,Quesería!$B$26,Quesería!$B$27,Quesería!$B$28,Quesería!$B$29) -> 0.15 | O33: NJT Automation. | P33: T13
A34: AO-300 | B34: Módulo de 4 salidas analógicas (5069-OF4) | C34: 1 | D34: Tinas TQ-301 y TQ-303, control y tablero | E34: 2 | F34: 600 | G34: US$ | H34: 2 | I34: 1 | J34: =E34*F34*$C$6/1000000*(1+(H34=1)*$C$9+(H34=2)*$C$11)*(1+I34*$C$10) -> 5.03152 | K34: 1 | L34: 3.2 | M34: 4 | N34: =CHOOSE(M34,Quesería!$B$26,Quesería!$B$27,Quesería!$B$28,Quesería!$B$29) -> 0.25 | O34: Estimado. | P34: T13
A35: DI-300 | B35: Módulo de 16 entradas digitales (5069-IB16) | C35: 1 | D35: Tinas TQ-301 y TQ-303, control y tablero | E35: 2 | F35: 419.99 | G35: US$ | H35: 2 | I35: 1 | J35: =E35*F35*$C$6/1000000*(1+(H35=1)*$C$9+(H35=2)*$C$11)*(1+I35*$C$10) -> 3.5219802 | K35: 1 | L35: 3.2 | M35: 2 | N35: =CHOOSE(M35,Quesería!$B$26,Quesería!$B$27,Quesería!$B$28,Quesería!$B$29) -> 0.1 | O35: NJT Automation, nuevo en caja abierta. | P35: T13
A36: DO-300 | B36: Módulo de 16 salidas digitales (5069-OB16) | C36: 1 | D36: Tinas TQ-301 y TQ-303, control y tablero | E36: 2 | F36: 450 | G36: US$ | H36: 2 | I36: 1 | J36: =E36*F36*$C$6/1000000*(1+(H36=1)*$C$9+(H36=2)*$C$11)*(1+I36*$C$10) -> 3.77364 | K36: 1 | L36: 3.2 | M36: 4 | N36: =CHOOSE(M36,Quesería!$B$26,Quesería!$B$27,Quesería!$B$28,Quesería!$B$29) -> 0.25 | O36: Estimado. | P36: T13
A37: PS-300 | B37: Distribuidor de potencia del bus (5069-FPD) y fuente de 24 V | C37: 1 | D37: Tinas TQ-301 y TQ-303, control y tablero | E37: 1 | F37: 400 | G37: US$ | H37: 2 | I37: 1 | J37: =E37*F37*$C$6/1000000*(1+(H37=1)*$C$9+(H37=2)*$C$11)*(1+I37*$C$10) -> 1.6771733 | K37: 1 | L37: 3.2 | M37: 4 | N37: =CHOOSE(M37,Quesería!$B$26,Quesería!$B$27,Quesería!$B$28,Quesería!$B$29) -> 0.25 | O37: Estimado. | P37: T13
A38: TC-300 | B38: Tablero de control en acero inoxidable: protecciones, borneras, cableado y canalización | C38: 1 | D38: Tinas TQ-301 y TQ-303, control y tablero | E38: 1 | F38: 25000000 | G38: $ | H38: 0 | I38: 1 | J38: =E38*F38*1/1000000*(1+(H38=1)*$C$9+(H38=2)*$C$11)*(1+I38*$C$10) -> 28.75 | K38: 1 | L38: 3.1 | M38: 4 | N38: =CHOOSE(M38,Quesería!$B$26,Quesería!$B$27,Quesería!$B$28,Quesería!$B$29) -> 0.25 | O38: Estimado de un tablerista nacional. | P38: T13
A39: FT-302 | B39: Caudalímetro electromagnético sanitario DN50 (Promag H 100) | C39: 1 | D39: Tina TQ-302 del doble crema | E39: 1 | F39: 4816.4 | G39: US$ | H39: 2 | I39: 1 | J39: =E39*F39*$C$6/1000000*(1+(H39=1)*$C$9+(H39=2)*$C$11)*(1+I39*$C$10) -> 20.194844 | K39: 1 | L39: 3.1 | M39: 2 | N39: =CHOOSE(M39,Quesería!$B$26,Quesería!$B$27,Quesería!$B$28,Quesería!$B$29) -> 0.1 | O39: Instrumart. | P39: T2
A40: LT-302 | B40: Radar de nivel sanitario (Micropilot FMR43) | C40: 1 | D40: Tina TQ-302 del doble crema | E40: 1 | F40: 1936.25 | G40: US$ | H40: 2 | I40: 1 | J40: =E40*F40*$C$6/1000000*(1+(H40=1)*$C$9+(H40=2)*$C$11)*(1+I40*$C$10) -> 8.1185672 | K40: 1 | L40: 3.1 | M40: 2 | N40: =CHOOSE(M40,Quesería!$B$26,Quesería!$B$27,Quesería!$B$28,Quesería!$B$29) -> 0.1 | O40: Instrumart. | P40: T2
A41: LSHH-302 | B41: Interruptor de nivel alto (Liquiphant FTL33) | C41: 1 | D41: Tina TQ-302 del doble crema | E41: 1 | F41: 436.59 | G41: US$ | H41: 2 | I41: 1 | J41: =E41*F41*$C$6/1000000*(1+(H41=1)*$C$9+(H41=2)*$C$11)*(1+I41*$C$10) -> 1.8305928 | K41: 1 | L41: 3.1 | M41: 2 | N41: =CHOOSE(M41,Quesería!$B$26,Quesería!$B$27,Quesería!$B$28,Quesería!$B$29) -> 0.1 | O41: Instrumart. | P41: T2
A42: TT-302 | B42: RTD sanitaria Pt100 con transmisor | C42: 1 | D42: Tina TQ-302 del doble crema | E42: 1 | F42: 480 | G42: US$ | H42: 2 | I42: 1 | J42: =E42*F42*$C$6/1000000*(1+(H42=1)*$C$9+(H42=2)*$C$11)*(1+I42*$C$10) -> 2.012608 | K42: 1 | L42: 3.1 | M42: 3 | N42: =CHOOSE(M42,Quesería!$B$26,Quesería!$B$27,Quesería!$B$28,Quesería!$B$29) -> 0.15 | O42: Intempco RS80 más transmisor estimado. | P42: T2
A43: XV-302 | B43: Válvula de mariposa sanitaria DN50 con actuador neumático | C43: 1 | D43: Tina TQ-302 del doble crema | E43: 1 | F43: 1218.22 | G43: US$ | H43: 2 | I43: 1 | J43: =E43*F43*$C$6/1000000*(1+(H43=1)*$C$9+(H43=2)*$C$11)*(1+I43*$C$10) -> 5.1079153 | K43: 1 | L43: 3.1 | M43: 2 | N43: =CHOOSE(M43,Quesería!$B$26,Quesería!$B$27,Quesería!$B$28,Quesería!$B$29) -> 0.1 | O43: Tameson. | P43: T2
A44: TV-302 | B44: Válvula de control de la camisa | C44: 1 | D44: Tina TQ-302 del doble crema | E44: 1 | F44: 2500 | G44: US$ | H44: 2 | I44: 1 | J44: =E44*F44*$C$6/1000000*(1+(H44=1)*$C$9+(H44=2)*$C$11)*(1+I44*$C$10) -> 10.482333 | K44: 1 | L44: 3.1 | M44: 4 | N44: =CHOOSE(M44,Quesería!$B$26,Quesería!$B$27,Quesería!$B$28,Quesería!$B$29) -> 0.25 | O44: Estimado. | P44: T2
A45: E18 | B45: Controladora de peso con detector de metales (estación E18) | C45: 1 | D45: Estación E18 de inspección | E45: 1 | F45: =Cotizaciones!$B$13 -> 7000 | G45: US$ | H45: 1 | I45: 1 | J45: =E45*F45*$C$6/1000000*(1+(H45=1)*$C$9+(H45=2)*$C$11)*(1+I45*$C$10) -> 33.178864 | K45: 1 | L45: 3.1 | M45: 2 | N45: =CHOOSE(M45,Quesería!$B$26,Quesería!$B$27,Quesería!$B$28,Quesería!$B$29) -> 0.1 | O45: Hoja Cotizaciones. | P45: E18
A46: AT-GR | B46: Analizador de grasa en línea para la estandarización (NIR) | C46: 1 | D46: Estandarización de grasa (recepción) | E46: 1 | F46: 28000 | G46: US$ | H46: 2 | I46: 1 | J46: =E46*F46*$C$6/1000000*(1+(H46=1)*$C$9+(H46=2)*$C$11)*(1+I46*$C$10) -> 117.40213 | K46: =Quesería!$B$16 -> 0.36 | L46: 3.1 | M46: 4 | N46: =CHOOSE(M46,Quesería!$B$26,Quesería!$B$27,Quesería!$B$28,Quesería!$B$29) -> 0.25 | O46: FOSS, Anton Paar y Maselli: precio a solicitud. Estimado. | P46: GR
A47: FV-GR | B47: Válvula de remezcla de crema para la estandarización | C47: 1 | D47: Estandarización de grasa (recepción) | E47: 1 | F47: 3000 | G47: US$ | H47: 2 | I47: 1 | J47: =E47*F47*$C$6/1000000*(1+(H47=1)*$C$9+(H47=2)*$C$11)*(1+I47*$C$10) -> 12.5788 | K47: =Quesería!$B$16 -> 0.36 | L47: 3.1 | M47: 4 | N47: =CHOOSE(M47,Quesería!$B$26,Quesería!$B$27,Quesería!$B$28,Quesería!$B$29) -> 0.25 | O47: Estimado. | P47: GR
A48: IGN-P | B48: Ignition Platform (servidor) | C48: 1 | D48: SCADA, historiador y MES | E48: 1 | F48: 1200 | G48: US$ | H48: 0 | I48: 0 | J48: =E48*F48*$C$6/1000000*(1+(H48=1)*$C$9+(H48=2)*$C$11)*(1+I48*$C$10) -> 3.804552 | K48: =Quesería!$B$16 -> 0.36 | L48: 3.3 | M48: 2 | N48: =CHOOSE(M48,Quesería!$B$26,Quesería!$B$27,Quesería!$B$28,Quesería!$B$29) -> 0.1 | O48: Inductive Automation, lista 2026 (G2). | P48: SC
A49: IGN-A | B49: Ignition Application Building Suite (pantallas, alarmas, reportes) | C49: 1 | D49: SCADA, historiador y MES | E49: 1 | F49: 13500 | G49: US$ | H49: 0 | I49: 0 | J49: =E49*F49*$C$6/1000000*(1+(H49=1)*$C$9+(H49=2)*$C$11)*(1+I49*$C$10) -> 42.80121 | K49: =Quesería!$B$16 -> 0.36 | L49: 3.3 | M49: 2 | N49: =CHOOSE(M49,Quesería!$B$26,Quesería!$B$27,Quesería!$B$28,Quesería!$B$29) -> 0.1 | O49: Inductive Automation, lista 2026 (G2). | P49: SC
A50: IGN-H | B50: Ignition Industrial Historian | C50: 1 | D50: SCADA, historiador y MES | E50: 1 | F50: 3500 | G50: US$ | H50: 0 | I50: 0 | J50: =E50*F50*$C$6/1000000*(1+(H50=1)*$C$9+(H50=2)*$C$11)*(1+I50*$C$10) -> 11.09661 | K50: =Quesería!$B$16 -> 0.36 | L50: 3.3 | M50: 2 | N50: =CHOOSE(M50,Quesería!$B$26,Quesería!$B$27,Quesería!$B$28,Quesería!$B$29) -> 0.1 | O50: Inductive Automation, lista 2026 (G2). | P50: SC
A51: SRV-01 | B51: Servidor del SCADA y el MES (Dell PowerEdge T160) con soporte de 3 años | C51: 1 | D51: SCADA, historiador y MES | E51: 1 | F51: 2500 | G51: US$ | H51: 2 | I51: 1 | J51: =E51*F51*$C$6/1000000*(1+(H51=1)*$C$9+(H51=2)*$C$11)*(1+I51*$C$10) -> 10.482333 | K51: =Quesería!$B$16 -> 0.36 | L51: 2.5 | M51: 3 | N51: =CHOOSE(M51,Quesería!$B$26,Quesería!$B$27,Quesería!$B$28,Quesería!$B$29) -> 0.15 | O51: SHI: configuración base más soporte ProSupport de 3 años (US$1.279). | P51: SC
A52: SW-01/02 | B52: Switch industrial administrable | C52: 1 | D52: SCADA, historiador y MES | E52: 2 | F52: 1200 | G52: US$ | H52: 2 | I52: 1 | J52: =E52*F52*$C$6/1000000*(1+(H52=1)*$C$9+(H52=2)*$C$11)*(1+I52*$C$10) -> 10.06304 | K52: =Quesería!$B$16 -> 0.36 | L52: 2.5 | M52: 4 | N52: =CHOOSE(M52,Quesería!$B$26,Quesería!$B$27,Quesería!$B$28,Quesería!$B$29) -> 0.25 | O52: Estimado. | P52: SC
A53: AN-01 | B53: Analizador de leche y suero por ultrasonido (grasa, proteína, sólidos no grasos y densidad) para el balance de sólidos por lote | C53: 1 | D53: SCADA, historiador y MES | E53: 1 | F53: 1139.3 | G53: € | H53: 1 | I53: 0 | J53: =E53*F53*$C$7/1000000*(1+(H53=1)*$C$9+(H53=2)*$C$11)*(1+I53*$C$10) -> 5.2873432 | K53: 1 | L53: 5.1 | M53: 2 | N53: =CHOOSE(M53,Quesería!$B$26,Quesería!$B$27,Quesería!$B$28,Quesería!$B$29) -> 0.1 | O53: Milkotester Master Pro, lista de Serowar 2026; calibración para suero. | P53: SC
A54: FW-01 | B54: Firewall industrial entre la red de planta y la del ERP (zonas y conductos de IEC 62443), con un año de protección | C54: 1 | D54: SCADA, historiador y MES | E54: 1 | F54: 3690.64 | G54: US$ | H54: 2 | I54: 1 | J54: =E54*F54*$C$6/1000000*(1+(H54=1)*$C$9+(H54=2)*$C$11)*(1+I54*$C$10) -> 15.474608 | K54: =Quesería!$B$16 -> 0.36 | L54: 2.5 | M54: 2 | N54: =CHOOSE(M54,Quesería!$B$26,Quesería!$B$27,Quesería!$B$28,Quesería!$B$29) -> 0.1 | O54: FortiGate Rugged 60F con FortiCare y UTP por un año (FGR-60F-BDL-950-12), lista de AVFirewalls 2026. | P54: SC
A55: HMI-01/02 | B55: Estación de operación de acero inoxidable en la sala de tinas | C55: 1 | D55: SCADA, historiador y MES | E55: 2 | F55: 2500 | G55: US$ | H55: 2 | I55: 1 | J55: =E55*F55*$C$6/1000000*(1+(H55=1)*$C$9+(H55=2)*$C$11)*(1+I55*$C$10) -> 20.964667 | K55: 1 | L55: 3.3 | M55: 4 | N55: =CHOOSE(M55,Quesería!$B$26,Quesería!$B$27,Quesería!$B$28,Quesería!$B$29) -> 0.25 | O55: Estimado. | P55: SC
A56: UPS-01 | B56: UPS del servidor y del tablero | C56: 1 | D56: SCADA, historiador y MES | E56: 1 | F56: 800 | G56: US$ | H56: 2 | I56: 1 | J56: =E56*F56*$C$6/1000000*(1+(H56=1)*$C$9+(H56=2)*$C$11)*(1+I56*$C$10) -> 3.3543467 | K56: =Quesería!$B$16 -> 0.36 | L56: 2.5 | M56: 4 | N56: =CHOOSE(M56,Quesería!$B$26,Quesería!$B$27,Quesería!$B$28,Quesería!$B$29) -> 0.25 | O56: Estimado. | P56: SC
A57: MON-AT | B57: Monitoreo de estado de equipos antiguos (prensa, termoformadora, empacadoras, marmitas): transformador de corriente y contacto de marcha | C57: 1 | D57: SCADA, historiador y MES | E57: 6 | F57: 180 | G57: US$ | H57: 2 | I57: 1 | J57: =E57*F57*$C$6/1000000*(1+(H57=1)*$C$9+(H57=2)*$C$11)*(1+I57*$C$10) -> 4.528368 | K57: 1 | L57: 5.1 | M57: 4 | N57: =CHOOSE(M57,Quesería!$B$26,Quesería!$B$27,Quesería!$B$28,Quesería!$B$29) -> 0.25 | O57: Estimado. | P57: SC
A58: RIO-01/02 | B58: Módulo de E/S remotas Ethernet para el monitoreo de equipos antiguos | C58: 1 | D58: SCADA, historiador y MES | E58: 2 | F58: 350 | G58: US$ | H58: 2 | I58: 1 | J58: =E58*F58*$C$6/1000000*(1+(H58=1)*$C$9+(H58=2)*$C$11)*(1+I58*$C$10) -> 2.9350533 | K58: 1 | L58: 5.1 | M58: 3 | N58: =CHOOSE(M58,Quesería!$B$26,Quesería!$B$27,Quesería!$B$28,Quesería!$B$29) -> 0.15 | O58: Precio de referencia de módulos Ethernet de 8 entradas digitales. | P58: SC
A59: HI-306 | B59: Hiladora-moldeadora continua de 300 kg/h (E13), con su PLC y protocolo abierto | C59: 2 | D59: Hiladora E13 | E59: 1 | F59: =Cotizaciones!$F$14*1000000 -> 322600000 | G59: $ | H59: 0 | I59: 0 | J59: =E59*F59/1000000 -> 322.6 | K59: 1 | L59: 3.1 | M59: 3 | N59: =CHOOSE(M59,Quesería!$B$26,Quesería!$B$27,Quesería!$B$28,Quesería!$B$29) -> 0.15 | O59: Hoja Cotizaciones. | P59: HI
A60: CIP-01 | B60: CIP automático del circuito de quesos | C60: 2 | D60: CIP del circuito de quesos | E60: 1 | F60: =Cotizaciones!$F$15*1000000 -> 1.0666667e+08 | G60: $ | H60: 0 | I60: 0 | J60: =E60*F60/1000000 -> 106.66667 | K60: 1 | L60: 3.1 | M60: 3 | N60: =CHOOSE(M60,Quesería!$B$26,Quesería!$B$27,Quesería!$B$28,Quesería!$B$29) -> 0.15 | O60: Hoja Cotizaciones. | P60: CIP
A61: HE-SU | B61: Enfriador de placas y tanque pulmón del suero | C61: 2 | D61: Suero | E61: 1 | F61: =Cotizaciones!$F$21*1000000 -> 80000000 | G61: $ | H61: 0 | I61: 0 | J61: =E61*F61/1000000 -> 80 | K61: 1 | L61: 3.1 | M61: 4 | N61: =CHOOSE(M61,Quesería!$B$26,Quesería!$B$27,Quesería!$B$28,Quesería!$B$29) -> 0.25 | O61: Hoja Cotizaciones. | P61: SU
A62: IO-E2 | B62: Módulos de E/S para el CIP y el suero (5069: 1 IF8, 1 OF4, 2 IB16, 1 OB16) | C62: 2 | D62: Instrumentación y control de la etapa 2 | E62: 1 | F62: 2800 | G62: US$ | H62: 2 | I62: 1 | J62: =E62*F62*$C$6/1000000*(1+(H62=1)*$C$9+(H62=2)*$C$11)*(1+I62*$C$10) -> 11.740213 | K62: 1 | L62: 3.2 | M62: 3 | N62: =CHOOSE(M62,Quesería!$B$26,Quesería!$B$27,Quesería!$B$28,Quesería!$B$29) -> 0.15 | O62: NJT Automation y estimados, como en la etapa 1. | P62: E2
A63: TC-E2 | B63: Ampliación del tablero de control | C63: 2 | D63: Instrumentación y control de la etapa 2 | E63: 1 | F63: 8000000 | G63: $ | H63: 0 | I63: 1 | J63: =E63*F63*1/1000000*(1+(H63=1)*$C$9+(H63=2)*$C$11)*(1+I63*$C$10) -> 9.2 | K63: 1 | L63: 3.1 | M63: 4 | N63: =CHOOSE(M63,Quesería!$B$26,Quesería!$B$27,Quesería!$B$28,Quesería!$B$29) -> 0.25 | O63: Estimado. | P63: E2
A64: FT/LT/TT-SU | B64: Caudal, nivel y temperatura del suero | C64: 2 | D64: Instrumentación y control de la etapa 2 | E64: 1 | F64: 7200 | G64: US$ | H64: 2 | I64: 1 | J64: =E64*F64*$C$6/1000000*(1+(H64=1)*$C$9+(H64=2)*$C$11)*(1+I64*$C$10) -> 30.18912 | K64: 1 | L64: 3.1 | M64: 3 | N64: =CHOOSE(M64,Quesería!$B$26,Quesería!$B$27,Quesería!$B$28,Quesería!$B$29) -> 0.15 | O64: Mismos instrumentos de la etapa 1 en versión básica. | P64: E2
A65: TT/AT-315 | B65: Temperatura y concentración de la salmuera (E15) | C65: 2 | D65: Instrumentación y control de la etapa 2 | E65: 1 | F65: 2000 | G65: US$ | H65: 2 | I65: 1 | J65: =E65*F65*$C$6/1000000*(1+(H65=1)*$C$9+(H65=2)*$C$11)*(1+I65*$C$10) -> 8.3858667 | K65: 1 | L65: 3.1 | M65: 4 | N65: =CHOOSE(M65,Quesería!$B$26,Quesería!$B$27,Quesería!$B$28,Quesería!$B$29) -> 0.25 | O65: Estimado. | P65: E2
A66: CP-01 | B66: Celda de paletizado con cobot, llave en mano (brazo, pinza, base, transportador y seguridad) | C66: 3 | D66: Celda de paletizado (etapa 3, fuera de la evaluación) | E66: 1 | F66: 110000 | G66: US$ | H66: 1 | I66: 1 | J66: =E66*F66*$C$6/1000000*(1+(H66=1)*$C$9+(H66=2)*$C$11)*(1+I66*$C$10) -> 521.38215 | K66: 1 | L66: 4.2 | M66: 3 | N66: =CHOOSE(M66,Quesería!$B$26,Quesería!$B$27,Quesería!$B$28,Quesería!$B$29) -> 0.15 | O66: Standard Bots (2026): celdas con cobot de US$60.000 a 160.000; brazo desde US$39.500. | P66: CP
A67: Total del BOM | J67: =SUM(J14:J66) -> 1756.245
A68: Hiladora, CIP y suero toman su valor de la hoja Cotizaciones, que ya incluye importación e instalación. Las licencias de Ignition no pagan importación ni instalación. Lo que es común a la planta lo paga la quesería en proporción a su leche (36 % de la recepción): las herramientas de mantenimiento, la estandarización de grasa y la plataforma del SCADA (licencias, servidor y red), que después reciben las demás líneas sin comprarla de nuevo. La señal de cada instrumento y actuador está en la lista de señales del paquete 3.1; el número de módulos de E/S cubre las señales con una reserva cercana al 25 %.
A70: Del BOM a la inversión de la quesería
A71: Rubro | C71: Etapa | D71: Rubro en la hoja Quesería | E71: Ítems | F71: Valor del BOM ($ M) | G71: Madurez ponderada | H71: Reparto a la quesería | I71: A la quesería ($ M) | J71: % imprevistos ponderado | K71: Valor en la hoja Quesería ($ M) | L71: Diferencia
A72: Etapa 0: herramientas de mantenimiento y medición | C72: =Quesería!B70 -> 0 | D72: Diagnóstico de la planta, plan de mantenimiento y orden de la operación | E72: =COUNTIF($P$14:$P$66,"D0") -> 6 | F72: =SUMIF($P$14:$P$66,"D0",$J$14:$J$66) -> 56.872528 | G72: =IF(F72>0,SUMPRODUCT(($P$14:$P$66="D0")*$J$14:$J$66*$M$14:$M$66)/F72,0) -> 3.5770102 | H72: =IF(F72>0,SUMPRODUCT(($P$14:$P$66="D0")*$J$14:$J$66*$K$14:$K$66)/F72,0) -> 0.36 | I72: =F72*H72 -> 20.47411 | J72: =IF(F72>0,SUMPRODUCT(($P$14:$P$66="D0")*$J$14:$J$66*$N$14:$N$66)/F72,0) -> 0.21827576 | K72: =Quesería!F70 -> 20.47411 | L72: =I72-K72 -> 0
A73: Tinas TQ-301 y TQ-303, control y tablero | C73: =Quesería!B71 -> 1 | D73: Automatización de 2 tinas: liras con variador, sensor de coagulación, dosificación | E73: =COUNTIF($P$14:$P$66,"T13") -> 19 | F73: =SUMIF($P$14:$P$66,"T13",$J$14:$J$66) -> 267.50965 | G73: =IF(F73>0,SUMPRODUCT(($P$14:$P$66="T13")*$J$14:$J$66*$M$14:$M$66)/F73,0) -> 3.1401374 | H73: =IF(F73>0,SUMPRODUCT(($P$14:$P$66="T13")*$J$14:$J$66*$K$14:$K$66)/F73,0) -> 1 | I73: =F73*H73 -> 267.50965 | J73: =IF(F73>0,SUMPRODUCT(($P$14:$P$66="T13")*$J$14:$J$66*$N$14:$N$66)/F73,0) -> 0.18229324 | K73: =Quesería!F71 -> 267.50965 | L73: =I73-K73 -> 0
A74: Tina TQ-302 del doble crema | C74: =Quesería!B72 -> 1 | D74: Tina del doble crema: medición y mando básicos (caudal, nivel, temperatura, válvula y bomba) | E74: =COUNTIF($P$14:$P$66,"T2") -> 6 | F74: =SUMIF($P$14:$P$66,"T2",$J$14:$J$66) -> 47.746861 | G74: =IF(F74>0,SUMPRODUCT(($P$14:$P$66="T2")*$J$14:$J$66*$M$14:$M$66)/F74,0) -> 2.4812311 | H74: =IF(F74>0,SUMPRODUCT(($P$14:$P$66="T2")*$J$14:$J$66*$K$14:$K$66)/F74,0) -> 1 | I74: =F74*H74 -> 47.746861 | J74: =IF(F74>0,SUMPRODUCT(($P$14:$P$66="T2")*$J$14:$J$66*$N$14:$N$66)/F74,0) -> 0.13503854 | K74: =Quesería!F72 -> 47.746861 | L74: =I74-K74 -> 0
A75: Estación E18 de inspección | C75: =Quesería!B73 -> 1 | D75: Controladora de peso y detector de metales en la salida del empaque | E75: =COUNTIF($P$14:$P$66,"E18") -> 1 | F75: =SUMIF($P$14:$P$66,"E18",$J$14:$J$66) -> 33.178864 | G75: =IF(F75>0,SUMPRODUCT(($P$14:$P$66="E18")*$J$14:$J$66*$M$14:$M$66)/F75,0) -> 2 | H75: =IF(F75>0,SUMPRODUCT(($P$14:$P$66="E18")*$J$14:$J$66*$K$14:$K$66)/F75,0) -> 1 | I75: =F75*H75 -> 33.178864 | J75: =IF(F75>0,SUMPRODUCT(($P$14:$P$66="E18")*$J$14:$J$66*$N$14:$N$66)/F75,0) -> 0.1 | K75: =Quesería!F73 -> 33.178864 | L75: =I75-K75 -> 0
A76: Estandarización de grasa (recepción) | C76: =Quesería!B74 -> 1 | D76: Medidor de grasa en línea en la estandarización | E76: =COUNTIF($P$14:$P$66,"GR") -> 2 | F76: =SUMIF($P$14:$P$66,"GR",$J$14:$J$66) -> 129.98093 | G76: =IF(F76>0,SUMPRODUCT(($P$14:$P$66="GR")*$J$14:$J$66*$M$14:$M$66)/F76,0) -> 4 | H76: =IF(F76>0,SUMPRODUCT(($P$14:$P$66="GR")*$J$14:$J$66*$K$14:$K$66)/F76,0) -> 0.36 | I76: =F76*H76 -> 46.793136 | J76: =IF(F76>0,SUMPRODUCT(($P$14:$P$66="GR")*$J$14:$J$66*$N$14:$N$66)/F76,0) -> 0.25 | K76: =Quesería!F74 -> 46.793136 | L76: =I76-K76 -> 0
A77: SCADA, historiador y MES | C77: =Quesería!B75 -> 1 | D77: SCADA, historiador y MES ligero de la quesería (red, servidor, licencias e instrumentación) | E77: =COUNTIF($P$14:$P$66,"SC") -> 11 | F77: =SUMIF($P$14:$P$66,"SC",$J$14:$J$66) -> 130.79213 | G77: =IF(F77>0,SUMPRODUCT(($P$14:$P$66="SC")*$J$14:$J$66*$M$14:$M$66)/F77,0) -> 2.6975819 | H77: =IF(F77>0,SUMPRODUCT(($P$14:$P$66="SC")*$J$14:$J$66*$K$14:$K$66)/F77,0) -> 0.5249784 | I77: =F77*H77 -> 68.663043 | J77: =IF(F77>0,SUMPRODUCT(($P$14:$P$66="SC")*$J$14:$J$66*$N$14:$N$66)/F77,0) -> 0.14975401 | K77: =Quesería!F75 -> 68.663043 | L77: =I77-K77 -> 0
A78: Hiladora E13 | C78: =Quesería!B84 -> 2 | D78: Hiladora-moldeadora continua para doble crema y mozzarella | E78: =COUNTIF($P$14:$P$66,"HI") -> 1 | F78: =SUMIF($P$14:$P$66,"HI",$J$14:$J$66) -> 322.6 | G78: =IF(F78>0,SUMPRODUCT(($P$14:$P$66="HI")*$J$14:$J$66*$M$14:$M$66)/F78,0) -> 3 | H78: =IF(F78>0,SUMPRODUCT(($P$14:$P$66="HI")*$J$14:$J$66*$K$14:$K$66)/F78,0) -> 1 | I78: =F78*H78 -> 322.6 | J78: =IF(F78>0,SUMPRODUCT(($P$14:$P$66="HI")*$J$14:$J$66*$N$14:$N$66)/F78,0) -> 0.15 | K78: =Quesería!F84 -> 322.6 | L78: =I78-K78 -> 0
A79: CIP del circuito de quesos | C79: =Quesería!B85 -> 2 | D79: CIP automático del circuito de quesos | E79: =COUNTIF($P$14:$P$66,"CIP") -> 1 | F79: =SUMIF($P$14:$P$66,"CIP",$J$14:$J$66) -> 106.66667 | G79: =IF(F79>0,SUMPRODUCT(($P$14:$P$66="CIP")*$J$14:$J$66*$M$14:$M$66)/F79,0) -> 3 | H79: =IF(F79>0,SUMPRODUCT(($P$14:$P$66="CIP")*$J$14:$J$66*$K$14:$K$66)/F79,0) -> 1 | I79: =F79*H79 -> 106.66667 | J79: =IF(F79>0,SUMPRODUCT(($P$14:$P$66="CIP")*$J$14:$J$66*$N$14:$N$66)/F79,0) -> 0.15 | K79: =Quesería!F85 -> 106.66667 | L79: =I79-K79 -> 0
A80: Suero | C80: =Quesería!B86 -> 2 | D80: Enfriador de placas y tanque pulmón del suero (opción, fuera de la oferta) | E80: =COUNTIF($P$14:$P$66,"SU") -> 1 | F80: =SUMIF($P$14:$P$66,"SU",$J$14:$J$66) -> 80 | G80: =IF(F80>0,SUMPRODUCT(($P$14:$P$66="SU")*$J$14:$J$66*$M$14:$M$66)/F80,0) -> 4 | H80: 0 | I80: =F80*H80 -> 0 | J80: =IF(F80>0,SUMPRODUCT(($P$14:$P$66="SU")*$J$14:$J$66*$N$14:$N$66)/F80,0) -> 0.25 | K80: =Quesería!F86 -> 0 | L80: =I80-K80 -> 0
A81: Instrumentación y control de la etapa 2 | C81: =Quesería!B87 -> 2 | D81: Instrumentación y control de la etapa 2: E/S del PLC, ampliación del tablero, salmuera y suero | E81: =COUNTIF($P$14:$P$66,"E2") -> 4 | F81: =SUMIF($P$14:$P$66,"E2",$J$14:$J$66) -> 59.5152 | G81: =IF(F81>0,SUMPRODUCT(($P$14:$P$66="E2")*$J$14:$J$66*$M$14:$M$66)/F81,0) -> 3.2954853 | H81: =IF(F81>0,SUMPRODUCT(($P$14:$P$66="E2")*$J$14:$J$66*$K$14:$K$66)/F81,0) -> 1 | I81: =F81*H81 -> 59.5152 | J81: =IF(F81>0,SUMPRODUCT(($P$14:$P$66="E2")*$J$14:$J$66*$N$14:$N$66)/F81,0) -> 0.17954853 | K81: =Quesería!F87 -> 59.5152 | L81: =I81-K81 -> 0
A82: Celda de paletizado (etapa 3, fuera de la evaluación) | C82: 3 | D82: Fuera de la evaluación: se valora para la decisión de la etapa 3. | E82: =COUNTIF($P$14:$P$66,"CP") -> 1 | F82: =SUMIF($P$14:$P$66,"CP",$J$14:$J$66) -> 521.38215 | G82: =IF(F82>0,SUMPRODUCT(($P$14:$P$66="CP")*$J$14:$J$66*$M$14:$M$66)/F82,0) -> 3 | J82: =IF(F82>0,SUMPRODUCT(($P$14:$P$66="CP")*$J$14:$J$66*$N$14:$N$66)/F82,0) -> 0.15
A83: Total que entra a la inversión (sin imprevistos) | I83: =SUM(I72:I82) -> 973.14753 | K83: =SUM(K72:K82) -> 973.14753
A84: Comprobación: BOM que entra a la quesería − rubros de equipos de la hoja Quesería ($ M) | L84: =SUM(L72:L82) -> 0
A85: El reparto de cada rubro pondera la parte de la quesería de cada ítem. Los imprevistos de cada rubro se ponderan con la madurez del precio de cada ítem; la hoja Quesería toma del BOM la madurez ponderada y el porcentaje de imprevistos de cada rubro.

Sheet Escenarios
A1: Escenarios de la oferta
A2: La misma evaluación de la hoja Quesería con los supuestos que más mueven el resultado. La columna Oferta reproduce la hoja Quesería. Los flujos de cada escenario están agrupados debajo: se abren con el signo + de la izquierda.
A4: Qué cambia en cada escenario
A5: Supuesto | B5: Oferta | C5: Conservador | D5: Conservador con compuerta | E5: Sin arranque en 2027 | F5: Sin reubicación del personal | G5: Beneficios −20 % | H5: Beneficios +20 % | I5: Inversión +20 % | J5: Inversión −20 % | K5: Costos operativos +30 % | L5: Costos operativos −30 % | M5: Inflación del consenso | N5: Inflación persistente | O5: Salario mínimo 2027: 7 % | P5: Salario mínimo 2027: 10 % | Q5: Renta 30 % | R5: Crédito ordinario | S5: Garantía del FNG | T5: Sin crédito fiscal por innovación | U5: Sin las dos gestiones | V5: Adverso combinado | W5: Sin herramientas | X5: Con el costo de capital del proyecto | Y5: Solo etapas 0 y 1 | Z5: Sin el contrato de la cadena | AA5: Cadena sin pronto pago | AB5: Con la opción del suero a $45/kg | AC5: Enfriador del suero sin contrato | AD5: Opción del suero sin descuento ambiental
A6: Horas extra restantes que elimina la hiladora (1 = se cuentan) | B6: 1 | C6: 1 | D6: 1 | E6: 1 | F6: 1 | G6: 1 | H6: 1 | I6: 1 | J6: 1 | K6: 1 | L6: 1 | M6: 1 | N6: 1 | O6: 1 | P6: 1 | Q6: 1 | R6: 1 | S6: 1 | T6: 1 | U6: 1 | V6: 1 | W6: 1 | X6: 1 | Y6: 1 | Z6: 1 | AA6: 1 | AB6: 1 | AC6: 1 | AD6: 1
A7: Descuento ambiental del enfriador del suero (1 = se toma, si se compra) | B7: 1 | C7: 0 | D7: 0 | E7: 1 | F7: 1 | G7: 1 | H7: 1 | I7: 1 | J7: 1 | K7: 1 | L7: 1 | M7: 1 | N7: 1 | O7: 1 | P7: 1 | Q7: 1 | R7: 1 | S7: 1 | T7: 1 | U7: 1 | V7: 1 | W7: 1 | X7: 1 | Y7: 1 | Z7: 1 | AA7: 1 | AB7: 1 | AC7: 1 | AD7: 0
A8: Valor de los equipos al año 10 (1 = se cuenta) | B8: 1 | C8: 0 | D8: 0 | E8: 1 | F8: 1 | G8: 1 | H8: 1 | I8: 1 | J8: 1 | K8: 1 | L8: 1 | M8: 1 | N8: 1 | O8: 1 | P8: 1 | Q8: 1 | R8: 1 | S8: 1 | T8: 1 | U8: 1 | V8: 1 | W8: 1 | X8: 1 | Y8: 1 | Z8: 1 | AA8: 1 | AB8: 1 | AC8: 1 | AD8: 1
A9: Reubicación de los 2 operarios del hilado (1 = se cuenta) | B9: 1 | C9: 1 | D9: 1 | E9: 1 | F9: 0 | G9: 1 | H9: 1 | I9: 1 | J9: 1 | K9: 1 | L9: 1 | M9: 1 | N9: 1 | O9: 1 | P9: 1 | Q9: 1 | R9: 1 | S9: 1 | T9: 1 | U9: 1 | V9: 1 | W9: 1 | X9: 1 | Y9: 1 | Z9: 1 | AA9: 1 | AB9: 1 | AC9: 1 | AD9: 1
A10: Factor de beneficios | B10: 1 | C10: 1 | D10: 1 | E10: 1 | F10: 1 | G10: 0.8 | H10: 1.2 | I10: 1 | J10: 1 | K10: 1 | L10: 1 | M10: 1 | N10: 1 | O10: 1 | P10: 1 | Q10: 1 | R10: 1 | S10: 1 | T10: 1 | U10: 1 | V10: 0.8 | W10: 1 | X10: 1 | Y10: 1 | Z10: 1 | AA10: 1 | AB10: 1 | AC10: 1 | AD10: 1
A11: Factor de inversión | B11: 1 | C11: 1 | D11: 1 | E11: 1 | F11: 1 | G11: 1 | H11: 1 | I11: 1.2 | J11: 0.8 | K11: 1 | L11: 1 | M11: 1 | N11: 1 | O11: 1 | P11: 1 | Q11: 1 | R11: 1 | S11: 1 | T11: 1 | U11: 1 | V11: 1.2 | W11: 1 | X11: 1 | Y11: 1 | Z11: 1 | AA11: 1 | AB11: 1 | AC11: 1 | AD11: 1
A12: Factor de costos operativos nuevos | B12: 1 | C12: 1 | D12: 1 | E12: 1 | F12: 1 | G12: 1 | H12: 1 | I12: 1 | J12: 1 | K12: 1.3 | L12: 0.7 | M12: 1 | N12: 1 | O12: 1 | P12: 1 | Q12: 1 | R12: 1 | S12: 1 | T12: 1 | U12: 1 | V12: 1.3 | W12: 1 | X12: 1 | Y12: 1 | Z12: 1 | AA12: 1 | AB12: 1 | AC12: 1 | AD12: 1
A13: Garantía del crédito (0 = prenda sobre los equipos; 1 = FNG) | B13: =Quesería!$B$49 -> 0 | C13: 1 | D13: 1 | E13: =Quesería!$B$49 -> 0 | F13: =Quesería!$B$49 -> 0 | G13: =Quesería!$B$49 -> 0 | H13: =Quesería!$B$49 -> 0 | I13: =Quesería!$B$49 -> 0 | J13: =Quesería!$B$49 -> 0 | K13: =Quesería!$B$49 -> 0 | L13: =Quesería!$B$49 -> 0 | ... R13: =Quesería!$B$49 -> 0 | S13: 1 | T13: =Quesería!$B$49 -> 0 | U13: 1 | V13: =Quesería!$B$49 -> 0 | W13: 1 | X13: 1 | Y13: =Quesería!$B$49 -> 0 | Z13: =Quesería!$B$49 -> 0 | AA13: =Quesería!$B$49 -> 0 | AB13: =Quesería!$B$49 -> 0 | AC13: =Quesería!$B$49 -> 0 | AD13: =Quesería!$B$49 -> 0
A14: Tasa del crédito | B14: =Quesería!$B$45 -> 0.141 | C14: =Quesería!$B$45 -> 0.141 | D14: =Quesería!$B$45 -> 0.141 | E14: =Quesería!$B$45 -> 0.141 | F14: =Quesería!$B$45 -> 0.141 | G14: =Quesería!$B$45 -> 0.141 | H14: =Quesería!$B$45 -> 0.141 | I14: =Quesería!$B$45 -> 0.141 | ... Q14: =Quesería!$B$45 -> 0.141 | R14: 0.157 | S14: =Quesería!$B$45 -> 0.141 | T14: =Quesería!$B$45 -> 0.141 | U14: =Quesería!$B$45 -> 0.141 | V14: =Quesería!$B$45 -> 0.141 | W14: =Quesería!$B$45 -> 0.141 | X14: =Quesería!$B$45 -> 0.141 | Y14: =Quesería!$B$45 -> 0.141 | Z14: =Quesería!$B$45 -> 0.141 | ... AD14: =Quesería!$B$45 -> 0.141
A15: Ruta de inflación (1 base, 2 consenso, 3 persistente) | B15: =Quesería!$B$7 -> 1 | C15: =Quesería!$B$7 -> 1 | D15: =Quesería!$B$7 -> 1 | E15: =Quesería!$B$7 -> 1 | F15: =Quesería!$B$7 -> 1 | G15: =Quesería!$B$7 -> 1 | H15: =Quesería!$B$7 -> 1 | I15: =Quesería!$B$7 -> 1 | ... L15: =Quesería!$B$7 -> 1 | M15: 2 | N15: 3 | O15: =Quesería!$B$7 -> 1 | P15: =Quesería!$B$7 -> 1 | Q15: =Quesería!$B$7 -> 1 | R15: =Quesería!$B$7 -> 1 | S15: =Quesería!$B$7 -> 1 | T15: =Quesería!$B$7 -> 1 | U15: =Quesería!$B$7 -> 1 | V15: =Quesería!$B$7 -> 1 | ... AD15: =Quesería!$B$7 -> 1
A16: Incremento del salario mínimo de 2027 | B16: =Entorno!$B$12 -> 0.085 | C16: =Entorno!$B$12 -> 0.085 | D16: =Entorno!$B$12 -> 0.085 | E16: =Entorno!$B$12 -> 0.085 | F16: =Entorno!$B$12 -> 0.085 | G16: =Entorno!$B$12 -> 0.085 | H16: =Entorno!$B$12 -> 0.085 | I16: =Entorno!$B$12 -> 0.085 | ... N16: =Entorno!$B$12 -> 0.085 | O16: 0.07 | P16: 0.1 | Q16: =Entorno!$B$12 -> 0.085 | R16: =Entorno!$B$12 -> 0.085 | S16: =Entorno!$B$12 -> 0.085 | T16: =Entorno!$B$12 -> 0.085 | U16: =Entorno!$B$12 -> 0.085 | V16: =Entorno!$B$12 -> 0.085 | W16: =Entorno!$B$12 -> 0.085 | X16: =Entorno!$B$12 -> 0.085 | ... AD16: =Entorno!$B$12 -> 0.085
A17: Impuesto de renta | B17: =Quesería!$B$54 -> 0.35 | C17: =Quesería!$B$54 -> 0.35 | D17: =Quesería!$B$54 -> 0.35 | E17: =Quesería!$B$54 -> 0.35 | F17: =Quesería!$B$54 -> 0.35 | G17: =Quesería!$B$54 -> 0.35 | H17: =Quesería!$B$54 -> 0.35 | I17: =Quesería!$B$54 -> 0.35 | ... P17: =Quesería!$B$54 -> 0.35 | Q17: 0.3 | R17: =Quesería!$B$54 -> 0.35 | S17: =Quesería!$B$54 -> 0.35 | T17: =Quesería!$B$54 -> 0.35 | U17: =Quesería!$B$54 -> 0.35 | V17: =Quesería!$B$54 -> 0.35 | W17: =Quesería!$B$54 -> 0.35 | X17: =Quesería!$B$54 -> 0.35 | Y17: =Quesería!$B$54 -> 0.35 | ... AD17: =Quesería!$B$54 -> 0.35
A18: Costo de capital (1 = del proyecto; 0 = 16 % de la empresa) | B18: 1 | C18: 1 | D18: 1 | E18: 1 | F18: 1 | G18: 1 | H18: 1 | I18: 1 | J18: 1 | K18: 1 | L18: 1 | M18: 1 | N18: 1 | O18: 1 | P18: 1 | Q18: 1 | R18: 1 | S18: 1 | T18: 1 | U18: 1 | V18: 1 | W18: 0 | X18: 1 | Y18: 1 | Z18: 1 | AA18: 1 | AB18: 1 | AC18: 1 | AD18: 1
A19: Depreciación fiscal por tipo de activo (1 = sí; 0 = todo a 10 años) | B19: 1 | C19: 1 | D19: 1 | E19: 1 | F19: 1 | G19: 1 | H19: 1 | I19: 1 | J19: 1 | K19: 1 | L19: 1 | M19: 1 | N19: 1 | O19: 1 | P19: 1 | Q19: 1 | R19: 1 | S19: 1 | T19: 1 | U19: 1 | V19: 1 | W19: 0 | X19: 0 | Y19: 1 | Z19: 1 | AA19: 1 | AB19: 1 | AC19: 1 | AD19: 1
A20: Crédito fiscal por innovación, art. 256-1 (1 = se obtiene) | B20: =Quesería!$B$59 -> 1 | C20: 0 | D20: 0 | E20: =Quesería!$B$59 -> 1 | F20: =Quesería!$B$59 -> 1 | G20: =Quesería!$B$59 -> 1 | H20: =Quesería!$B$59 -> 1 | I20: =Quesería!$B$59 -> 1 | J20: =Quesería!$B$59 -> 1 | K20: =Quesería!$B$59 -> 1 | L20: =Quesería!$B$59 -> 1 | ... S20: =Quesería!$B$59 -> 1 | T20: 0 | U20: 0 | V20: =Quesería!$B$59 -> 1 | W20: 0 | X20: 0 | Y20: =Quesería!$B$59 -> 1 | Z20: =Quesería!$B$59 -> 1 | AA20: =Quesería!$B$59 -> 1 | AB20: =Quesería!$B$59 -> 1 | AC20: =Quesería!$B$59 -> 1 | AD20: =Quesería!$B$59 -> 1
A21: Etapa 2 (1 = se hace) | B21: 1 | C21: 1 | D21: 0 | E21: 1 | F21: 1 | G21: 1 | H21: 1 | I21: 1 | J21: 1 | K21: 1 | L21: 1 | M21: 1 | N21: 1 | O21: 1 | P21: 1 | Q21: 1 | R21: 1 | S21: 1 | T21: 1 | U21: 1 | V21: 1 | W21: 1 | X21: 1 | Y21: 0 | Z21: 1 | AA21: 1 | AB21: 1 | AC21: 1 | AD21: 1
A22: Beneficios según su respaldo (1 = caso conservador) | B22: 0 | C22: 1 | D22: 1 | E22: 0 | F22: 0 | G22: 0 | H22: 0 | I22: 0 | J22: 0 | K22: 0 | L22: 0 | M22: 0 | N22: 0 | O22: 0 | P22: 0 | Q22: 0 | R22: 0 | S22: 0 | T22: 0 | U22: 0 | V22: 0 | W22: 0 | X22: 0 | Y22: 0 | Z22: 0 | AA22: 0 | AB22: 0 | AC22: 0 | AD22: 0
A23: Arranque de la etapa 1 en 2027 (1 = se cuenta) | B23: 1 | C23: 1 | D23: 1 | E23: 0 | F23: 1 | G23: 1 | H23: 1 | I23: 1 | J23: 1 | K23: 1 | L23: 1 | M23: 1 | N23: 1 | O23: 1 | P23: 1 | Q23: 1 | R23: 1 | S23: 1 | T23: 1 | U23: 1 | V23: 1 | W23: 1 | X23: 1 | Y23: 1 | Z23: 1 | AA23: 1 | AB23: 1 | AC23: 1 | AD23: 1
A24: Contrato de marca propia con la cadena (1 = se firma) | B24: 1 | C24: 1 | D24: 1 | E24: 1 | F24: 1 | G24: 1 | H24: 1 | I24: 1 | J24: 1 | K24: 1 | L24: 1 | M24: 1 | N24: 1 | O24: 1 | P24: 1 | Q24: 1 | R24: 1 | S24: 1 | T24: 1 | U24: 1 | V24: 1 | W24: 1 | X24: 1 | Y24: 1 | Z24: 0 | AA24: 1 | AB24: 1 | AC24: 1 | AD24: 1
A25: Pronto pago de la cadena a 30 días (1 = se pacta) | B25: 1 | C25: 1 | D25: 1 | E25: 1 | F25: 1 | G25: 1 | H25: 1 | I25: 1 | J25: 1 | K25: 1 | L25: 1 | M25: 1 | N25: 1 | O25: 1 | P25: 1 | Q25: 1 | R25: 1 | S25: 1 | T25: 1 | U25: 1 | V25: 1 | W25: 1 | X25: 1 | Y25: 1 | Z25: 1 | AA25: 0 | AB25: 1 | AC25: 1 | AD25: 1
A26: Opción del suero: se compra el enfriador (1 = sí) | B26: 0 | C26: 0 | D26: 0 | E26: 0 | F26: 0 | G26: 0 | H26: 0 | I26: 0 | J26: 0 | K26: 0 | L26: 0 | M26: 0 | N26: 0 | O26: 0 | P26: 0 | Q26: 0 | R26: 0 | S26: 0 | T26: 0 | U26: 0 | V26: 0 | W26: 0 | X26: 0 | Y26: 0 | Z26: 0 | AA26: 0 | AB26: 1 | AC26: 1 | AD26: 1
A27: Contrato de venta del suero enfriado a $45/kg (1 = se firma) | B27: 1 | C27: 1 | D27: 1 | E27: 1 | F27: 1 | G27: 1 | H27: 1 | I27: 1 | J27: 1 | K27: 1 | L27: 1 | M27: 1 | N27: 1 | O27: 1 | P27: 1 | Q27: 1 | R27: 1 | S27: 1 | T27: 1 | U27: 1 | V27: 1 | W27: 1 | X27: 1 | Y27: 1 | Z27: 1 | AA27: 1 | AB27: 1 | AC27: 0 | AD27: 1
A28: Ajuste de las tasas nominales por la inflación de la ruta (Fisher) | B28: =CHOOSE(B$15,Entorno!$M$7,Entorno!$M$8,Entorno!$M$9)-CHOOSE(Quesería!$B$7,Entorno!$M$7,Entorno!$M$8,Entorno!$M$9) -> 0 | C28: =CHOOSE(C$15,Entorno!$M$7,Entorno!$M$8,Entorno!$M$9)-CHOOSE(Quesería!$B$7,Entorno!$M$7,Entorno!$M$8,Entorno!$M$9) -> 0 | D28: =CHOOSE(D$15,Entorno!$M$7,Entorno!$M$8,Entorno!$M$9)-CHOOSE(Quesería!$B$7,Entorno!$M$7,Entorno!$M$8,Entorno!$M$9) -> 0 | E28: =CHOOSE(E$15,Entorno!$M$7,Entorno!$M$8,Entorno!$M$9)-CHOOSE(Quesería!$B$7,Entorno!$M$7,Entorno!$M$8,Entorno!$M$9) -> 0 | F28: =CHOOSE(F$15,Entorno!$M$7,Entorno!$M$8,Entorno!$M$9)-CHOOSE(Quesería!$B$7,Entorno!$M$7,Entorno!$M$8,Entorno!$M$9) -> 0 | G28: =CHOOSE(G$15,Entorno!$M$7,Entorno!$M$8,Entorno!$M$9)-CHOOSE(Quesería!$B$7,Entorno!$M$7,Entorno!$M$8,Entorno!$M$9) -> 0 | H28: =CHOOSE(H$15,Entorno!$M$7,Entorno!$M$8,Entorno!$M$9)-CHOOSE(Quesería!$B$7,Entorno!$M$7,Entorno!$M$8,Entorno!$M$9) -> 0 | I28: =CHOOSE(I$15,Entorno!$M$7,Entorno!$M$8,Entorno!$M$9)-CHOOSE(Quesería!$B$7,Entorno!$M$7,Entorno!$M$8,Entorno!$M$9) -> 0 | ... AD28: =CHOOSE(AD$15,Entorno!$M$7,Entorno!$M$8,Entorno!$M$9)-CHOOSE(Quesería!$B$7,Entorno!$M$7,Entorno!$M$8,Entorno!$M$9) -> 0
A29: Costo de capital del proyecto | B29: =IF(B$18=1,Quesería!$B$44*(B$14+B$28+B$13*Quesería!$B$51*1.19)*(1-B$17)+(1-Quesería!$B$44)*(Quesería!$B$11+B$28),Quesería!$B$8+B$28) -> 0.1470725 | C29: =IF(C$18=1,Quesería!$B$44*(C$14+C$28+C$13*Quesería!$B$51*1.19)*(1-C$17)+(1-Quesería!$B$44)*(Quesería!$B$11+C$28),Quesería!$B$8+C$28) -> 0.15707772 | D29: =IF(D$18=1,Quesería!$B$44*(D$14+D$28+D$13*Quesería!$B$51*1.19)*(1-D$17)+(1-Quesería!$B$44)*(Quesería!$B$11+D$28),Quesería!$B$8+D$28) -> 0.15707772 | E29: =IF(E$18=1,Quesería!$B$44*(E$14+E$28+E$13*Quesería!$B$51*1.19)*(1-E$17)+(1-Quesería!$B$44)*(Quesería!$B$11+E$28),Quesería!$B$8+E$28) -> 0.1470725 | F29: =IF(F$18=1,Quesería!$B$44*(F$14+F$28+F$13*Quesería!$B$51*1.19)*(1-F$17)+(1-Quesería!$B$44)*(Quesería!$B$11+F$28),Quesería!$B$8+F$28) -> 0.1470725 | G29: =IF(G$18=1,Quesería!$B$44*(G$14+G$28+G$13*Quesería!$B$51*1.19)*(1-G$17)+(1-Quesería!$B$44)*(Quesería!$B$11+G$28),Quesería!$B$8+G$28) -> 0.1470725 | H29: =IF(H$18=1,Quesería!$B$44*(H$14+H$28+H$13*Quesería!$B$51*1.19)*(1-H$17)+(1-Quesería!$B$44)*(Quesería!$B$11+H$28),Quesería!$B$8+H$28) -> 0.1470725 | I29: =IF(I$18=1,Quesería!$B$44*(I$14+I$28+I$13*Quesería!$B$51*1.19)*(1-I$17)+(1-Quesería!$B$44)*(Quesería!$B$11+I$28),Quesería!$B$8+I$28) -> 0.1470725 | ... AD29: =IF(AD$18=1,Quesería!$B$44*(AD$14+AD$28+AD$13*Quesería!$B$51*1.19)*(1-AD$17)+(1-Quesería!$B$44)*(Quesería!$B$11+AD$28),Quesería!$B$8+AD$28) -> 0.1470725
A30: Conservador: cada beneficio según su respaldo (contratado y medido 100 %, técnicamente justificado 75 %, por medir 50 %, hipotético 0 %), sin descuento ambiental ni crédito fiscal, con garantía del FNG y sin valor final de los equipos. Conservador con compuerta: lo mismo, pero la etapa 2 no se hace porque sus condiciones no se cumplen. Las rutas de inflación mueven las tasas nominales en la misma proporción (Fisher). Crédito ordinario: 15,7 %, tasa de los créditos empresariales a medianas empresas a 3–5 años en la misma fuente. Garantía del FNG: si el banco no acepta la prenda. Sin crédito fiscal: si el CNBT no certifica la inversión. Renta 30 %: si prospera la reducción anunciada por el Gobierno. Adverso combinado: beneficios −20 %, inversión +20 % y costos +30 % a la vez. Los escenarios de herramientas se explican en la hoja Herramientas.
A32: Resultados por escenario
B33: Oferta | C33: Conservador | D33: Conservador con compuerta | E33: Sin arranque en 2027 | F33: Sin reubicación del personal | G33: Beneficios −20 % | H33: Beneficios +20 % | I33: Inversión +20 % | J33: Inversión −20 % | K33: Costos operativos +30 % | L33: Costos operativos −30 % | M33: Inflación del consenso | N33: Inflación persistente | O33: Salario mínimo 2027: 7 % | P33: Salario mínimo 2027: 10 % | Q33: Renta 30 % | R33: Crédito ordinario | S33: Garantía del FNG | T33: Sin crédito fiscal por innovación | U33: Sin las dos gestiones | V33: Adverso combinado | W33: Sin herramientas | X33: Con el costo de capital del proyecto | Y33: Solo etapas 0 y 1 | Z33: Sin el contrato de la cadena | AA33: Cadena sin pronto pago | AB33: Con la opción del suero a $45/kg | AC33: Enfriador del suero sin contrato | AD33: Opción del suero sin descuento ambiental
A34: Costo de capital del proyecto | B34: =$B$29 -> 0.1470725 | C34: =$C$29 -> 0.15707772 | D34: =$D$29 -> 0.15707772 | E34: =$E$29 -> 0.1470725 | F34: =$F$29 -> 0.1470725 | G34: =$G$29 -> 0.1470725 | H34: =$H$29 -> 0.1470725 | I34: =$I$29 -> 0.1470725 | J34: =$J$29 -> 0.1470725 | K34: =$K$29 -> 0.1470725 | L34: =$L$29 -> 0.1470725 | M34: =$M$29 -> 0.14271157 | N34: =$N$29 -> 0.16394087 | O34: =$O$29 -> 0.1470725 | P34: =$P$29 -> 0.1470725 | Q34: =$Q$29 -> 0.151655 | R34: =$R$29 -> 0.1538325 | S34: =$S$29 -> 0.15707772 | T34: =$T$29 -> 0.1470725 | U34: =$U$29 -> 0.15707772 | V34: =$V$29 -> 0.1470725 | W34: =$W$29 -> 0.16 | X34: =$X$29 -> 0.15707772 | Y34: =$Y$29 -> 0.1470725 | Z34: =$Z$29 -> 0.1470725 | AA34: =$AA$29 -> 0.1470725 | AB34: =$AB$29 -> 0.1470725 | AC34: =$AC$29 -> 0.1470725 | AD34: =$AD$29 -> 0.1470725
A35: TIR del proyecto en pesos corrientes (frente al costo de capital) | B35: =IRR(B72:L72) -> 0.24327136 | C35: =IRR(B115:L115) -> 0.10059389 | D35: =IRR(B158:L158) -> 0.051712808 | E35: =IRR(B201:L201) -> 0.22799434 | F35: =IRR(B244:L244) -> 0.19286058 | G35: =IRR(B287:L287) -> 0.18563795 | H35: =IRR(B330:L330) -> 0.296246 | I35: =IRR(B373:L373) -> 0.20028755 | J35: =IRR(B416:L416) -> 0.30276339 | K35: =IRR(B459:L459) -> 0.23114664 | L35: =IRR(B502:L502) -> 0.2552319 | M35: =IRR(B545:L545) -> 0.23777509 | N35: =IRR(B588:L588) -> 0.26314899 | O35: =IRR(B631:L631) -> 0.24288351 | P35: =IRR(B674:L674) -> 0.2436589 | Q35: =IRR(B717:L717) -> 0.25601006 | R35: =IRR(B760:L760) -> 0.24327136 | S35: =IRR(B803:L803) -> 0.24327136 | T35: =IRR(B846:L846) -> 0.20291645 | U35: =IRR(B889:L889) -> 0.20291645 | V35: =IRR(B932:L932) -> 0.13552512 | W35: =IRR(B975:L975) -> 0.19722515 | X35: =IRR(B1018:L1018) -> 0.19722515 | Y35: =IRR(B1061:L1061) -> 0.23493226 | Z35: =IRR(B1104:L1104) -> 0.23153138 | AA35: =IRR(B1147:L1147) -> 0.23023769 | AB35: =IRR(B1190:L1190) -> 0.23775257 | AC35: =IRR(B1233:L1233) -> 0.22247624 | AD35: =IRR(B1276:L1276) -> 0.2344666
A36: TIR del proyecto en pesos constantes | B36: =IRR(B71:L71) -> 0.19238125 | C36: =IRR(B114:L114) -> 0.056207952 | D36: =IRR(B157:L157) -> 0.0085183252 | E36: =IRR(B200:L200) -> 0.17776979 | F36: =IRR(B243:L243) -> 0.14421449 | G36: =IRR(B286:L286) -> 0.13728095 | H36: =IRR(B329:L329) -> 0.2430101 | I36: =IRR(B372:L372) -> 0.15128181 | J36: =IRR(B415:L415) -> 0.24924803 | K36: =IRR(B458:L458) -> 0.18080502 | L36: =IRR(B501:L501) -> 0.20379975 | M36: =IRR(B544:L544) -> 0.19428789 | N36: =IRR(B587:L587) -> 0.18605539 | O36: =IRR(B630:L630) -> 0.19201068 | P36: =IRR(B673:L673) -> 0.19275152 | Q36: =IRR(B716:L716) -> 0.20455447 | R36: =IRR(B759:L759) -> 0.19238125 | S36: =IRR(B802:L802) -> 0.19238125 | T36: =IRR(B845:L845) -> 0.15405215 | U36: =IRR(B888:L888) -> 0.15405215 | V36: =IRR(B931:L931) -> 0.089360202 | W36: =IRR(B974:L974) -> 0.14859408 | X36: =IRR(B1017:L1017) -> 0.14859408 | Y36: =IRR(B1060:L1060) -> 0.18283046 | Z36: =IRR(B1103:L1103) -> 0.18094757 | AA36: =IRR(B1146:L1146) -> 0.18017258 | AB36: =IRR(B1189:L1189) -> 0.18718228 | AC36: =IRR(B1232:L1232) -> 0.17257864 | AD36: =IRR(B1275:L1275) -> 0.18405848
A37: VPN al costo de capital ($ M de 2026) | B37: =SUMPRODUCT(B71:L71,B75:L75) -> 639.5567 | C37: =SUMPRODUCT(B114:L114,B118:L118) -> -361.21367 | D37: =SUMPRODUCT(B157:L157,B161:L161) -> -340.70845 | E37: =SUMPRODUCT(B200:L200,B204:L204) -> 562.01798 | F37: =SUMPRODUCT(B243:L243,B247:L247) -> 288.29355 | G37: =SUMPRODUCT(B286:L286,B290:L290) -> 242.43744 | H37: =SUMPRODUCT(B329:L329,B333:L333) -> 1036.676 | I37: =SUMPRODUCT(B372:L372,B376:L376) -> 406.56306 | J37: =SUMPRODUCT(B415:L415,B419:L419) -> 872.55033 | K37: =SUMPRODUCT(B458:L458,B462:L462) -> 554.46356 | L37: =SUMPRODUCT(B501:L501,B505:L505) -> 724.64984 | M37: =SUMPRODUCT(B544:L544,B548:L548) -> 631.10916 | N37: =SUMPRODUCT(B587:L587,B591:L591) -> 662.13122 | O37: =SUMPRODUCT(B630:L630,B634:L634) -> 636.69995 | P37: =SUMPRODUCT(B673:L673,B677:L677) -> 642.41345 | Q37: =SUMPRODUCT(B716:L716,B720:L720) -> 692.71452 | R37: =SUMPRODUCT(B759:L759,B763:L763) -> 580.0425 | S37: =SUMPRODUCT(B802:L802,B806:L806) -> 552.4468 | T37: =SUMPRODUCT(B845:L845,B849:L849) -> 402.88946 | U37: =SUMPRODUCT(B888:L888,B892:L892) -> 318.77091 | V37: =SUMPRODUCT(B931:L931,B935:L935) -> -82.468074 | W37: =SUMPRODUCT(B974:L974,B978:L978) -> 264.16566 | X37: =SUMPRODUCT(B1017:L1017,B1021:L1021) -> 287.92607 | Y37: =SUMPRODUCT(B1060:L1060,B1064:L1064) -> 286.1896 | Z37: =SUMPRODUCT(B1103:L1103,B1107:L1107) -> 511.16951 | AA37: =SUMPRODUCT(B1146:L1146,B1150:L1150) -> 601.47103 | AB37: =SUMPRODUCT(B1189:L1189,B1193:L1193) -> 631.36332 | AC37: =SUMPRODUCT(B1232:L1232,B1236:L1236) -> 515.38173 | AD37: =SUMPRODUCT(B1275:L1275,B1279:L1279) -> 613.05584
A38: Recuperación (años) | B38: =SUM(B74:L74) -> 4.6824017 | C38: =SUM(B117:L117) -> 8.1875686 | D38: =SUM(B160:L160) -> 9.6028099 | E38: =SUM(B203:L203) -> 4.92204 | F38: =SUM(B246:L246) -> 5.6802899 | G38: =SUM(B289:L289) -> 5.7975817 | H38: =SUM(B332:L332) -> 4.0179378 | I38: =SUM(B375:L375) -> 5.451937 | J38: =SUM(B418:L418) -> 3.9601815 | K38: =SUM(B461:L461) -> 4.8813997 | L38: =SUM(B504:L504) -> 4.5008433 | M38: =SUM(B547:L547) -> 4.6527186 | N38: =SUM(B590:L590) -> 4.7796053 | O38: =SUM(B633:L633) -> 4.6884057 | P38: =SUM(B676:L676) -> 4.6764183 | Q38: =SUM(B719:L719) -> 4.4992012 | R38: =SUM(B762:L762) -> 4.6824017 | S38: =SUM(B805:L805) -> 4.6824017 | T38: =SUM(B848:L848) -> 5.5477447 | U38: =SUM(B891:L891) -> 5.5477447 | V38: =SUM(B934:L934) -> 7.0140269 | W38: =SUM(B977:L977) -> 5.6682428 | X38: =SUM(B1020:L1020) -> 5.6682428 | Y38: =SUM(B1063:L1063) -> 3.7886014 | Z38: =SUM(B1106:L1106) -> 4.6422236 | AA38: =SUM(B1149:L1149) -> 5.1664836 | AB38: =SUM(B1192:L1192) -> 4.7946521 | AC38: =SUM(B1235:L1235) -> 5.0493479 | AD38: =SUM(B1278:L1278) -> 4.8535349
A39: Recuperación descontada (años) | B39: =IF(SUM(B78:L78)=0,"Más de 10",SUM(B78:L78)) -> 6.4410043 | C39: =IF(SUM(B121:L121)=0,"Más de 10",SUM(B121:L121)) -> Más de 10 | D39: =IF(SUM(B164:L164)=0,"Más de 10",SUM(B164:L164)) -> Más de 10 | E39: =IF(SUM(B207:L207)=0,"Más de 10",SUM(B207:L207)) -> 6.8566902 | F39: =IF(SUM(B250:L250)=0,"Más de 10",SUM(B250:L250)) -> 8.2262342 | G39: =IF(SUM(B293:L293)=0,"Más de 10",SUM(B293:L293)) -> 8.4796912 | H39: =IF(SUM(B336:L336)=0,"Más de 10",SUM(B336:L336)) -> 5.1911015 | I39: =IF(SUM(B379:L379)=0,"Más de 10",SUM(B379:L379)) -> 7.8290461 | J39: =IF(SUM(B422:L422)=0,"Más de 10",SUM(B422:L422)) -> 5.0686673 | K39: =IF(SUM(B465:L465)=0,"Más de 10",SUM(B465:L465)) -> 6.7843103 | L39: =IF(SUM(B508:L508)=0,"Más de 10",SUM(B508:L508)) -> 6.1246887 | M39: =IF(SUM(B551:L551)=0,"Más de 10",SUM(B551:L551)) -> 6.4469857 | N39: =IF(SUM(B594:L594)=0,"Más de 10",SUM(B594:L594)) -> 6.4639954 | O39: =IF(SUM(B637:L637)=0,"Más de 10",SUM(B637:L637)) -> 6.451589 | P39: =IF(SUM(B680:L680)=0,"Más de 10",SUM(B680:L680)) -> 6.4304524 | Q39: =IF(SUM(B723:L723)=0,"Más de 10",SUM(B723:L723)) -> 6.2070168 | R39: =IF(SUM(B766:L766)=0,"Más de 10",SUM(B766:L766)) -> 6.5942064 | S39: =IF(SUM(B809:L809)=0,"Más de 10",SUM(B809:L809)) -> 6.6703998 | T39: =IF(SUM(B852:L852)=0,"Más de 10",SUM(B852:L852)) -> 7.8046 | U39: =IF(SUM(B895:L895)=0,"Más de 10",SUM(B895:L895)) -> 8.1623474 | V39: =IF(SUM(B938:L938)=0,"Más de 10",SUM(B938:L938)) -> Más de 10 | W39: =IF(SUM(B981:L981)=0,"Más de 10",SUM(B981:L981)) -> 8.53223 | X39: =IF(SUM(B1024:L1024)=0,"Más de 10",SUM(B1024:L1024)) -> 8.4091609 | Y39: =IF(SUM(B1067:L1067)=0,"Más de 10",SUM(B1067:L1067)) -> 6.0409878 | Z39: =IF(SUM(B1110:L1110)=0,"Más de 10",SUM(B1110:L1110)) -> 6.5355755 | AA39: =IF(SUM(B1153:L1153)=0,"Más de 10",SUM(B1153:L1153)) -> 7.1002909 | AB39: =IF(SUM(B1196:L1196)=0,"Más de 10",SUM(B1196:L1196)) -> 6.6042867 | AC39: =IF(SUM(B1239:L1239)=0,"Más de 10",SUM(B1239:L1239)) -> 7.0541796 | AD39: =IF(SUM(B1282:L1282)=0,"Más de 10",SUM(B1282:L1282)) -> 6.6989497
A40: ROI a 10 años | B40: =SUM(B71:L71)/SUM(B54:L54) -> 1.2996922 | C40: =SUM(B114:L114)/SUM(B97:L97) -> 0.37071234 | D40: =SUM(B157:L157)/SUM(B140:L140) -> 0.045588489 | E40: =SUM(B200:L200)/SUM(B183:L183) -> 1.2505365 | F40: =SUM(B243:L243)/SUM(B226:L226) -> 0.91661486 | G40: =SUM(B286:L286)/SUM(B269:L269) -> 0.86680484 | H40: =SUM(B329:L329)/SUM(B312:L312) -> 1.7325795 | I40: =SUM(B372:L372)/SUM(B355:L355) -> 0.9700533 | J40: =SUM(B415:L415)/SUM(B398:L398) -> 1.7941505 | K40: =SUM(B458:L458)/SUM(B441:L441) -> 1.209887 | L40: =SUM(B501:L501)/SUM(B484:L484) -> 1.3894974 | M40: =SUM(B544:L544)/SUM(B527:L527) -> 1.3146358 | N40: =SUM(B587:L587)/SUM(B570:L570) -> 1.2480665 | O40: =SUM(B630:L630)/SUM(B613:L613) -> 1.296558 | P40: =SUM(B673:L673)/SUM(B656:L656) -> 1.3028263 | Q40: =SUM(B716:L716)/SUM(B699:L699) -> 1.4062962 | R40: =SUM(B759:L759)/SUM(B742:L742) -> 1.2996922 | S40: =SUM(B802:L802)/SUM(B785:L785) -> 1.2996922 | T40: =SUM(B845:L845)/SUM(B828:L828) -> 1.1296082 | U40: =SUM(B888:L888)/SUM(B871:L871) -> 1.1296082 | V40: =SUM(B931:L931)/SUM(B914:L914) -> 0.52845824 | W40: =SUM(B974:L974)/SUM(B957:L957) -> 1.1218111 | X40: =SUM(B1017:L1017)/SUM(B1000:L1000) -> 1.1218111 | Y40: =SUM(B1060:L1060)/SUM(B1043:L1043) -> 0.97848581 | Z40: =SUM(B1103:L1103)/SUM(B1086:L1086) -> 1.0918817 | AA40: =SUM(B1146:L1146)/SUM(B1129:L1129) -> 1.347328 | AB40: =SUM(B1189:L1189)/SUM(B1172:L1172) -> 1.2466001 | AC40: =SUM(B1232:L1232)/SUM(B1215:L1215) -> 1.1256161 | AD40: =SUM(B1275:L1275)/SUM(B1258:L1258) -> 1.2347607
A41: TIR del inversionista en pesos corrientes (frente al 25 %) | B41: =IFERROR(IRR(B87:L87),"No existe") -> 0.42102438 | C41: =IFERROR(IRR(B130:L130),"No existe") -> 0.09362684 | D41: =IFERROR(IRR(B173:L173),"No existe") -> -0.00065953761 | E41: =IFERROR(IRR(B216:L216),"No existe") -> 0.36480203 | F41: =IFERROR(IRR(B259:L259),"No existe") -> 0.30861776 | G41: =IFERROR(IRR(B302:L302),"No existe") -> 0.2898649 | H41: =IFERROR(IRR(B345:L345),"No existe") -> 0.54819181 | I41: =IFERROR(IRR(B388:L388),"No existe") -> 0.32339577 | J41: =IFERROR(IRR(B431:L431),"No existe") -> 0.56236497 | K41: =IFERROR(IRR(B474:L474),"No existe") -> 0.39221625 | L41: =IFERROR(IRR(B517:L517),"No existe") -> 0.44973183 | M41: =IFERROR(IRR(B560:L560),"No existe") -> 0.41661349 | N41: =IFERROR(IRR(B603:L603),"No existe") -> 0.43506768 | O41: =IFERROR(IRR(B646:L646),"No existe") -> 0.42017498 | P41: =IFERROR(IRR(B689:L689),"No existe") -> 0.42187295 | Q41: =IFERROR(IRR(B732:L732),"No existe") -> 0.43851471 | R41: =IFERROR(IRR(B775:L775),"No existe") -> 0.40644658 | S41: =IFERROR(IRR(B818:L818),"No existe") -> 0.39333511 | T41: =IFERROR(IRR(B861:L861),"No existe") -> 0.3012011 | U41: =IFERROR(IRR(B904:L904),"No existe") -> 0.28261102 | V41: =IFERROR(IRR(B947:L947),"No existe") -> 0.18126158 | W41: =IFERROR(IRR(B990:L990),"No existe") -> 0.26637623 | X41: =IFERROR(IRR(B1033:L1033),"No existe") -> 0.26637623 | Y41: =IFERROR(IRR(B1076:L1076),"No existe") -> 0.49664051 | Z41: =IFERROR(IRR(B1119:L1119),"No existe") -> 0.41944875 | AA41: =IFERROR(IRR(B1162:L1162),"No existe") -> 0.36707528 | AB41: =IFERROR(IRR(B1205:L1205),"No existe") -> 0.41042322 | AC41: =IFERROR(IRR(B1248:L1248),"No existe") -> 0.37689636 | AD41: =IFERROR(IRR(B1291:L1291),"No existe") -> 0.39878201
A42: TIR del inversionista en pesos constantes | B42: =IFERROR(IRR(B86:L86),"No existe") -> 0.36208684 | C42: =IFERROR(IRR(B129:L129),"No existe") -> 0.05019807 | D42: =IFERROR(IRR(B172:L172),"No existe") -> -0.040489299 | E42: =IFERROR(IRR(B215:L215),"No existe") -> 0.30847196 | F42: =IFERROR(IRR(B258:L258),"No existe") -> 0.25499094 | G42: =IFERROR(IRR(B301:L301),"No existe") -> 0.23705744 | H42: =IFERROR(IRR(B344:L344),"No existe") -> 0.48328547 | I42: =IFERROR(IRR(B387:L387),"No existe") -> 0.26900784 | J42: =IFERROR(IRR(B430:L430),"No existe") -> 0.49682519 | K42: =IFERROR(IRR(B473:L473),"No existe") -> 0.33466521 | L42: =IFERROR(IRR(B516:L516),"No existe") -> 0.3894107 | M42: =IFERROR(IRR(B559:L559),"No existe") -> 0.36597775 | N42: =IFERROR(IRR(B602:L602),"No existe") -> 0.34748139 | O42: =IFERROR(IRR(B645:L645),"No existe") -> 0.3612774 | P42: =IFERROR(IRR(B688:L688),"No existe") -> 0.3628955 | Q42: =IFERROR(IRR(B731:L731),"No existe") -> 0.37879433 | R42: =IFERROR(IRR(B774:L774),"No existe") -> 0.34825254 | S42: =IFERROR(IRR(B817:L817),"No existe") -> 0.33579364 | T42: =IFERROR(IRR(B860:L860),"No existe") -> 0.24844982 | U42: =IFERROR(IRR(B903:L903),"No existe") -> 0.23074734 | V42: =IFERROR(IRR(B946:L946),"No existe") -> 0.13349458 | W42: =IFERROR(IRR(B989:L989),"No existe") -> 0.21516906 | X42: =IFERROR(IRR(B1032:L1032),"No existe") -> 0.21516906 | Y42: =IFERROR(IRR(B1075:L1075),"No existe") -> 0.43065327 | Z42: =IFERROR(IRR(B1118:L1118),"No existe") -> 0.3600488 | AA42: =IFERROR(IRR(B1161:L1161),"No existe") -> 0.31122485 | AB42: =IFERROR(IRR(B1204:L1204),"No existe") -> 0.35206723 | AC42: =IFERROR(IRR(B1247:L1247),"No existe") -> 0.32010271 | AD42: =IFERROR(IRR(B1290:L1290),"No existe") -> 0.34102989
A43: Cobertura mínima del servicio de la deuda | B43: =MIN(D90:L90) -> 1.3435688 | C43: =MIN(D133:L133) -> 0.86804837 | D43: =MIN(D176:L176) -> 0.60444403 | E43: =MIN(D219:L219) -> 1.3435688 | F43: =MIN(D262:L262) -> 1.0920617 | G43: =MIN(D305:L305) -> 1.1037925 | H43: =MIN(D348:L348) -> 1.5833452 | I43: =MIN(D391:L391) -> 1.1619298 | J43: =MIN(D434:L434) -> 1.6160274 | K43: =MIN(D477:L477) -> 1.28861 | L43: =MIN(D520:L520) -> 1.3985277 | M43: =MIN(D563:L563) -> 1.3473478 | N43: =MIN(D606:L606) -> 1.3192438 | O43: =MIN(D649:L649) -> 1.3415244 | P43: =MIN(D692:L692) -> 1.3456132 | Q43: =MIN(D735:L735) -> 1.3875465 | R43: =MIN(D778:L778) -> 1.2970223 | S43: =MIN(D821:L821) -> 1.287914 | T43: =MIN(D864:L864) -> 1.3435688 | U43: =MIN(D907:L907) -> 1.287914 | V43: =MIN(D950:L950) -> 0.91260969 | W43: =MIN(D993:L993) -> 1.2950538 | X43: =MIN(D1036:L1036) -> 1.2950538 | Y43: =MIN(D1079:L1079) -> 1.1593449 | Z43: =MIN(D1122:L1122) -> 1.3348719 | AA43: =MIN(D1165:L1165) -> 1.2023269 | AB43: =MIN(D1208:L1208) -> 1.3137081 | AC43: =MIN(D1251:L1251) -> 1.2360752 | AD43: =MIN(D1294:L1294) -> 1.3137081
A45: Flujos de cada escenario (años 0 a 10)
A46: $ M | B46: Año 0 | C46: Año 1 | D46: Año 2 | E46: Año 3 | F46: Año 4 | G46: Año 5 | H46: Año 6 | I46: Año 7 | J46: Año 8 | K46: Año 9 | L46: Año 10
A47: Año (número) | B47: 0 | C47: 1 | D47: 2 | E47: 3 | F47: 4 | G47: 5 | H47: 6 | I47: 7 | J47: 8 | K47: 9 | L47: 10
A49: Oferta
A50: Inflación del año | B50: =CHOOSE($B$15,Entorno!B$7,Entorno!B$8,Entorno!B$9) -> 0.06 | C50: =CHOOSE($B$15,Entorno!C$7,Entorno!C$8,Entorno!C$9) -> 0.05 | D50: =CHOOSE($B$15,Entorno!D$7,Entorno!D$8,Entorno!D$9) -> 0.045 | E50: =CHOOSE($B$15,Entorno!E$7,Entorno!E$8,Entorno!E$9) -> 0.04 | F50: =CHOOSE($B$15,Entorno!F$7,Entorno!F$8,Entorno!F$9) -> 0.04 | G50: =CHOOSE($B$15,Entorno!G$7,Entorno!G$8,Entorno!G$9) -> 0.04 | H50: =CHOOSE($B$15,Entorno!H$7,Entorno!H$8,Entorno!H$9) -> 0.04 | I50: =CHOOSE($B$15,Entorno!I$7,Entorno!I$8,Entorno!I$9) -> 0.04 | ... L50: =CHOOSE($B$15,Entorno!L$7,Entorno!L$8,Entorno!L$9) -> 0.04
A51: Índice de precios (2026 = 1) | B51: =1+B50 -> 1.06 | C51: =B51*(1+C50) -> 1.113 | D51: =C51*(1+D50) -> 1.163085 | E51: =D51*(1+E50) -> 1.2096084 | F51: =E51*(1+F50) -> 1.2579927 | G51: =F51*(1+G50) -> 1.3083124 | H51: =G51*(1+H50) -> 1.3606449 | I51: =H51*(1+I50) -> 1.4150707 | J51: =I51*(1+J50) -> 1.4716736 | ... L51: =K51*(1+L50) -> 1.5917621
A52: Salario mínimo real (2026 = 1) | B52: =(1+$B$16)/(1+B50) -> 1.0235849 | C52: =B52*(1+Entorno!$B$13) -> 1.0287028 | D52: =C52*(1+Entorno!$B$13) -> 1.0338463 | E52: =D52*(1+Entorno!$B$13) -> 1.0390156 | F52: =E52*(1+Entorno!$B$13) -> 1.0442107 | G52: =F52*(1+Entorno!$B$13) -> 1.0494317 | H52: =G52*(1+Entorno!$B$13) -> 1.0546789 | I52: =H52*(1+Entorno!$B$13) -> 1.0599523 | J52: =I52*(1+Entorno!$B$13) -> 1.065252 | ... L52: =K52*(1+Entorno!$B$13) -> 1.0759312
A53: Factor de pesos constantes | B53: =1/B51 -> 0.94339623 | C53: =1/C51 -> 0.8984726 | D53: =1/D51 -> 0.85978239 | E53: =1/E51 -> 0.82671384 | F53: =1/F51 -> 0.79491715 | G53: =1/G51 -> 0.76434341 | H53: =1/H51 -> 0.73494559 | I53: =1/I51 -> 0.70667845 | ... L53: =1/L51 -> 0.62823457
A54: Inversión | B54: =IF(B$47=0,Quesería!$F$92,IF(B$47=1,(Quesería!$F$93-(-$B$26)*Quesería!$D$86*(1+Quesería!$I$86))*$B$21,0))*$B$11 -> 930.80024 | C54: =IF(C$47=0,Quesería!$F$92,IF(C$47=1,(Quesería!$F$93-(-$B$26)*Quesería!$D$86*(1+Quesería!$I$86))*$B$21,0))*$B$11 -> 658.46907 | D54: =IF(D$47=0,Quesería!$F$92,IF(D$47=1,(Quesería!$F$93-(-$B$26)*Quesería!$D$86*(1+Quesería!$I$86))*$B$21,0))*$B$11 -> 0 | E54: =IF(E$47=0,Quesería!$F$92,IF(E$47=1,(Quesería!$F$93-(-$B$26)*Quesería!$D$86*(1+Quesería!$I$86))*$B$21,0))*$B$11 -> 0 | F54: =IF(F$47=0,Quesería!$F$92,IF(F$47=1,(Quesería!$F$93-(-$B$26)*Quesería!$D$86*(1+Quesería!$I$86))*$B$21,0))*$B$11 -> 0 | G54: =IF(G$47=0,Quesería!$F$92,IF(G$47=1,(Quesería!$F$93-(-$B$26)*Quesería!$D$86*(1+Quesería!$I$86))*$B$21,0))*$B$11 -> 0 | H54: =IF(H$47=0,Quesería!$F$92,IF(H$47=1,(Quesería!$F$93-(-$B$26)*Quesería!$D$86*(1+Quesería!$I$86))*$B$21,0))*$B$11 -> 0 | I54: =IF(I$47=0,Quesería!$F$92,IF(I$47=1,(Quesería!$F$93-(-$B$26)*Quesería!$D$86*(1+Quesería!$I$86))*$B$21,0))*$B$11 -> 0 | ... L54: =IF(L$47=0,Quesería!$F$92,IF(L$47=1,(Quesería!$F$93-(-$B$26)*Quesería!$D$86*(1+Quesería!$I$86))*$B$21,0))*$B$11 -> 0
A55: Reposición de equipos | B55: =IF(B$47=5,Quesería!$F$99,IF(B$47=6,Quesería!$F$100,0))*$B$11 -> 0 | C55: =IF(C$47=5,Quesería!$F$99,IF(C$47=6,Quesería!$F$100,0))*$B$11 -> 0 | D55: =IF(D$47=5,Quesería!$F$99,IF(D$47=6,Quesería!$F$100,0))*$B$11 -> 0 | E55: =IF(E$47=5,Quesería!$F$99,IF(E$47=6,Quesería!$F$100,0))*$B$11 -> 0 | F55: =IF(F$47=5,Quesería!$F$99,IF(F$47=6,Quesería!$F$100,0))*$B$11 -> 0 | G55: =IF(G$47=5,Quesería!$F$99,IF(G$47=6,Quesería!$F$100,0))*$B$11 -> 27.465217 | H55: =IF(H$47=5,Quesería!$F$99,IF(H$47=6,Quesería!$F$100,0))*$B$11 -> 46.389156 | I55: =IF(I$47=5,Quesería!$F$99,IF(I$47=6,Quesería!$F$100,0))*$B$11 -> 0 | ... L55: =IF(L$47=5,Quesería!$F$99,IF(L$47=6,Quesería!$F$100,0))*$B$11 -> 0
A56: IVA de equipos y contratos | B56: =Quesería!$B$55*(IF(B$47=0,SUMPRODUCT((Quesería!$C$70:$C$89=0)*(Quesería!$H$70:$H$89>0)*(Quesería!$J$70:$J$89>0)*Quesería!$F$70:$F$89*(1+Quesería!$I$70:$I$89)),IF(B$47=1,(SUMPRODUCT((Quesería!$C$70:$C$89=1)*(Quesería!$H$70:$H$89>0)*(Quesería!$J$70:$J$89>0)*Quesería!$F$70:$F$89*(1+Quesería!$I$70:$I$89))-(-$B$26)*Quesería!$D$86*(1+Quesería!$I$86))*$B$21,0))*$B$11+B55) -> 149.11567 | C56: =Quesería!$B$55*(IF(C$47=0,SUMPRODUCT((Quesería!$C$70:$C$89=0)*(Quesería!$H$70:$H$89>0)*(Quesería!$J$70:$J$89>0)*Quesería!$F$70:$F$89*(1+Quesería!$I$70:$I$89)),IF(C$47=1,(SUMPRODUCT((Quesería!$C$70:$C$89=1)*(Quesería!$H$70:$H$89>0)*(Quesería!$J$70:$J$89>0)*Quesería!$F$70:$F$89*(1+Quesería!$I$70:$I$89))-(-$B$26)*Quesería!$D$86*(1+Quesería!$I$86))*$B$21,0))*$B$11+C55) -> 125.10912 | D56: =Quesería!$B$55*(IF(D$47=0,SUMPRODUCT((Quesería!$C$70:$C$89=0)*(Quesería!$H$70:$H$89>0)*(Quesería!$J$70:$J$89>0)*Quesería!$F$70:$F$89*(1+Quesería!$I$70:$I$89)),IF(D$47=1,(SUMPRODUCT((Quesería!$C$70:$C$89=1)*(Quesería!$H$70:$H$89>0)*(Quesería!$J$70:$J$89>0)*Quesería!$F$70:$F$89*(1+Quesería!$I$70:$I$89))-(-$B$26)*Quesería!$D$86*(1+Quesería!$I$86))*$B$21,0))*$B$11+D55) -> 0 | E56: =Quesería!$B$55*(IF(E$47=0,SUMPRODUCT((Quesería!$C$70:$C$89=0)*(Quesería!$H$70:$H$89>0)*(Quesería!$J$70:$J$89>0)*Quesería!$F$70:$F$89*(1+Quesería!$I$70:$I$89)),IF(E$47=1,(SUMPRODUCT((Quesería!$C$70:$C$89=1)*(Quesería!$H$70:$H$89>0)*(Quesería!$J$70:$J$89>0)*Quesería!$F$70:$F$89*(1+Quesería!$I$70:$I$89))-(-$B$26)*Quesería!$D$86*(1+Quesería!$I$86))*$B$21,0))*$B$11+E55) -> 0 | F56: =Quesería!$B$55*(IF(F$47=0,SUMPRODUCT((Quesería!$C$70:$C$89=0)*(Quesería!$H$70:$H$89>0)*(Quesería!$J$70:$J$89>0)*Quesería!$F$70:$F$89*(1+Quesería!$I$70:$I$89)),IF(F$47=1,(SUMPRODUCT((Quesería!$C$70:$C$89=1)*(Quesería!$H$70:$H$89>0)*(Quesería!$J$70:$J$89>0)*Quesería!$F$70:$F$89*(1+Quesería!$I$70:$I$89))-(-$B$26)*Quesería!$D$86*(1+Quesería!$I$86))*$B$21,0))*$B$11+F55) -> 0 | G56: =Quesería!$B$55*(IF(G$47=0,SUMPRODUCT((Quesería!$C$70:$C$89=0)*(Quesería!$H$70:$H$89>0)*(Quesería!$J$70:$J$89>0)*Quesería!$F$70:$F$89*(1+Quesería!$I$70:$I$89)),IF(G$47=1,(SUMPRODUCT((Quesería!$C$70:$C$89=1)*(Quesería!$H$70:$H$89>0)*(Quesería!$J$70:$J$89>0)*Quesería!$F$70:$F$89*(1+Quesería!$I$70:$I$89))-(-$B$26)*Quesería!$D$86*(1+Quesería!$I$86))*$B$21,0))*$B$11+G55) -> 5.2183913 | H56: =Quesería!$B$55*(IF(H$47=0,SUMPRODUCT((Quesería!$C$70:$C$89=0)*(Quesería!$H$70:$H$89>0)*(Quesería!$J$70:$J$89>0)*Quesería!$F$70:$F$89*(1+Quesería!$I$70:$I$89)),IF(H$47=1,(SUMPRODUCT((Quesería!$C$70:$C$89=1)*(Quesería!$H$70:$H$89>0)*(Quesería!$J$70:$J$89>0)*Quesería!$F$70:$F$89*(1+Quesería!$I$70:$I$89))-(-$B$26)*Quesería!$D$86*(1+Quesería!$I$86))*$B$21,0))*$B$11+H55) -> 8.8139396 | I56: =Quesería!$B$55*(IF(I$47=0,SUMPRODUCT((Quesería!$C$70:$C$89=0)*(Quesería!$H$70:$H$89>0)*(Quesería!$J$70:$J$89>0)*Quesería!$F$70:$F$89*(1+Quesería!$I$70:$I$89)),IF(I$47=1,(SUMPRODUCT((Quesería!$C$70:$C$89=1)*(Quesería!$H$70:$H$89>0)*(Quesería!$J$70:$J$89>0)*Quesería!$F$70:$F$89*(1+Quesería!$I$70:$I$89))-(-$B$26)*Quesería!$D$86*(1+Quesería!$I$86))*$B$21,0))*$B$11+I55) -> 0 | ... L56: =Quesería!$B$55*(IF(L$47=0,SUMPRODUCT((Quesería!$C$70:$C$89=0)*(Quesería!$H$70:$H$89>0)*(Quesería!$J$70:$J$89>0)*Quesería!$F$70:$F$89*(1+Quesería!$I$70:$I$89)),IF(L$47=1,(SUMPRODUCT((Quesería!$C$70:$C$89=1)*(Quesería!$H$70:$H$89>0)*(Quesería!$J$70:$J$89>0)*Quesería!$F$70:$F$89*(1+Quesería!$I$70:$I$89))-(-$B$26)*Quesería!$D$86*(1+Quesería!$I$86))*$B$21,0))*$B$11+L55) -> 0
A57: Beneficio de las etapas 0 y 1 | B57: =IF(B$47=0,($B$22*Quesería!$J$126+(1-$B$22)*Quesería!$E$122)*Quesería!$B$20*Quesería!$B$21/12*$B$23,(($B$22*Quesería!$J$126+(1-$B$22)*Quesería!$E$122)+($B$22*Quesería!$J$104+(1-$B$22)*Quesería!$E$104)*(B52-1))*IF(B$47=1,Quesería!$B$20,1))*$B$10 -> 120.71677 | C57: =IF(C$47=0,($B$22*Quesería!$J$126+(1-$B$22)*Quesería!$E$122)*Quesería!$B$20*Quesería!$B$21/12*$B$23,(($B$22*Quesería!$J$126+(1-$B$22)*Quesería!$E$122)+($B$22*Quesería!$J$104+(1-$B$22)*Quesería!$E$104)*(C52-1))*IF(C$47=1,Quesería!$B$20,1))*$B$10 -> 181.32832 | D57: =IF(D$47=0,($B$22*Quesería!$J$126+(1-$B$22)*Quesería!$E$122)*Quesería!$B$20*Quesería!$B$21/12*$B$23,(($B$22*Quesería!$J$126+(1-$B$22)*Quesería!$E$122)+($B$22*Quesería!$J$104+(1-$B$22)*Quesería!$E$104)*(D52-1))*IF(D$47=1,Quesería!$B$20,1))*$B$10 -> 241.83158 | E57: =IF(E$47=0,($B$22*Quesería!$J$126+(1-$B$22)*Quesería!$E$122)*Quesería!$B$20*Quesería!$B$21/12*$B$23,(($B$22*Quesería!$J$126+(1-$B$22)*Quesería!$E$122)+($B$22*Quesería!$J$104+(1-$B$22)*Quesería!$E$104)*(E52-1))*IF(E$47=1,Quesería!$B$20,1))*$B$10 -> 241.89237 | F57: =IF(F$47=0,($B$22*Quesería!$J$126+(1-$B$22)*Quesería!$E$122)*Quesería!$B$20*Quesería!$B$21/12*$B$23,(($B$22*Quesería!$J$126+(1-$B$22)*Quesería!$E$122)+($B$22*Quesería!$J$104+(1-$B$22)*Quesería!$E$104)*(F52-1))*IF(F$47=1,Quesería!$B$20,1))*$B$10 -> 241.95346 | G57: =IF(G$47=0,($B$22*Quesería!$J$126+(1-$B$22)*Quesería!$E$122)*Quesería!$B$20*Quesería!$B$21/12*$B$23,(($B$22*Quesería!$J$126+(1-$B$22)*Quesería!$E$122)+($B$22*Quesería!$J$104+(1-$B$22)*Quesería!$E$104)*(G52-1))*IF(G$47=1,Quesería!$B$20,1))*$B$10 -> 242.01486 | H57: =IF(H$47=0,($B$22*Quesería!$J$126+(1-$B$22)*Quesería!$E$122)*Quesería!$B$20*Quesería!$B$21/12*$B$23,(($B$22*Quesería!$J$126+(1-$B$22)*Quesería!$E$122)+($B$22*Quesería!$J$104+(1-$B$22)*Quesería!$E$104)*(H52-1))*IF(H$47=1,Quesería!$B$20,1))*$B$10 -> 242.07657 | I57: =IF(I$47=0,($B$22*Quesería!$J$126+(1-$B$22)*Quesería!$E$122)*Quesería!$B$20*Quesería!$B$21/12*$B$23,(($B$22*Quesería!$J$126+(1-$B$22)*Quesería!$E$122)+($B$22*Quesería!$J$104+(1-$B$22)*Quesería!$E$104)*(I52-1))*IF(I$47=1,Quesería!$B$20,1))*$B$10 -> 242.13858 | ... L57: =IF(L$47=0,($B$22*Quesería!$J$126+(1-$B$22)*Quesería!$E$122)*Quesería!$B$20*Quesería!$B$21/12*$B$23,(($B$22*Quesería!$J$126+(1-$B$22)*Quesería!$E$122)+($B$22*Quesería!$J$104+(1-$B$22)*Quesería!$E$104)*(L52-1))*IF(L$47=1,Quesería!$B$20,1))*$B$10 -> 242.3265
A58: Beneficio de la etapa 2 | B58: =IF(B$47<=1,0,((($B$22*Quesería!$J$127+(1-$B$22)*Quesería!$E$123)-($B$22*Quesería!$J$113+(1-$B$22)*Quesería!$E$113)+$B$6*($B$22*Quesería!$J$113+(1-$B$22)*Quesería!$E$113)-(1-$B$9)*(($B$22*Quesería!$J$119+(1-$B$22)*Quesería!$E$119)+($B$22*Quesería!$J$118+(1-$B$22)*Quesería!$E$118))-(1-$B$24)*($B$22*Quesería!$J$117+(1-$B$22)*Quesería!$E$117)+$B$24*(1-$B$25)*'Beneficios y costos'!$B$144-(-$B$26*$B$27)*'Beneficios y costos'!$C$167)+($B$6*($B$22*Quesería!$J$113+(1-$B$22)*Quesería!$E$113)+$B$9*($B$22*Quesería!$J$119+(1-$B$22)*Quesería!$E$119))*(B52-1))*IF(B$47=2,Quesería!$B$20,1)+IF(B$47=2,Quesería!$B$24*$B$9*($B$22*Quesería!$J$119+(1-$B$22)*Quesería!$E$119)*B52,0))*$B$10*$B$21 -> 0 | C58: =IF(C$47<=1,0,((($B$22*Quesería!$J$127+(1-$B$22)*Quesería!$E$123)-($B$22*Quesería!$J$113+(1-$B$22)*Quesería!$E$113)+$B$6*($B$22*Quesería!$J$113+(1-$B$22)*Quesería!$E$113)-(1-$B$9)*(($B$22*Quesería!$J$119+(1-$B$22)*Quesería!$E$119)+($B$22*Quesería!$J$118+(1-$B$22)*Quesería!$E$118))-(1-$B$24)*($B$22*Quesería!$J$117+(1-$B$22)*Quesería!$E$117)+$B$24*(1-$B$25)*'Beneficios y costos'!$B$144-(-$B$26*$B$27)*'Beneficios y costos'!$C$167)+($B$6*($B$22*Quesería!$J$113+(1-$B$22)*Quesería!$E$113)+$B$9*($B$22*Quesería!$J$119+(1-$B$22)*Quesería!$E$119))*(C52-1))*IF(C$47=2,Quesería!$B$20,1)+IF(C$47=2,Quesería!$B$24*$B$9*($B$22*Quesería!$J$119+(1-$B$22)*Quesería!$E$119)*C52,0))*$B$10*$B$21 -> 0 | D58: =IF(D$47<=1,0,((($B$22*Quesería!$J$127+(1-$B$22)*Quesería!$E$123)-($B$22*Quesería!$J$113+(1-$B$22)*Quesería!$E$113)+$B$6*($B$22*Quesería!$J$113+(1-$B$22)*Quesería!$E$113)-(1-$B$9)*(($B$22*Quesería!$J$119+(1-$B$22)*Quesería!$E$119)+($B$22*Quesería!$J$118+(1-$B$22)*Quesería!$E$118))-(1-$B$24)*($B$22*Quesería!$J$117+(1-$B$22)*Quesería!$E$117)+$B$24*(1-$B$25)*'Beneficios y costos'!$B$144-(-$B$26*$B$27)*'Beneficios y costos'!$C$167)+($B$6*($B$22*Quesería!$J$113+(1-$B$22)*Quesería!$E$113)+$B$9*($B$22*Quesería!$J$119+(1-$B$22)*Quesería!$E$119))*(D52-1))*IF(D$47=2,Quesería!$B$20,1)+IF(D$47=2,Quesería!$B$24*$B$9*($B$22*Quesería!$J$119+(1-$B$22)*Quesería!$E$119)*D52,0))*$B$10*$B$21 -> 257.35149 | E58: =IF(E$47<=1,0,((($B$22*Quesería!$J$127+(1-$B$22)*Quesería!$E$123)-($B$22*Quesería!$J$113+(1-$B$22)*Quesería!$E$113)+$B$6*($B$22*Quesería!$J$113+(1-$B$22)*Quesería!$E$113)-(1-$B$9)*(($B$22*Quesería!$J$119+(1-$B$22)*Quesería!$E$119)+($B$22*Quesería!$J$118+(1-$B$22)*Quesería!$E$118))-(1-$B$24)*($B$22*Quesería!$J$117+(1-$B$22)*Quesería!$E$117)+$B$24*(1-$B$25)*'Beneficios y costos'!$B$144-(-$B$26*$B$27)*'Beneficios y costos'!$C$167)+($B$6*($B$22*Quesería!$J$113+(1-$B$22)*Quesería!$E$113)+$B$9*($B$22*Quesería!$J$119+(1-$B$22)*Quesería!$E$119))*(E52-1))*IF(E$47=2,Quesería!$B$20,1)+IF(E$47=2,Quesería!$B$24*$B$9*($B$22*Quesería!$J$119+(1-$B$22)*Quesería!$E$119)*E52,0))*$B$10*$B$21 -> 328.49482 | F58: =IF(F$47<=1,0,((($B$22*Quesería!$J$127+(1-$B$22)*Quesería!$E$123)-($B$22*Quesería!$J$113+(1-$B$22)*Quesería!$E$113)+$B$6*($B$22*Quesería!$J$113+(1-$B$22)*Quesería!$E$113)-(1-$B$9)*(($B$22*Quesería!$J$119+(1-$B$22)*Quesería!$E$119)+($B$22*Quesería!$J$118+(1-$B$22)*Quesería!$E$118))-(1-$B$24)*($B$22*Quesería!$J$117+(1-$B$22)*Quesería!$E$117)+$B$24*(1-$B$25)*'Beneficios y costos'!$B$144-(-$B$26*$B$27)*'Beneficios y costos'!$C$167)+($B$6*($B$22*Quesería!$J$113+(1-$B$22)*Quesería!$E$113)+$B$9*($B$22*Quesería!$J$119+(1-$B$22)*Quesería!$E$119))*(F52-1))*IF(F$47=2,Quesería!$B$20,1)+IF(F$47=2,Quesería!$B$24*$B$9*($B$22*Quesería!$J$119+(1-$B$22)*Quesería!$E$119)*F52,0))*$B$10*$B$21 -> 328.74294 | G58: =IF(G$47<=1,0,((($B$22*Quesería!$J$127+(1-$B$22)*Quesería!$E$123)-($B$22*Quesería!$J$113+(1-$B$22)*Quesería!$E$113)+$B$6*($B$22*Quesería!$J$113+(1-$B$22)*Quesería!$E$113)-(1-$B$9)*(($B$22*Quesería!$J$119+(1-$B$22)*Quesería!$E$119)+($B$22*Quesería!$J$118+(1-$B$22)*Quesería!$E$118))-(1-$B$24)*($B$22*Quesería!$J$117+(1-$B$22)*Quesería!$E$117)+$B$24*(1-$B$25)*'Beneficios y costos'!$B$144-(-$B$26*$B$27)*'Beneficios y costos'!$C$167)+($B$6*($B$22*Quesería!$J$113+(1-$B$22)*Quesería!$E$113)+$B$9*($B$22*Quesería!$J$119+(1-$B$22)*Quesería!$E$119))*(G52-1))*IF(G$47=2,Quesería!$B$20,1)+IF(G$47=2,Quesería!$B$24*$B$9*($B$22*Quesería!$J$119+(1-$B$22)*Quesería!$E$119)*G52,0))*$B$10*$B$21 -> 328.99229 | H58: =IF(H$47<=1,0,((($B$22*Quesería!$J$127+(1-$B$22)*Quesería!$E$123)-($B$22*Quesería!$J$113+(1-$B$22)*Quesería!$E$113)+$B$6*($B$22*Quesería!$J$113+(1-$B$22)*Quesería!$E$113)-(1-$B$9)*(($B$22*Quesería!$J$119+(1-$B$22)*Quesería!$E$119)+($B$22*Quesería!$J$118+(1-$B$22)*Quesería!$E$118))-(1-$B$24)*($B$22*Quesería!$J$117+(1-$B$22)*Quesería!$E$117)+$B$24*(1-$B$25)*'Beneficios y costos'!$B$144-(-$B$26*$B$27)*'Beneficios y costos'!$C$167)+($B$6*($B$22*Quesería!$J$113+(1-$B$22)*Quesería!$E$113)+$B$9*($B$22*Quesería!$J$119+(1-$B$22)*Quesería!$E$119))*(H52-1))*IF(H$47=2,Quesería!$B$20,1)+IF(H$47=2,Quesería!$B$24*$B$9*($B$22*Quesería!$J$119+(1-$B$22)*Quesería!$E$119)*H52,0))*$B$10*$B$21 -> 329.2429 | I58: =IF(I$47<=1,0,((($B$22*Quesería!$J$127+(1-$B$22)*Quesería!$E$123)-($B$22*Quesería!$J$113+(1-$B$22)*Quesería!$E$113)+$B$6*($B$22*Quesería!$J$113+(1-$B$22)*Quesería!$E$113)-(1-$B$9)*(($B$22*Quesería!$J$119+(1-$B$22)*Quesería!$E$119)+($B$22*Quesería!$J$118+(1-$B$22)*Quesería!$E$118))-(1-$B$24)*($B$22*Quesería!$J$117+(1-$B$22)*Quesería!$E$117)+$B$24*(1-$B$25)*'Beneficios y costos'!$B$144-(-$B$26*$B$27)*'Beneficios y costos'!$C$167)+($B$6*($B$22*Quesería!$J$113+(1-$B$22)*Quesería!$E$113)+$B$9*($B$22*Quesería!$J$119+(1-$B$22)*Quesería!$E$119))*(I52-1))*IF(I$47=2,Quesería!$B$20,1)+IF(I$47=2,Quesería!$B$24*$B$9*($B$22*Quesería!$J$119+(1-$B$22)*Quesería!$E$119)*I52,0))*$B$10*$B$21 -> 329.49476 | ... L58: =IF(L$47<=1,0,((($B$22*Quesería!$J$127+(1-$B$22)*Quesería!$E$123)-($B$22*Quesería!$J$113+(1-$B$22)*Quesería!$E$113)+$B$6*($B$22*Quesería!$J$113+(1-$B$22)*Quesería!$E$113)-(1-$B$9)*(($B$22*Quesería!$J$119+(1-$B$22)*Quesería!$E$119)+($B$22*Quesería!$J$118+(1-$B$22)*Quesería!$E$118))-(1-$B$24)*($B$22*Quesería!$J$117+(1-$B$22)*Quesería!$E$117)+$B$24*(1-$B$25)*'Beneficios y costos'!$B$144-(-$B$26*$B$27)*'Beneficios y costos'!$C$167)+($B$6*($B$22*Quesería!$J$113+(1-$B$22)*Quesería!$E$113)+$B$9*($B$22*Quesería!$J$119+(1-$B$22)*Quesería!$E$119))*(L52-1))*IF(L$47=2,Quesería!$B$20,1)+IF(L$47=2,Quesería!$B$24*$B$9*($B$22*Quesería!$J$119+(1-$B$22)*Quesería!$E$119)*L52,0))*$B$10*$B$21 -> 330.25791
A59: Beneficio total | B59: =B57+B58 -> 120.71677 | C59: =C57+C58 -> 181.32832 | D59: =D57+D58 -> 499.18307 | E59: =E57+E58 -> 570.38719 | F59: =F57+F58 -> 570.6964 | G59: =G57+G58 -> 571.00716 | H59: =H57+H58 -> 571.31947 | I59: =I57+I58 -> 571.63334 | ... L59: =L57+L58 -> 572.5844
A60: Costos operativos nuevos | B60: =(IF(B$47>=1,(Quesería!$B$31+Quesería!$B$33)*Quesería!$F$94*$B$11+Quesería!$B$32+'Beneficios y costos'!$B$249,0)+IF(B$47>=2,((Quesería!$B$31+Quesería!$B$33)*(Quesería!$F$95-(-$B$26)*Quesería!$D$86)*$B$11+'Beneficios y costos'!$C$249-(-$B$26)*'Beneficios y costos'!$H$235)*$B$21,0))*$B$12 -> 0 | C60: =(IF(C$47>=1,(Quesería!$B$31+Quesería!$B$33)*Quesería!$F$94*$B$11+Quesería!$B$32+'Beneficios y costos'!$B$249,0)+IF(C$47>=2,((Quesería!$B$31+Quesería!$B$33)*(Quesería!$F$95-(-$B$26)*Quesería!$D$86)*$B$11+'Beneficios y costos'!$C$249-(-$B$26)*'Beneficios y costos'!$H$235)*$B$21,0))*$B$12 -> 42.094649 | D60: =(IF(D$47>=1,(Quesería!$B$31+Quesería!$B$33)*Quesería!$F$94*$B$11+Quesería!$B$32+'Beneficios y costos'!$B$249,0)+IF(D$47>=2,((Quesería!$B$31+Quesería!$B$33)*(Quesería!$F$95-(-$B$26)*Quesería!$D$86)*$B$11+'Beneficios y costos'!$C$249-(-$B$26)*'Beneficios y costos'!$H$235)*$B$21,0))*$B$12 -> 76.496482 | E60: =(IF(E$47>=1,(Quesería!$B$31+Quesería!$B$33)*Quesería!$F$94*$B$11+Quesería!$B$32+'Beneficios y costos'!$B$249,0)+IF(E$47>=2,((Quesería!$B$31+Quesería!$B$33)*(Quesería!$F$95-(-$B$26)*Quesería!$D$86)*$B$11+'Beneficios y costos'!$C$249-(-$B$26)*'Beneficios y costos'!$H$235)*$B$21,0))*$B$12 -> 76.496482 | F60: =(IF(F$47>=1,(Quesería!$B$31+Quesería!$B$33)*Quesería!$F$94*$B$11+Quesería!$B$32+'Beneficios y costos'!$B$249,0)+IF(F$47>=2,((Quesería!$B$31+Quesería!$B$33)*(Quesería!$F$95-(-$B$26)*Quesería!$D$86)*$B$11+'Beneficios y costos'!$C$249-(-$B$26)*'Beneficios y costos'!$H$235)*$B$21,0))*$B$12 -> 76.496482 | G60: =(IF(G$47>=1,(Quesería!$B$31+Quesería!$B$33)*Quesería!$F$94*$B$11+Quesería!$B$32+'Beneficios y costos'!$B$249,0)+IF(G$47>=2,((Quesería!$B$31+Quesería!$B$33)*(Quesería!$F$95-(-$B$26)*Quesería!$D$86)*$B$11+'Beneficios y costos'!$C$249-(-$B$26)*'Beneficios y costos'!$H$235)*$B$21,0))*$B$12 -> 76.496482 | H60: =(IF(H$47>=1,(Quesería!$B$31+Quesería!$B$33)*Quesería!$F$94*$B$11+Quesería!$B$32+'Beneficios y costos'!$B$249,0)+IF(H$47>=2,((Quesería!$B$31+Quesería!$B$33)*(Quesería!$F$95-(-$B$26)*Quesería!$D$86)*$B$11+'Beneficios y costos'!$C$249-(-$B$26)*'Beneficios y costos'!$H$235)*$B$21,0))*$B$12 -> 76.496482 | I60: =(IF(I$47>=1,(Quesería!$B$31+Quesería!$B$33)*Quesería!$F$94*$B$11+Quesería!$B$32+'Beneficios y costos'!$B$249,0)+IF(I$47>=2,((Quesería!$B$31+Quesería!$B$33)*(Quesería!$F$95-(-$B$26)*Quesería!$D$86)*$B$11+'Beneficios y costos'!$C$249-(-$B$26)*'Beneficios y costos'!$H$235)*$B$21,0))*$B$12 -> 76.496482 | ... L60: =(IF(L$47>=1,(Quesería!$B$31+Quesería!$B$33)*Quesería!$F$94*$B$11+Quesería!$B$32+'Beneficios y costos'!$B$249,0)+IF(L$47>=2,((Quesería!$B$31+Quesería!$B$33)*(Quesería!$F$95-(-$B$26)*Quesería!$D$86)*$B$11+'Beneficios y costos'!$C$249-(-$B$26)*'Beneficios y costos'!$H$235)*$B$21,0))*$B$12 -> 76.496482
A61: Costo de la transición del personal | B61: =IF(B$47=1,2*Quesería!$B$22*Quesería!$B$23/12*B52,0)*$B$21 -> 0 | C61: =IF(C$47=1,2*Quesería!$B$22*Quesería!$B$23/12*C52,0)*$B$21 -> 18.516651 | D61: =IF(D$47=1,2*Quesería!$B$22*Quesería!$B$23/12*D52,0)*$B$21 -> 0 | E61: =IF(E$47=1,2*Quesería!$B$22*Quesería!$B$23/12*E52,0)*$B$21 -> 0 | F61: =IF(F$47=1,2*Quesería!$B$22*Quesería!$B$23/12*F52,0)*$B$21 -> 0 | G61: =IF(G$47=1,2*Quesería!$B$22*Quesería!$B$23/12*G52,0)*$B$21 -> 0 | H61: =IF(H$47=1,2*Quesería!$B$22*Quesería!$B$23/12*H52,0)*$B$21 -> 0 | I61: =IF(I$47=1,2*Quesería!$B$22*Quesería!$B$23/12*I52,0)*$B$21 -> 0 | ... L61: =IF(L$47=1,2*Quesería!$B$22*Quesería!$B$23/12*L52,0)*$B$21 -> 0
A62: GMF de los pagos del proyecto | B62: =Quesería!$B$52*(B54+B55+B56+B60+B61) -> 4.3196636 | C62: =Quesería!$B$52*(C54+C55+C56+C60+C61) -> 3.376758 | D62: =Quesería!$B$52*(D54+D55+D56+D60+D61) -> 0.30598593 | E62: =Quesería!$B$52*(E54+E55+E56+E60+E61) -> 0.30598593 | F62: =Quesería!$B$52*(F54+F55+F56+F60+F61) -> 0.30598593 | G62: =Quesería!$B$52*(G54+G55+G56+G60+G61) -> 0.43672036 | H62: =Quesería!$B$52*(H54+H55+H56+H60+H61) -> 0.52679831 | I62: =Quesería!$B$52*(I54+I55+I56+I60+I61) -> 0.30598593 | ... L62: =Quesería!$B$52*(L54+L55+L56+L60+L61) -> 0.30598593
A63: Depreciación y gastos deducibles de la inversión | B63: =(IF($B$19=1,(SUMPRODUCT((Quesería!$C$70:$C$89=0)*(Quesería!$J$70:$J$89>0)*(B$47>=1)*(B$47<=Quesería!$J$70:$J$89)*(Quesería!$H$70:$H$89>0)*Quesería!$F$70:$F$89*(1+Quesería!$I$70:$I$89)/(Quesería!$J$70:$J$89+(Quesería!$J$70:$J$89=0)))+SUMPRODUCT((Quesería!$C$70:$C$89=0)*(Quesería!$J$70:$J$89=0)*(B$47=0)*(Quesería!$H$70:$H$89>0)*Quesería!$F$70:$F$89*(1+Quesería!$I$70:$I$89)))*$B$51+((SUMPRODUCT((Quesería!$C$70:$C$89=1)*(Quesería!$J$70:$J$89>0)*(B$47>=2)*(B$47<=Quesería!$J$70:$J$89+1)*(Quesería!$H$70:$H$89>0)*Quesería!$F$70:$F$89*(1+Quesería!$I$70:$I$89)/(Quesería!$J$70:$J$89+(Quesería!$J$70:$J$89=0)))+SUMPRODUCT((Quesería!$C$70:$C$89=1)*(Quesería!$J$70:$J$89=0)*(B$47=1)*(Quesería!$H$70:$H$89>0)*Quesería!$F$70:$F$89*(1+Quesería!$I$70:$I$89)))-(-$B$26)*IF(AND(B$47>=2,B$47<=Quesería!$J$86+1),Quesería!$D$86*(1+Quesería!$I$86)/Quesería!$J$86,0))*$C$51*$B$21,IF(AND(B$47>=1,B$47<=Quesería!$B$30),Quesería!$F$92/Quesería!$B$30,0)*$B$51+IF(AND(B$47>=2,B$47<=Quesería!$B$30+1),(Quesería!$F$93-(-$B$26)*Quesería!$D$86*(1+Quesería!$I$86))/Quesería!$B$30,0)*$C$51*$B$21)*$B$11+IF(AND(B$47>=6,B$47<=10),$G55*$G51/5,0)+IF(AND(B$47>=7,B$47<=11),$H55*$H51/5,0))*B53 -> 145.98092 | C63: =(IF($B$19=1,(SUMPRODUCT((Quesería!$C$70:$C$89=0)*(Quesería!$J$70:$J$89>0)*(C$47>=1)*(C$47<=Quesería!$J$70:$J$89)*(Quesería!$H$70:$H$89>0)*Quesería!$F$70:$F$89*(1+Quesería!$I$70:$I$89)/(Quesería!$J$70:$J$89+(Quesería!$J$70:$J$89=0)))+SUMPRODUCT((Quesería!$C$70:$C$89=0)*(Quesería!$J$70:$J$89=0)*(C$47=0)*(Quesería!$H$70:$H$89>0)*Quesería!$F$70:$F$89*(1+Quesería!$I$70:$I$89)))*$B$51+((SUMPRODUCT((Quesería!$C$70:$C$89=1)*(Quesería!$J$70:$J$89>0)*(C$47>=2)*(C$47<=Quesería!$J$70:$J$89+1)*(Quesería!$H$70:$H$89>0)*Quesería!$F$70:$F$89*(1+Quesería!$I$70:$I$89)/(Quesería!$J$70:$J$89+(Quesería!$J$70:$J$89=0)))+SUMPRODUCT((Quesería!$C$70:$C$89=1)*(Quesería!$J$70:$J$89=0)*(C$47=1)*(Quesería!$H$70:$H$89>0)*Quesería!$F$70:$F$89*(1+Quesería!$I$70:$I$89)))-(-$B$26)*IF(AND(C$47>=2,C$47<=Quesería!$J$86+1),Quesería!$D$86*(1+Quesería!$I$86)/Quesería!$J$86,0))*$C$51*$B$21,IF(AND(C$47>=1,C$47<=Quesería!$B$30),Quesería!$F$92/Quesería!$B$30,0)*$B$51+IF(AND(C$47>=2,C$47<=Quesería!$B$30+1),(Quesería!$F$93-(-$B$26)*Quesería!$D$86*(1+Quesería!$I$86))/Quesería!$B$30,0)*$C$51*$B$21)*$B$11+IF(AND(C$47>=6,C$47<=10),$G55*$G51/5,0)+IF(AND(C$47>=7,C$47<=11),$H55*$H51/5,0))*C53 -> 82.263327 | D63: =(IF($B$19=1,(SUMPRODUCT((Quesería!$C$70:$C$89=0)*(Quesería!$J$70:$J$89>0)*(D$47>=1)*(D$47<=Quesería!$J$70:$J$89)*(Quesería!$H$70:$H$89>0)*Quesería!$F$70:$F$89*(1+Quesería!$I$70:$I$89)/(Quesería!$J$70:$J$89+(Quesería!$J$70:$J$89=0)))+SUMPRODUCT((Quesería!$C$70:$C$89=0)*(Quesería!$J$70:$J$89=0)*(D$47=0)*(Quesería!$H$70:$H$89>0)*Quesería!$F$70:$F$89*(1+Quesería!$I$70:$I$89)))*$B$51+((SUMPRODUCT((Quesería!$C$70:$C$89=1)*(Quesería!$J$70:$J$89>0)*(D$47>=2)*(D$47<=Quesería!$J$70:$J$89+1)*(Quesería!$H$70:$H$89>0)*Quesería!$F$70:$F$89*(1+Quesería!$I$70:$I$89)/(Quesería!$J$70:$J$89+(Quesería!$J$70:$J$89=0)))+SUMPRODUCT((Quesería!$C$70:$C$89=1)*(Quesería!$J$70:$J$89=0)*(D$47=1)*(Quesería!$H$70:$H$89>0)*Quesería!$F$70:$F$89*(1+Quesería!$I$70:$I$89)))-(-$B$26)*IF(AND(D$47>=2,D$47<=Quesería!$J$86+1),Quesería!$D$86*(1+Quesería!$I$86)/Quesería!$J$86,0))*$C$51*$B$21,IF(AND(D$47>=1,D$47<=Quesería!$B$30),Quesería!$F$92/Quesería!$B$30,0)*$B$51+IF(AND(D$47>=2,D$47<=Quesería!$B$30+1),(Quesería!$F$93-(-$B$26)*Quesería!$D$86*(1+Quesería!$I$86))/Quesería!$B$30,0)*$C$51*$B$21)*$B$11+IF(AND(D$47>=6,D$47<=10),$G55*$G51/5,0)+IF(AND(D$47>=7,D$47<=11),$H55*$H51/5,0))*D53 -> 141.73228 | E63: =(IF($B$19=1,(SUMPRODUCT((Quesería!$C$70:$C$89=0)*(Quesería!$J$70:$J$89>0)*(E$47>=1)*(E$47<=Quesería!$J$70:$J$89)*(Quesería!$H$70:$H$89>0)*Quesería!$F$70:$F$89*(1+Quesería!$I$70:$I$89)/(Quesería!$J$70:$J$89+(Quesería!$J$70:$J$89=0)))+SUMPRODUCT((Quesería!$C$70:$C$89=0)*(Quesería!$J$70:$J$89=0)*(E$47=0)*(Quesería!$H$70:$H$89>0)*Quesería!$F$70:$F$89*(1+Quesería!$I$70:$I$89)))*$B$51+((SUMPRODUCT((Quesería!$C$70:$C$89=1)*(Quesería!$J$70:$J$89>0)*(E$47>=2)*(E$47<=Quesería!$J$70:$J$89+1)*(Quesería!$H$70:$H$89>0)*Quesería!$F$70:$F$89*(1+Quesería!$I$70:$I$89)/(Quesería!$J$70:$J$89+(Quesería!$J$70:$J$89=0)))+SUMPRODUCT((Quesería!$C$70:$C$89=1)*(Quesería!$J$70:$J$89=0)*(E$47=1)*(Quesería!$H$70:$H$89>0)*Quesería!$F$70:$F$89*(1+Quesería!$I$70:$I$89)))-(-$B$26)*IF(AND(E$47>=2,E$47<=Quesería!$J$86+1),Quesería!$D$86*(1+Quesería!$I$86)/Quesería!$J$86,0))*$C$51*$B$21,IF(AND(E$47>=1,E$47<=Quesería!$B$30),Quesería!$F$92/Quesería!$B$30,0)*$B$51+IF(AND(E$47>=2,E$47<=Quesería!$B$30+1),(Quesería!$F$93-(-$B$26)*Quesería!$D$86*(1+Quesería!$I$86))/Quesería!$B$30,0)*$C$51*$B$21)*$B$11+IF(AND(E$47>=6,E$47<=10),$G55*$G51/5,0)+IF(AND(E$47>=7,E$47<=11),$H55*$H51/5,0))*E53 -> 136.28104 | F63: =(IF($B$19=1,(SUMPRODUCT((Quesería!$C$70:$C$89=0)*(Quesería!$J$70:$J$89>0)*(F$47>=1)*(F$47<=Quesería!$J$70:$J$89)*(Quesería!$H$70:$H$89>0)*Quesería!$F$70:$F$89*(1+Quesería!$I$70:$I$89)/(Quesería!$J$70:$J$89+(Quesería!$J$70:$J$89=0)))+SUMPRODUCT((Quesería!$C$70:$C$89=0)*(Quesería!$J$70:$J$89=0)*(F$47=0)*(Quesería!$H$70:$H$89>0)*Quesería!$F$70:$F$89*(1+Quesería!$I$70:$I$89)))*$B$51+((SUMPRODUCT((Quesería!$C$70:$C$89=1)*(Quesería!$J$70:$J$89>0)*(F$47>=2)*(F$47<=Quesería!$J$70:$J$89+1)*(Quesería!$H$70:$H$89>0)*Quesería!$F$70:$F$89*(1+Quesería!$I$70:$I$89)/(Quesería!$J$70:$J$89+(Quesería!$J$70:$J$89=0)))+SUMPRODUCT((Quesería!$C$70:$C$89=1)*(Quesería!$J$70:$J$89=0)*(F$47=1)*(Quesería!$H$70:$H$89>0)*Quesería!$F$70:$F$89*(1+Quesería!$I$70:$I$89)))-(-$B$26)*IF(AND(F$47>=2,F$47<=Quesería!$J$86+1),Quesería!$D$86*(1+Quesería!$I$86)/Quesería!$J$86,0))*$C$51*$B$21,IF(AND(F$47>=1,F$47<=Quesería!$B$30),Quesería!$F$92/Quesería!$B$30,0)*$B$51+IF(AND(F$47>=2,F$47<=Quesería!$B$30+1),(Quesería!$F$93-(-$B$26)*Quesería!$D$86*(1+Quesería!$I$86))/Quesería!$B$30,0)*$C$51*$B$21)*$B$11+IF(AND(F$47>=6,F$47<=10),$G55*$G51/5,0)+IF(AND(F$47>=7,F$47<=11),$H55*$H51/5,0))*F53 -> 131.03946 | G63: =(IF($B$19=1,(SUMPRODUCT((Quesería!$C$70:$C$89=0)*(Quesería!$J$70:$J$89>0)*(G$47>=1)*(G$47<=Quesería!$J$70:$J$89)*(Quesería!$H$70:$H$89>0)*Quesería!$F$70:$F$89*(1+Quesería!$I$70:$I$89)/(Quesería!$J$70:$J$89+(Quesería!$J$70:$J$89=0)))+SUMPRODUCT((Quesería!$C$70:$C$89=0)*(Quesería!$J$70:$J$89=0)*(G$47=0)*(Quesería!$H$70:$H$89>0)*Quesería!$F$70:$F$89*(1+Quesería!$I$70:$I$89)))*$B$51+((SUMPRODUCT((Quesería!$C$70:$C$89=1)*(Quesería!$J$70:$J$89>0)*(G$47>=2)*(G$47<=Quesería!$J$70:$J$89+1)*(Quesería!$H$70:$H$89>0)*Quesería!$F$70:$F$89*(1+Quesería!$I$70:$I$89)/(Quesería!$J$70:$J$89+(Quesería!$J$70:$J$89=0)))+SUMPRODUCT((Quesería!$C$70:$C$89=1)*(Quesería!$J$70:$J$89=0)*(G$47=1)*(Quesería!$H$70:$H$89>0)*Quesería!$F$70:$F$89*(1+Quesería!$I$70:$I$89)))-(-$B$26)*IF(AND(G$47>=2,G$47<=Quesería!$J$86+1),Quesería!$D$86*(1+Quesería!$I$86)/Quesería!$J$86,0))*$C$51*$B$21,IF(AND(G$47>=1,G$47<=Quesería!$B$30),Quesería!$F$92/Quesería!$B$30,0)*$B$51+IF(AND(G$47>=2,G$47<=Quesería!$B$30+1),(Quesería!$F$93-(-$B$26)*Quesería!$D$86*(1+Quesería!$I$86))/Quesería!$B$30,0)*$C$51*$B$21)*$B$11+IF(AND(G$47>=6,G$47<=10),$G55*$G51/5,0)+IF(AND(G$47>=7,G$47<=11),$H55*$H51/5,0))*G53 -> 125.99948 | H63: =(IF($B$19=1,(SUMPRODUCT((Quesería!$C$70:$C$89=0)*(Quesería!$J$70:$J$89>0)*(H$47>=1)*(H$47<=Quesería!$J$70:$J$89)*(Quesería!$H$70:$H$89>0)*Quesería!$F$70:$F$89*(1+Quesería!$I$70:$I$89)/(Quesería!$J$70:$J$89+(Quesería!$J$70:$J$89=0)))+SUMPRODUCT((Quesería!$C$70:$C$89=0)*(Quesería!$J$70:$J$89=0)*(H$47=0)*(Quesería!$H$70:$H$89>0)*Quesería!$F$70:$F$89*(1+Quesería!$I$70:$I$89)))*$B$51+((SUMPRODUCT((Quesería!$C$70:$C$89=1)*(Quesería!$J$70:$J$89>0)*(H$47>=2)*(H$47<=Quesería!$J$70:$J$89+1)*(Quesería!$H$70:$H$89>0)*Quesería!$F$70:$F$89*(1+Quesería!$I$70:$I$89)/(Quesería!$J$70:$J$89+(Quesería!$J$70:$J$89=0)))+SUMPRODUCT((Quesería!$C$70:$C$89=1)*(Quesería!$J$70:$J$89=0)*(H$47=1)*(Quesería!$H$70:$H$89>0)*Quesería!$F$70:$F$89*(1+Quesería!$I$70:$I$89)))-(-$B$26)*IF(AND(H$47>=2,H$47<=Quesería!$J$86+1),Quesería!$D$86*(1+Quesería!$I$86)/Quesería!$J$86,0))*$C$51*$B$21,IF(AND(H$47>=1,H$47<=Quesería!$B$30),Quesería!$F$92/Quesería!$B$30,0)*$B$51+IF(AND(H$47>=2,H$47<=Quesería!$B$30+1),(Quesería!$F$93-(-$B$26)*Quesería!$D$86*(1+Quesería!$I$86))/Quesería!$B$30,0)*$C$51*$B$21)*$B$11+IF(AND(H$47>=6,H$47<=10),$G55*$G51/5,0)+IF(AND(H$47>=7,H$47<=11),$H55*$H51/5,0))*H53 -> 114.13473 | I63: =(IF($B$19=1,(SUMPRODUCT((Quesería!$C$70:$C$89=0)*(Quesería!$J$70:$J$89>0)*(I$47>=1)*(I$47<=Quesería!$J$70:$J$89)*(Quesería!$H$70:$H$89>0)*Quesería!$F$70:$F$89*(1+Quesería!$I$70:$I$89)/(Quesería!$J$70:$J$89+(Quesería!$J$70:$J$89=0)))+SUMPRODUCT((Quesería!$C$70:$C$89=0)*(Quesería!$J$70:$J$89=0)*(I$47=0)*(Quesería!$H$70:$H$89>0)*Quesería!$F$70:$F$89*(1+Quesería!$I$70:$I$89)))*$B$51+((SUMPRODUCT((Quesería!$C$70:$C$89=1)*(Quesería!$J$70:$J$89>0)*(I$47>=2)*(I$47<=Quesería!$J$70:$J$89+1)*(Quesería!$H$70:$H$89>0)*Quesería!$F$70:$F$89*(1+Quesería!$I$70:$I$89)/(Quesería!$J$70:$J$89+(Quesería!$J$70:$J$89=0)))+SUMPRODUCT((Quesería!$C$70:$C$89=1)*(Quesería!$J$70:$J$89=0)*(I$47=1)*(Quesería!$H$70:$H$89>0)*Quesería!$F$70:$F$89*(1+Quesería!$I$70:$I$89)))-(-$B$26)*IF(AND(I$47>=2,I$47<=Quesería!$J$86+1),Quesería!$D$86*(1+Quesería!$I$86)/Quesería!$J$86,0))*$C$51*$B$21,IF(AND(I$47>=1,I$47<=Quesería!$B$30),Quesería!$F$92/Quesería!$B$30,0)*$B$51+IF(AND(I$47>=2,I$47<=Quesería!$B$30+1),(Quesería!$F$93-(-$B$26)*Quesería!$D$86*(1+Quesería!$I$86))/Quesería!$B$30,0)*$C$51*$B$21)*$B$11+IF(AND(I$47>=6,I$47<=10),$G55*$G51/5,0)+IF(AND(I$47>=7,I$47<=11),$H55*$H51/5,0))*I53 -> 118.66592 | ... L63: =(IF($B$19=1,(SUMPRODUCT((Quesería!$C$70:$C$89=0)*(Quesería!$J$70:$J$89>0)*(L$47>=1)*(L$47<=Quesería!$J$70:$J$89)*(Quesería!$H$70:$H$89>0)*Quesería!$F$70:$F$89*(1+Quesería!$I$70:$I$89)/(Quesería!$J$70:$J$89+(Quesería!$J$70:$J$89=0)))+SUMPRODUCT((Quesería!$C$70:$C$89=0)*(Quesería!$J$70:$J$89=0)*(L$47=0)*(Quesería!$H$70:$H$89>0)*Quesería!$F$70:$F$89*(1+Quesería!$I$70:$I$89)))*$B$51+((SUMPRODUCT((Quesería!$C$70:$C$89=1)*(Quesería!$J$70:$J$89>0)*(L$47>=2)*(L$47<=Quesería!$J$70:$J$89+1)*(Quesería!$H$70:$H$89>0)*Quesería!$F$70:$F$89*(1+Quesería!$I$70:$I$89)/(Quesería!$J$70:$J$89+(Quesería!$J$70:$J$89=0)))+SUMPRODUCT((Quesería!$C$70:$C$89=1)*(Quesería!$J$70:$J$89=0)*(L$47=1)*(Quesería!$H$70:$H$89>0)*Quesería!$F$70:$F$89*(1+Quesería!$I$70:$I$89)))-(-$B$26)*IF(AND(L$47>=2,L$47<=Quesería!$J$86+1),Quesería!$D$86*(1+Quesería!$I$86)/Quesería!$J$86,0))*$C$51*$B$21,IF(AND(L$47>=1,L$47<=Quesería!$B$30),Quesería!$F$92/Quesería!$B$30,0)*$B$51+IF(AND(L$47>=2,L$47<=Quesería!$B$30+1),(Quesería!$F$93-(-$B$26)*Quesería!$D$86*(1+Quesería!$I$86))/Quesería!$B$30,0)*$C$51*$B$21)*$B$11+IF(AND(L$47>=6,L$47<=10),$G55*$G51/5,0)+IF(AND(L$47>=7,L$47<=11),$H55*$H51/5,0))*L53 -> 105.49357
A64: Descuento tributario (art. 255) | B64: =IF(B$47=1,MIN($B$7*$B$26*Quesería!$B$56*Quesería!$D$86*$B$11*$B$21,Quesería!$B$57*Quesería!$B$58),0) -> 0 | C64: =IF(C$47=1,MIN($B$7*$B$26*Quesería!$B$56*Quesería!$D$86*$B$11*$B$21,Quesería!$B$57*Quesería!$B$58),0) -> 0 | D64: =IF(D$47=1,MIN($B$7*$B$26*Quesería!$B$56*Quesería!$D$86*$B$11*$B$21,Quesería!$B$57*Quesería!$B$58),0) -> 0 | E64: =IF(E$47=1,MIN($B$7*$B$26*Quesería!$B$56*Quesería!$D$86*$B$11*$B$21,Quesería!$B$57*Quesería!$B$58),0) -> 0 | F64: =IF(F$47=1,MIN($B$7*$B$26*Quesería!$B$56*Quesería!$D$86*$B$11*$B$21,Quesería!$B$57*Quesería!$B$58),0) -> 0 | G64: =IF(G$47=1,MIN($B$7*$B$26*Quesería!$B$56*Quesería!$D$86*$B$11*$B$21,Quesería!$B$57*Quesería!$B$58),0) -> 0 | H64: =IF(H$47=1,MIN($B$7*$B$26*Quesería!$B$56*Quesería!$D$86*$B$11*$B$21,Quesería!$B$57*Quesería!$B$58),0) -> 0 | I64: =IF(I$47=1,MIN($B$7*$B$26*Quesería!$B$56*Quesería!$D$86*$B$11*$B$21,Quesería!$B$57*Quesería!$B$58),0) -> 0 | ... L64: =IF(L$47=1,MIN($B$7*$B$26*Quesería!$B$56*Quesería!$D$86*$B$11*$B$21,Quesería!$B$57*Quesería!$B$58),0) -> 0
A65: Crédito fiscal por innovación (art. 256-1) | B65: 0 | C65: =$B$20*Quesería!$B$60*Quesería!$F$98*$B$11*$B$51/C51/2 -> 138.12868 | D65: =$B$20*Quesería!$B$60*Quesería!$F$98*$B$11*$B$51/D51/2 -> 132.18056 | E65: 0 | F65: 0 | G65: 0 | H65: 0 | I65: 0 | J65: 0 | K65: 0 | L65: 0
A66: IVA recuperado como descuento de renta (art. 258-1) | B66: =0 -> 0 | C66: =B56*B51/C51 -> 142.01493 | D66: =C56*C51/D51 -> 119.72165 | E66: =D56*D51/E51 -> 0 | F66: =E56*E51/F51 -> 0 | G66: =F56*F51/G51 -> 0 | H66: =G56*G51/H51 -> 5.0176839 | I66: =H56*H51/I51 -> 8.4749419 | J66: =I56*I51/J51 -> 0 | ... L66: =K56*K51/L51 -> 0
A67: Impuesto de renta | B67: =$B$17*(B59-B60-B61-0.5*B62-B63)-B64-B65-B66 -> -9.5983912 | C67: =$B$17*(C59-C60-C61-0.5*C62-C63)-C64-C65-C66 -> -267.27575 | D67: =$B$17*(D59-D60-D61-0.5*D62-D63)-D64-D65-D66 -> -153.62175 | E67: =$B$17*(E59-E60-E61-0.5*E62-E63)-E64-E65-E66 -> 125.10984 | F67: =$B$17*(F59-F60-F61-0.5*F62-F63)-F64-F65-F66 -> 127.05261 | G67: =$B$17*(G59-G60-G61-0.5*G62-G63)-G64-G65-G66 -> 128.90249 | H67: =$B$17*(H59-H60-H61-0.5*H62-H63)-H64-H65-H66 -> 128.13102 | I67: =$B$17*(I59-I60-I61-0.5*I62-I63)-I64-I65-I66 -> 123.23634 | ... L67: =$B$17*(L59-L60-L61-0.5*L62-L63)-L64-L65-L66 -> 136.65448
A68: Ventas adicionales | B68: =(IF(B$47>=1,Quesería!$G$124*IF(B$47=1,Quesería!$B$20,1),Quesería!$G$124*Quesería!$B$20*Quesería!$B$21/12*$B$23)+IF(B$47>=2,(Quesería!$G$125-(1-$B$24)*Quesería!$G$117-(-$B$26*$B$27)*'Beneficios y costos'!$D$167)*$B$21*IF(B$47=2,Quesería!$B$20,1),0))*$B$10 -> 77.404287 | C68: =(IF(C$47>=1,Quesería!$G$124*IF(C$47=1,Quesería!$B$20,1),Quesería!$G$124*Quesería!$B$20*Quesería!$B$21/12*$B$23)+IF(C$47>=2,(Quesería!$G$125-(1-$B$24)*Quesería!$G$117-(-$B$26*$B$27)*'Beneficios y costos'!$D$167)*$B$21*IF(C$47=2,Quesería!$B$20,1),0))*$B$10 -> 116.10643 | D68: =(IF(D$47>=1,Quesería!$G$124*IF(D$47=1,Quesería!$B$20,1),Quesería!$G$124*Quesería!$B$20*Quesería!$B$21/12*$B$23)+IF(D$47>=2,(Quesería!$G$125-(1-$B$24)*Quesería!$G$117-(-$B$26*$B$27)*'Beneficios y costos'!$D$167)*$B$21*IF(D$47=2,Quesería!$B$20,1),0))*$B$10 -> 2023.7892 | E68: =(IF(E$47>=1,Quesería!$G$124*IF(E$47=1,Quesería!$B$20,1),Quesería!$G$124*Quesería!$B$20*Quesería!$B$21/12*$B$23)+IF(E$47>=2,(Quesería!$G$125-(1-$B$24)*Quesería!$G$117-(-$B$26*$B$27)*'Beneficios y costos'!$D$167)*$B$21*IF(E$47=2,Quesería!$B$20,1),0))*$B$10 -> 2646.7827 | F68: =(IF(F$47>=1,Quesería!$G$124*IF(F$47=1,Quesería!$B$20,1),Quesería!$G$124*Quesería!$B$20*Quesería!$B$21/12*$B$23)+IF(F$47>=2,(Quesería!$G$125-(1-$B$24)*Quesería!$G$117-(-$B$26*$B$27)*'Beneficios y costos'!$D$167)*$B$21*IF(F$47=2,Quesería!$B$20,1),0))*$B$10 -> 2646.7827 | G68: =(IF(G$47>=1,Quesería!$G$124*IF(G$47=1,Quesería!$B$20,1),Quesería!$G$124*Quesería!$B$20*Quesería!$B$21/12*$B$23)+IF(G$47>=2,(Quesería!$G$125-(1-$B$24)*Quesería!$G$117-(-$B$26*$B$27)*'Beneficios y costos'!$D$167)*$B$21*IF(G$47=2,Quesería!$B$20,1),0))*$B$10 -> 2646.7827 | H68: =(IF(H$47>=1,Quesería!$G$124*IF(H$47=1,Quesería!$B$20,1),Quesería!$G$124*Quesería!$B$20*Quesería!$B$21/12*$B$23)+IF(H$47>=2,(Quesería!$G$125-(1-$B$24)*Quesería!$G$117-(-$B$26*$B$27)*'Beneficios y costos'!$D$167)*$B$21*IF(H$47=2,Quesería!$B$20,1),0))*$B$10 -> 2646.7827 | I68: =(IF(I$47>=1,Quesería!$G$124*IF(I$47=1,Quesería!$B$20,1),Quesería!$G$124*Quesería!$B$20*Quesería!$B$21/12*$B$23)+IF(I$47>=2,(Quesería!$G$125-(1-$B$24)*Quesería!$G$117-(-$B$26*$B$27)*'Beneficios y costos'!$D$167)*$B$21*IF(I$47=2,Quesería!$B$20,1),0))*$B$10 -> 2646.7827 | ... L68: =(IF(L$47>=1,Quesería!$G$124*IF(L$47=1,Quesería!$B$20,1),Quesería!$G$124*Quesería!$B$20*Quesería!$B$21/12*$B$23)+IF(L$47>=2,(Quesería!$G$125-(1-$B$24)*Quesería!$G$117-(-$B$26*$B$27)*'Beneficios y costos'!$D$167)*$B$21*IF(L$47=2,Quesería!$B$20,1),0))*$B$10 -> 2646.7827
A69: Inversión en capital de trabajo | B69: =(B68*(Quesería!$B$38+Quesería!$B$40*Quesería!$B$39)/365-B60*Quesería!$B$42/365+IF(B$47>=2,($B$25*'Beneficios y costos'!$B$147+(1-$B$25)*'Beneficios y costos'!$B$148)*$B$24*$B$21*$B$10*IF(B$47=2,Quesería!$B$20,1),0)) -> 7.231469 | C69: =(C68*(Quesería!$B$38+Quesería!$B$40*Quesería!$B$39)/365-C60*Quesería!$B$42/365+IF(C$47>=2,($B$25*'Beneficios y costos'!$B$147+(1-$B$25)*'Beneficios y costos'!$B$148)*$B$24*$B$21*$B$10*IF(C$47=2,Quesería!$B$20,1),0))-(B68*(Quesería!$B$38+Quesería!$B$40*Quesería!$B$39)/365-B60*Quesería!$B$42/365+IF(B$47>=2,($B$25*'Beneficios y costos'!$B$147+(1-$B$25)*'Beneficios y costos'!$B$148)*$B$24*$B$21*$B$10*IF(B$47=2,Quesería!$B$20,1),0))*B51/C51 -> 1.4228785 | D69: =(D68*(Quesería!$B$38+Quesería!$B$40*Quesería!$B$39)/365-D60*Quesería!$B$42/365+IF(D$47>=2,($B$25*'Beneficios y costos'!$B$147+(1-$B$25)*'Beneficios y costos'!$B$148)*$B$24*$B$21*$B$10*IF(D$47=2,Quesería!$B$20,1),0))-(C68*(Quesería!$B$38+Quesería!$B$40*Quesería!$B$39)/365-C60*Quesería!$B$42/365+IF(C$47>=2,($B$25*'Beneficios y costos'!$B$147+(1-$B$25)*'Beneficios y costos'!$B$148)*$B$24*$B$21*$B$10*IF(C$47=2,Quesería!$B$20,1),0))*C51/D51 -> 121.06797 | E69: =(E68*(Quesería!$B$38+Quesería!$B$40*Quesería!$B$39)/365-E60*Quesería!$B$42/365+IF(E$47>=2,($B$25*'Beneficios y costos'!$B$147+(1-$B$25)*'Beneficios y costos'!$B$148)*$B$24*$B$21*$B$10*IF(E$47=2,Quesería!$B$20,1),0))-(D68*(Quesería!$B$38+Quesería!$B$40*Quesería!$B$39)/365-D60*Quesería!$B$42/365+IF(D$47>=2,($B$25*'Beneficios y costos'!$B$147+(1-$B$25)*'Beneficios y costos'!$B$148)*$B$24*$B$21*$B$10*IF(D$47=2,Quesería!$B$20,1),0))*D51/E51 -> 44.684953 | F69: =(F68*(Quesería!$B$38+Quesería!$B$40*Quesería!$B$39)/365-F60*Quesería!$B$42/365+IF(F$47>=2,($B$25*'Beneficios y costos'!$B$147+(1-$B$25)*'Beneficios y costos'!$B$148)*$B$24*$B$21*$B$10*IF(F$47=2,Quesería!$B$20,1),0))-(E68*(Quesería!$B$38+Quesería!$B$40*Quesería!$B$39)/365-E60*Quesería!$B$42/365+IF(E$47>=2,($B$25*'Beneficios y costos'!$B$147+(1-$B$25)*'Beneficios y costos'!$B$148)*$B$24*$B$21*$B$10*IF(E$47=2,Quesería!$B$20,1),0))*E51/F51 -> 6.490106 | G69: =(G68*(Quesería!$B$38+Quesería!$B$40*Quesería!$B$39)/365-G60*Quesería!$B$42/365+IF(G$47>=2,($B$25*'Beneficios y costos'!$B$147+(1-$B$25)*'Beneficios y costos'!$B$148)*$B$24*$B$21*$B$10*IF(G$47=2,Quesería!$B$20,1),0))-(F68*(Quesería!$B$38+Quesería!$B$40*Quesería!$B$39)/365-F60*Quesería!$B$42/365+IF(F$47>=2,($B$25*'Beneficios y costos'!$B$147+(1-$B$25)*'Beneficios y costos'!$B$148)*$B$24*$B$21*$B$10*IF(F$47=2,Quesería!$B$20,1),0))*F51/G51 -> 6.490106 | H69: =(H68*(Quesería!$B$38+Quesería!$B$40*Quesería!$B$39)/365-H60*Quesería!$B$42/365+IF(H$47>=2,($B$25*'Beneficios y costos'!$B$147+(1-$B$25)*'Beneficios y costos'!$B$148)*$B$24*$B$21*$B$10*IF(H$47=2,Quesería!$B$20,1),0))-(G68*(Quesería!$B$38+Quesería!$B$40*Quesería!$B$39)/365-G60*Quesería!$B$42/365+IF(G$47>=2,($B$25*'Beneficios y costos'!$B$147+(1-$B$25)*'Beneficios y costos'!$B$148)*$B$24*$B$21*$B$10*IF(G$47=2,Quesería!$B$20,1),0))*G51/H51 -> 6.490106 | I69: =(I68*(Quesería!$B$38+Quesería!$B$40*Quesería!$B$39)/365-I60*Quesería!$B$42/365+IF(I$47>=2,($B$25*'Beneficios y costos'!$B$147+(1-$B$25)*'Beneficios y costos'!$B$148)*$B$24*$B$21*$B$10*IF(I$47=2,Quesería!$B$20,1),0))-(H68*(Quesería!$B$38+Quesería!$B$40*Quesería!$B$39)/365-H60*Quesería!$B$42/365+IF(H$47>=2,($B$25*'Beneficios y costos'!$B$147+(1-$B$25)*'Beneficios y costos'!$B$148)*$B$24*$B$21*$B$10*IF(H$47=2,Quesería!$B$20,1),0))*H51/I51 -> 6.490106 | J69: =(J68*(Quesería!$B$38+Quesería!$B$40*Quesería!$B$39)/365-J60*Quesería!$B$42/365+IF(J$47>=2,($B$25*'Beneficios y costos'!$B$147+(1-$B$25)*'Beneficios y costos'!$B$148)*$B$24*$B$21*$B$10*IF(J$47=2,Quesería!$B$20,1),0))-(I68*(Quesería!$B$38+Quesería!$B$40*Quesería!$B$39)/365-I60*Quesería!$B$42/365+IF(I$47>=2,($B$25*'Beneficios y costos'!$B$147+(1-$B$25)*'Beneficios y costos'!$B$148)*$B$24*$B$21*$B$10*IF(I$47=2,Quesería!$B$20,1),0))*I51/J51 -> 6.490106 | K69: =(K68*(Quesería!$B$38+Quesería!$B$40*Quesería!$B$39)/365-K60*Quesería!$B$42/365+IF(K$47>=2,($B$25*'Beneficios y costos'!$B$147+(1-$B$25)*'Beneficios y costos'!$B$148)*$B$24*$B$21*$B$10*IF(K$47=2,Quesería!$B$20,1),0))-(J68*(Quesería!$B$38+Quesería!$B$40*Quesería!$B$39)/365-J60*Quesería!$B$42/365+IF(J$47>=2,($B$25*'Beneficios y costos'!$B$147+(1-$B$25)*'Beneficios y costos'!$B$148)*$B$24*$B$21*$B$10*IF(J$47=2,Quesería!$B$20,1),0))*J51/K51 -> 6.490106 | L69: =-(K68*(Quesería!$B$38+Quesería!$B$40*Quesería!$B$39)/365-K60*Quesería!$B$42/365+IF(K$47>=2,($B$25*'Beneficios y costos'!$B$147+(1-$B$25)*'Beneficios y costos'!$B$148)*$B$24*$B$21*$B$10*IF(K$47=2,Quesería!$B$20,1),0))*K51/L51 -> -162.25265
A70: Valor de los equipos al año 10, después de impuestos | B70: 0 | C70: 0 | D70: 0 | E70: 0 | F70: 0 | G70: 0 | H70: 0 | I70: 0 | J70: 0 | K70: 0 | L70: =$B$8*Quesería!$B$36*(Quesería!$F$94+(Quesería!$F$95-(-$B$26)*Quesería!$D$86)*$B$21)*$B$11*(1-$B$17) -> 61.923773
A71: Flujo de caja libre del proyecto | B71: =B59-B60-B61-B62-B67-B54-B55-B56-B69+B70 -> -961.15188 | C71: =C59-C60-C61-C62-C67-C54-C55-C56-C69+C70 -> -400.38506 | D71: =D59-D60-D61-D62-D67-D54-D55-D56-D69+D70 -> 454.93438 | E71: =E59-E60-E61-E62-E67-E54-E55-E56-E69+E70 -> 323.78993 | F71: =F59-F60-F61-F62-F67-F54-F55-F56-F69+F70 -> 360.35121 | G71: =G59-G60-G61-G62-G67-G54-G55-G56-G69+G70 -> 325.99775 | H71: =H59-H60-H61-H62-H67-H54-H55-H56-H69+H70 -> 304.47197 | I71: =I59-I60-I61-I62-I67-I54-I55-I56-I69+I70 -> 365.10443 | ... L71: =L59-L60-L61-L62-L67-L54-L55-L56-L69+L70 -> 583.30388
A72: Flujo de caja libre en pesos corrientes | B72: =B71*B51 -> -1018.821 | C72: =C71*C51 -> -445.62857 | D72: =D71*D51 -> 529.12735 | E72: =E71*E51 -> 391.65902 | F72: =F71*F51 -> 453.31921 | G72: =G71*G51 -> 426.50691 | H72: =H71*H51 -> 414.27824 | I72: =I71*I51 -> 516.64859 | ... L72: =L71*L51 -> 928.48103
A73: Flujo acumulado | B73: =B71 -> -961.15188 | C73: =B73+C71 -> -1361.5369 | D73: =C73+D71 -> -906.60256 | E73: =D73+E71 -> -582.81263 | F73: =E73+F71 -> -222.46141 | G73: =F73+G71 -> 103.53633 | H73: =G73+H71 -> 408.0083 | I73: =H73+I71 -> 773.11273 | J73: =I73+J71 -> 1128.3498 | ... L73: =K73+L71 -> 2065.5609
A74: Recuperación (auxiliar) | B74: 0 | C74: =IF(AND(B73<0,C73>=0),B$47+(-B73)/C71,0) -> 0 | D74: =IF(AND(C73<0,D73>=0),C$47+(-C73)/D71,0) -> 0 | E74: =IF(AND(D73<0,E73>=0),D$47+(-D73)/E71,0) -> 0 | F74: =IF(AND(E73<0,F73>=0),E$47+(-E73)/F71,0) -> 0 | G74: =IF(AND(F73<0,G73>=0),F$47+(-F73)/G71,0) -> 4.6824017 | H74: =IF(AND(G73<0,H73>=0),G$47+(-G73)/H71,0) -> 0 | I74: =IF(AND(H73<0,I73>=0),H$47+(-H73)/I71,0) -> 0 | J74: =IF(AND(I73<0,J73>=0),I$47+(-I73)/J71,0) -> 0 | ... L74: =IF(AND(K73<0,L73>=0),K$47+(-K73)/L71,0) -> 0
A75: Factor de descuento del proyecto | B75: =(B51/$B$51)/(1+$B$29)^B$47 -> 1 | C75: =(C51/$B$51)/(1+$B$29)^C$47 -> 0.9153737 | D75: =(D51/$B$51)/(1+$B$29)^D$47 -> 0.83391897 | E75: =(E51/$B$51)/(1+$B$29)^E$47 -> 0.75607752 | F75: =(F51/$B$51)/(1+$B$29)^F$47 -> 0.68550211 | G75: =(G51/$B$51)/(1+$B$29)^G$47 -> 0.6215145 | H75: =(H51/$B$51)/(1+$B$29)^H$47 -> 0.56349976 | I75: =(I51/$B$51)/(1+$B$29)^I$47 -> 0.51090036 | ... L75: =(L51/$B$51)/(1+$B$29)^L$47 -> 0.38077079
A76: Flujo descontado | B76: =B71*B75 -> -961.15188 | C76: =C71*C75 -> -366.50195 | D76: =D71*D75 -> 379.37841 | E76: =E71*E75 -> 244.81029 | F76: =F71*F75 -> 247.02152 | G76: =G71*G75 -> 202.61233 | H76: =H71*H75 -> 171.56988 | I76: =I71*I75 -> 186.53198 | ... L76: =L71*L75 -> 222.10508
A77: Flujo descontado acumulado | B77: =B76 -> -961.15188 | C77: =B77+C76 -> -1327.6538 | D77: =C77+D76 -> -948.27542 | E77: =D77+E76 -> -703.46514 | F77: =E77+F76 -> -456.44362 | G77: =F77+G76 -> -253.83129 | H77: =G77+H76 -> -82.261409 | I77: =H77+I76 -> 104.27057 | J77: =I77+J76 -> 268.82024 | ... L77: =K77+L76 -> 639.5567
A78: Recuperación descontada (auxiliar) | B78: 0 | C78: =IF(AND(B77<0,C77>=0),B$47+(-B77)/C76,0) -> 0 | D78: =IF(AND(C77<0,D77>=0),C$47+(-C77)/D76,0) -> 0 | E78: =IF(AND(D77<0,E77>=0),D$47+(-D77)/E76,0) -> 0 | F78: =IF(AND(E77<0,F77>=0),E$47+(-E77)/F76,0) -> 0 | G78: =IF(AND(F77<0,G77>=0),F$47+(-F77)/G76,0) -> 0 | H78: =IF(AND(G77<0,H77>=0),G$47+(-G77)/H76,0) -> 0 | I78: =IF(AND(H77<0,I77>=0),H$47+(-H77)/I76,0) -> 6.4410043 | J78: =IF(AND(I77<0,J77>=0),I$47+(-I77)/J76,0) -> 0 | ... L78: =IF(AND(K77<0,L77>=0),K$47+(-K77)/L76,0) -> 0
A79: Saldo del crédito al cierre del año, pesos corrientes | B79: =IF(B$47<0,0,(Quesería!$B$44*$B$54*$B$51)*(1-MAX(0,MIN(B$47-0-Quesería!$B$47,(Quesería!$B$46-Quesería!$B$47)))/(Quesería!$B$46-Quesería!$B$47))*IF(B$47>=2,1-Quesería!$B$48,1))+IF(B$47<1,0,(Quesería!$B$44*$C$54*$C$51)*(1-MAX(0,MIN(B$47-1-Quesería!$B$47,(Quesería!$B$46-Quesería!$B$47)))/(Quesería!$B$46-Quesería!$B$47))*IF(B$47>=2,1-Quesería!$B$48,1)) -> 641.32136 | C79: =IF(C$47<0,0,(Quesería!$B$44*$B$54*$B$51)*(1-MAX(0,MIN(C$47-0-Quesería!$B$47,(Quesería!$B$46-Quesería!$B$47)))/(Quesería!$B$46-Quesería!$B$47))*IF(C$47>=2,1-Quesería!$B$48,1))+IF(C$47<1,0,(Quesería!$B$44*$C$54*$C$51)*(1-MAX(0,MIN(C$47-1-Quesería!$B$47,(Quesería!$B$46-Quesería!$B$47)))/(Quesería!$B$46-Quesería!$B$47))*IF(C$47>=2,1-Quesería!$B$48,1)) -> 1117.6908 | D79: =IF(D$47<0,0,(Quesería!$B$44*$B$54*$B$51)*(1-MAX(0,MIN(D$47-0-Quesería!$B$47,(Quesería!$B$46-Quesería!$B$47)))/(Quesería!$B$46-Quesería!$B$47))*IF(D$47>=2,1-Quesería!$B$48,1))+IF(D$47<1,0,(Quesería!$B$44*$C$54*$C$51)*(1-MAX(0,MIN(D$47-1-Quesería!$B$47,(Quesería!$B$46-Quesería!$B$47)))/(Quesería!$B$46-Quesería!$B$47))*IF(D$47>=2,1-Quesería!$B$48,1)) -> 1010.8039 | E79: =IF(E$47<0,0,(Quesería!$B$44*$B$54*$B$51)*(1-MAX(0,MIN(E$47-0-Quesería!$B$47,(Quesería!$B$46-Quesería!$B$47)))/(Quesería!$B$46-Quesería!$B$47))*IF(E$47>=2,1-Quesería!$B$48,1))+IF(E$47<1,0,(Quesería!$B$44*$C$54*$C$51)*(1-MAX(0,MIN(E$47-1-Quesería!$B$47,(Quesería!$B$46-Quesería!$B$47)))/(Quesería!$B$46-Quesería!$B$47))*IF(E$47>=2,1-Quesería!$B$48,1)) -> 824.52212 | F79: =IF(F$47<0,0,(Quesería!$B$44*$B$54*$B$51)*(1-MAX(0,MIN(F$47-0-Quesería!$B$47,(Quesería!$B$46-Quesería!$B$47)))/(Quesería!$B$46-Quesería!$B$47))*IF(F$47>=2,1-Quesería!$B$48,1))+IF(F$47<1,0,(Quesería!$B$44*$C$54*$C$51)*(1-MAX(0,MIN(F$47-1-Quesería!$B$47,(Quesería!$B$46-Quesería!$B$47)))/(Quesería!$B$46-Quesería!$B$47))*IF(F$47>=2,1-Quesería!$B$48,1)) -> 638.24031 | G79: =IF(G$47<0,0,(Quesería!$B$44*$B$54*$B$51)*(1-MAX(0,MIN(G$47-0-Quesería!$B$47,(Quesería!$B$46-Quesería!$B$47)))/(Quesería!$B$46-Quesería!$B$47))*IF(G$47>=2,1-Quesería!$B$48,1))+IF(G$47<1,0,(Quesería!$B$44*$C$54*$C$51)*(1-MAX(0,MIN(G$47-1-Quesería!$B$47,(Quesería!$B$46-Quesería!$B$47)))/(Quesería!$B$46-Quesería!$B$47))*IF(G$47>=2,1-Quesería!$B$48,1)) -> 451.95851 | H79: =IF(H$47<0,0,(Quesería!$B$44*$B$54*$B$51)*(1-MAX(0,MIN(H$47-0-Quesería!$B$47,(Quesería!$B$46-Quesería!$B$47)))/(Quesería!$B$46-Quesería!$B$47))*IF(H$47>=2,1-Quesería!$B$48,1))+IF(H$47<1,0,(Quesería!$B$44*$C$54*$C$51)*(1-MAX(0,MIN(H$47-1-Quesería!$B$47,(Quesería!$B$46-Quesería!$B$47)))/(Quesería!$B$46-Quesería!$B$47))*IF(H$47>=2,1-Quesería!$B$48,1)) -> 265.67671 | I79: =IF(I$47<0,0,(Quesería!$B$44*$B$54*$B$51)*(1-MAX(0,MIN(I$47-0-Quesería!$B$47,(Quesería!$B$46-Quesería!$B$47)))/(Quesería!$B$46-Quesería!$B$47))*IF(I$47>=2,1-Quesería!$B$48,1))+IF(I$47<1,0,(Quesería!$B$44*$C$54*$C$51)*(1-MAX(0,MIN(I$47-1-Quesería!$B$47,(Quesería!$B$46-Quesería!$B$47)))/(Quesería!$B$46-Quesería!$B$47))*IF(I$47>=2,1-Quesería!$B$48,1)) -> 79.394908 | ... L79: =IF(L$47<0,0,(Quesería!$B$44*$B$54*$B$51)*(1-MAX(0,MIN(L$47-0-Quesería!$B$47,(Quesería!$B$46-Quesería!$B$47)))/(Quesería!$B$46-Quesería!$B$47))*IF(L$47>=2,1-Quesería!$B$48,1))+IF(L$47<1,0,(Quesería!$B$44*$C$54*$C$51)*(1-MAX(0,MIN(L$47-1-Quesería!$B$47,(Quesería!$B$46-Quesería!$B$47)))/(Quesería!$B$46-Quesería!$B$47))*IF(L$47>=2,1-Quesería!$B$48,1)) -> 0
A80: Desembolso del crédito | B80: =Quesería!$B$44*B54 -> 605.02016 | C80: =Quesería!$B$44*C54 -> 428.00489 | D80: =Quesería!$B$44*D54 -> 0 | E80: =Quesería!$B$44*E54 -> 0 | F80: =Quesería!$B$44*F54 -> 0 | G80: =Quesería!$B$44*G54 -> 0 | H80: =Quesería!$B$44*H54 -> 0 | I80: =Quesería!$B$44*I54 -> 0 | ... L80: =Quesería!$B$44*L54 -> 0
A81: Intereses | B81: =(IF(AND(B$47>0,B$47<=0+Quesería!$B$46),($B$14+$B$28)*(Quesería!$B$44*$B$54*$B$51)*(1-MAX(0,MIN((B$47-1)-0-Quesería!$B$47,(Quesería!$B$46-Quesería!$B$47)))/(Quesería!$B$46-Quesería!$B$47))*IF(B$47>2,1-Quesería!$B$48,1),0)+IF(AND(B$47>1,B$47<=1+Quesería!$B$46),($B$14+$B$28)*(Quesería!$B$44*$C$54*$C$51)*(1-MAX(0,MIN((B$47-1)-1-Quesería!$B$47,(Quesería!$B$46-Quesería!$B$47)))/(Quesería!$B$46-Quesería!$B$47))*IF(B$47>2,1-Quesería!$B$48,1),0))*B53 -> 0 | C81: =(IF(AND(C$47>0,C$47<=0+Quesería!$B$46),($B$14+$B$28)*(Quesería!$B$44*$B$54*$B$51)*(1-MAX(0,MIN((C$47-1)-0-Quesería!$B$47,(Quesería!$B$46-Quesería!$B$47)))/(Quesería!$B$46-Quesería!$B$47))*IF(C$47>2,1-Quesería!$B$48,1),0)+IF(AND(C$47>1,C$47<=1+Quesería!$B$46),($B$14+$B$28)*(Quesería!$B$44*$C$54*$C$51)*(1-MAX(0,MIN((C$47-1)-1-Quesería!$B$47,(Quesería!$B$46-Quesería!$B$47)))/(Quesería!$B$46-Quesería!$B$47))*IF(C$47>2,1-Quesería!$B$48,1),0))*C53 -> 81.245564 | D81: =(IF(AND(D$47>0,D$47<=0+Quesería!$B$46),($B$14+$B$28)*(Quesería!$B$44*$B$54*$B$51)*(1-MAX(0,MIN((D$47-1)-0-Quesería!$B$47,(Quesería!$B$46-Quesería!$B$47)))/(Quesería!$B$46-Quesería!$B$47))*IF(D$47>2,1-Quesería!$B$48,1),0)+IF(AND(D$47>1,D$47<=1+Quesería!$B$46),($B$14+$B$28)*(Quesería!$B$44*$C$54*$C$51)*(1-MAX(0,MIN((D$47-1)-1-Quesería!$B$47,(Quesería!$B$46-Quesería!$B$47)))/(Quesería!$B$46-Quesería!$B$47))*IF(D$47>2,1-Quesería!$B$48,1),0))*D53 -> 135.49689 | E81: =(IF(AND(E$47>0,E$47<=0+Quesería!$B$46),($B$14+$B$28)*(Quesería!$B$44*$B$54*$B$51)*(1-MAX(0,MIN((E$47-1)-0-Quesería!$B$47,(Quesería!$B$46-Quesería!$B$47)))/(Quesería!$B$46-Quesería!$B$47))*IF(E$47>2,1-Quesería!$B$48,1),0)+IF(AND(E$47>1,E$47<=1+Quesería!$B$46),($B$14+$B$28)*(Quesería!$B$44*$C$54*$C$51)*(1-MAX(0,MIN((E$47-1)-1-Quesería!$B$47,(Quesería!$B$46-Quesería!$B$47)))/(Quesería!$B$46-Quesería!$B$47))*IF(E$47>2,1-Quesería!$B$48,1),0))*E53 -> 117.82603 | F81: =(IF(AND(F$47>0,F$47<=0+Quesería!$B$46),($B$14+$B$28)*(Quesería!$B$44*$B$54*$B$51)*(1-MAX(0,MIN((F$47-1)-0-Quesería!$B$47,(Quesería!$B$46-Quesería!$B$47)))/(Quesería!$B$46-Quesería!$B$47))*IF(F$47>2,1-Quesería!$B$48,1),0)+IF(AND(F$47>1,F$47<=1+Quesería!$B$46),($B$14+$B$28)*(Quesería!$B$44*$C$54*$C$51)*(1-MAX(0,MIN((F$47-1)-1-Quesería!$B$47,(Quesería!$B$46-Quesería!$B$47)))/(Quesería!$B$46-Quesería!$B$47))*IF(F$47>2,1-Quesería!$B$48,1),0))*F53 -> 92.415175 | G81: =(IF(AND(G$47>0,G$47<=0+Quesería!$B$46),($B$14+$B$28)*(Quesería!$B$44*$B$54*$B$51)*(1-MAX(0,MIN((G$47-1)-0-Quesería!$B$47,(Quesería!$B$46-Quesería!$B$47)))/(Quesería!$B$46-Quesería!$B$47))*IF(G$47>2,1-Quesería!$B$48,1),0)+IF(AND(G$47>1,G$47<=1+Quesería!$B$46),($B$14+$B$28)*(Quesería!$B$44*$C$54*$C$51)*(1-MAX(0,MIN((G$47-1)-1-Quesería!$B$47,(Quesería!$B$46-Quesería!$B$47)))/(Quesería!$B$46-Quesería!$B$47))*IF(G$47>2,1-Quesería!$B$48,1),0))*G53 -> 68.784704 | H81: =(IF(AND(H$47>0,H$47<=0+Quesería!$B$46),($B$14+$B$28)*(Quesería!$B$44*$B$54*$B$51)*(1-MAX(0,MIN((H$47-1)-0-Quesería!$B$47,(Quesería!$B$46-Quesería!$B$47)))/(Quesería!$B$46-Quesería!$B$47))*IF(H$47>2,1-Quesería!$B$48,1),0)+IF(AND(H$47>1,H$47<=1+Quesería!$B$46),($B$14+$B$28)*(Quesería!$B$44*$C$54*$C$51)*(1-MAX(0,MIN((H$47-1)-1-Quesería!$B$47,(Quesería!$B$46-Quesería!$B$47)))/(Quesería!$B$46-Quesería!$B$47))*IF(H$47>2,1-Quesería!$B$48,1),0))*H53 -> 46.835253 | I81: =(IF(AND(I$47>0,I$47<=0+Quesería!$B$46),($B$14+$B$28)*(Quesería!$B$44*$B$54*$B$51)*(1-MAX(0,MIN((I$47-1)-0-Quesería!$B$47,(Quesería!$B$46-Quesería!$B$47)))/(Quesería!$B$46-Quesería!$B$47))*IF(I$47>2,1-Quesería!$B$48,1),0)+IF(AND(I$47>1,I$47<=1+Quesería!$B$46),($B$14+$B$28)*(Quesería!$B$44*$C$54*$C$51)*(1-MAX(0,MIN((I$47-1)-1-Quesería!$B$47,(Quesería!$B$46-Quesería!$B$47)))/(Quesería!$B$46-Quesería!$B$47))*IF(I$47>2,1-Quesería!$B$48,1),0))*I53 -> 26.472469 | ... L81: =(IF(AND(L$47>0,L$47<=0+Quesería!$B$46),($B$14+$B$28)*(Quesería!$B$44*$B$54*$B$51)*(1-MAX(0,MIN((L$47-1)-0-Quesería!$B$47,(Quesería!$B$46-Quesería!$B$47)))/(Quesería!$B$46-Quesería!$B$47))*IF(L$47>2,1-Quesería!$B$48,1),0)+IF(AND(L$47>1,L$47<=1+Quesería!$B$46),($B$14+$B$28)*(Quesería!$B$44*$C$54*$C$51)*(1-MAX(0,MIN((L$47-1)-1-Quesería!$B$47,(Quesería!$B$46-Quesería!$B$47)))/(Quesería!$B$46-Quesería!$B$47))*IF(L$47>2,1-Quesería!$B$48,1),0))*L53 -> 0
A82: Abono a capital | B82: =((IF(AND(B$47>0+Quesería!$B$47,B$47<=0+Quesería!$B$46),(Quesería!$B$44*$B$54*$B$51)/(Quesería!$B$46-Quesería!$B$47),0)*IF(B$47>2,1-Quesería!$B$48,1)+IF(B$47=2,Quesería!$B$48*(Quesería!$B$44*$B$54*$B$51)*(1-MAX(0,MIN(2-0-Quesería!$B$47,(Quesería!$B$46-Quesería!$B$47)))/(Quesería!$B$46-Quesería!$B$47)),0))+(IF(AND(B$47>1+Quesería!$B$47,B$47<=1+Quesería!$B$46),(Quesería!$B$44*$C$54*$C$51)/(Quesería!$B$46-Quesería!$B$47),0)*IF(B$47>2,1-Quesería!$B$48,1)+IF(B$47=2,Quesería!$B$48*(Quesería!$B$44*$C$54*$C$51)*(1-MAX(0,MIN(2-1-Quesería!$B$47,(Quesería!$B$46-Quesería!$B$47)))/(Quesería!$B$46-Quesería!$B$47)),0)))*B53 -> 0 | C82: =((IF(AND(C$47>0+Quesería!$B$47,C$47<=0+Quesería!$B$46),(Quesería!$B$44*$B$54*$B$51)/(Quesería!$B$46-Quesería!$B$47),0)*IF(C$47>2,1-Quesería!$B$48,1)+IF(C$47=2,Quesería!$B$48*(Quesería!$B$44*$B$54*$B$51)*(1-MAX(0,MIN(2-0-Quesería!$B$47,(Quesería!$B$46-Quesería!$B$47)))/(Quesería!$B$46-Quesería!$B$47)),0))+(IF(AND(C$47>1+Quesería!$B$47,C$47<=1+Quesería!$B$46),(Quesería!$B$44*$C$54*$C$51)/(Quesería!$B$46-Quesería!$B$47),0)*IF(C$47>2,1-Quesería!$B$48,1)+IF(C$47=2,Quesería!$B$48*(Quesería!$B$44*$C$54*$C$51)*(1-MAX(0,MIN(2-1-Quesería!$B$47,(Quesería!$B$46-Quesería!$B$47)))/(Quesería!$B$46-Quesería!$B$47)),0)))*C53 -> 0 | D82: =((IF(AND(D$47>0+Quesería!$B$47,D$47<=0+Quesería!$B$46),(Quesería!$B$44*$B$54*$B$51)/(Quesería!$B$46-Quesería!$B$47),0)*IF(D$47>2,1-Quesería!$B$48,1)+IF(D$47=2,Quesería!$B$48*(Quesería!$B$44*$B$54*$B$51)*(1-MAX(0,MIN(2-0-Quesería!$B$47,(Quesería!$B$46-Quesería!$B$47)))/(Quesería!$B$46-Quesería!$B$47)),0))+(IF(AND(D$47>1+Quesería!$B$47,D$47<=1+Quesería!$B$46),(Quesería!$B$44*$C$54*$C$51)/(Quesería!$B$46-Quesería!$B$47),0)*IF(D$47>2,1-Quesería!$B$48,1)+IF(D$47=2,Quesería!$B$48*(Quesería!$B$44*$C$54*$C$51)*(1-MAX(0,MIN(2-1-Quesería!$B$47,(Quesería!$B$46-Quesería!$B$47)))/(Quesería!$B$46-Quesería!$B$47)),0)))*D53 -> 91.899469 | E82: =((IF(AND(E$47>0+Quesería!$B$47,E$47<=0+Quesería!$B$46),(Quesería!$B$44*$B$54*$B$51)/(Quesería!$B$46-Quesería!$B$47),0)*IF(E$47>2,1-Quesería!$B$48,1)+IF(E$47=2,Quesería!$B$48*(Quesería!$B$44*$B$54*$B$51)*(1-MAX(0,MIN(2-0-Quesería!$B$47,(Quesería!$B$46-Quesería!$B$47)))/(Quesería!$B$46-Quesería!$B$47)),0))+(IF(AND(E$47>1+Quesería!$B$47,E$47<=1+Quesería!$B$46),(Quesería!$B$44*$C$54*$C$51)/(Quesería!$B$46-Quesería!$B$47),0)*IF(E$47>2,1-Quesería!$B$48,1)+IF(E$47=2,Quesería!$B$48*(Quesería!$B$44*$C$54*$C$51)*(1-MAX(0,MIN(2-1-Quesería!$B$47,(Quesería!$B$46-Quesería!$B$47)))/(Quesería!$B$46-Quesería!$B$47)),0)))*E53 -> 154.00174 | F82: =((IF(AND(F$47>0+Quesería!$B$47,F$47<=0+Quesería!$B$46),(Quesería!$B$44*$B$54*$B$51)/(Quesería!$B$46-Quesería!$B$47),0)*IF(F$47>2,1-Quesería!$B$48,1)+IF(F$47=2,Quesería!$B$48*(Quesería!$B$44*$B$54*$B$51)*(1-MAX(0,MIN(2-0-Quesería!$B$47,(Quesería!$B$46-Quesería!$B$47)))/(Quesería!$B$46-Quesería!$B$47)),0))+(IF(AND(F$47>1+Quesería!$B$47,F$47<=1+Quesería!$B$46),(Quesería!$B$44*$C$54*$C$51)/(Quesería!$B$46-Quesería!$B$47),0)*IF(F$47>2,1-Quesería!$B$48,1)+IF(F$47=2,Quesería!$B$48*(Quesería!$B$44*$C$54*$C$51)*(1-MAX(0,MIN(2-1-Quesería!$B$47,(Quesería!$B$46-Quesería!$B$47)))/(Quesería!$B$46-Quesería!$B$47)),0)))*F53 -> 148.0786 | G82: =((IF(AND(G$47>0+Quesería!$B$47,G$47<=0+Quesería!$B$46),(Quesería!$B$44*$B$54*$B$51)/(Quesería!$B$46-Quesería!$B$47),0)*IF(G$47>2,1-Quesería!$B$48,1)+IF(G$47=2,Quesería!$B$48*(Quesería!$B$44*$B$54*$B$51)*(1-MAX(0,MIN(2-0-Quesería!$B$47,(Quesería!$B$46-Quesería!$B$47)))/(Quesería!$B$46-Quesería!$B$47)),0))+(IF(AND(G$47>1+Quesería!$B$47,G$47<=1+Quesería!$B$46),(Quesería!$B$44*$C$54*$C$51)/(Quesería!$B$46-Quesería!$B$47),0)*IF(G$47>2,1-Quesería!$B$48,1)+IF(G$47=2,Quesería!$B$48*(Quesería!$B$44*$C$54*$C$51)*(1-MAX(0,MIN(2-1-Quesería!$B$47,(Quesería!$B$46-Quesería!$B$47)))/(Quesería!$B$46-Quesería!$B$47)),0)))*G53 -> 142.38327 | H82: =((IF(AND(H$47>0+Quesería!$B$47,H$47<=0+Quesería!$B$46),(Quesería!$B$44*$B$54*$B$51)/(Quesería!$B$46-Quesería!$B$47),0)*IF(H$47>2,1-Quesería!$B$48,1)+IF(H$47=2,Quesería!$B$48*(Quesería!$B$44*$B$54*$B$51)*(1-MAX(0,MIN(2-0-Quesería!$B$47,(Quesería!$B$46-Quesería!$B$47)))/(Quesería!$B$46-Quesería!$B$47)),0))+(IF(AND(H$47>1+Quesería!$B$47,H$47<=1+Quesería!$B$46),(Quesería!$B$44*$C$54*$C$51)/(Quesería!$B$46-Quesería!$B$47),0)*IF(H$47>2,1-Quesería!$B$48,1)+IF(H$47=2,Quesería!$B$48*(Quesería!$B$44*$C$54*$C$51)*(1-MAX(0,MIN(2-1-Quesería!$B$47,(Quesería!$B$46-Quesería!$B$47)))/(Quesería!$B$46-Quesería!$B$47)),0)))*H53 -> 136.90699 | I82: =((IF(AND(I$47>0+Quesería!$B$47,I$47<=0+Quesería!$B$46),(Quesería!$B$44*$B$54*$B$51)/(Quesería!$B$46-Quesería!$B$47),0)*IF(I$47>2,1-Quesería!$B$48,1)+IF(I$47=2,Quesería!$B$48*(Quesería!$B$44*$B$54*$B$51)*(1-MAX(0,MIN(2-0-Quesería!$B$47,(Quesería!$B$46-Quesería!$B$47)))/(Quesería!$B$46-Quesería!$B$47)),0))+(IF(AND(I$47>1+Quesería!$B$47,I$47<=1+Quesería!$B$46),(Quesería!$B$44*$C$54*$C$51)/(Quesería!$B$46-Quesería!$B$47),0)*IF(I$47>2,1-Quesería!$B$48,1)+IF(I$47=2,Quesería!$B$48*(Quesería!$B$44*$C$54*$C$51)*(1-MAX(0,MIN(2-1-Quesería!$B$47,(Quesería!$B$46-Quesería!$B$47)))/(Quesería!$B$46-Quesería!$B$47)),0)))*I53 -> 131.64134 | ... L82: =((IF(AND(L$47>0+Quesería!$B$47,L$47<=0+Quesería!$B$46),(Quesería!$B$44*$B$54*$B$51)/(Quesería!$B$46-Quesería!$B$47),0)*IF(L$47>2,1-Quesería!$B$48,1)+IF(L$47=2,Quesería!$B$48*(Quesería!$B$44*$B$54*$B$51)*(1-MAX(0,MIN(2-0-Quesería!$B$47,(Quesería!$B$46-Quesería!$B$47)))/(Quesería!$B$46-Quesería!$B$47)),0))+(IF(AND(L$47>1+Quesería!$B$47,L$47<=1+Quesería!$B$46),(Quesería!$B$44*$C$54*$C$51)/(Quesería!$B$46-Quesería!$B$47),0)*IF(L$47>2,1-Quesería!$B$48,1)+IF(L$47=2,Quesería!$B$48*(Quesería!$B$44*$C$54*$C$51)*(1-MAX(0,MIN(2-1-Quesería!$B$47,(Quesería!$B$46-Quesería!$B$47)))/(Quesería!$B$46-Quesería!$B$47)),0)))*L53 -> 0
A83: Garantía del crédito | B83: =$B$13*Quesería!$B$51*(1+0.19)*B79*B53+(1-$B$13)*IF(B$47=0,Quesería!$B$50,0) -> 4 | C83: =$B$13*Quesería!$B$51*(1+0.19)*C79*C53+(1-$B$13)*IF(C$47=0,Quesería!$B$50,0) -> 0 | D83: =$B$13*Quesería!$B$51*(1+0.19)*D79*D53+(1-$B$13)*IF(D$47=0,Quesería!$B$50,0) -> 0 | E83: =$B$13*Quesería!$B$51*(1+0.19)*E79*E53+(1-$B$13)*IF(E$47=0,Quesería!$B$50,0) -> 0 | F83: =$B$13*Quesería!$B$51*(1+0.19)*F79*F53+(1-$B$13)*IF(F$47=0,Quesería!$B$50,0) -> 0 | G83: =$B$13*Quesería!$B$51*(1+0.19)*G79*G53+(1-$B$13)*IF(G$47=0,Quesería!$B$50,0) -> 0 | H83: =$B$13*Quesería!$B$51*(1+0.19)*H79*H53+(1-$B$13)*IF(H$47=0,Quesería!$B$50,0) -> 0 | I83: =$B$13*Quesería!$B$51*(1+0.19)*I79*I53+(1-$B$13)*IF(I$47=0,Quesería!$B$50,0) -> 0 | ... L83: =$B$13*Quesería!$B$51*(1+0.19)*L79*L53+(1-$B$13)*IF(L$47=0,Quesería!$B$50,0) -> 0
A84: GMF del servicio de la deuda | B84: =Quesería!$B$52*(B81+B82+B83) -> 0.016 | C84: =Quesería!$B$52*(C81+C82+C83) -> 0.32498226 | D84: =Quesería!$B$52*(D81+D82+D83) -> 0.90958545 | E84: =Quesería!$B$52*(E81+E82+E83) -> 1.0873111 | F84: =Quesería!$B$52*(F81+F82+F83) -> 0.96197509 | G84: =Quesería!$B$52*(G81+G82+G83) -> 0.84467189 | H84: =Quesería!$B$52*(H81+H82+H83) -> 0.73496897 | I84: =Quesería!$B$52*(I81+I82+I83) -> 0.63245522 | ... L84: =Quesería!$B$52*(L81+L82+L83) -> 0
A85: Ahorro de impuesto por los gastos financieros | B85: =$B$17*(B81+B83+0.5*B84) -> 1.4028 | C85: =$B$17*(C81+C83+0.5*C84) -> 28.492819 | D85: =$B$17*(D81+D83+0.5*D84) -> 47.58309 | E85: =$B$17*(E81+E83+0.5*E84) -> 41.429389 | F85: =$B$17*(F81+F83+0.5*F84) -> 32.513657 | G85: =$B$17*(G81+G83+0.5*G84) -> 24.222464 | H85: =$B$17*(H81+H83+0.5*H84) -> 16.520958 | I85: =$B$17*(I81+I83+0.5*I84) -> 9.3760437 | ... L85: =$B$17*(L81+L83+0.5*L84) -> 0
A86: Flujo del inversionista | B86: =B71+B80-B81-B82-B83-B84+B85 -> -358.74492 | C86: =C71+C80-C81-C82-C83-C84+C85 -> -25.457892 | D86: =D71+D80-D81-D82-D83-D84+D85 -> 274.21152 | E86: =E71+E80-E81-E82-E83-E84+E85 -> 92.304239 | F86: =F71+F80-F81-F82-F83-F84+F85 -> 151.40912 | G86: =G71+G80-G81-G82-G83-G84+G85 -> 138.20757 | H86: =H71+H80-H81-H82-H83-H84+H85 -> 136.51572 | I86: =I71+I80-I81-I82-I83-I84+I85 -> 215.73421 | ... L86: =L71+L80-L81-L82-L83-L84+L85 -> 583.30388
A87: Flujo del inversionista en pesos corrientes | B87: =B86*B51 -> -380.26962 | C87: =C86*C51 -> -28.334634 | D87: =D86*D51 -> 318.93131 | E87: =E86*E51 -> 111.65198 | F87: =F86*F51 -> 190.47157 | G87: =G86*G51 -> 180.81868 | H87: =H86*H51 -> 185.74942 | I87: =I86*I51 -> 305.27917 | ... L87: =L86*L51 -> 928.48103
A88: Factor de descuento del inversionista | B88: =(B51/$B$51)/(1+Quesería!$B$11+$B$28)^B$47 -> 1 | C88: =(C51/$B$51)/(1+Quesería!$B$11+$B$28)^C$47 -> 0.84 | D88: =(D51/$B$51)/(1+Quesería!$B$11+$B$28)^D$47 -> 0.70224 | E88: =(E51/$B$51)/(1+Quesería!$B$11+$B$28)^E$47 -> 0.58426368 | F88: =(F51/$B$51)/(1+Quesería!$B$11+$B$28)^F$47 -> 0.48610738 | G88: =(G51/$B$51)/(1+Quesería!$B$11+$B$28)^G$47 -> 0.40444134 | H88: =(H51/$B$51)/(1+Quesería!$B$11+$B$28)^H$47 -> 0.3364952 | I88: =(I51/$B$51)/(1+Quesería!$B$11+$B$28)^I$47 -> 0.279964 | ... L88: =(L51/$B$51)/(1+Quesería!$B$11+$B$28)^L$47 -> 0.16123977
A89: Flujo de la operación disponible para la deuda | B89: =B71+B54+B56+B85 -> 120.16683 | C89: =C71+C54+C56+C85 -> 411.68595 | D89: =D71+D54+D56+D85 -> 502.51747 | E89: =E71+E54+E56+E85 -> 365.21932 | F89: =F71+F54+F56+F85 -> 392.86487 | G89: =G71+G54+G56+G85 -> 355.4386 | H89: =H71+H54+H56+H85 -> 329.80687 | I89: =I71+I54+I56+I85 -> 374.48047 | ... L89: =L71+L54+L56+L85 -> 583.30388
A90: Cobertura del servicio de la deuda (veces) | B90: =IF(AND(B$47>=1,(B81+B82+B83)>0.001),B89/(B81+B82+B83),"") | C90: =IF(AND(C$47>=1,(C81+C82+C83)>0.001),C89/(C81+C82+C83),"") -> 5.0671807 | D90: =IF(AND(D$47>=1,(D81+D82+D83)>0.001),D89/(D81+D82+D83),"") -> 2.2098747 | E90: =IF(AND(E$47>=1,(E81+E82+E83)>0.001),E89/(E81+E82+E83),"") -> 1.3435688 | F90: =IF(AND(F$47>=1,(F81+F82+F83)>0.001),F89/(F81+F82+F83),"") -> 1.6335761 | G90: =IF(AND(G$47>=1,(G81+G82+G83)>0.001),G89/(G81+G82+G83),"") -> 1.6832032 | H90: =IF(AND(H$47>=1,(H81+H82+H83)>0.001),H89/(H81+H82+H83),"") -> 1.7949431 | I90: =IF(AND(I$47>=1,(I81+I82+I83)>0.001),I89/(I81+I82+I83),"") -> 2.3684236 | ... L90: =IF(AND(L$47>=1,(L81+L82+L83)>0.001),L89/(L81+L82+L83),"")
A92: Conservador
A93: Inflación del año | B93: =CHOOSE($C$15,Entorno!B$7,Entorno!B$8,Entorno!B$9) -> 0.06 | C93: =CHOOSE($C$15,Entorno!C$7,Entorno!C$8,Entorno!C$9) -> 0.05 | D93: =CHOOSE($C$15,Entorno!D$7,Entorno!D$8,Entorno!D$9) -> 0.045 | E93: =CHOOSE($C$15,Entorno!E$7,Entorno!E$8,Entorno!E$9) -> 0.04 | F93: =CHOOSE($C$15,Entorno!F$7,Entorno!F$8,Entorno!F$9) -> 0.04 | G93: =CHOOSE($C$15,Entorno!G$7,Entorno!G$8,Entorno!G$9) -> 0.04 | H93: =CHOOSE($C$15,Entorno!H$7,Entorno!H$8,Entorno!H$9) -> 0.04 | I93: =CHOOSE($C$15,Entorno!I$7,Entorno!I$8,Entorno!I$9) -> 0.04 | ... L93: =CHOOSE($C$15,Entorno!L$7,Entorno!L$8,Entorno!L$9) -> 0.04
A94: Índice de precios (2026 = 1) | B94: =1+B93 -> 1.06 | C94: =B94*(1+C93) -> 1.113 | D94: =C94*(1+D93) -> 1.163085 | E94: =D94*(1+E93) -> 1.2096084 | F94: =E94*(1+F93) -> 1.2579927 | G94: =F94*(1+G93) -> 1.3083124 | H94: =G94*(1+H93) -> 1.3606449 | I94: =H94*(1+I93) -> 1.4150707 | J94: =I94*(1+J93) -> 1.4716736 | ... L94: =K94*(1+L93) -> 1.5917621
A95: Salario mínimo real (2026 = 1) | B95: =(1+$C$16)/(1+B93) -> 1.0235849 | C95: =B95*(1+Entorno!$B$13) -> 1.0287028 | D95: =C95*(1+Entorno!$B$13) -> 1.0338463 | E95: =D95*(1+Entorno!$B$13) -> 1.0390156 | F95: =E95*(1+Entorno!$B$13) -> 1.0442107 | G95: =F95*(1+Entorno!$B$13) -> 1.0494317 | H95: =G95*(1+Entorno!$B$13) -> 1.0546789 | I95: =H95*(1+Entorno!$B$13) -> 1.0599523 | J95: =I95*(1+Entorno!$B$13) -> 1.065252 | ... L95: =K95*(1+Entorno!$B$13) -> 1.0759312
A96: Factor de pesos constantes | B96: =1/B94 -> 0.94339623 | C96: =1/C94 -> 0.8984726 | D96: =1/D94 -> 0.85978239 | E96: =1/E94 -> 0.82671384 | F96: =1/F94 -> 0.79491715 | G96: =1/G94 -> 0.76434341 | H96: =1/H94 -> 0.73494559 | I96: =1/I94 -> 0.70667845 | ... L96: =1/L94 -> 0.62823457
A97: Inversión | B97: =IF(B$47=0,Quesería!$F$92,IF(B$47=1,(Quesería!$F$93-(-$C$26)*Quesería!$D$86*(1+Quesería!$I$86))*$C$21,0))*$C$11 -> 930.80024 | C97: =IF(C$47=0,Quesería!$F$92,IF(C$47=1,(Quesería!$F$93-(-$C$26)*Quesería!$D$86*(1+Quesería!$I$86))*$C$21,0))*$C$11 -> 658.46907 | D97: =IF(D$47=0,Quesería!$F$92,IF(D$47=1,(Quesería!$F$93-(-$C$26)*Quesería!$D$86*(1+Quesería!$I$86))*$C$21,0))*$C$11 -> 0 | E97: =IF(E$47=0,Quesería!$F$92,IF(E$47=1,(Quesería!$F$93-(-$C$26)*Quesería!$D$86*(1+Quesería!$I$86))*$C$21,0))*$C$11 -> 0 | F97: =IF(F$47=0,Quesería!$F$92,IF(F$47=1,(Quesería!$F$93-(-$C$26)*Quesería!$D$86*(1+Quesería!$I$86))*$C$21,0))*$C$11 -> 0 | G97: =IF(G$47=0,Quesería!$F$92,IF(G$47=1,(Quesería!$F$93-(-$C$26)*Quesería!$D$86*(1+Quesería!$I$86))*$C$21,0))*$C$11 -> 0 | H97: =IF(H$47=0,Quesería!$F$92,IF(H$47=1,(Quesería!$F$93-(-$C$26)*Quesería!$D$86*(1+Quesería!$I$86))*$C$21,0))*$C$11 -> 0 | I97: =IF(I$47=0,Quesería!$F$92,IF(I$47=1,(Quesería!$F$93-(-$C$26)*Quesería!$D$86*(1+Quesería!$I$86))*$C$21,0))*$C$11 -> 0 | ... L97: =IF(L$47=0,Quesería!$F$92,IF(L$47=1,(Quesería!$F$93-(-$C$26)*Quesería!$D$86*(1+Quesería!$I$86))*$C$21,0))*$C$11 -> 0
A98: Reposición de equipos | B98: =IF(B$47=5,Quesería!$F$99,IF(B$47=6,Quesería!$F$100,0))*$C$11 -> 0 | C98: =IF(C$47=5,Quesería!$F$99,IF(C$47=6,Quesería!$F$100,0))*$C$11 -> 0 | D98: =IF(D$47=5,Quesería!$F$99,IF(D$47=6,Quesería!$F$100,0))*$C$11 -> 0 | E98: =IF(E$47=5,Quesería!$F$99,IF(E$47=6,Quesería!$F$100,0))*$C$11 -> 0 | F98: =IF(F$47=5,Quesería!$F$99,IF(F$47=6,Quesería!$F$100,0))*$C$11 -> 0 | G98: =IF(G$47=5,Quesería!$F$99,IF(G$47=6,Quesería!$F$100,0))*$C$11 -> 27.465217 | H98: =IF(H$47=5,Quesería!$F$99,IF(H$47=6,Quesería!$F$100,0))*$C$11 -> 46.389156 | I98: =IF(I$47=5,Quesería!$F$99,IF(I$47=6,Quesería!$F$100,0))*$C$11 -> 0 | ... L98: =IF(L$47=5,Quesería!$F$99,IF(L$47=6,Quesería!$F$100,0))*$C$11 -> 0
A99: IVA de equipos y contratos | B99: =Quesería!$B$55*(IF(B$47=0,SUMPRODUCT((Quesería!$C$70:$C$89=0)*(Quesería!$H$70:$H$89>0)*(Quesería!$J$70:$J$89>0)*Quesería!$F$70:$F$89*(1+Quesería!$I$70:$I$89)),IF(B$47=1,(SUMPRODUCT((Quesería!$C$70:$C$89=1)*(Quesería!$H$70:$H$89>0)*(Quesería!$J$70:$J$89>0)*Quesería!$F$70:$F$89*(1+Quesería!$I$70:$I$89))-(-$C$26)*Quesería!$D$86*(1+Quesería!$I$86))*$C$21,0))*$C$11+B98) -> 149.11567 | C99: =Quesería!$B$55*(IF(C$47=0,SUMPRODUCT((Quesería!$C$70:$C$89=0)*(Quesería!$H$70:$H$89>0)*(Quesería!$J$70:$J$89>0)*Quesería!$F$70:$F$89*(1+Quesería!$I$70:$I$89)),IF(C$47=1,(SUMPRODUCT((Quesería!$C$70:$C$89=1)*(Quesería!$H$70:$H$89>0)*(Quesería!$J$70:$J$89>0)*Quesería!$F$70:$F$89*(1+Quesería!$I$70:$I$89))-(-$C$26)*Quesería!$D$86*(1+Quesería!$I$86))*$C$21,0))*$C$11+C98) -> 125.10912 | D99: =Quesería!$B$55*(IF(D$47=0,SUMPRODUCT((Quesería!$C$70:$C$89=0)*(Quesería!$H$70:$H$89>0)*(Quesería!$J$70:$J$89>0)*Quesería!$F$70:$F$89*(1+Quesería!$I$70:$I$89)),IF(D$47=1,(SUMPRODUCT((Quesería!$C$70:$C$89=1)*(Quesería!$H$70:$H$89>0)*(Quesería!$J$70:$J$89>0)*Quesería!$F$70:$F$89*(1+Quesería!$I$70:$I$89))-(-$C$26)*Quesería!$D$86*(1+Quesería!$I$86))*$C$21,0))*$C$11+D98) -> 0 | E99: =Quesería!$B$55*(IF(E$47=0,SUMPRODUCT((Quesería!$C$70:$C$89=0)*(Quesería!$H$70:$H$89>0)*(Quesería!$J$70:$J$89>0)*Quesería!$F$70:$F$89*(1+Quesería!$I$70:$I$89)),IF(E$47=1,(SUMPRODUCT((Quesería!$C$70:$C$89=1)*(Quesería!$H$70:$H$89>0)*(Quesería!$J$70:$J$89>0)*Quesería!$F$70:$F$89*(1+Quesería!$I$70:$I$89))-(-$C$26)*Quesería!$D$86*(1+Quesería!$I$86))*$C$21,0))*$C$11+E98) -> 0 | F99: =Quesería!$B$55*(IF(F$47=0,SUMPRODUCT((Quesería!$C$70:$C$89=0)*(Quesería!$H$70:$H$89>0)*(Quesería!$J$70:$J$89>0)*Quesería!$F$70:$F$89*(1+Quesería!$I$70:$I$89)),IF(F$47=1,(SUMPRODUCT((Quesería!$C$70:$C$89=1)*(Quesería!$H$70:$H$89>0)*(Quesería!$J$70:$J$89>0)*Quesería!$F$70:$F$89*(1+Quesería!$I$70:$I$89))-(-$C$26)*Quesería!$D$86*(1+Quesería!$I$86))*$C$21,0))*$C$11+F98) -> 0 | G99: =Quesería!$B$55*(IF(G$47=0,SUMPRODUCT((Quesería!$C$70:$C$89=0)*(Quesería!$H$70:$H$89>0)*(Quesería!$J$70:$J$89>0)*Quesería!$F$70:$F$89*(1+Quesería!$I$70:$I$89)),IF(G$47=1,(SUMPRODUCT((Quesería!$C$70:$C$89=1)*(Quesería!$H$70:$H$89>0)*(Quesería!$J$70:$J$89>0)*Quesería!$F$70:$F$89*(1+Quesería!$I$70:$I$89))-(-$C$26)*Quesería!$D$86*(1+Quesería!$I$86))*$C$21,0))*$C$11+G98) -> 5.2183913 | H99: =Quesería!$B$55*(IF(H$47=0,SUMPRODUCT((Quesería!$C$70:$C$89=0)*(Quesería!$H$70:$H$89>0)*(Quesería!$J$70:$J$89>0)*Quesería!$F$70:$F$89*(1+Quesería!$I$70:$I$89)),IF(H$47=1,(SUMPRODUCT((Quesería!$C$70:$C$89=1)*(Quesería!$H$70:$H$89>0)*(Quesería!$J$70:$J$89>0)*Quesería!$F$70:$F$89*(1+Quesería!$I$70:$I$89))-(-$C$26)*Quesería!$D$86*(1+Quesería!$I$86))*$C$21,0))*$C$11+H98) -> 8.8139396 | I99: =Quesería!$B$55*(IF(I$47=0,SUMPRODUCT((Quesería!$C$70:$C$89=0)*(Quesería!$H$70:$H$89>0)*(Quesería!$J$70:$J$89>0)*Quesería!$F$70:$F$89*(1+Quesería!$I$70:$I$89)),IF(I$47=1,(SUMPRODUCT((Quesería!$C$70:$C$89=1)*(Quesería!$H$70:$H$89>0)*(Quesería!$J$70:$J$89>0)*Quesería!$F$70:$F$89*(1+Quesería!$I$70:$I$89))-(-$C$26)*Quesería!$D$86*(1+Quesería!$I$86))*$C$21,0))*$C$11+I98) -> 0 | ... L99: =Quesería!$B$55*(IF(L$47=0,SUMPRODUCT((Quesería!$C$70:$C$89=0)*(Quesería!$H$70:$H$89>0)*(Quesería!$J$70:$J$89>0)*Quesería!$F$70:$F$89*(1+Quesería!$I$70:$I$89)),IF(L$47=1,(SUMPRODUCT((Quesería!$C$70:$C$89=1)*(Quesería!$H$70:$H$89>0)*(Quesería!$J$70:$J$89>0)*Quesería!$F$70:$F$89*(1+Quesería!$I$70:$I$89))-(-$C$26)*Quesería!$D$86*(1+Quesería!$I$86))*$C$21,0))*$C$11+L98) -> 0
A100: Beneficio de las etapas 0 y 1 | B100: =IF(B$47=0,($C$22*Quesería!$J$126+(1-$C$22)*Quesería!$E$122)*Quesería!$B$20*Quesería!$B$21/12*$C$23,(($C$22*Quesería!$J$126+(1-$C$22)*Quesería!$E$122)+($C$22*Quesería!$J$104+(1-$C$22)*Quesería!$E$104)*(B95-1))*IF(B$47=1,Quesería!$B$20,1))*$C$10 -> 78.172998 | C100: =IF(C$47=0,($C$22*Quesería!$J$126+(1-$C$22)*Quesería!$E$122)*Quesería!$B$20*Quesería!$B$21/12*$C$23,(($C$22*Quesería!$J$126+(1-$C$22)*Quesería!$E$122)+($C$22*Quesería!$J$104+(1-$C$22)*Quesería!$E$104)*(C95-1))*IF(C$47=1,Quesería!$B$20,1))*$C$10 -> 117.44937 | D100: =IF(D$47=0,($C$22*Quesería!$J$126+(1-$C$22)*Quesería!$E$122)*Quesería!$B$20*Quesería!$B$21/12*$C$23,(($C$22*Quesería!$J$126+(1-$C$22)*Quesería!$E$122)+($C$22*Quesería!$J$104+(1-$C$22)*Quesería!$E$104)*(D95-1))*IF(D$47=1,Quesería!$B$20,1))*$C$10 -> 156.64452 | E100: =IF(E$47=0,($C$22*Quesería!$J$126+(1-$C$22)*Quesería!$E$122)*Quesería!$B$20*Quesería!$B$21/12*$C$23,(($C$22*Quesería!$J$126+(1-$C$22)*Quesería!$E$122)+($C$22*Quesería!$J$104+(1-$C$22)*Quesería!$E$104)*(E95-1))*IF(E$47=1,Quesería!$B$20,1))*$C$10 -> 156.69011 | F100: =IF(F$47=0,($C$22*Quesería!$J$126+(1-$C$22)*Quesería!$E$122)*Quesería!$B$20*Quesería!$B$21/12*$C$23,(($C$22*Quesería!$J$126+(1-$C$22)*Quesería!$E$122)+($C$22*Quesería!$J$104+(1-$C$22)*Quesería!$E$104)*(F95-1))*IF(F$47=1,Quesería!$B$20,1))*$C$10 -> 156.73593 | G100: =IF(G$47=0,($C$22*Quesería!$J$126+(1-$C$22)*Quesería!$E$122)*Quesería!$B$20*Quesería!$B$21/12*$C$23,(($C$22*Quesería!$J$126+(1-$C$22)*Quesería!$E$122)+($C$22*Quesería!$J$104+(1-$C$22)*Quesería!$E$104)*(G95-1))*IF(G$47=1,Quesería!$B$20,1))*$C$10 -> 156.78198 | H100: =IF(H$47=0,($C$22*Quesería!$J$126+(1-$C$22)*Quesería!$E$122)*Quesería!$B$20*Quesería!$B$21/12*$C$23,(($C$22*Quesería!$J$126+(1-$C$22)*Quesería!$E$122)+($C$22*Quesería!$J$104+(1-$C$22)*Quesería!$E$104)*(H95-1))*IF(H$47=1,Quesería!$B$20,1))*$C$10 -> 156.82826 | I100: =IF(I$47=0,($C$22*Quesería!$J$126+(1-$C$22)*Quesería!$E$122)*Quesería!$B$20*Quesería!$B$21/12*$C$23,(($C$22*Quesería!$J$126+(1-$C$22)*Quesería!$E$122)+($C$22*Quesería!$J$104+(1-$C$22)*Quesería!$E$104)*(I95-1))*IF(I$47=1,Quesería!$B$20,1))*$C$10 -> 156.87477 | ... L100: =IF(L$47=0,($C$22*Quesería!$J$126+(1-$C$22)*Quesería!$E$122)*Quesería!$B$20*Quesería!$B$21/12*$C$23,(($C$22*Quesería!$J$126+(1-$C$22)*Quesería!$E$122)+($C$22*Quesería!$J$104+(1-$C$22)*Quesería!$E$104)*(L95-1))*IF(L$47=1,Quesería!$B$20,1))*$C$10 -> 157.01571
