Workbook

Sheet Portada
B2: Modelo financiero de la quesería
B3: Lácteos Fúquene · Oferta de IntegraMotion S.A.S.
B5: Documento
B6: Elaboró | C6: IntegraMotion S.A.S. · Producción y evaluación económica
B7: Curso | C7: Automatización de Procesos de Manufactura · 2026-2S · Universidad Nacional de Colombia
B8: Unidades | C8: Millones de pesos constantes de 2026, salvo donde se indique
B9: Estado de los chequeos | C9: =Chequeos!$C$29 -> OK
B10: Chequeos en OK | C10: =Chequeos!$B$29 -> 22 de 22
B12: Resultados de la oferta
B13: Costo de capital del proyecto | C13: =Quesería!B161 -> 0.139155 | D13: Crédito de fomento más garantía, después de impuestos, y capital propio al 25 %.
B14: TIR del proyecto en pesos corrientes | C14: =Quesería!B162 -> 0.21421387 | D14: Se compara con el costo de capital.
B15: TIR del proyecto en pesos constantes | C15: =Quesería!B163 -> 0.16467046 | D15: Se compara con la tasa real equivalente.
B16: Tasa real equivalente | C16: =Quesería!B164 -> 0.092019164 | D16: Costo de capital sin la inflación promedio de 2027 a 2037 (hoja Entorno).
B17: VPN a 10 años al costo de capital ($ M de 2026) | C17: =Quesería!B165 -> 367.41984 | D17: Valor que crea el proyecto después de pagar el capital.
B18: Recuperación simple (años) | C18: =Quesería!B166 -> 5.1086246 | D18: Años hasta recuperar la inversión con los flujos sin descontar.
B19: Recuperación descontada (años) | C19: =Quesería!B167 -> 6.9418802 | D19: Lo mismo, con los flujos descontados al costo de capital.
B20: TIR del inversionista en pesos corrientes | C20: =Quesería!B169 -> 0.41220926 | D20: Se compara con el 25 % que exige el socio.
B21: Cobertura mínima del servicio de la deuda | C21: =Quesería!B172 -> 1.2094267 | D21: Del proyecto solo; la empresa completa en la hoja Empresa.
B22: VPN si no se obtiene el crédito fiscal por innovación ($ M) | C22: =Escenarios!$T$33 -> 213.60067 | D22: La oferta incluye la gestión del crédito; sin la certificación el proyecto sigue creando valor.
B23: VPN si la primera compuerta no se supera: solo la etapa 0 ($ M) | C23: =Herramientas!B36 -> 84.568705 | D23: Con los ahorros conservadores supuestos. Sensibilidad en la hoja Herramientas.
B24: Deuda total / EBITDA más alta de la empresa | C24: =Empresa!$B$41 -> 1.2006412 | D24: Con el crédito del proyecto.
B25: Inversión total ($ M de 2026) | C25: =Quesería!$F$85 -> 1267.5137 | D25: Con imprevistos, sin IVA.
B26: Beneficio anual pleno ($ M de 2026) | C26: =Quesería!$E$111 -> 413.72349 | D26: A salarios de 2026; los ahorros de mano de obra crecen con el salario mínimo real.
B28: Contenido
B29: Quesería | C29: Supuestos, inversión, beneficios, flujo de caja, crédito y resultados de la oferta.
B30: Entorno | C30: Inflación y salario mínimo de 2027 a 2037 y lectura política y económica, con fuentes.
B31: Beneficios y costos | C31: Balance de masa de los quesos, cálculo de cada beneficio y costos operativos nuevos (energía, vapor y calibración).
B32: Cotizaciones | C32: Precios de referencia de los equipos y tasas de cambio.
B33: Escenarios | C33: La evaluación completa con los supuestos que más mueven el resultado.
B34: Riesgo | C34: Punto de equilibrio, gráfico de tornado, escenarios clave y respuesta a cada riesgo.
B35: Herramientas | C35: Herramientas económicas una sobre otra, valor de cada etapa y protecciones en los contratos.
B36: Empresa | C36: Efecto en el estado de resultados y el endeudamiento de Lácteos Fúquene.
B37: IntegraMotion | C37: Precio de los dos contratos, gastos de funcionamiento, entregables y plan de negocio.
B38: APU | C38: Análisis de precios unitarios de la ingeniería.
B39: Chequeos | C39: Diferencias que deben dar cero.
B41: Cómo se lee
B42: Texto azul | C42: Dato de entrada: se puede cambiar.
B43: Texto negro | C43: Fórmula: no se escribe encima.
B44: Fondo amarillo | C44: Cifra clave o supuesto que más mueve el resultado.

Sheet Quesería
A1: Modelo financiero de la quesería — Lácteos Fúquene
A2: Oferta de IntegraMotion S.A.S. Millones de pesos constantes de 2026. Texto azul: datos de entrada; negro: fórmulas; fondo amarillo: cifras clave.
A4: Supuestos
A5: Supuesto | B5: Valor | C5: Unidad | D5: Fuente o criterio
A6: Ruta de inflación (1 base, 2 consenso de los analistas, 3 persistente) | B6: 1 | C6: ruta | D6: Hoja Entorno: inflación de cada año de 2027 a 2037.
A7: Costo de capital de la empresa con su deuda actual | B7: 0.16 | C7: % | D7: 70 % deuda al 18 % (intereses / deuda de 2026: 252 / 1.400) y 30 % capital propio al 25 %. Es la referencia de la primera entrega.
A8: Costo de capital del proyecto en pesos corrientes | B8: =$B$40*($B$41+$B$48*$B$44*1.19)*(1-$B$10)+(1-$B$40)*$B$46 -> 0.139155 | C8: % | D8: Con la deuda que de verdad financia el proyecto: crédito de fomento más la comisión de la garantía, después de impuestos (70 %), y capital propio al 25 % (30 %). Con él se descuentan los flujos.
A9: Tasa real equivalente | B9: =(1+$B$8)/(1+CHOOSE($B$6,Entorno!$M$7,Entorno!$M$8,Entorno!$M$9))-1 -> 0.092019164 | C9: % | D9: El costo de capital sin la inflación promedio de la ruta; con ella se compara la TIR en pesos constantes.
A10: Impuesto de renta | B10: 0.35 | C10: % | D10: Tarifa general de personas jurídicas.
A11: Vida fiscal de maquinaria y equipo | B11: 10 | C11: años | D11: Línea recta, 10 % anual (art. 137 ET). La de cada rubro está en la tabla de inversión.
A12: Beneficio del primer año de cada etapa | B12: 0.75 | C12: % del pleno | D12: Arranque, ajuste de recetas y formación.
A13: Meses de operación de la etapa 1 en 2027 | B13: 4 | C13: meses | D13: El contrato 1 dura 4 meses: la etapa 1 arranca a mitad de 2027. Se cuentan 4 meses con el beneficio de arranque; la compuerta de diciembre usa esos datos medidos.
A14: Costo de reemplazar a un operario con alguien de afuera | B14: 0.3 | C14: % del costo anual | D14: Reclutamiento, vacante y curva de aprendizaje: 30 a 50 % del salario anual (Semana, febrero de 2026). Se evita al cubrir las vacantes con personal ya formado.
A15: Parte del contrato 1 que es diagnóstico, medidas organizacionales y gestión | B15: =2/6 -> 0.33333333 | C15: % | D15: Dos de los seis integrantes (procesos y finanzas). Se deduce como gasto y su IVA va en la declaración de IVA.
A16: Caso conservador: beneficio contratado | B16: 1 | C16: % del beneficio | D16: Respaldo 1. El suero: el contrato firmado es condición de la compuerta.
A17: Caso conservador: beneficio medido en la planta | B17: 1 | C17: % del beneficio | D17: Respaldo 2. Medido en la etapa 0 con el protocolo de medida y verificación.
A18: Caso conservador: beneficio técnicamente justificado | B18: 0.75 | C18: % del beneficio | D18: Respaldo 3. Balance de masa, VSM, literatura o datos de la planta.
A19: Caso conservador: beneficio por medir en la etapa 0 | B19: 0.5 | C19: % del beneficio | D19: Respaldo 4. Supuesto razonable que todavía no tiene medición.
A20: Caso conservador: beneficio hipotético | B20: 0 | C20: % del beneficio | D20: Respaldo 5.
A21: Mantenimiento de equipos nuevos | B21: 0.03 | C21: % equipos/año | D21: Práctica de la industria para equipos de proceso.
A22: Suscripciones de software del SCADA de la quesería | B22: 12 | C22: $ M/año | D22: Licencias de SCADA, historiador y analítica dimensionadas para una línea.
A23: Días de cartera sobre las ventas adicionales | B23: 30 | C23: días | D23: Política comercial de la planta. El capital de trabajo suma cartera e inventario al costo y resta las cuentas por pagar; se recupera al final del horizonte.
A24: Días de inventario del queso adicional | B24: 5 | C24: días | D24: Queso fresco: se despacha en la semana. Se valora al costo, no al precio.
A25: Costo de ventas sobre ventas | B25: 0.82 | C25: % | D25: Estado de resultados del caso: leche, insumos, nómina, energía y mantenimiento sobre las ventas.
A26: Días de cuentas por pagar sobre los costos operativos nuevos | B26: 22 | C26: días | D26: Balance del caso: cuentas por pagar de 1.206 sobre compras de leche e insumos.
A27: Leche de la quesería | B27: 9000 | C27: L/día | D27: Reparto de la leche de la planta.
A28: Leche de la planta | B28: 25000 | C28: L/día | D28: Caso de estudio.
A29: Parte de la quesería en la leche | B29: =$B$27/$B$28 -> 0.36 | C29: % | D29: Reparte la grasa en línea, el mantenimiento y la etapa 0.
A30: Ventas de la quesería | B30: 6772 | C30: $ M/año | D30: Caso de estudio (294 días de operación).
A31: Ventas de la planta | B31: 30457 | C31: $ M/año | D31: Caso de estudio.
A32: Parte de la quesería en las ventas | B32: =$B$30/$B$31 -> 0.22234626 | C32: % | D32: Reparte la reducción de merma.
A33: Costo anual de un operario | B33: 36 | C33: $ M/año | D33: Salario, prestaciones y aportes.
A34: Meses de traslape mientras se forman los operarios de la hiladora | B34: 3 | C34: meses | D34: Los 2 operarios que pasan a cubrir vacantes siguen en el hilado hasta que la hiladora opera sola; esas vacantes se cubren mientras tanto.
A35: Descuento tributario por inversión ambiental (art. 255 ET) | B35: 0.25 | C35: % inversión | D35: Sobre el enfriador y el tanque del suero, que dejan de verterlo. Requiere certificado de la CAR; IntegraMotion lo tramita.
A36: IVA de equipos y contratos de integración | B36: 0.19 | C36: % | D36: Se paga al comprar y se recupera como descuento en la declaración de renta del año, que se presenta al año siguiente (art. 258-1 ET: activos fijos productivos y servicios para ponerlos en uso). El IVA del diagnóstico y del aval se descuenta en la declaración de IVA. Los valores de la inversión van sin IVA.
A37: Reposición del hardware del SCADA en el año 5 | B37: 0.4 | C37: % del rubro SCADA | D37: Servidor, red y estaciones (vida fiscal de 5 años); las licencias siguen en las suscripciones.
A38: Reposición parcial de instrumentación en el año 6 | B38: 0.1 | C38: % de los equipos de la etapa 1 | D38: Sensores, celdas de carga y sondas en ambiente húmedo y con lavados.
A39: Valor de los equipos al año 10 | B39: 0.1 | C39: % de su costo | D39: Se vende o se toma como parte de pago; se grava completo.
A40: Parte de la inversión financiada con crédito | B40: 0.7 | C40: % | D40: Líneas Bancóldex Impulso a la Productividad y Transformación Digital, a través del banco de la empresa.
A41: Tasa del crédito de fomento (efectiva anual, pesos corrientes) | B41: 0.141 | C41: % | D41: Superfinanciera, datos abiertos: créditos con recursos de redescuento a medianas empresas, 3 a 5 años, mayo a julio de 2026. El crédito se pacta en pesos corrientes; cada pago se pasa a pesos constantes con el factor del flujo.
A42: Plazo del crédito, incluida la gracia | B42: 7 | C42: años | D42: Bancóldex Impulso a la Productividad: hasta 7 años con 12 meses de gracia.
A43: Gracia a capital | B43: 1 | C43: años | D43: Se pagan solo intereses.
A44: Comisión de la garantía del Fondo Nacional de Garantías | B44: 0.0199 | C44: % anual del saldo | D44: Garantía Preferente del FNG, 1,99 % anual (La República), con IVA, sobre el saldo. La oferta la reemplaza por prenda sobre los equipos; se usa en el escenario Garantía del FNG.
... A46: Rentabilidad que exige el inversionista en pesos corrientes | B46: 0.25 | C46: % | D46: Lo que espera ganar el socio por arriesgar su capital.
A47: Rentabilidad exigida real equivalente | B47: =(1+$B$46)/(1+CHOOSE($B$6,Entorno!$M$7,Entorno!$M$8,Entorno!$M$9))-1 -> 0.19827763 | C47: % | D47: Misma conversión de la tasa de descuento.
A48: Garantía del crédito (0 = prenda sobre los equipos; 1 = FNG) | B48: 0 | C48: 0 / 1 | D48: IntegraMotion negocia la prenda con el banco.
A49: Crédito fiscal por innovación en la oferta (1 = se incluye; 0 = no) | B49: 1 | C49: 0 / 1 | D49: Gestión que IntegraMotion se compromete a hacer: postular el proyecto ante Minciencias. Queda condicionado a la certificación del CNBT; el escenario Sin crédito fiscal muestra el resultado sin él.
A50: Tope del descuento del art. 255 sobre el impuesto de la empresa | B50: 0.25 | C50: % del impuesto | D50: Art. 258 ET.
A51: Impuesto de renta a cargo de la empresa | B51: 334 | C51: $ M/año | D51: Estado de resultados del caso (2026).
A52: Crédito fiscal por inversión en innovación (art. 256-1 ET) | B52: 0.5 | C52: % inversión | D52: Para micro, pequeñas y medianas empresas: Lácteos Fúquene es mediana. IntegraMotion postula el proyecto ante Minciencias con el aval de un actor reconocido; el CNBT certifica la inversión y el crédito se compensa con impuestos nacionales en los dos años siguientes. La inversión se sigue depreciando (DIAN, concepto 012495 de 2026).
A53: Avalúo y registro de la garantía mobiliaria (prenda) | B53: 4 | C53: $ M | D53: Ley 1676 de 2013: avalúo de los equipos e inscripción en el registro de garantías mobiliarias de Confecámaras. Supuesto; se cotiza.
A54: Póliza todo riesgo de los equipos nuevos | B54: 0.0025 | C54: % equipos/año | D54: El banco la pide endosada a su favor. Supuesto; se cotiza.
A55: Imprevistos: precio cerrado (contratos y SENA) | B55: 0.05 | C55: % del rubro | D55: Clasificación de estimados AACE 18R-97: la contingencia baja a medida que el precio madura. Solo cubre cambios de alcance.
A56: Imprevistos: precio publicado de catálogo | B56: 0.1 | C56: % del rubro | D56: Falta la cotización formal y el flete real.
A57: Imprevistos: estimado con referencias de mercado | B57: 0.15 | C57: % del rubro | D57: Equipos con precios de referencia de máquinas parecidas (hoja Cotizaciones).
A58: Imprevistos: estimado sin cotización | B58: 0.25 | C58: % del rubro | D58: Estimado de orden de magnitud (clase 4 a 5 de AACE).
A60: Inversión
A61: Componente | B61: Etapa | C61: Año | D61: Planta | E61: Reparto | F61: Quesería | G61: ¿Equipo? | H61: Madurez del precio (1 a 4) | I61: % imprevistos | J61: Vida fiscal (años; 0 = gasto) | K61: Innovación (1 = sí)
A62: Diagnóstico de la planta, plan de mantenimiento y orden de la operación | B62: 0 | C62: 0 | D62: 60 | E62: =$B$29 -> 0.36 | F62: =D62*E62 -> 21.6 | G62: 0 | H62: 4 | I62: =CHOOSE(H62,$B$55,$B$56,$B$57,$B$58) -> 0.25 | J62: 0 | K62: 0
A63: Automatización de 2 tinas: liras con variador, sensor de coagulación, dosificación | B63: 1 | C63: 0 | D63: 180 | E63: 1 | F63: =D63*E63 -> 180 | G63: 1 | H63: 4 | I63: =CHOOSE(H63,$B$55,$B$56,$B$57,$B$58) -> 0.25 | J63: 10 | K63: 1
A64: Tina del doble crema: medición y mando básicos (caudal, nivel, temperatura, válvula y bomba) | B64: 1 | C64: 0 | D64: 30 | E64: 1 | F64: =D64*E64 -> 30 | G64: 1 | H64: 4 | I64: =CHOOSE(H64,$B$55,$B$56,$B$57,$B$58) -> 0.25 | J64: 10 | K64: 0
A65: Controladora de peso y detector de metales en la salida del empaque | B65: 1 | C65: 0 | D65: =Cotizaciones!$F$13 -> 33.178864 | E65: 1 | F65: =D65*E65 -> 33.178864 | G65: 1 | H65: 2 | I65: =CHOOSE(H65,$B$55,$B$56,$B$57,$B$58) -> 0.1 | J65: 10 | K65: 0
A66: Medidor de grasa en línea en la estandarización | B66: 1 | C66: 0 | D66: 120 | E66: =$B$29 -> 0.36 | F66: =D66*E66 -> 43.2 | G66: 1 | H66: 4 | I66: =CHOOSE(H66,$B$55,$B$56,$B$57,$B$58) -> 0.25 | J66: 10 | K66: 0
A67: SCADA, historiador y MES ligero de la quesería (red, servidor, licencias e instrumentación) | B67: 1 | C67: 0 | D67: =200/3 -> 66.666667 | E67: 1 | F67: =D67*E67 -> 66.666667 | G67: 1 | H67: 3 | I67: =CHOOSE(H67,$B$55,$B$56,$B$57,$B$58) -> 0.15 | J67: 5 | K67: 1
A68: Contrato 1 con IntegraMotion: ingeniería e integración de la etapa 1 | B68: 1 | C68: 0 | D68: =IntegraMotion!$F$44*Entorno!$B$14*(1-$B$15) -> 88.781084 | E68: 1 | F68: =D68*E68 -> 88.781084 | G68: 0 | H68: 1 | I68: =CHOOSE(H68,$B$55,$B$56,$B$57,$B$58) -> 0.05 | J68: 10 | K68: 1
A69: Contrato 1 con IntegraMotion: diagnóstico, medidas organizacionales y gestión (etapa 0) | B69: 1 | C69: 0 | D69: =IntegraMotion!$F$44*Entorno!$B$14*$B$15 -> 44.390542 | E69: 1 | F69: =D69*E69 -> 44.390542 | G69: 0 | H69: 1 | I69: =CHOOSE(H69,$B$55,$B$56,$B$57,$B$58) -> 0.05 | J69: 0 | K69: 0
A70: Formación de los operarios con el SENA | B70: 1 | C70: 0 | D70: =20/3 -> 6.6666667 | E70: 1 | F70: =D70*E70 -> 6.6666667 | G70: 0 | H70: 1 | I70: =CHOOSE(H70,$B$55,$B$56,$B$57,$B$58) -> 0.05 | J70: 0 | K70: 0
A71: Aval y seguimiento del proyecto de innovación por un actor reconocido por Minciencias | B71: 1 | C71: 0 | D71: 15 | E71: 1 | F71: =D71*E71 -> 15 | G71: 0 | H71: 4 | I71: =CHOOSE(H71,$B$55,$B$56,$B$57,$B$58) -> 0.25 | J71: 0 | K71: 1
A72: Imprevistos de las etapas 0 y 1 | B72: 1 | C72: 0 | D72: =SUMPRODUCT(F62:F71,I62:I71) -> 92.759801 | E72: 1 | F72: =D72*E72 -> 92.759801 | G72: 0 | K72: 0
A73: Hiladora-moldeadora continua para doble crema y mozzarella | B73: 2 | C73: 1 | D73: 322.6 | E73: 1 | F73: =D73*E73 -> 322.6 | G73: 1 | H73: 3 | I73: =CHOOSE(H73,$B$55,$B$56,$B$57,$B$58) -> 0.15 | J73: 10 | K73: 0
A74: CIP automático del circuito de quesos | B74: 2 | C74: 1 | D74: =320/3 -> 106.66667 | E74: 1 | F74: =D74*E74 -> 106.66667 | G74: 1 | H74: 3 | I74: =CHOOSE(H74,$B$55,$B$56,$B$57,$B$58) -> 0.15 | J74: 10 | K74: 0
A75: Enfriador de placas y tanque pulmón para el suero | B75: 2 | C75: 1 | D75: 80 | E75: 1 | F75: =D75*E75 -> 80 | G75: 1 | H75: 4 | I75: =CHOOSE(H75,$B$55,$B$56,$B$57,$B$58) -> 0.25 | J75: 10 | K75: 0
A76: Contrato 2 con IntegraMotion: integración de la etapa 2 | B76: 2 | C76: 1 | D76: =IntegraMotion!$F$64*Entorno!$B$15 -> 49.15564 | E76: 1 | F76: =D76*E76 -> 49.15564 | G76: 0 | H76: 1 | I76: =CHOOSE(H76,$B$55,$B$56,$B$57,$B$58) -> 0.05 | J76: 10 | K76: 0
A77: Imprevistos de la etapa 2 | B77: 2 | C77: 1 | D77: =SUMPRODUCT(F73:F76,I73:I76) -> 86.847782 | E77: 1 | F77: =D77*E77 -> 86.847782 | G77: 0 | K77: 0
A78: Todo se dimensiona para la quesería. SCADA, CIP y formación: un tercio del costo estimado para toda la planta. Contratos con IntegraMotion: hoja IntegraMotion, sin IVA, reajustados con el salario mínimo real del año en que se ejecutan (hoja Entorno). Diagnóstico y grasa en línea están en la recepción común: se carga la parte de la leche de quesos. La tina del doble crema lleva solo medición y mando básicos porque no usa sensor de coagulación. Controladora de peso y detector de metales (estación E18 del diseño): precio publicado en la hoja Cotizaciones; el resto, estimados con referencias en esa hoja.
A79: Madurez del precio: 1 precio cerrado, 2 precio publicado, 3 estimado con referencias, 4 estimado sin cotización. Los imprevistos de cada etapa suman cada rubro por su porcentaje (supuestos de arriba). Vida fiscal: art. 137 ET (maquinaria 10 años; equipo de cómputo y redes 5 años); el diagnóstico, la formación y el aval son gastos deducibles del año. Los imprevistos se deducen y llevan IVA según el rubro al que pertenecen. Innovación: rubros del proyecto que se postula ante Minciencias (control del corte por coagulación, SCADA y MES, la ingeniería que los desarrolla y el aval); la compra de equipos estándar no califica.
A80: Inversión del año 0 (etapas 0 y 1) | F80: =SUMIFS(F62:F77,C62:C77,0) -> 622.24362
A81: Inversión del año 1 (etapa 2) | F81: =SUMIFS(F62:F77,C62:C77,1) -> 645.27009
A82: Equipos del año 0 | F82: =SUMIFS(F62:F77,C62:C77,0,G62:G77,1) -> 353.04553
A83: Equipos del año 1 | F83: =SUMIFS(F62:F77,C62:C77,1,G62:G77,1) -> 509.26667
A84: Imprevistos sobre la inversión sin imprevistos | F84: =(F72+F77)/(SUM(F62:F77)-F72-F77) -> 0.16509474
A85: Inversión total | F85: =$F$80+$F$81 -> 1267.5137
A86: Inversión del proyecto de innovación (base del crédito fiscal) | F86: =SUMPRODUCT(F62:F77,K62:K77) -> 350.44775
A87: Reposición del año 5 (hardware del SCADA) | F87: =$B$37*F67 -> 26.666667
A88: Reposición del año 6 (instrumentación) | F88: =$B$38*$F$82 -> 35.304553
A90: Beneficios anuales en régimen
A91: Medida | B91: Etapa | C91: Planta | D91: Reparto | E91: Quesería | F91: Δ ventas planta | G91: Δ ventas quesería | H91: Respaldo (1 a 5) | I91: Factor conservador | J91: Quesería, caso conservador
A92: Horas extra del hilado evitadas con el orden del hilado (0,5 h/día) | B92: 1 | C92: ='Beneficios y costos'!$C$73 -> 11.76 | D92: 1 | E92: =C92*D92 -> 11.76 | F92: ='Beneficios y costos'!$D$73 -> 0 | G92: =F92*D92 -> 0 | H92: 3 | I92: =CHOOSE(H92,$B$16,$B$17,$B$18,$B$19,$B$20) -> 0.75 | J92: =E92*I92 -> 8.82
A93: Mayor rendimiento del campesino y la mozzarella (sensor de coagulación) | B93: 1 | C93: ='Beneficios y costos'!$C$74 -> 52.798395 | D93: 1 | E93: =C93*D93 -> 52.798395 | F93: ='Beneficios y costos'!$D$74 -> 54.825269 | G93: =F93*D93 -> 54.825269 | H93: 3 | I93: =CHOOSE(H93,$B$16,$B$17,$B$18,$B$19,$B$20) -> 0.75 | J93: =E93*I93 -> 39.598796
A94: Estandarización de grasa en línea | B94: 1 | C94: ='Beneficios y costos'!$C$75 -> 52.00416 | D94: =$B$29 -> 0.36 | E94: =C94*D94 -> 18.721498 | F94: ='Beneficios y costos'!$D$75 -> 52.00416 | G94: =F94*D94 -> 18.721498 | H94: 3 | I94: =CHOOSE(H94,$B$16,$B$17,$B$18,$B$19,$B$20) -> 0.75 | J94: =E94*I94 -> 14.041123
A95: Menor merma (de 2,0 a 1,5 % de las ventas) | B95: 1 | C95: ='Beneficios y costos'!$C$76 -> 152.285 | D95: =$B$32 -> 0.22234626 | E95: =C95*D95 -> 33.86 | F95: 0 | G95: =F95*D95 -> 0 | H95: 4 | I95: =CHOOSE(H95,$B$16,$B$17,$B$18,$B$19,$B$20) -> 0.5 | J95: =E95*I95 -> 16.93
A96: Mantenimiento preventivo (20 % menos gasto) | B96: 1 | C96: ='Beneficios y costos'!$C$77 -> 91.4 | D96: =$B$29 -> 0.36 | E96: =C96*D96 -> 32.904 | F96: 0 | G96: =F96*D96 -> 0 | H96: 3 | I96: =CHOOSE(H96,$B$16,$B$17,$B$18,$B$19,$B$20) -> 0.75 | J96: =E96*I96 -> 24.678
A97: Menor sobrepeso de los tres quesos (de 1,0 a 0,5 %) | B97: 1 | C97: ='Beneficios y costos'!$C$78 -> 32.5056 | D97: 1 | E97: =C97*D97 -> 32.5056 | F97: ='Beneficios y costos'!$D$78 -> 33.86 | G97: =F97*D97 -> 33.86 | H97: 4 | I97: =CHOOSE(H97,$B$16,$B$17,$B$18,$B$19,$B$20) -> 0.5 | J97: =E97*I97 -> 16.2528
A98: Hiladora-moldeadora: más doble crema y mozzarella | B98: 2 | C98: ='Beneficios y costos'!$C$79 -> 70.703173 | D98: 1 | E98: =C98*D98 -> 70.703173 | F98: ='Beneficios y costos'!$D$79 -> 73.548454 | G98: =F98*D98 -> 73.548454 | H98: 3 | I98: =CHOOSE(H98,$B$16,$B$17,$B$18,$B$19,$B$20) -> 0.75 | J98: =E98*I98 -> 53.02738
A99: Horas extra restantes que elimina la hiladora (0,5 h/día) | B99: 2 | C99: ='Beneficios y costos'!$C$80 -> 11.76 | D99: 1 | E99: =C99*D99 -> 11.76 | F99: 0 | G99: =F99*D99 -> 0 | H99: 3 | I99: =CHOOSE(H99,$B$16,$B$17,$B$18,$B$19,$B$20) -> 0.75 | J99: =E99*I99 -> 8.82
A100: Limpieza CIP automática del circuito de quesos | B100: 2 | C100: ='Beneficios y costos'!$C$81 -> 121.8 | D100: ='Beneficios y costos'!$B$25 -> 0.33333333 | E100: =C100*D100 -> 40.6 | F100: 0 | G100: =F100*D100 -> 0 | H100: 4 | I100: =CHOOSE(H100,$B$16,$B$17,$B$18,$B$19,$B$20) -> 0.5 | J100: =E100*I100 -> 20.3
A101: Contrato de venta del suero enfriado | B101: 2 | C101: ='Beneficios y costos'!$C$82 -> 36.110821 | D101: 1 | E101: =C101*D101 -> 36.110821 | F101: ='Beneficios y costos'!$D$82 -> 36.110821 | G101: =F101*D101 -> 36.110821 | H101: 1 | I101: =CHOOSE(H101,$B$16,$B$17,$B$18,$B$19,$B$20) -> 1 | J101: =E101*I101 -> 36.110821
A102: Relevo natural: 2 contrataciones que se evitan porque los operarios liberados cubren vacantes | B102: 2 | C102: ='Beneficios y costos'!$C$83 -> 72 | D102: 1 | E102: =C102*D102 -> 72 | F102: 0 | G102: =F102*D102 -> 0 | H102: 4 | I102: =CHOOSE(H102,$B$16,$B$17,$B$18,$B$19,$B$20) -> 0.5 | J102: =E102*I102 -> 36
A103: Respaldo: 1 contratado, 2 medido en la planta, 3 técnicamente justificado, 4 por medir en la etapa 0, 5 hipotético. El caso conservador toma cada beneficio por su factor. Relevo: no reduce la nómina actual; evita 2 contrataciones. Con unas 100 personas y una rotación de 15 % o más habría unas 15 vacantes al año, pero que sean compatibles se confirma en la segunda compuerta con el plan de reasignación; por eso va como «por medir». El costo de selección evitado se cuenta aparte, una sola vez.
A104: Cada beneficio se calcula en la hoja Beneficios y costos, a partir del balance de masa y de los precios. Nadie sale de la empresa: los 2 operarios cubren vacantes que la planta tendría que contratar.
...

Sheet Entorno
A1: Entorno económico y político del proyecto
A2: La quesería se ejecuta en 2027 y 2028 y opera hasta 2037. Precios en pesos de 2026; esta hoja dice cuánto cambian año por año la inflación y el salario mínimo.
A4: Inflación y salario mínimo, año por año
B5: Año 0 | C5: Año 1 | D5: Año 2 | E5: Año 3 | F5: Año 4 | G5: Año 5 | H5: Año 6 | I5: Año 7 | J5: Año 8 | K5: Año 9 | L5: Año 10 | M5: Promedio
A6: Año calendario | B6: 2027 | C6: 2028 | D6: 2029 | E6: 2030 | F6: 2031 | G6: 2032 | H6: 2033 | I6: 2034 | J6: 2035 | K6: 2036 | L6: 2037
A7: Ruta 1 · base: inflación de cada año | B7: 0.06 | C7: 0.05 | D7: 0.045 | E7: 0.04 | F7: 0.04 | G7: 0.04 | H7: 0.04 | I7: 0.04 | J7: 0.04 | K7: 0.04 | L7: 0.04 | M7: =EXP(SUMPRODUCT(LN(1+B7:L7))/11)-1 -> 0.043163928
A8: Ruta 2 · consenso de los analistas | B8: 0.059 | C8: 0.045 | D8: 0.037 | E8: 0.034 | F8: 0.034 | G8: 0.034 | H8: 0.034 | I8: 0.034 | J8: 0.034 | K8: 0.034 | L8: 0.034 | M8: =EXP(SUMPRODUCT(LN(1+B8:L8))/11)-1 -> 0.037518712
A9: Ruta 3 · inflación persistente | B9: 0.065 | C9: 0.065 | D9: 0.065 | E9: 0.065 | F9: 0.065 | G9: 0.065 | H9: 0.065 | I9: 0.065 | J9: 0.065 | K9: 0.065 | L9: 0.065 | M9: =EXP(SUMPRODUCT(LN(1+B9:L9))/11)-1 -> 0.065
A10: Promedio geométrico de 2027 a 2037. La ruta que usa el modelo se elige en los supuestos de la hoja Quesería.
A12: Incremento del salario mínimo para 2027 | B12: 0.085 | D12: Davivienda: inflación de 2026 (6,91 %) − productividad (0,32 %) + «sorpresa política» (1,91 %). Gremios: 8 % a 9,5 %; Credicorp: 9 % a 10 %.
A13: Aumento real del salario mínimo desde 2028 | B13: 0.005 | D13: El Gobierno plantea volver a ajustarlo por inflación y productividad; la productividad del trabajo ha estado cerca de cero.
A14: Salario mínimo real de 2027 con la ruta base (2026 = 1) | B14: =(1+B12)/(1+B7) -> 1.0235849 | D14: Cuánto sube por encima de la inflación.
A15: Salario mínimo real de 2028 con la ruta base (2026 = 1) | B15: =B14*(1+B13) -> 1.0287028 | D15: Reajusta los contratos de IntegraMotion: la etapa 2 se ejecuta en 2028.
A16: Salario mínimo de 2027 en pesos | B16: =1750905*(1+B12) -> 1899731.9 | D16: Decreto de 2026: $1.750.905.
A17: Afecta lo que depende del salario: horas extra y relevo de operarios (beneficios), traslape del personal y honorarios de IntegraMotion.
A19: Cómo se armaron las rutas
A20: • Encuesta de analistas del Banco de la República (septiembre de 2026): 6,8 % al cierre de 2026, 5,1 % al cierre de 2027, 4,0 % en agosto de 2028 y 3,4 % a cinco años. Los analistas han subido su pronóstico casi todos los meses de 2026.
A21: • Inflación de septiembre de 2026: 6,29 % anual (DANE), la más alta desde julio de 2024. Tasa del Banco de la República: 12,25 % desde el 1 de octubre, con una subida de 25 puntos básicos y la junta dividida.
A22: • Rutas en promedio de cada año. Consenso: de 6,8 % en diciembre de 2026 a 5,1 % en diciembre de 2027 da 5,9 % para 2027; luego 4,5 %, 3,7 % y 3,4 %. Ruta base: por encima del consenso cada año, con más margen desde 2028, y 4 % desde 2030, el techo del rango de la meta (2 % a 4 %). Ruta persistente: la inflación se queda cerca del dato de septiembre todo el horizonte.
A24: Lectura política y económica (octubre de 2026)
A25: • Salario mínimo: en 2026 subió 23,7 %, muy por encima de la inflación. El Gobierno de Abelardo de la Espriella y su ministro de Hacienda piden volver a un ajuste técnico (inflación más productividad); los analistas esperan 8 % a 10 % para 2027 por una prima política. La decisión se toma a más tardar el 30 de diciembre.
A26: • Presupuesto General de 2027: el Congreso lo aprobó el 20 de octubre por $634,9 billones, pero quedó en vilo por un presunto vicio de trámite en el artículo 65 (Senado y Cámara habrían aprobado textos distintos); si se confirma, el Gobierno lo expide por decreto. Suma incertidumbre fiscal: hace menos probable que las tasas de interés bajen rápido.
A27: • Política monetaria: el Banco de la República volvió a subir la tasa en septiembre. Davivienda espera bajadas graduales hasta 11 % al cierre de 2027. El crédito de fomento se pacta sobre la IBR más un margen, así que sigue esa tendencia.
A28: • Impuestos: el Gobierno anunció una reforma para bajar la carga de las empresas, sin tarifa definida todavía. El modelo deja la renta en 35 % y prueba 30 % en la hoja Escenarios.
A29: • Energía: el gas para la industria depende cada vez más de importaciones y El Niño presiona las tarifas. La hoja Escenarios prueba costos operativos 30 % más altos.
A31: Cómo entra al modelo
... A43: • Presupuesto de 2027 aprobado y en vilo: portafolio.co/economia/gobierno/presupuesto-de-2027-recien-aprobado-en-vilo-por-inminente-hundimiento-por-vicio-de-tramite-en-el-congreso-504829

Sheet Beneficios y costos
A1: Beneficios y costos operativos de la quesería
A2: Cada beneficio sale del balance de masa, de los precios y de la mejora que se espera; cada costo nuevo, del consumo de los equipos. $ M constantes de 2026. Las cifras en azul se miden en la etapa 0.
A4: Datos de la operación
A5: Dato | B5: Valor | C5: Unidad | D5: Fuente o criterio
A6: Días de operación al año | B6: 294 | C6: días | D6: Caso: lunes a sábado menos festivos.
A7: Densidad de la leche | B7: 1.03 | C7: kg/L | D7: Valor típico.
A8: Grasa de la leche cruda | B8: 0.036 | C8: % m/m | D8: Hato Holstein de la sabana de Ubaté.
A9: Grasa de la crema | B9: 0.4 | C9: % m/m | D9: Descremadora centrífuga.
A10: Grasa de más que se deja hoy al estandarizar a mano | B10: 0.0008 | C10: puntos | D10: Cuadro de Pearson y muestreo: el operario deja margen para no quedar por debajo del mínimo.
A11: Grasa de más con el medidor en línea | B11: 0.0003 | C11: puntos | D11: Medidor de grasa y densidad con válvula de remezcla.
A12: Crema añadida al fundido del doble crema | B12: 30 | C12: kg/día | D12: Sale de la crema de la estandarización.
A13: Agua de lavado del grano del campesino | B13: 0.03 | C13: kg/kg leche | D13: Sale con el suero.
A14: Queso adicional por el corte con sensor de coagulación | B14: 0.0015 | C14: kg/kg leche | D14: Menos finos al suero en el campesino y la mozzarella (0,15 puntos de rendimiento).
A15: Queso adicional con la hiladora-moldeadora | B15: 0.02 | C15: % del queso hilado | D15: Menos grasa y finos al agua de hilado que en la marmita a mano.
A16: Sobrepeso de los quesos hoy | B16: 0.01 | C16: % del peso | D16: Igual al de las bolsas UHT del caso.
A17: Sobrepeso con la controladora de peso | B17: 0.005 | C17: % del peso | D17: La controladora rechaza y ajusta el corte.
... A24: Ahorro con limpieza CIP automática | B24: 0.1 | C24: % de ese gasto | D24: Recuperación de soluciones y ciclos medidos en lugar de lavado a mano.
A25: Parte del circuito de quesos en la limpieza | B25: =1/3 -> 0.33333333 | C25: % | D25: Uno de los tres circuitos (quesos, yogur y UHT).
A26: Horas extra diarias del hilado que se evitan en cada etapa | B26: 0.5 | C26: h/día | D26: VSM: el hilado a mano necesita 8,4 h en una ventana de 7,4 h.
A27: Operarios del hilado | B27: 4 | C27: personas | D27: Dos parejas.
A28: Costo de la hora extra | B28: 20000 | C28: $/h | D28: Costo de la hora de un salario mínimo más el recargo de 25 %.
A29: Precio de la crema vendida | B29: 9000 | C29: $/kg | D29: Crema al 40 % a granel.
A30: Precio de la leche entera UHT | B30: 3100 | C30: $/L | D30: Precio a distribuidor del caso.
A31: Precio del suero hoy, sin enfriar | B31: 30 | C31: $/kg | D31: Caso de estudio.
A32: Precio del suero enfriado con contrato | B32: 45 | C32: $/kg | D32: Contrato anual con una fábrica de alimento balanceado; se valida en la etapa 0 con dos cotizaciones.
A33: Operarios que libera la hiladora y cubren vacantes | B33: 2 | C33: personas | D33: Nadie sale de la empresa: cubren vacantes que la planta tendría que contratar.
A35: Quesos
A36: Referencia | B36: Leche (L/día) | C36: Grasa objetivo | D36: Rendimiento (kg/kg) | E36: Precio ($/kg) | F36: Insumos y empaque ($/kg)
A37: Q1 campesino | B37: 4500 | C37: 0.026 | D37: 0.12 | E37: 19500 | F37: 750
A38: Q2 doble crema (leche entera, sin estandarizar) | B38: 3000 | C38: =$B$8 -> 0.036 | D38: 0.13 | E38: 22000 | F38: 900
A39: Q3 mozzarella | B39: 1500 | C39: 0.026 | D39: 0.1 | E39: 24000 | F39: 800
A40: Rendimiento del campesino y la mozzarella sobre leche estandarizada; el del doble crema, sobre leche entera e incluye la crema del fundido. Precios: Corabastos y mercado mayorista, 2026.
A42: Estandarización de grasa de toda la recepción (kg/día)
A43: Referencia | B43: Leche (L/día) | C43: Grasa objetivo | D43: Crema retirada hoy | E43: Crema con medidor | F43: Crema adicional
A44: L1 leche entera UHT | B44: 6500 | C44: 0.03 | D44: =MAX(0,B44*$B$7*($B$8-(C44+$B$10))/($B$9-(C44+$B$10))) -> 94.295775 | E44: =MAX(0,B44*$B$7*($B$8-(C44+$B$11))/($B$9-(C44+$B$11))) -> 103.22288 | F44: =E44-D44 -> 8.9271088
A45: L2 deslactosada | B45: 3500 | C45: 0.015 | D45: =MAX(0,B45*$B$7*($B$8-(C45+$B$10))/($B$9-(C45+$B$10))) -> 189.5393 | E45: =MAX(0,B45*$B$7*($B$8-(C45+$B$11))/($B$9-(C45+$B$11))) -> 193.97842 | F45: =E45-D45 -> 4.4391223
A46: L3 bebida láctea | B46: 2000 | C46: 0.02 | D46: =MAX(0,B46*$B$7*($B$8-(C46+$B$10))/($B$9-(C46+$B$10))) -> 82.57384 | E46: =MAX(0,B46*$B$7*($B$8-(C46+$B$11))/($B$9-(C46+$B$11))) -> 85.177772 | F46: =E46-D46 -> 2.6039323
A47: Q1 campesino | B47: =B37 -> 4500 | C47: =C37 -> 0.026 | D47: =MAX(0,B47*$B$7*($B$8-(C47+$B$10))/($B$9-(C47+$B$10))) -> 114.26045 | E47: =MAX(0,B47*$B$7*($B$8-(C47+$B$11))/($B$9-(C47+$B$11))) -> 120.30907 | F47: =E47-D47 -> 6.0486213
A48: Q3 mozzarella | B48: =B39 -> 1500 | C48: =C39 -> 0.026 | D48: =MAX(0,B48*$B$7*($B$8-(C48+$B$10))/($B$9-(C48+$B$10))) -> 38.086817 | E48: =MAX(0,B48*$B$7*($B$8-(C48+$B$11))/($B$9-(C48+$B$11))) -> 40.103024 | F48: =E48-D48 -> 2.0162071
A49: Y1 yogur natural | B49: 1400 | C49: 0.03 | D49: =MAX(0,B49*$B$7*($B$8-(C49+$B$10))/($B$9-(C49+$B$10))) -> 20.309859 | E49: =MAX(0,B49*$B$7*($B$8-(C49+$B$11))/($B$9-(C49+$B$11))) -> 22.232621 | F49: =E49-D49 -> 1.9227619
A50: Y2 yogur de fresa | B50: 1400 | C50: 0.03 | D50: =MAX(0,B50*$B$7*($B$8-(C50+$B$10))/($B$9-(C50+$B$10))) -> 20.309859 | E50: =MAX(0,B50*$B$7*($B$8-(C50+$B$11))/($B$9-(C50+$B$11))) -> 22.232621 | F50: =E50-D50 -> 1.9227619
A51: Y3 yogur de mora | B51: 1200 | C51: 0.03 | D51: =MAX(0,B51*$B$7*($B$8-(C51+$B$10))/($B$9-(C51+$B$10))) -> 17.408451 | E51: =MAX(0,B51*$B$7*($B$8-(C51+$B$11))/($B$9-(C51+$B$11))) -> 19.056532 | F51: =E51-D51 -> 1.6480816
A52: Total | B52: =SUM(B44:B51) -> 22000 | D52: =SUM(D44:D51) -> 576.78435 | E52: =SUM(E44:E51) -> 606.31295 | F52: =SUM(F44:F51) -> 29.528597
A53: Balance de grasa: crema = leche × (grasa de la leche − grasa objetivo) / (grasa de la crema − grasa objetivo). Hoy el objetivo lleva la grasa de más del ajuste manual. El doble crema usa leche entera y no se estandariza.
A55: Balance de masa de los quesos (kg/día)
A56: Corriente | B56: Q1 campesino | C56: Q2 doble crema | D56: Q3 mozzarella | E56: Total
A57: Leche | B57: =B37*$B$7 -> 4635 | C57: =B38*$B$7 -> 3090 | D57: =B39*$B$7 -> 1545 | E57: =SUM(B57:D57) -> 9270
A58: Crema retirada en la estandarización | B58: =D47 -> 114.26045 | C58: =0 -> 0 | D58: =D48 -> 38.086817 | E58: =SUM(B58:D58) -> 152.34727
A59: Crema añadida al fundido | B59: =0 -> 0 | C59: =$B$12 -> 30 | D59: =0 -> 0 | E59: =SUM(B59:D59) -> 30
A60: Leche para quesería | B60: =B57-B58 -> 4520.7395 | C60: =C57-C58 -> 3090 | D60: =D57-D58 -> 1506.9132 | E60: =SUM(B60:D60) -> 9117.6527
A61: Agua de lavado del grano | B61: =B60*$B$13 -> 135.62219 | C61: =0 -> 0 | D61: =0 -> 0 | E61: =SUM(B61:D61) -> 135.62219
A62: Queso hoy | B62: =B60*D37 -> 542.48875 | C62: =C60*D38 -> 401.7 | D62: =D60*D39 -> 150.69132 | E62: =SUM(B62:D62) -> 1094.8801
A63: Suero | B63: =B60+B59+B61-B62 -> 4113.873 | C63: =C60+C59+C61-C62 -> 2718.3 | D63: =D60+D59+D61-D62 -> 1356.2219 | E63: =SUM(B63:D63) -> 8188.3949
A64: Cierre: entradas − salidas (debe ser 0) | B64: =(B57+B59+B61)-(B58+B62+B63) -> 0 | C64: =(C57+C59+C61)-(C58+C62+C63) -> 0 | D64: =(D57+D59+D61)-(D58+D62+D63) -> 0 | E64: =SUM(B64:D64) -> 0
A65: Queso adicional por el sensor de coagulación (etapa 1) | B65: =B60*$B$14 -> 6.7811093 | C65: =0 -> 0 | D65: =D60*$B$14 -> 2.2603698 | E65: =SUM(B65:D65) -> 9.0414791
A66: Queso adicional por la hiladora (etapa 2) | B66: =0 -> 0 | C66: =(C62+C65)*$B$15 -> 8.034 | D66: =(D62+D65)*$B$15 -> 3.0590338 | E66: =SUM(B66:D66) -> 11.093034
A67: Queso que pasa por el hilado con la hiladora | B67: =0 -> 0 | C67: =C62+C65+C66 -> 409.734 | D67: =D62+D65+D66 -> 156.01072 | E67: =SUM(B67:D67) -> 565.74472
A68: Queso adicional frente a la producción actual | B68: =(E65+E66)/E62 -> 0.018389697 | D68: Se vende a los mismos clientes: es menos del 2 % del queso que ya se despacha.
A69: El suero total coincide con los 8.188 kg/día del caso. El queso adicional usa la misma leche: no se compra más.
A71: Beneficios anuales en régimen
A72: Medida | B72: Etapa | C72: Beneficio planta ($ M/año) | D72: Δ ventas planta ($ M/año) | E72: Cálculo
A73: Horas extra del hilado evitadas con el orden del hilado | B73: 1 | C73: =$B$26*$B$27*$B$6*$B$28/1000000 -> 11.76 | D73: =0 -> 0 | E73: Horas × operarios × días × costo de la hora extra.
A74: Mayor rendimiento del campesino y la mozzarella | B74: 1 | C74: =(B65*(E37-F37)+D65*(E39-F39))*$B$6/1000000 -> 52.798395 | D74: =(B65*E37+D65*E39)*$B$6/1000000 -> 54.825269 | E74: Queso adicional × (precio − insumos) × días.
A75: Estandarización de grasa en línea (toda la recepción) | B75: 1 | C75: =F52*$B$6*($B$29-$B$30/$B$7)/1000000 -> 52.00416 | D75: =F52*$B$6*($B$29-$B$30/$B$7)/1000000 -> 52.00416 | E75: Crema adicional × (precio de la crema − leche UHT que deja de venderse) × días.
A76: Menor merma y devoluciones (toda la planta) | B76: 1 | C76: =($B$19-$B$20)*Quesería!$B$31 -> 152.285 | D76: =0 -> 0 | E76: Reducción de la merma × ventas de la planta.
A77: Mantenimiento preventivo (toda la planta) | B77: 1 | C77: =$B$22*$B$21 -> 91.4 | D77: =0 -> 0 | E77: Ahorro × gasto de mantenimiento.
A78: Menor sobrepeso de los tres quesos | B78: 1 | C78: =($B$16-$B$17)*Quesería!$B$30*(1-$B$18) -> 32.5056 | D78: =($B$16-$B$17)*Quesería!$B$30 -> 33.86 | E78: Sobrepeso evitado × ventas de quesos, menos el empaque.
A79: Hiladora-moldeadora: más doble crema y mozzarella | B79: 2 | C79: =(C66*(E38-F38)+D66*(E39-F39))*$B$6/1000000 -> 70.703173 | D79: =(C66*E38+D66*E39)*$B$6/1000000 -> 73.548454 | E79: Queso adicional × (precio − insumos) × días.
A80: Horas extra restantes que elimina la hiladora | B80: 2 | C80: =$B$26*$B$27*$B$6*$B$28/1000000 -> 11.76 | D80: =0 -> 0 | E80: Igual que en la etapa 1.
A81: Limpieza CIP automática (las tres líneas) | B81: 2 | C81: =$B$24*$B$23 -> 121.8 | D81: =0 -> 0 | E81: Ahorro × gasto de energía, agua, gas y químicos; la quesería toma su circuito.
A82: Contrato de venta del suero enfriado | B82: 2 | C82: =E63*$B$6*($B$32-$B$31)/1000000 -> 36.110821 | D82: =E63*$B$6*($B$32-$B$31)/1000000 -> 36.110821 | E82: Suero × días × (precio con contrato − precio actual). La energía del enfriamiento va en los costos.
A83: Relevo natural: operarios liberados por la hiladora cubren vacantes | B83: 2 | C83: =$B$33*Quesería!$B$33 -> 72 | D83: =0 -> 0 | E83: Operarios × costo anual de un operario.
A85: Costos operativos nuevos
A86: Dato | B86: Valor | C86: Unidad | D86: Fuente o criterio
A87: Tarifa de energía eléctrica | B87: 1036 | C87: $/kWh | D87: Enel Colombia, tarifa comercial e industrial, agosto de 2026.
A88: Precio del gas natural para la industria | B88: 20 | C88: US$/MBTU | D88: Precio esperado para la industria en 2026 con gas importado (Vanti, en Portafolio).
A89: Tasa de cambio | B89: =Cotizaciones!$B$6 -> 3170.46 | C89: $/US$ | D89: Hoja Cotizaciones.
A90: Energía útil de un kg de vapor | B90: 2.7 | C90: MJ/kg | D90: Vapor saturado de baja presión.
A91: Eficiencia de la caldera | B91: 0.8 | C91: % | D91: Caldera de gas en buen estado.
A92: Costo del vapor | B92: =B90/B91/1055*B88*B89 -> 202.84934 | C92: $/kg | D92: 1 MBTU = 1.055 MJ.
A93: Vapor de la hiladora | B93: 0.15 | C93: kg/kg de queso hilado | D93: Hiladora con inyección de vapor; se cuenta todo como adicional aunque reemplaza el agua caliente de las marmitas.
A94: Calor específico del suero | B94: 3.9 | C94: kJ/kg·K
A95: Enfriamiento con agua helada | B95: 16 | C95: °C | D95: De 20 a 4 °C; el primer tramo, de 38 a 20 °C, se hace con agua de torre.
A96: Rendimiento del equipo de agua helada | B96: 3 | C96: kWh frío/kWh eléctrico | D96: Valor típico de un enfriador de agua.
A98: Consumo eléctrico | B98: Etapa | C98: kW | D98: h/día | E98: kWh/día | F98: Días/año | G98: kWh/año | H98: $ M/año | I98: Reparto | J98: Quesería ($ M/año)
A99: Controladora de peso y detector de metales | B99: 1 | C99: 1.2 | D99: 8 | E99: =C99*D99 -> 9.6 | F99: =$B$6 -> 294 | G99: =E99*F99 -> 2822.4 | H99: =G99*$B$87/1000000 -> 2.9240064 | I99: 1 | J99: =H99*I99 -> 2.9240064
A100: Medidor de grasa en línea (recepción común) | B100: 1 | C100: 0.3 | D100: 10 | E100: =C100*D100 -> 3 | F100: =$B$6 -> 294 | G100: =E100*F100 -> 882 | H100: =G100*$B$87/1000000 -> 0.913752 | I100: =Quesería!$B$29 -> 0.36 | J100: =H100*I100 -> 0.32895072
A101: SCADA: servidor, red y estaciones | B101: 1 | C101: 0.6 | D101: 24 | E101: =C101*D101 -> 14.4 | F101: 365 | G101: =E101*F101 -> 5256 | H101: =G101*$B$87/1000000 -> 5.445216 | I101: 1 | J101: =H101*I101 -> 5.445216
A102: Hiladora-moldeadora: motores y bombas | B102: 2 | C102: 7.5 | D102: 4 | E102: =C102*D102 -> 30 | F102: =$B$6 -> 294 | G102: =E102*F102 -> 8820 | H102: =G102*$B$87/1000000 -> 9.13752 | I102: 1 | J102: =H102*I102 -> 9.13752
A103: CIP: bombas de impulsión y retorno | B103: 2 | C103: 7.7 | D103: 1.5 | E103: =C103*D103 -> 11.55 | F103: =$B$6 -> 294 | G103: =E103*F103 -> 3395.7 | H103: =G103*$B$87/1000000 -> 3.5179452 | I103: 1 | J103: =H103*I103 -> 3.5179452
A104: Enfriamiento del suero: agua helada y bombas | B104: 2 | E104: =E63*$B$94*$B$95/3600/$B$96+2*4 -> 55.310726 | F104: =$B$6 -> 294 | G104: =E104*F104 -> 16261.353 | H104: =G104*$B$87/1000000 -> 16.846762 | I104: 1 | J104: =H104*I104 -> 16.846762
A105: Vapor de la hiladora | B105: 2 | E105: =$B$93*E67 -> 84.861708 | F105: =$B$6 -> 294 | G105: kg de vapor/día | H105: =E105*F105*$B$92/1000000 -> 5.0609575 | I105: 1 | J105: =H105*I105 -> 5.0609575
A106: Las liras con variador reemplazan motores que ya existen: no suman consumo.
A107: Costo del enfriamiento por kg de suero | B107: =J104*1000000/(E63*$B$6) -> 6.997942 | C107: $/kg | D107: Antes se suponían $5/kg; el cálculo de energía da esta cifra.
A109: Calibración y verificación | B109: Etapa | C109: $ M/año (planta) | D109: Reparto | E109: Quesería ($ M/año)
A110: Controladora de peso: calibración con pesas patrón | B110: 1 | C110: 1.5 | D110: 1 | E110: =C110*D110 -> 1.5
A111: Detector de metales: probetas de prueba y verificación | B111: 1 | C111: 0.5 | D111: 1 | E111: =C111*D111 -> 0.5
A112: Medidor de grasa: contraste con el laboratorio y recalibración | B112: 1 | C112: 2 | D112: =Quesería!$B$29 -> 0.36 | E112: =C112*D112 -> 0.72
A113: Sensores de coagulación, temperatura y caudal de las tinas | B113: 1 | C113: 2 | D113: 1 | E113: =C113*D113 -> 2
A114: Conductivímetros y temperatura del CIP | B114: 2 | C114: 0.8 | D114: 1 | E114: =C114*D114 -> 0.8
...

Sheet Cotizaciones
A1: Cotizaciones y precios de referencia de los equipos
A2: Precios publicados en octubre de 2026, convertidos a pesos con la TRM y el euro del día. Sin cotización formal todavía: las cifras en azul se reemplazan cuando lleguen las de los proveedores.
A4: Tasas de cambio y factores
A5: Concepto | B5: Valor | C5: Unidad | D5: Fuente
A6: Tasa representativa del mercado (16 de octubre de 2026) | B6: 3170.46 | C6: $/US$ | D6: Superintendencia Financiera, citada por Noticias Caracol, 16-oct-2026.
A7: Euro en pesos (15 de octubre de 2026) | B7: 3569.9 | C7: $/€ | D7: Investing.com, citado por Portafolio, 15-oct-2026.
A8: Flete, seguro, arancel y nacionalización de un equipo importado | B8: 0.3 | C8: % del precio | D8: Supuesto: flete marítimo e internación desde Asia o Europa; confirmar con el agente de aduanas.
A9: Instalación, integración y puesta en marcha | B9: 0.15 | C9: % del precio | D9: Supuesto: montaje, cableado al PLC y pruebas en sitio.
A11: Equipos de la inversión
A12: Equipo | B12: Precio de referencia | C12: Moneda | D12: Precio en $ M | E12: Con nacionalización e instalación ($ M) | F12: Valor en el modelo ($ M) | G12: Estado | H12: Referencia | I12: Lectura
A13: Controladora de peso y detector de metales (estación E18) | B13: 7000 | C13: US$ | D13: =B13*$B$6/1000000 -> 22.19322 | E13: =D13*(1+$B$8)*(1+$B$9) -> 33.178864 | F13: =E13 -> 33.178864 | G13: Precio publicado | H13: Made-in-China, catálogo de controladoras de peso: equipo combinado con detector de metales, US$6.500–7.000 por unidad (oct-2026). | I13: Equipo de origen chino. Una marca europea puede costar 3 a 4 veces más; se recomienda pedir las dos cotizaciones.
A14: Hiladora-moldeadora continua de 300 kg/h | B14: 39000 | C14: € | D14: =B14*$B$7/1000000 -> 139.2261 | E14: =D14*(1+$B$8)*(1+$B$9) -> 208.14302 | F14: 322.6 | G14: Estimado con referencias | H14: Werktuigen: DIMA 100 Compact usada (2023), 100 kg/h, €39.000. Ullmer's: cocedora-hiladora DIMA usada, US$35.000. Made-in-China: cocedora-hiladora por lotes, US$12.500–18.500. | I14: Las referencias son de máquinas usadas de 100 kg/h o de equipos por lotes. Una continua nueva de 300 kg/h (Milkylab, CMT, Dima) es de precio a solicitud; el estimado equivale a unos US$102.000.
A15: CIP automático del circuito de quesos | B15: 5000 | C15: US$ | D15: =B15*$B$6/1000000 -> 15.8523 | E15: =D15*(1+$B$8)*(1+$B$9) -> 23.699189 | F15: =320/3 -> 106.66667 | G15: Estimado con referencias | H15: Accio: sistemas CIP automáticos de US$4.000–10.000 (estaciones pequeñas) hasta US$80.000 (línea completa de leche). | I15: El estimado (un tercio de una estación de tres circuitos) está dentro del rango publicado.
A16: SCADA, historiador y MES ligero (licencias Ignition) | B16: 9500 | C16: US$ | D16: =B16*$B$6/1000000 -> 30.11937 | E16: =D16*(1+$B$8)*(1+$B$9) -> 45.028458 | F16: =200/3 -> 66.666667 | G16: Estimado con referencias | H16: Industrial Monitor Direct (jul-2026): Ignition Vision ilimitado US$6.500; paquete «The Works» US$9.500. | I16: Las licencias son una parte; el valor del modelo incluye servidor, red e instrumentación de la quesería.
A17: Controlador de las tinas (CompactLogix 1769-L33ER) | B17: 2200 | C17: US$ | D17: =B17*$B$6/1000000 -> 6.975012 | E17: =D17*(1+$B$8)*(1+$B$9) -> 10.427643 | F17: =E17 -> 10.427643 | G17: Precio publicado | H17: NJT Automation: 1769-L33ER nuevo, caja abierta, US$2.199,99. | I17: Componente incluido en la automatización de las tinas; se muestra como referencia del costo del control.
A18: Automatización de 2 tinas (liras con variador, sensor de coagulación, dosificación) | F18: 180 | G18: Estimado | H18: Pendiente: sensor de coagulación y liras motorizadas son de precio a solicitud.
A19: Tina del doble crema: medición y mando básicos | F19: 30 | G19: Estimado | H19: Pendiente de cotización.
A20: Medidor de grasa en línea (planta) | F20: 120 | G20: Estimado | H20: FOSS, Anton Paar y Maselli: precio a solicitud.
A21: Enfriador de placas y tanque pulmón del suero | F21: 80 | G21: Estimado | H21: Pendiente de cotización.
A23: Siguiente paso: solicitud formal de cotización a proveedores en Colombia (equipos de proceso lácteo, instrumentación y control) para la hiladora, las tinas, el medidor de grasa, el CIP y la estación E18.

Sheet Escenarios
A1: Escenarios de la oferta
A2: La misma evaluación de la hoja Quesería con los supuestos que más mueven el resultado. La columna Oferta reproduce la hoja Quesería.
A4: Qué cambia en cada escenario
A5: Supuesto | B5: Oferta | C5: Conservador | D5: Conservador con compuerta | E5: Sin arranque en 2027 | F5: Sin relevo natural | G5: Beneficios −20 % | H5: Beneficios +20 % | I5: Inversión +20 % | J5: Inversión −20 % | K5: Costos operativos +30 % | L5: Costos operativos −30 % | M5: Inflación del consenso | N5: Inflación persistente | O5: Salario mínimo 2027: 7 % | P5: Salario mínimo 2027: 10 % | Q5: Renta 30 % | R5: Crédito ordinario | S5: Garantía del FNG | T5: Sin crédito fiscal por innovación | U5: Sin las dos gestiones | V5: Adverso combinado | W5: Sin herramientas | X5: Con el costo de capital del proyecto | Y5: Solo etapas 0 y 1
A6: Horas extra restantes que elimina la hiladora (1 = se cuentan) | B6: 1 | C6: 1 | D6: 1 | E6: 1 | F6: 1 | G6: 1 | H6: 1 | I6: 1 | J6: 1 | K6: 1 | L6: 1 | M6: 1 | N6: 1 | O6: 1 | P6: 1 | Q6: 1 | R6: 1 | S6: 1 | T6: 1 | U6: 1 | V6: 1 | W6: 1 | X6: 1 | Y6: 1
A7: Descuento tributario del suero (1 = se toma) | B7: 1 | C7: 0 | D7: 0 | E7: 1 | F7: 1 | G7: 1 | H7: 1 | I7: 1 | J7: 1 | K7: 1 | L7: 1 | M7: 1 | N7: 1 | O7: 1 | P7: 1 | Q7: 1 | R7: 1 | S7: 1 | T7: 1 | U7: 1 | V7: 1 | W7: 1 | X7: 1 | Y7: 1
A8: Valor de los equipos al año 10 (1 = se cuenta) | B8: 1 | C8: 0 | D8: 0 | E8: 1 | F8: 1 | G8: 1 | H8: 1 | I8: 1 | J8: 1 | K8: 1 | L8: 1 | M8: 1 | N8: 1 | O8: 1 | P8: 1 | Q8: 1 | R8: 1 | S8: 1 | T8: 1 | U8: 1 | V8: 1 | W8: 1 | X8: 1 | Y8: 1
A9: Relevo natural de 2 operarios (1 = se cuenta) | B9: 1 | C9: 1 | D9: 1 | E9: 1 | F9: 0 | G9: 1 | H9: 1 | I9: 1 | J9: 1 | K9: 1 | L9: 1 | M9: 1 | N9: 1 | O9: 1 | P9: 1 | Q9: 1 | R9: 1 | S9: 1 | T9: 1 | U9: 1 | V9: 1 | W9: 1 | X9: 1 | Y9: 1
A10: Factor de beneficios | B10: 1 | C10: 1 | D10: 1 | E10: 1 | F10: 1 | G10: 0.8 | H10: 1.2 | I10: 1 | J10: 1 | K10: 1 | L10: 1 | M10: 1 | N10: 1 | O10: 1 | P10: 1 | Q10: 1 | R10: 1 | S10: 1 | T10: 1 | U10: 1 | V10: 0.8 | W10: 1 | X10: 1 | Y10: 1
A11: Factor de inversión | B11: 1 | C11: 1 | D11: 1 | E11: 1 | F11: 1 | G11: 1 | H11: 1 | I11: 1.2 | J11: 0.8 | K11: 1 | L11: 1 | M11: 1 | N11: 1 | O11: 1 | P11: 1 | Q11: 1 | R11: 1 | S11: 1 | T11: 1 | U11: 1 | V11: 1.2 | W11: 1 | X11: 1 | Y11: 1
A12: Factor de costos operativos nuevos | B12: 1 | C12: 1 | D12: 1 | E12: 1 | F12: 1 | G12: 1 | H12: 1 | I12: 1 | J12: 1 | K12: 1.3 | L12: 0.7 | M12: 1 | N12: 1 | O12: 1 | P12: 1 | Q12: 1 | R12: 1 | S12: 1 | T12: 1 | U12: 1 | V12: 1.3 | W12: 1 | X12: 1 | Y12: 1
A13: Garantía del crédito (0 = prenda sobre los equipos; 1 = FNG) | B13: =Quesería!$B$48 -> 0 | C13: 1 | D13: 1 | E13: =Quesería!$B$48 -> 0 | F13: =Quesería!$B$48 -> 0 | G13: =Quesería!$B$48 -> 0 | H13: =Quesería!$B$48 -> 0 | I13: =Quesería!$B$48 -> 0 | J13: =Quesería!$B$48 -> 0 | K13: =Quesería!$B$48 -> 0 | L13: =Quesería!$B$48 -> 0 | ... R13: =Quesería!$B$48 -> 0 | S13: 1 | T13: =Quesería!$B$48 -> 0 | U13: 1 | V13: =Quesería!$B$48 -> 0 | W13: 1 | X13: 1 | Y13: =Quesería!$B$48 -> 0
A14: Tasa del crédito | B14: =Quesería!$B$41 -> 0.141 | C14: =Quesería!$B$41 -> 0.141 | D14: =Quesería!$B$41 -> 0.141 | E14: =Quesería!$B$41 -> 0.141 | F14: =Quesería!$B$41 -> 0.141 | G14: =Quesería!$B$41 -> 0.141 | H14: =Quesería!$B$41 -> 0.141 | I14: =Quesería!$B$41 -> 0.141 | ... Q14: =Quesería!$B$41 -> 0.141 | R14: 0.157 | S14: =Quesería!$B$41 -> 0.141 | T14: =Quesería!$B$41 -> 0.141 | U14: =Quesería!$B$41 -> 0.141 | V14: =Quesería!$B$41 -> 0.141 | W14: =Quesería!$B$41 -> 0.141 | X14: =Quesería!$B$41 -> 0.141 | Y14: =Quesería!$B$41 -> 0.141
A15: Ruta de inflación (1 base, 2 consenso, 3 persistente) | B15: =Quesería!$B$6 -> 1 | C15: =Quesería!$B$6 -> 1 | D15: =Quesería!$B$6 -> 1 | E15: =Quesería!$B$6 -> 1 | F15: =Quesería!$B$6 -> 1 | G15: =Quesería!$B$6 -> 1 | H15: =Quesería!$B$6 -> 1 | I15: =Quesería!$B$6 -> 1 | ... L15: =Quesería!$B$6 -> 1 | M15: 2 | N15: 3 | O15: =Quesería!$B$6 -> 1 | P15: =Quesería!$B$6 -> 1 | Q15: =Quesería!$B$6 -> 1 | R15: =Quesería!$B$6 -> 1 | S15: =Quesería!$B$6 -> 1 | T15: =Quesería!$B$6 -> 1 | U15: =Quesería!$B$6 -> 1 | V15: =Quesería!$B$6 -> 1 | ... Y15: =Quesería!$B$6 -> 1
A16: Incremento del salario mínimo de 2027 | B16: =Entorno!$B$12 -> 0.085 | C16: =Entorno!$B$12 -> 0.085 | D16: =Entorno!$B$12 -> 0.085 | E16: =Entorno!$B$12 -> 0.085 | F16: =Entorno!$B$12 -> 0.085 | G16: =Entorno!$B$12 -> 0.085 | H16: =Entorno!$B$12 -> 0.085 | I16: =Entorno!$B$12 -> 0.085 | ... N16: =Entorno!$B$12 -> 0.085 | O16: 0.07 | P16: 0.1 | Q16: =Entorno!$B$12 -> 0.085 | R16: =Entorno!$B$12 -> 0.085 | S16: =Entorno!$B$12 -> 0.085 | T16: =Entorno!$B$12 -> 0.085 | U16: =Entorno!$B$12 -> 0.085 | V16: =Entorno!$B$12 -> 0.085 | W16: =Entorno!$B$12 -> 0.085 | X16: =Entorno!$B$12 -> 0.085 | Y16: =Entorno!$B$12 -> 0.085
A17: Impuesto de renta | B17: =Quesería!$B$10 -> 0.35 | C17: =Quesería!$B$10 -> 0.35 | D17: =Quesería!$B$10 -> 0.35 | E17: =Quesería!$B$10 -> 0.35 | F17: =Quesería!$B$10 -> 0.35 | G17: =Quesería!$B$10 -> 0.35 | H17: =Quesería!$B$10 -> 0.35 | I17: =Quesería!$B$10 -> 0.35 | ... P17: =Quesería!$B$10 -> 0.35 | Q17: 0.3 | R17: =Quesería!$B$10 -> 0.35 | S17: =Quesería!$B$10 -> 0.35 | T17: =Quesería!$B$10 -> 0.35 | U17: =Quesería!$B$10 -> 0.35 | V17: =Quesería!$B$10 -> 0.35 | W17: =Quesería!$B$10 -> 0.35 | X17: =Quesería!$B$10 -> 0.35 | Y17: =Quesería!$B$10 -> 0.35
A18: Costo de capital (1 = del proyecto; 0 = 16 % de la empresa) | B18: 1 | C18: 1 | D18: 1 | E18: 1 | F18: 1 | G18: 1 | H18: 1 | I18: 1 | J18: 1 | K18: 1 | L18: 1 | M18: 1 | N18: 1 | O18: 1 | P18: 1 | Q18: 1 | R18: 1 | S18: 1 | T18: 1 | U18: 1 | V18: 1 | W18: 0 | X18: 1 | Y18: 1
A19: Depreciación fiscal por tipo de activo (1 = sí; 0 = todo a 10 años) | B19: 1 | C19: 1 | D19: 1 | E19: 1 | F19: 1 | G19: 1 | H19: 1 | I19: 1 | J19: 1 | K19: 1 | L19: 1 | M19: 1 | N19: 1 | O19: 1 | P19: 1 | Q19: 1 | R19: 1 | S19: 1 | T19: 1 | U19: 1 | V19: 1 | W19: 0 | X19: 0 | Y19: 1
A20: Crédito fiscal por innovación, art. 256-1 (1 = certificado) | B20: =Quesería!$B$49 -> 1 | C20: 0 | D20: 0 | E20: =Quesería!$B$49 -> 1 | F20: =Quesería!$B$49 -> 1 | G20: =Quesería!$B$49 -> 1 | H20: =Quesería!$B$49 -> 1 | I20: =Quesería!$B$49 -> 1 | J20: =Quesería!$B$49 -> 1 | K20: =Quesería!$B$49 -> 1 | L20: =Quesería!$B$49 -> 1 | ... S20: =Quesería!$B$49 -> 1 | T20: 0 | U20: 0 | V20: =Quesería!$B$49 -> 1 | W20: 0 | X20: 0 | Y20: =Quesería!$B$49 -> 1
A21: Etapa 2 (1 = se hace) | B21: 1 | C21: 1 | D21: 0 | E21: 1 | F21: 1 | G21: 1 | H21: 1 | I21: 1 | J21: 1 | K21: 1 | L21: 1 | M21: 1 | N21: 1 | O21: 1 | P21: 1 | Q21: 1 | R21: 1 | S21: 1 | T21: 1 | U21: 1 | V21: 1 | W21: 1 | X21: 1 | Y21: 0
A22: Beneficios según su respaldo (1 = caso conservador) | B22: 0 | C22: 1 | D22: 1 | E22: 0 | F22: 0 | G22: 0 | H22: 0 | I22: 0 | J22: 0 | K22: 0 | L22: 0 | M22: 0 | N22: 0 | O22: 0 | P22: 0 | Q22: 0 | R22: 0 | S22: 0 | T22: 0 | U22: 0 | V22: 0 | W22: 0 | X22: 0 | Y22: 0
A23: Arranque de la etapa 1 en 2027 (1 = se cuenta) | B23: 1 | C23: 1 | D23: 1 | E23: 0 | F23: 1 | G23: 1 | H23: 1 | I23: 1 | J23: 1 | K23: 1 | L23: 1 | M23: 1 | N23: 1 | O23: 1 | P23: 1 | Q23: 1 | R23: 1 | S23: 1 | T23: 1 | U23: 1 | V23: 1 | W23: 1 | X23: 1 | Y23: 1
A24: Ajuste de las tasas nominales por la inflación de la ruta (Fisher) | B24: =CHOOSE(B$15,Entorno!$M$7,Entorno!$M$8,Entorno!$M$9)-CHOOSE(Quesería!$B$6,Entorno!$M$7,Entorno!$M$8,Entorno!$M$9) -> 0 | C24: =CHOOSE(C$15,Entorno!$M$7,Entorno!$M$8,Entorno!$M$9)-CHOOSE(Quesería!$B$6,Entorno!$M$7,Entorno!$M$8,Entorno!$M$9) -> 0 | D24: =CHOOSE(D$15,Entorno!$M$7,Entorno!$M$8,Entorno!$M$9)-CHOOSE(Quesería!$B$6,Entorno!$M$7,Entorno!$M$8,Entorno!$M$9) -> 0 | E24: =CHOOSE(E$15,Entorno!$M$7,Entorno!$M$8,Entorno!$M$9)-CHOOSE(Quesería!$B$6,Entorno!$M$7,Entorno!$M$8,Entorno!$M$9) -> 0 | F24: =CHOOSE(F$15,Entorno!$M$7,Entorno!$M$8,Entorno!$M$9)-CHOOSE(Quesería!$B$6,Entorno!$M$7,Entorno!$M$8,Entorno!$M$9) -> 0 | G24: =CHOOSE(G$15,Entorno!$M$7,Entorno!$M$8,Entorno!$M$9)-CHOOSE(Quesería!$B$6,Entorno!$M$7,Entorno!$M$8,Entorno!$M$9) -> 0 | H24: =CHOOSE(H$15,Entorno!$M$7,Entorno!$M$8,Entorno!$M$9)-CHOOSE(Quesería!$B$6,Entorno!$M$7,Entorno!$M$8,Entorno!$M$9) -> 0 | I24: =CHOOSE(I$15,Entorno!$M$7,Entorno!$M$8,Entorno!$M$9)-CHOOSE(Quesería!$B$6,Entorno!$M$7,Entorno!$M$8,Entorno!$M$9) -> 0 | ... Y24: =CHOOSE(Y$15,Entorno!$M$7,Entorno!$M$8,Entorno!$M$9)-CHOOSE(Quesería!$B$6,Entorno!$M$7,Entorno!$M$8,Entorno!$M$9) -> 0
A25: Costo de capital del proyecto | B25: =IF(B$18=1,Quesería!$B$40*(B$14+B$24+B$13*Quesería!$B$44*1.19)*(1-B$17)+(1-Quesería!$B$40)*(Quesería!$B$46+B$24),Quesería!$B$7+B$24) -> 0.139155 | C25: =IF(C$18=1,Quesería!$B$40*(C$14+C$24+C$13*Quesería!$B$44*1.19)*(1-C$17)+(1-Quesería!$B$40)*(Quesería!$B$46+C$24),Quesería!$B$7+C$24) -> 0.14992986 | D25: =IF(D$18=1,Quesería!$B$40*(D$14+D$24+D$13*Quesería!$B$44*1.19)*(1-D$17)+(1-Quesería!$B$40)*(Quesería!$B$46+D$24),Quesería!$B$7+D$24) -> 0.14992986 | E25: =IF(E$18=1,Quesería!$B$40*(E$14+E$24+E$13*Quesería!$B$44*1.19)*(1-E$17)+(1-Quesería!$B$40)*(Quesería!$B$46+E$24),Quesería!$B$7+E$24) -> 0.139155 | F25: =IF(F$18=1,Quesería!$B$40*(F$14+F$24+F$13*Quesería!$B$44*1.19)*(1-F$17)+(1-Quesería!$B$40)*(Quesería!$B$46+F$24),Quesería!$B$7+F$24) -> 0.139155 | G25: =IF(G$18=1,Quesería!$B$40*(G$14+G$24+G$13*Quesería!$B$44*1.19)*(1-G$17)+(1-Quesería!$B$40)*(Quesería!$B$46+G$24),Quesería!$B$7+G$24) -> 0.139155 | H25: =IF(H$18=1,Quesería!$B$40*(H$14+H$24+H$13*Quesería!$B$44*1.19)*(1-H$17)+(1-Quesería!$B$40)*(Quesería!$B$46+H$24),Quesería!$B$7+H$24) -> 0.139155 | I25: =IF(I$18=1,Quesería!$B$40*(I$14+I$24+I$13*Quesería!$B$44*1.19)*(1-I$17)+(1-Quesería!$B$40)*(Quesería!$B$46+I$24),Quesería!$B$7+I$24) -> 0.139155 | ... Y25: =IF(Y$18=1,Quesería!$B$40*(Y$14+Y$24+Y$13*Quesería!$B$44*1.19)*(1-Y$17)+(1-Quesería!$B$40)*(Quesería!$B$46+Y$24),Quesería!$B$7+Y$24) -> 0.139155
A26: Conservador: cada beneficio según su respaldo (contratado y medido 100 %, técnicamente justificado 75 %, por medir 50 %, hipotético 0 %), sin descuento ambiental ni crédito fiscal, con garantía del FNG y sin valor final de los equipos. Conservador con compuerta: lo mismo, pero la etapa 2 no se hace porque sus condiciones no se cumplen. Las rutas de inflación mueven las tasas nominales en la misma proporción (Fisher). Crédito ordinario: 15,7 %, tasa de los créditos empresariales a medianas empresas a 3–5 años en la misma fuente. Garantía del FNG: si el banco no acepta la prenda. Sin crédito fiscal: si el CNBT no certifica la inversión. Renta 30 %: si prospera la reducción anunciada por el Gobierno. Adverso combinado: beneficios −20 %, inversión +20 % y costos +30 % a la vez. Los escenarios de herramientas se explican en la hoja Herramientas.
A28: Resultados por escenario
B29: Oferta | C29: Conservador | D29: Conservador con compuerta | E29: Sin arranque en 2027 | F29: Sin relevo natural | G29: Beneficios −20 % | H29: Beneficios +20 % | I29: Inversión +20 % | J29: Inversión −20 % | K29: Costos operativos +30 % | L29: Costos operativos −30 % | M29: Inflación del consenso | N29: Inflación persistente | O29: Salario mínimo 2027: 7 % | P29: Salario mínimo 2027: 10 % | Q29: Renta 30 % | R29: Crédito ordinario | S29: Garantía del FNG | T29: Sin crédito fiscal por innovación | U29: Sin las dos gestiones | V29: Adverso combinado | W29: Sin herramientas | X29: Con el costo de capital del proyecto | Y29: Solo etapas 0 y 1
A30: Costo de capital del proyecto | B30: =$B$25 -> 0.139155 | C30: =$C$25 -> 0.14992986 | D30: =$D$25 -> 0.14992986 | E30: =$E$25 -> 0.139155 | F30: =$F$25 -> 0.139155 | G30: =$G$25 -> 0.139155 | H30: =$H$25 -> 0.139155 | I30: =$I$25 -> 0.139155 | J30: =$J$25 -> 0.139155 | K30: =$K$25 -> 0.139155 | L30: =$L$25 -> 0.139155 | M30: =$M$25 -> 0.13489286 | N30: =$N$25 -> 0.15564123 | O30: =$O$25 -> 0.139155 | P30: =$P$25 -> 0.139155 | Q30: =$Q$25 -> 0.14409 | R30: =$R$25 -> 0.146435 | S30: =$S$25 -> 0.14992986 | T30: =$T$25 -> 0.139155 | U30: =$U$25 -> 0.14992986 | V30: =$V$25 -> 0.139155 | W30: =$W$25 -> 0.16 | X30: =$X$25 -> 0.14992986 | Y30: =$Y$25 -> 0.139155
A31: TIR del proyecto en pesos corrientes (frente al costo de capital) | B31: =IRR(B68:L68) -> 0.21421387 | C31: =IRR(B111:L111) -> 0.062952682 | D31: =IRR(B154:L154) -> 0.057937208 | E31: =IRR(B197:L197) -> 0.2066915 | F31: =IRR(B240:L240) -> 0.16039918 | G31: =IRR(B283:L283) -> 0.15125665 | H31: =IRR(B326:L326) -> 0.27173209 | I31: =IRR(B369:L369) -> 0.17059022 | J31: =IRR(B412:L412) -> 0.27467606 | K31: =IRR(B455:L455) -> 0.1946857 | L31: =IRR(B498:L498) -> 0.23317777 | M31: =IRR(B541:L541) -> 0.20842777 | N31: =IRR(B584:L584) -> 0.23525123 | O31: =IRR(B627:L627) -> 0.21330547 | P31: =IRR(B670:L670) -> 0.21512052 | Q31: =IRR(B713:L713) -> 0.2250889 | R31: =IRR(B756:L756) -> 0.21421387 | S31: =IRR(B799:L799) -> 0.21421387 | T31: =IRR(B842:L842) -> 0.17926805 | U31: =IRR(B885:L885) -> 0.17926805 | V31: =IRR(B928:L928) -> 0.09300273 | W31: =IRR(B971:L971) -> 0.17427009 | X31: =IRR(B1014:L1014) -> 0.17427009 | Y31: =IRR(B1057:L1057) -> 0.24010284
A32: TIR del proyecto en pesos constantes | B32: =IRR(B67:L67) -> 0.16467046 | C32: =IRR(B110:L110) -> 0.020128529 | D32: =IRR(B153:L153) -> 0.014477445 | E32: =IRR(B196:L196) -> 0.15746907 | F32: =IRR(B239:L239) -> 0.11322879 | G32: =IRR(B282:L282) -> 0.10448845 | H32: =IRR(B325:L325) -> 0.21963093 | I32: =IRR(B368:L368) -> 0.12296903 | J32: =IRR(B411:L411) -> 0.22244945 | K32: =IRR(B454:L454) -> 0.14600996 | L32: =IRR(B497:L497) -> 0.18278915 | M32: =IRR(B540:L540) -> 0.16616325 | N32: =IRR(B583:L583) -> 0.15986031 | O32: =IRR(B626:L626) -> 0.1638021 | P32: =IRR(B669:L669) -> 0.16553712 | Q32: =IRR(B712:L712) -> 0.17506959 | R32: =IRR(B755:L755) -> 0.16467046 | S32: =IRR(B798:L798) -> 0.16467046 | T32: =IRR(B841:L841) -> 0.13142032 | U32: =IRR(B884:L884) -> 0.13142032 | V32: =IRR(B927:L927) -> 0.048778661 | W32: =IRR(B970:L970) -> 0.12662818 | X32: =IRR(B1013:L1013) -> 0.12662818 | Y32: =IRR(B1056:L1056) -> 0.18783588
A33: VPN al costo de capital ($ M de 2026) | B33: =SUMPRODUCT(B67:L67,B71:L71) -> 367.41984 | C33: =SUMPRODUCT(B110:L110,B114:L114) -> -396.60213 | D33: =SUMPRODUCT(B153:L153,B157:L157) -> -209.22818 | E33: =SUMPRODUCT(B196:L196,B200:L200) -> 338.06199 | F33: =SUMPRODUCT(B239:L239,B243:L243) -> 97.936235 | G33: =SUMPRODUCT(B282:L282,B286:L286) -> 55.947949 | H33: =SUMPRODUCT(B325:L325,B329:L329) -> 678.89173 | I33: =SUMPRODUCT(B368:L368,B372:L372) -> 177.39427 | J33: =SUMPRODUCT(B411:L411,B415:L415) -> 557.44542 | K33: =SUMPRODUCT(B454:L454,B458:L458) -> 267.23581 | L33: =SUMPRODUCT(B497:L497,B501:L501) -> 467.60387 | M33: =SUMPRODUCT(B540:L540,B544:L544) -> 359.36482 | N33: =SUMPRODUCT(B583:L583,B587:L587) -> 391.67116 | O33: =SUMPRODUCT(B626:L626,B630:L630) -> 362.58857 | P33: =SUMPRODUCT(B669:L669,B673:L673) -> 372.25111 | Q33: =SUMPRODUCT(B712:L712,B716:L716) -> 396.09283 | R33: =SUMPRODUCT(B755:L755,B759:L759) -> 323.12592 | S33: =SUMPRODUCT(B798:L798,B802:L802) -> 302.64226 | T33: =SUMPRODUCT(B841:L841,B845:L845) -> 213.60067 | U33: =SUMPRODUCT(B884:L884,B888:L888) -> 150.26438 | V33: =SUMPRODUCT(B927:L927,B931:L931) -> -240.57876 | W33: =SUMPRODUCT(B970:L970,B974:L974) -> 72.665882 | X33: =SUMPRODUCT(B1013:L1013,B1017:L1017) -> 128.42404 | Y33: =SUMPRODUCT(B1056:L1056,B1060:L1060) -> 230.72914
A34: Recuperación (años) | B34: =SUM(B70:L70) -> 5.1086246 | C34: =SUM(B113:L113) -> 9.1444375 | D34: =SUM(B156:L156) -> 9.3454343 | E34: =SUM(B199:L199) -> 5.2500686 | F34: =SUM(B242:L242) -> 6.2962931 | G34: =SUM(B285:L285) -> 6.4997148 | H34: =SUM(B328:L328) -> 4.2317242 | I34: =SUM(B371:L371) -> 6.0695033 | J34: =SUM(B414:L414) -> 4.1981579 | K34: =SUM(B457:L457) -> 5.5101944 | L34: =SUM(B500:L500) -> 4.7773802 | M34: =SUM(B543:L543) -> 5.0812319 | N34: =SUM(B586:L586) -> 5.1956736 | O34: =SUM(B629:L629) -> 5.125911 | P34: =SUM(B672:L672) -> 5.0914875 | Q34: =SUM(B715:L715) -> 4.9228841 | R34: =SUM(B758:L758) -> 5.1086246 | S34: =SUM(B801:L801) -> 5.1086246 | T34: =SUM(B844:L844) -> 5.9075513 | U34: =SUM(B887:L887) -> 5.9075513 | V34: =SUM(B930:L930) -> 8.2278054 | W34: =SUM(B973:L973) -> 6.027743 | X34: =SUM(B1016:L1016) -> 6.027743 | Y34: =SUM(B1059:L1059) -> 3.8396594
A35: Recuperación descontada (años) | B35: =IF(SUM(B74:L74)=0,"Más de 10",SUM(B74:L74)) -> 6.9418802 | C35: =IF(SUM(B117:L117)=0,"Más de 10",SUM(B117:L117)) -> Más de 10 | D35: =IF(SUM(B160:L160)=0,"Más de 10",SUM(B160:L160)) -> Más de 10 | E35: =IF(SUM(B203:L203)=0,"Más de 10",SUM(B203:L203)) -> 7.1775309 | F35: =IF(SUM(B246:L246)=0,"Más de 10",SUM(B246:L246)) -> 9.0960877 | G35: =IF(SUM(B289:L289)=0,"Más de 10",SUM(B289:L289)) -> 9.4670148 | H35: =IF(SUM(B332:L332)=0,"Más de 10",SUM(B332:L332)) -> 5.4887347 | I35: =IF(SUM(B375:L375)=0,"Más de 10",SUM(B375:L375)) -> 8.611522 | J35: =IF(SUM(B418:L418)=0,"Más de 10",SUM(B418:L418)) -> 5.4264531 | K35: =IF(SUM(B461:L461)=0,"Más de 10",SUM(B461:L461)) -> 7.6082508 | L35: =IF(SUM(B504:L504)=0,"Más de 10",SUM(B504:L504)) -> 6.4220156 | M35: =IF(SUM(B547:L547)=0,"Más de 10",SUM(B547:L547)) -> 6.965895 | N35: =IF(SUM(B590:L590)=0,"Más de 10",SUM(B590:L590)) -> 6.8998148 | O35: =IF(SUM(B633:L633)=0,"Más de 10",SUM(B633:L633)) -> 6.9681585 | P35: =IF(SUM(B676:L676)=0,"Más de 10",SUM(B676:L676)) -> 6.9157894 | Q35: =IF(SUM(B719:L719)=0,"Más de 10",SUM(B719:L719)) -> 6.7615991 | R35: =IF(SUM(B762:L762)=0,"Más de 10",SUM(B762:L762)) -> 7.1420269 | S35: =IF(SUM(B805:L805)=0,"Más de 10",SUM(B805:L805)) -> 7.2463687 | T35: =IF(SUM(B848:L848)=0,"Más de 10",SUM(B848:L848)) -> 8.2288547 | U35: =IF(SUM(B891:L891)=0,"Más de 10",SUM(B891:L891)) -> 8.6735057 | V35: =IF(SUM(B934:L934)=0,"Más de 10",SUM(B934:L934)) -> Más de 10 | W35: =IF(SUM(B977:L977)=0,"Más de 10",SUM(B977:L977)) -> 9.332824 | X35: =IF(SUM(B1020:L1020)=0,"Más de 10",SUM(B1020:L1020)) -> 8.9066379 | Y35: =IF(SUM(B1063:L1063)=0,"Más de 10",SUM(B1063:L1063)) -> 5.8022963
A36: ROI a 10 años | B36: =SUM(B67:L67)/SUM(B50:L50) -> 0.98500824 | C36: =SUM(B110:L110)/SUM(B93:L93) -> 0.11292459 | D36: =SUM(B153:L153)/SUM(B136:L136) -> 0.080052427 | E36: =SUM(B196:L196)/SUM(B179:L179) -> 0.96169896 | F36: =SUM(B239:L239)/SUM(B222:L222) -> 0.63259645 | G36: =SUM(B282:L282)/SUM(B265:L265) -> 0.584285 | H36: =SUM(B325:L325)/SUM(B308:L308) -> 1.3857315 | I36: =SUM(B368:L368)/SUM(B351:L351) -> 0.7016812 | J36: =SUM(B411:L411)/SUM(B394:L394) -> 1.4099988 | K36: =SUM(B454:L454)/SUM(B437:L437) -> 0.85613046 | L36: =SUM(B497:L497)/SUM(B480:L480) -> 1.113886 | M36: =SUM(B540:L540)/SUM(B523:L523) -> 0.9953056 | N36: =SUM(B583:L583)/SUM(B566:L566) -> 0.95072964 | O36: =SUM(B626:L626)/SUM(B609:L609) -> 0.97864244 | P36: =SUM(B669:L669)/SUM(B652:L652) -> 0.99137404 | Q36: =SUM(B712:L712)/SUM(B695:L695) -> 1.0675878 | R36: =SUM(B755:L755)/SUM(B738:L738) -> 0.98500824 | S36: =SUM(B798:L798)/SUM(B781:L781) -> 0.98500824 | T36: =SUM(B841:L841)/SUM(B824:L824) -> 0.85334901 | U36: =SUM(B884:L884)/SUM(B867:L867) -> 0.85334901 | V36: =SUM(B927:L927)/SUM(B910:L910) -> 0.25357289 | W36: =SUM(B970:L970)/SUM(B953:L953) -> 0.84619713 | X36: =SUM(B1013:L1013)/SUM(B996:L996) -> 0.84619713 | Y36: =SUM(B1056:L1056)/SUM(B1039:L1039) -> 1.0367483
A37: TIR del inversionista en pesos corrientes (frente al 25 %) | B37: =IRR(B83:L83) -> 0.41220926 | C37: =IRR(B126:L126) -> 0.016139976 | D37: =IRR(B169:L169) -> 0.0064963028 | E37: =IRR(B212:L212) -> 0.37516016 | F37: =IRR(B255:L255) -> 0.26745542 | G37: =IRR(B298:L298) -> 0.23939592 | H37: =IRR(B341:L341) -> 0.57813119 | I37: =IRR(B384:L384) -> 0.29210452 | J37: =IRR(B427:L427) -> 0.58413731 | K37: =IRR(B470:L470) -> 0.35767526 | L37: =IRR(B513:L513) -> 0.46572676 | M37: =IRR(B556:L556) -> 0.4072185 | N37: =IRR(B599:L599) -> 0.42760989 | O37: =IRR(B642:L642) -> 0.40982105 | P37: =IRR(B685:L685) -> 0.41459142 | Q37: =IRR(B728:L728) -> 0.42432534 | R37: =IRR(B771:L771) -> 0.39182372 | S37: =IRR(B814:L814) -> 0.37457397 | T37: =IRR(B857:L857) -> 0.28038084 | U37: =IRR(B900:L900) -> 0.25681294 | V37: =IRR(B943:L943) -> 0.092323305 | W37: =IRR(B986:L986) -> 0.24052487 | X37: =IRR(B1029:L1029) -> 0.24052487 | Y37: =IRR(B1072:L1072) -> 0.58607666
A38: TIR del inversionista en pesos constantes | B38: =IRR(B82:L82) -> 0.35343032 | C38: =IRR(B125:L125) -> -0.024019507 | D38: =IRR(B168:L168) -> -0.033548452 | E38: =IRR(B211:L211) -> 0.31813769 | F38: =IRR(B254:L254) -> 0.21561312 | G38: =IRR(B297:L297) -> 0.18889791 | H38: =IRR(B340:L340) -> 0.51139463 | I38: =IRR(B383:L383) -> 0.23907902 | J38: =IRR(B426:L426) -> 0.51714341 | K38: =IRR(B469:L469) -> 0.30153207 | L38: =IRR(B512:L512) -> 0.40436105 | M38: =IRR(B555:L555) -> 0.35669793 | N38: =IRR(B598:L598) -> 0.34047877 | O38: =IRR(B641:L641) -> 0.3511556 | P38: =IRR(B684:L684) -> 0.3556993 | Q38: =IRR(B727:L727) -> 0.36503364 | R38: =IRR(B770:L770) -> 0.33409475 | S38: =IRR(B813:L813) -> 0.3177285 | T38: =IRR(B856:L856) -> 0.22837889 | U38: =IRR(B899:L899) -> 0.20595132 | V38: =IRR(B942:L942) -> 0.048708834 | W38: =IRR(B985:L985) -> 0.19033771 | X38: =IRR(B1028:L1028) -> 0.19033771 | Y38: =IRR(B1071:L1071) -> 0.51496835
A39: Cobertura mínima del servicio de la deuda | B39: =MIN(D86:L86) -> 1.2094267 | C39: =MIN(D129:L129) -> 0.79546539 | D39: =MIN(D172:L172) -> 0.5906165 | E39: =MIN(D215:L215) -> 1.2094267 | F39: =MIN(D258:L258) -> 1.0036778 | G39: =MIN(D301:L301) -> 0.98254661 | H39: =MIN(D344:L344) -> 1.4363068 | I39: =MIN(D387:L387) -> 1.0482634 | J39: =MIN(D430:L430) -> 1.4511717 | K39: =MIN(D473:L473) -> 1.1360422 | L39: =MIN(D516:L516) -> 1.2828112 | M39: =MIN(D559:L559) -> 1.211207 | N39: =MIN(D602:L602) -> 1.1945178 | O39: =MIN(D645:L645) -> 1.2056531 | P39: =MIN(D688:L688) -> 1.2132003 | Q39: =MIN(D731:L731) -> 1.2332549 | R39: =MIN(D774:L774) -> 1.1687911 | S39: =MIN(D817:L817) -> 1.1606656 | T39: =MIN(D860:L860) -> 1.2094267 | U39: =MIN(D903:L903) -> 1.1606656 | V39: =MIN(D946:L946) -> 0.78943947 | W39: =MIN(D989:L989) -> 1.1634435 | X39: =MIN(D1032:L1032) -> 1.1634435 | Y39: =MIN(D1075:L1075) -> 1.0715971
A41: Flujos de cada escenario (años 0 a 10)
A42: $ M | B42: Año 0 | C42: Año 1 | D42: Año 2 | E42: Año 3 | F42: Año 4 | G42: Año 5 | H42: Año 6 | I42: Año 7 | J42: Año 8 | K42: Año 9 | L42: Año 10
A43: Año (número) | B43: 0 | C43: 1 | D43: 2 | E43: 3 | F43: 4 | G43: 5 | H43: 6 | I43: 7 | J43: 8 | K43: 9 | L43: 10
A45: Oferta
A46: Inflación del año | B46: =CHOOSE($B$15,Entorno!B$7,Entorno!B$8,Entorno!B$9) -> 0.06 | C46: =CHOOSE($B$15,Entorno!C$7,Entorno!C$8,Entorno!C$9) -> 0.05 | D46: =CHOOSE($B$15,Entorno!D$7,Entorno!D$8,Entorno!D$9) -> 0.045 | E46: =CHOOSE($B$15,Entorno!E$7,Entorno!E$8,Entorno!E$9) -> 0.04 | F46: =CHOOSE($B$15,Entorno!F$7,Entorno!F$8,Entorno!F$9) -> 0.04 | G46: =CHOOSE($B$15,Entorno!G$7,Entorno!G$8,Entorno!G$9) -> 0.04 | H46: =CHOOSE($B$15,Entorno!H$7,Entorno!H$8,Entorno!H$9) -> 0.04 | I46: =CHOOSE($B$15,Entorno!I$7,Entorno!I$8,Entorno!I$9) -> 0.04 | ... L46: =CHOOSE($B$15,Entorno!L$7,Entorno!L$8,Entorno!L$9) -> 0.04
A47: Índice de precios (2026 = 1) | B47: =1+B46 -> 1.06 | C47: =B47*(1+C46) -> 1.113 | D47: =C47*(1+D46) -> 1.163085 | E47: =D47*(1+E46) -> 1.2096084 | F47: =E47*(1+F46) -> 1.2579927 | G47: =F47*(1+G46) -> 1.3083124 | H47: =G47*(1+H46) -> 1.3606449 | I47: =H47*(1+I46) -> 1.4150707 | J47: =I47*(1+J46) -> 1.4716736 | ... L47: =K47*(1+L46) -> 1.5917621
A48: Salario mínimo real (2026 = 1) | B48: =(1+$B$16)/(1+B46) -> 1.0235849 | C48: =B48*(1+Entorno!$B$13) -> 1.0287028 | D48: =C48*(1+Entorno!$B$13) -> 1.0338463 | E48: =D48*(1+Entorno!$B$13) -> 1.0390156 | F48: =E48*(1+Entorno!$B$13) -> 1.0442107 | G48: =F48*(1+Entorno!$B$13) -> 1.0494317 | H48: =G48*(1+Entorno!$B$13) -> 1.0546789 | I48: =H48*(1+Entorno!$B$13) -> 1.0599523 | J48: =I48*(1+Entorno!$B$13) -> 1.065252 | ... L48: =K48*(1+Entorno!$B$13) -> 1.0759312
A49: Factor de pesos constantes | B49: =1/B47 -> 0.94339623 | C49: =1/C47 -> 0.8984726 | D49: =1/D47 -> 0.85978239 | E49: =1/E47 -> 0.82671384 | F49: =1/F47 -> 0.79491715 | G49: =1/G47 -> 0.76434341 | H49: =1/H47 -> 0.73494559 | I49: =1/I47 -> 0.70667845 | ... L49: =1/L47 -> 0.62823457
A50: Inversión | B50: =IF(B$43=0,Quesería!$F$80,IF(B$43=1,Quesería!$F$81*$B$21,0))*$B$11 -> 622.24362 | C50: =IF(C$43=0,Quesería!$F$80,IF(C$43=1,Quesería!$F$81*$B$21,0))*$B$11 -> 645.27009 | D50: =IF(D$43=0,Quesería!$F$80,IF(D$43=1,Quesería!$F$81*$B$21,0))*$B$11 -> 0 | E50: =IF(E$43=0,Quesería!$F$80,IF(E$43=1,Quesería!$F$81*$B$21,0))*$B$11 -> 0 | F50: =IF(F$43=0,Quesería!$F$80,IF(F$43=1,Quesería!$F$81*$B$21,0))*$B$11 -> 0 | G50: =IF(G$43=0,Quesería!$F$80,IF(G$43=1,Quesería!$F$81*$B$21,0))*$B$11 -> 0 | H50: =IF(H$43=0,Quesería!$F$80,IF(H$43=1,Quesería!$F$81*$B$21,0))*$B$11 -> 0 | I50: =IF(I$43=0,Quesería!$F$80,IF(I$43=1,Quesería!$F$81*$B$21,0))*$B$11 -> 0 | ... L50: =IF(L$43=0,Quesería!$F$80,IF(L$43=1,Quesería!$F$81*$B$21,0))*$B$11 -> 0
A51: Reposición de equipos | B51: =IF(B$43=5,Quesería!$F$87,IF(B$43=6,Quesería!$F$88,0))*$B$11 -> 0 | C51: =IF(C$43=5,Quesería!$F$87,IF(C$43=6,Quesería!$F$88,0))*$B$11 -> 0 | D51: =IF(D$43=5,Quesería!$F$87,IF(D$43=6,Quesería!$F$88,0))*$B$11 -> 0 | E51: =IF(E$43=5,Quesería!$F$87,IF(E$43=6,Quesería!$F$88,0))*$B$11 -> 0 | F51: =IF(F$43=5,Quesería!$F$87,IF(F$43=6,Quesería!$F$88,0))*$B$11 -> 0 | G51: =IF(G$43=5,Quesería!$F$87,IF(G$43=6,Quesería!$F$88,0))*$B$11 -> 26.666667 | H51: =IF(H$43=5,Quesería!$F$87,IF(H$43=6,Quesería!$F$88,0))*$B$11 -> 35.304553 | I51: =IF(I$43=5,Quesería!$F$87,IF(I$43=6,Quesería!$F$88,0))*$B$11 -> 0 | ... L51: =IF(L$43=5,Quesería!$F$87,IF(L$43=6,Quesería!$F$88,0))*$B$11 -> 0
A52: IVA de equipos y contratos | B52: =Quesería!$B$36*(IF(B$43=0,SUMPRODUCT((Quesería!$C$62:$C$77=0)*(Quesería!$H$62:$H$77>0)*(Quesería!$J$62:$J$77>0)*Quesería!$F$62:$F$77*(1+Quesería!$I$62:$I$77)),IF(B$43=1,SUMPRODUCT((Quesería!$C$62:$C$77=1)*(Quesería!$H$62:$H$77>0)*(Quesería!$J$62:$J$77>0)*Quesería!$F$62:$F$77*(1+Quesería!$I$62:$I$77))*$B$21,0))*$B$11+B51) -> 99.347875 | C52: =Quesería!$B$36*(IF(C$43=0,SUMPRODUCT((Quesería!$C$62:$C$77=0)*(Quesería!$H$62:$H$77>0)*(Quesería!$J$62:$J$77>0)*Quesería!$F$62:$F$77*(1+Quesería!$I$62:$I$77)),IF(C$43=1,SUMPRODUCT((Quesería!$C$62:$C$77=1)*(Quesería!$H$62:$H$77>0)*(Quesería!$J$62:$J$77>0)*Quesería!$F$62:$F$77*(1+Quesería!$I$62:$I$77))*$B$21,0))*$B$11+C51) -> 122.60132 | D52: =Quesería!$B$36*(IF(D$43=0,SUMPRODUCT((Quesería!$C$62:$C$77=0)*(Quesería!$H$62:$H$77>0)*(Quesería!$J$62:$J$77>0)*Quesería!$F$62:$F$77*(1+Quesería!$I$62:$I$77)),IF(D$43=1,SUMPRODUCT((Quesería!$C$62:$C$77=1)*(Quesería!$H$62:$H$77>0)*(Quesería!$J$62:$J$77>0)*Quesería!$F$62:$F$77*(1+Quesería!$I$62:$I$77))*$B$21,0))*$B$11+D51) -> 0 | E52: =Quesería!$B$36*(IF(E$43=0,SUMPRODUCT((Quesería!$C$62:$C$77=0)*(Quesería!$H$62:$H$77>0)*(Quesería!$J$62:$J$77>0)*Quesería!$F$62:$F$77*(1+Quesería!$I$62:$I$77)),IF(E$43=1,SUMPRODUCT((Quesería!$C$62:$C$77=1)*(Quesería!$H$62:$H$77>0)*(Quesería!$J$62:$J$77>0)*Quesería!$F$62:$F$77*(1+Quesería!$I$62:$I$77))*$B$21,0))*$B$11+E51) -> 0 | F52: =Quesería!$B$36*(IF(F$43=0,SUMPRODUCT((Quesería!$C$62:$C$77=0)*(Quesería!$H$62:$H$77>0)*(Quesería!$J$62:$J$77>0)*Quesería!$F$62:$F$77*(1+Quesería!$I$62:$I$77)),IF(F$43=1,SUMPRODUCT((Quesería!$C$62:$C$77=1)*(Quesería!$H$62:$H$77>0)*(Quesería!$J$62:$J$77>0)*Quesería!$F$62:$F$77*(1+Quesería!$I$62:$I$77))*$B$21,0))*$B$11+F51) -> 0 | G52: =Quesería!$B$36*(IF(G$43=0,SUMPRODUCT((Quesería!$C$62:$C$77=0)*(Quesería!$H$62:$H$77>0)*(Quesería!$J$62:$J$77>0)*Quesería!$F$62:$F$77*(1+Quesería!$I$62:$I$77)),IF(G$43=1,SUMPRODUCT((Quesería!$C$62:$C$77=1)*(Quesería!$H$62:$H$77>0)*(Quesería!$J$62:$J$77>0)*Quesería!$F$62:$F$77*(1+Quesería!$I$62:$I$77))*$B$21,0))*$B$11+G51) -> 5.0666667 | H52: =Quesería!$B$36*(IF(H$43=0,SUMPRODUCT((Quesería!$C$62:$C$77=0)*(Quesería!$H$62:$H$77>0)*(Quesería!$J$62:$J$77>0)*Quesería!$F$62:$F$77*(1+Quesería!$I$62:$I$77)),IF(H$43=1,SUMPRODUCT((Quesería!$C$62:$C$77=1)*(Quesería!$H$62:$H$77>0)*(Quesería!$J$62:$J$77>0)*Quesería!$F$62:$F$77*(1+Quesería!$I$62:$I$77))*$B$21,0))*$B$11+H51) -> 6.7078651 | I52: =Quesería!$B$36*(IF(I$43=0,SUMPRODUCT((Quesería!$C$62:$C$77=0)*(Quesería!$H$62:$H$77>0)*(Quesería!$J$62:$J$77>0)*Quesería!$F$62:$F$77*(1+Quesería!$I$62:$I$77)),IF(I$43=1,SUMPRODUCT((Quesería!$C$62:$C$77=1)*(Quesería!$H$62:$H$77>0)*(Quesería!$J$62:$J$77>0)*Quesería!$F$62:$F$77*(1+Quesería!$I$62:$I$77))*$B$21,0))*$B$11+I51) -> 0 | ... L52: =Quesería!$B$36*(IF(L$43=0,SUMPRODUCT((Quesería!$C$62:$C$77=0)*(Quesería!$H$62:$H$77>0)*(Quesería!$J$62:$J$77>0)*Quesería!$F$62:$F$77*(1+Quesería!$I$62:$I$77)),IF(L$43=1,SUMPRODUCT((Quesería!$C$62:$C$77=1)*(Quesería!$H$62:$H$77>0)*(Quesería!$J$62:$J$77>0)*Quesería!$F$62:$F$77*(1+Quesería!$I$62:$I$77))*$B$21,0))*$B$11+L51) -> 0
A53: Beneficio de las etapas 0 y 1 | B53: =IF(B$43=0,($B$22*Quesería!$J$109+(1-$B$22)*Quesería!$E$105)*Quesería!$B$12*Quesería!$B$13/12*$B$23,(($B$22*Quesería!$J$109+(1-$B$22)*Quesería!$E$105)+($B$22*Quesería!$J$92+(1-$B$22)*Quesería!$E$92)*(B48-1))*IF(B$43=1,Quesería!$B$12,1))*$B$10 -> 45.637373 | C53: =IF(C$43=0,($B$22*Quesería!$J$109+(1-$B$22)*Quesería!$E$105)*Quesería!$B$12*Quesería!$B$13/12*$B$23,(($B$22*Quesería!$J$109+(1-$B$22)*Quesería!$E$105)+($B$22*Quesería!$J$92+(1-$B$22)*Quesería!$E$92)*(C48-1))*IF(C$43=1,Quesería!$B$12,1))*$B$10 -> 137.16528 | D53: =IF(D$43=0,($B$22*Quesería!$J$109+(1-$B$22)*Quesería!$E$105)*Quesería!$B$12*Quesería!$B$13/12*$B$23,(($B$22*Quesería!$J$109+(1-$B$22)*Quesería!$E$105)+($B$22*Quesería!$J$92+(1-$B$22)*Quesería!$E$92)*(D48-1))*IF(D$43=1,Quesería!$B$12,1))*$B$10 -> 182.94753 | E53: =IF(E$43=0,($B$22*Quesería!$J$109+(1-$B$22)*Quesería!$E$105)*Quesería!$B$12*Quesería!$B$13/12*$B$23,(($B$22*Quesería!$J$109+(1-$B$22)*Quesería!$E$105)+($B$22*Quesería!$J$92+(1-$B$22)*Quesería!$E$92)*(E48-1))*IF(E$43=1,Quesería!$B$12,1))*$B$10 -> 183.00832 | F53: =IF(F$43=0,($B$22*Quesería!$J$109+(1-$B$22)*Quesería!$E$105)*Quesería!$B$12*Quesería!$B$13/12*$B$23,(($B$22*Quesería!$J$109+(1-$B$22)*Quesería!$E$105)+($B$22*Quesería!$J$92+(1-$B$22)*Quesería!$E$92)*(F48-1))*IF(F$43=1,Quesería!$B$12,1))*$B$10 -> 183.06941 | G53: =IF(G$43=0,($B$22*Quesería!$J$109+(1-$B$22)*Quesería!$E$105)*Quesería!$B$12*Quesería!$B$13/12*$B$23,(($B$22*Quesería!$J$109+(1-$B$22)*Quesería!$E$105)+($B$22*Quesería!$J$92+(1-$B$22)*Quesería!$E$92)*(G48-1))*IF(G$43=1,Quesería!$B$12,1))*$B$10 -> 183.13081 | H53: =IF(H$43=0,($B$22*Quesería!$J$109+(1-$B$22)*Quesería!$E$105)*Quesería!$B$12*Quesería!$B$13/12*$B$23,(($B$22*Quesería!$J$109+(1-$B$22)*Quesería!$E$105)+($B$22*Quesería!$J$92+(1-$B$22)*Quesería!$E$92)*(H48-1))*IF(H$43=1,Quesería!$B$12,1))*$B$10 -> 183.19252 | I53: =IF(I$43=0,($B$22*Quesería!$J$109+(1-$B$22)*Quesería!$E$105)*Quesería!$B$12*Quesería!$B$13/12*$B$23,(($B$22*Quesería!$J$109+(1-$B$22)*Quesería!$E$105)+($B$22*Quesería!$J$92+(1-$B$22)*Quesería!$E$92)*(I48-1))*IF(I$43=1,Quesería!$B$12,1))*$B$10 -> 183.25453 | ... L53: =IF(L$43=0,($B$22*Quesería!$J$109+(1-$B$22)*Quesería!$E$105)*Quesería!$B$12*Quesería!$B$13/12*$B$23,(($B$22*Quesería!$J$109+(1-$B$22)*Quesería!$E$105)+($B$22*Quesería!$J$92+(1-$B$22)*Quesería!$E$92)*(L48-1))*IF(L$43=1,Quesería!$B$12,1))*$B$10 -> 183.44244
A54: Beneficio de la etapa 2 | B54: =IF(B$43<=1,0,((($B$22*Quesería!$J$110+(1-$B$22)*Quesería!$E$106)-($B$22*Quesería!$J$99+(1-$B$22)*Quesería!$E$99)+$B$6*($B$22*Quesería!$J$99+(1-$B$22)*Quesería!$E$99)-(1-$B$9)*($B$22*Quesería!$J$102+(1-$B$22)*Quesería!$E$102))+($B$6*($B$22*Quesería!$J$99+(1-$B$22)*Quesería!$E$99)+$B$9*($B$22*Quesería!$J$102+(1-$B$22)*Quesería!$E$102))*(B48-1))*IF(B$43=2,Quesería!$B$12,1)+IF(B$43=2,Quesería!$B$14*$B$9*($B$22*Quesería!$J$102+(1-$B$22)*Quesería!$E$102)*B48,0))*$B$10*$B$21 -> 0 | C54: =IF(C$43<=1,0,((($B$22*Quesería!$J$110+(1-$B$22)*Quesería!$E$106)-($B$22*Quesería!$J$99+(1-$B$22)*Quesería!$E$99)+$B$6*($B$22*Quesería!$J$99+(1-$B$22)*Quesería!$E$99)-(1-$B$9)*($B$22*Quesería!$J$102+(1-$B$22)*Quesería!$E$102))+($B$6*($B$22*Quesería!$J$99+(1-$B$22)*Quesería!$E$99)+$B$9*($B$22*Quesería!$J$102+(1-$B$22)*Quesería!$E$102))*(C48-1))*IF(C$43=2,Quesería!$B$12,1)+IF(C$43=2,Quesería!$B$14*$B$9*($B$22*Quesería!$J$102+(1-$B$22)*Quesería!$E$102)*C48,0))*$B$10*$B$21 -> 0 | D54: =IF(D$43<=1,0,((($B$22*Quesería!$J$110+(1-$B$22)*Quesería!$E$106)-($B$22*Quesería!$J$99+(1-$B$22)*Quesería!$E$99)+$B$6*($B$22*Quesería!$J$99+(1-$B$22)*Quesería!$E$99)-(1-$B$9)*($B$22*Quesería!$J$102+(1-$B$22)*Quesería!$E$102))+($B$6*($B$22*Quesería!$J$99+(1-$B$22)*Quesería!$E$99)+$B$9*($B$22*Quesería!$J$102+(1-$B$22)*Quesería!$E$102))*(D48-1))*IF(D$43=2,Quesería!$B$12,1)+IF(D$43=2,Quesería!$B$14*$B$9*($B$22*Quesería!$J$102+(1-$B$22)*Quesería!$E$102)*D48,0))*$B$10*$B$21 -> 197.8378 | E54: =IF(E$43<=1,0,((($B$22*Quesería!$J$110+(1-$B$22)*Quesería!$E$106)-($B$22*Quesería!$J$99+(1-$B$22)*Quesería!$E$99)+$B$6*($B$22*Quesería!$J$99+(1-$B$22)*Quesería!$E$99)-(1-$B$9)*($B$22*Quesería!$J$102+(1-$B$22)*Quesería!$E$102))+($B$6*($B$22*Quesería!$J$99+(1-$B$22)*Quesería!$E$99)+$B$9*($B$22*Quesería!$J$102+(1-$B$22)*Quesería!$E$102))*(E48-1))*IF(E$43=2,Quesería!$B$12,1)+IF(E$43=2,Quesería!$B$14*$B$9*($B$22*Quesería!$J$102+(1-$B$22)*Quesería!$E$102)*E48,0))*$B$10*$B$21 -> 234.44194 | F54: =IF(F$43<=1,0,((($B$22*Quesería!$J$110+(1-$B$22)*Quesería!$E$106)-($B$22*Quesería!$J$99+(1-$B$22)*Quesería!$E$99)+$B$6*($B$22*Quesería!$J$99+(1-$B$22)*Quesería!$E$99)-(1-$B$9)*($B$22*Quesería!$J$102+(1-$B$22)*Quesería!$E$102))+($B$6*($B$22*Quesería!$J$99+(1-$B$22)*Quesería!$E$99)+$B$9*($B$22*Quesería!$J$102+(1-$B$22)*Quesería!$E$102))*(F48-1))*IF(F$43=2,Quesería!$B$12,1)+IF(F$43=2,Quesería!$B$14*$B$9*($B$22*Quesería!$J$102+(1-$B$22)*Quesería!$E$102)*F48,0))*$B$10*$B$21 -> 234.87708 | G54: =IF(G$43<=1,0,((($B$22*Quesería!$J$110+(1-$B$22)*Quesería!$E$106)-($B$22*Quesería!$J$99+(1-$B$22)*Quesería!$E$99)+$B$6*($B$22*Quesería!$J$99+(1-$B$22)*Quesería!$E$99)-(1-$B$9)*($B$22*Quesería!$J$102+(1-$B$22)*Quesería!$E$102))+($B$6*($B$22*Quesería!$J$99+(1-$B$22)*Quesería!$E$99)+$B$9*($B$22*Quesería!$J$102+(1-$B$22)*Quesería!$E$102))*(G48-1))*IF(G$43=2,Quesería!$B$12,1)+IF(G$43=2,Quesería!$B$14*$B$9*($B$22*Quesería!$J$102+(1-$B$22)*Quesería!$E$102)*G48,0))*$B$10*$B$21 -> 235.31439 | H54: =IF(H$43<=1,0,((($B$22*Quesería!$J$110+(1-$B$22)*Quesería!$E$106)-($B$22*Quesería!$J$99+(1-$B$22)*Quesería!$E$99)+$B$6*($B$22*Quesería!$J$99+(1-$B$22)*Quesería!$E$99)-(1-$B$9)*($B$22*Quesería!$J$102+(1-$B$22)*Quesería!$E$102))+($B$6*($B$22*Quesería!$J$99+(1-$B$22)*Quesería!$E$99)+$B$9*($B$22*Quesería!$J$102+(1-$B$22)*Quesería!$E$102))*(H48-1))*IF(H$43=2,Quesería!$B$12,1)+IF(H$43=2,Quesería!$B$14*$B$9*($B$22*Quesería!$J$102+(1-$B$22)*Quesería!$E$102)*H48,0))*$B$10*$B$21 -> 235.7539 | I54: =IF(I$43<=1,0,((($B$22*Quesería!$J$110+(1-$B$22)*Quesería!$E$106)-($B$22*Quesería!$J$99+(1-$B$22)*Quesería!$E$99)+$B$6*($B$22*Quesería!$J$99+(1-$B$22)*Quesería!$E$99)-(1-$B$9)*($B$22*Quesería!$J$102+(1-$B$22)*Quesería!$E$102))+($B$6*($B$22*Quesería!$J$99+(1-$B$22)*Quesería!$E$99)+$B$9*($B$22*Quesería!$J$102+(1-$B$22)*Quesería!$E$102))*(I48-1))*IF(I$43=2,Quesería!$B$12,1)+IF(I$43=2,Quesería!$B$14*$B$9*($B$22*Quesería!$J$102+(1-$B$22)*Quesería!$E$102)*I48,0))*$B$10*$B$21 -> 236.1956 | ... L54: =IF(L$43<=1,0,((($B$22*Quesería!$J$110+(1-$B$22)*Quesería!$E$106)-($B$22*Quesería!$J$99+(1-$B$22)*Quesería!$E$99)+$B$6*($B$22*Quesería!$J$99+(1-$B$22)*Quesería!$E$99)-(1-$B$9)*($B$22*Quesería!$J$102+(1-$B$22)*Quesería!$E$102))+($B$6*($B$22*Quesería!$J$99+(1-$B$22)*Quesería!$E$99)+$B$9*($B$22*Quesería!$J$102+(1-$B$22)*Quesería!$E$102))*(L48-1))*IF(L$43=2,Quesería!$B$12,1)+IF(L$43=2,Quesería!$B$14*$B$9*($B$22*Quesería!$J$102+(1-$B$22)*Quesería!$E$102)*L48,0))*$B$10*$B$21 -> 237.53399
A55: Beneficio total | B55: =B53+B54 -> 45.637373 | C55: =C53+C54 -> 137.16528 | D55: =D53+D54 -> 380.78533 | E55: =E53+E54 -> 417.45026 | F55: =F53+F54 -> 417.94649 | G55: =G53+G54 -> 418.4452 | H55: =H53+H54 -> 418.94641 | I55: =I53+I54 -> 419.45013 | ... L55: =L53+L54 -> 420.97643
A56: Costos operativos nuevos | B56: =(IF(B$43>=1,(Quesería!$B$21+Quesería!$B$54)*Quesería!$F$82*$B$11+Quesería!$B$22+'Beneficios y costos'!$B$118,0)+IF(B$43>=2,((Quesería!$B$21+Quesería!$B$54)*Quesería!$F$83*$B$11+'Beneficios y costos'!$C$118)*$B$21,0))*$B$12 -> 0 | C56: =(IF(C$43>=1,(Quesería!$B$21+Quesería!$B$54)*Quesería!$F$82*$B$11+Quesería!$B$22+'Beneficios y costos'!$B$118,0)+IF(C$43>=2,((Quesería!$B$21+Quesería!$B$54)*Quesería!$F$83*$B$11+'Beneficios y costos'!$C$118)*$B$21,0))*$B$12 -> 36.892153 | D56: =(IF(D$43>=1,(Quesería!$B$21+Quesería!$B$54)*Quesería!$F$82*$B$11+Quesería!$B$22+'Beneficios y costos'!$B$118,0)+IF(D$43>=2,((Quesería!$B$21+Quesería!$B$54)*Quesería!$F$83*$B$11+'Beneficios y costos'!$C$118)*$B$21,0))*$B$12 -> 88.806504 | E56: =(IF(E$43>=1,(Quesería!$B$21+Quesería!$B$54)*Quesería!$F$82*$B$11+Quesería!$B$22+'Beneficios y costos'!$B$118,0)+IF(E$43>=2,((Quesería!$B$21+Quesería!$B$54)*Quesería!$F$83*$B$11+'Beneficios y costos'!$C$118)*$B$21,0))*$B$12 -> 88.806504 | F56: =(IF(F$43>=1,(Quesería!$B$21+Quesería!$B$54)*Quesería!$F$82*$B$11+Quesería!$B$22+'Beneficios y costos'!$B$118,0)+IF(F$43>=2,((Quesería!$B$21+Quesería!$B$54)*Quesería!$F$83*$B$11+'Beneficios y costos'!$C$118)*$B$21,0))*$B$12 -> 88.806504 | G56: =(IF(G$43>=1,(Quesería!$B$21+Quesería!$B$54)*Quesería!$F$82*$B$11+Quesería!$B$22+'Beneficios y costos'!$B$118,0)+IF(G$43>=2,((Quesería!$B$21+Quesería!$B$54)*Quesería!$F$83*$B$11+'Beneficios y costos'!$C$118)*$B$21,0))*$B$12 -> 88.806504 | H56: =(IF(H$43>=1,(Quesería!$B$21+Quesería!$B$54)*Quesería!$F$82*$B$11+Quesería!$B$22+'Beneficios y costos'!$B$118,0)+IF(H$43>=2,((Quesería!$B$21+Quesería!$B$54)*Quesería!$F$83*$B$11+'Beneficios y costos'!$C$118)*$B$21,0))*$B$12 -> 88.806504 | I56: =(IF(I$43>=1,(Quesería!$B$21+Quesería!$B$54)*Quesería!$F$82*$B$11+Quesería!$B$22+'Beneficios y costos'!$B$118,0)+IF(I$43>=2,((Quesería!$B$21+Quesería!$B$54)*Quesería!$F$83*$B$11+'Beneficios y costos'!$C$118)*$B$21,0))*$B$12 -> 88.806504 | ... L56: =(IF(L$43>=1,(Quesería!$B$21+Quesería!$B$54)*Quesería!$F$82*$B$11+Quesería!$B$22+'Beneficios y costos'!$B$118,0)+IF(L$43>=2,((Quesería!$B$21+Quesería!$B$54)*Quesería!$F$83*$B$11+'Beneficios y costos'!$C$118)*$B$21,0))*$B$12 -> 88.806504
A57: Costo de la transición del personal | B57: =IF(B$43=1,2*Quesería!$B$33*Quesería!$B$34/12*B48,0)*$B$21 -> 0 | C57: =IF(C$43=1,2*Quesería!$B$33*Quesería!$B$34/12*C48,0)*$B$21 -> 18.516651 | D57: =IF(D$43=1,2*Quesería!$B$33*Quesería!$B$34/12*D48,0)*$B$21 -> 0 | E57: =IF(E$43=1,2*Quesería!$B$33*Quesería!$B$34/12*E48,0)*$B$21 -> 0 | F57: =IF(F$43=1,2*Quesería!$B$33*Quesería!$B$34/12*F48,0)*$B$21 -> 0 | G57: =IF(G$43=1,2*Quesería!$B$33*Quesería!$B$34/12*G48,0)*$B$21 -> 0 | H57: =IF(H$43=1,2*Quesería!$B$33*Quesería!$B$34/12*H48,0)*$B$21 -> 0 | I57: =IF(I$43=1,2*Quesería!$B$33*Quesería!$B$34/12*I48,0)*$B$21 -> 0 | ... L57: =IF(L$43=1,2*Quesería!$B$33*Quesería!$B$34/12*L48,0)*$B$21 -> 0
A58: GMF de los pagos del proyecto | B58: =Quesería!$B$45*(B50+B51+B52+B56+B57) -> 2.886366 | C58: =Quesería!$B$45*(C50+C51+C52+C56+C57) -> 3.2931208 | D58: =Quesería!$B$45*(D50+D51+D52+D56+D57) -> 0.35522602 | E58: =Quesería!$B$45*(E50+E51+E52+E56+E57) -> 0.35522602 | F58: =Quesería!$B$45*(F50+F51+F52+F56+F57) -> 0.35522602 | G58: =Quesería!$B$45*(G50+G51+G52+G56+G57) -> 0.48215935 | H58: =Quesería!$B$45*(H50+H51+H52+H56+H57) -> 0.52327569 | I58: =Quesería!$B$45*(I50+I51+I52+I56+I57) -> 0.35522602 | ... L58: =Quesería!$B$45*(L50+L51+L52+L56+L57) -> 0.35522602
A59: Depreciación fiscal en pesos constantes | B59: =(IF($B$19=1,(SUMPRODUCT((Quesería!$C$62:$C$77=0)*(Quesería!$J$62:$J$77>0)*(B$43>=1)*(B$43<=Quesería!$J$62:$J$77)*(Quesería!$H$62:$H$77>0)*Quesería!$F$62:$F$77*(1+Quesería!$I$62:$I$77)/(Quesería!$J$62:$J$77+(Quesería!$J$62:$J$77=0)))+SUMPRODUCT((Quesería!$C$62:$C$77=0)*(Quesería!$J$62:$J$77=0)*(B$43=0)*(Quesería!$H$62:$H$77>0)*Quesería!$F$62:$F$77*(1+Quesería!$I$62:$I$77)))*$B$47+(SUMPRODUCT((Quesería!$C$62:$C$77=1)*(Quesería!$J$62:$J$77>0)*(B$43>=2)*(B$43<=Quesería!$J$62:$J$77+1)*(Quesería!$H$62:$H$77>0)*Quesería!$F$62:$F$77*(1+Quesería!$I$62:$I$77)/(Quesería!$J$62:$J$77+(Quesería!$J$62:$J$77=0)))+SUMPRODUCT((Quesería!$C$62:$C$77=1)*(Quesería!$J$62:$J$77=0)*(B$43=1)*(Quesería!$H$62:$H$77>0)*Quesería!$F$62:$F$77*(1+Quesería!$I$62:$I$77)))*$C$47*$B$21,IF(AND(B$43>=1,B$43<=Quesería!$B$11),Quesería!$F$80/Quesería!$B$11,0)*$B$47+IF(AND(B$43>=2,B$43<=Quesería!$B$11+1),Quesería!$F$81/Quesería!$B$11,0)*$C$47*$B$21)*$B$11+IF(AND(B$43>=6,B$43<=10),$G51*$G47/5,0)+IF(AND(B$43>=7,B$43<=11),$H51*$H47/5,0))*B49 -> 99.360069 | C59: =(IF($B$19=1,(SUMPRODUCT((Quesería!$C$62:$C$77=0)*(Quesería!$J$62:$J$77>0)*(C$43>=1)*(C$43<=Quesería!$J$62:$J$77)*(Quesería!$H$62:$H$77>0)*Quesería!$F$62:$F$77*(1+Quesería!$I$62:$I$77)/(Quesería!$J$62:$J$77+(Quesería!$J$62:$J$77=0)))+SUMPRODUCT((Quesería!$C$62:$C$77=0)*(Quesería!$J$62:$J$77=0)*(C$43=0)*(Quesería!$H$62:$H$77>0)*Quesería!$F$62:$F$77*(1+Quesería!$I$62:$I$77)))*$B$47+(SUMPRODUCT((Quesería!$C$62:$C$77=1)*(Quesería!$J$62:$J$77>0)*(C$43>=2)*(C$43<=Quesería!$J$62:$J$77+1)*(Quesería!$H$62:$H$77>0)*Quesería!$F$62:$F$77*(1+Quesería!$I$62:$I$77)/(Quesería!$J$62:$J$77+(Quesería!$J$62:$J$77=0)))+SUMPRODUCT((Quesería!$C$62:$C$77=1)*(Quesería!$J$62:$J$77=0)*(C$43=1)*(Quesería!$H$62:$H$77>0)*Quesería!$F$62:$F$77*(1+Quesería!$I$62:$I$77)))*$C$47*$B$21,IF(AND(C$43>=1,C$43<=Quesería!$B$11),Quesería!$F$80/Quesería!$B$11,0)*$B$47+IF(AND(C$43>=2,C$43<=Quesería!$B$11+1),Quesería!$F$81/Quesería!$B$11,0)*$C$47*$B$21)*$B$11+IF(AND(C$43>=6,C$43<=10),$G51*$G47/5,0)+IF(AND(C$43>=7,C$43<=11),$H51*$H47/5,0))*C49 -> 57.100021 | D59: =(IF($B$19=1,(SUMPRODUCT((Quesería!$C$62:$C$77=0)*(Quesería!$J$62:$J$77>0)*(D$43>=1)*(D$43<=Quesería!$J$62:$J$77)*(Quesería!$H$62:$H$77>0)*Quesería!$F$62:$F$77*(1+Quesería!$I$62:$I$77)/(Quesería!$J$62:$J$77+(Quesería!$J$62:$J$77=0)))+SUMPRODUCT((Quesería!$C$62:$C$77=0)*(Quesería!$J$62:$J$77=0)*(D$43=0)*(Quesería!$H$62:$H$77>0)*Quesería!$F$62:$F$77*(1+Quesería!$I$62:$I$77)))*$B$47+(SUMPRODUCT((Quesería!$C$62:$C$77=1)*(Quesería!$J$62:$J$77>0)*(D$43>=2)*(D$43<=Quesería!$J$62:$J$77+1)*(Quesería!$H$62:$H$77>0)*Quesería!$F$62:$F$77*(1+Quesería!$I$62:$I$77)/(Quesería!$J$62:$J$77+(Quesería!$J$62:$J$77=0)))+SUMPRODUCT((Quesería!$C$62:$C$77=1)*(Quesería!$J$62:$J$77=0)*(D$43=1)*(Quesería!$H$62:$H$77>0)*Quesería!$F$62:$F$77*(1+Quesería!$I$62:$I$77)))*$C$47*$B$21,IF(AND(D$43>=1,D$43<=Quesería!$B$11),Quesería!$F$80/Quesería!$B$11,0)*$B$47+IF(AND(D$43>=2,D$43<=Quesería!$B$11+1),Quesería!$F$81/Quesería!$B$11,0)*$C$47*$B$21)*$B$11+IF(AND(D$43>=6,D$43<=10),$G51*$G47/5,0)+IF(AND(D$43>=7,D$43<=11),$H51*$H47/5,0))*D49 -> 116.3895 | E59: =(IF($B$19=1,(SUMPRODUCT((Quesería!$C$62:$C$77=0)*(Quesería!$J$62:$J$77>0)*(E$43>=1)*(E$43<=Quesería!$J$62:$J$77)*(Quesería!$H$62:$H$77>0)*Quesería!$F$62:$F$77*(1+Quesería!$I$62:$I$77)/(Quesería!$J$62:$J$77+(Quesería!$J$62:$J$77=0)))+SUMPRODUCT((Quesería!$C$62:$C$77=0)*(Quesería!$J$62:$J$77=0)*(E$43=0)*(Quesería!$H$62:$H$77>0)*Quesería!$F$62:$F$77*(1+Quesería!$I$62:$I$77)))*$B$47+(SUMPRODUCT((Quesería!$C$62:$C$77=1)*(Quesería!$J$62:$J$77>0)*(E$43>=2)*(E$43<=Quesería!$J$62:$J$77+1)*(Quesería!$H$62:$H$77>0)*Quesería!$F$62:$F$77*(1+Quesería!$I$62:$I$77)/(Quesería!$J$62:$J$77+(Quesería!$J$62:$J$77=0)))+SUMPRODUCT((Quesería!$C$62:$C$77=1)*(Quesería!$J$62:$J$77=0)*(E$43=1)*(Quesería!$H$62:$H$77>0)*Quesería!$F$62:$F$77*(1+Quesería!$I$62:$I$77)))*$C$47*$B$21,IF(AND(E$43>=1,E$43<=Quesería!$B$11),Quesería!$F$80/Quesería!$B$11,0)*$B$47+IF(AND(E$43>=2,E$43<=Quesería!$B$11+1),Quesería!$F$81/Quesería!$B$11,0)*$C$47*$B$21)*$B$11+IF(AND(E$43>=6,E$43<=10),$G51*$G47/5,0)+IF(AND(E$43>=7,E$43<=11),$H51*$H47/5,0))*E49 -> 111.91298 | F59: =(IF($B$19=1,(SUMPRODUCT((Quesería!$C$62:$C$77=0)*(Quesería!$J$62:$J$77>0)*(F$43>=1)*(F$43<=Quesería!$J$62:$J$77)*(Quesería!$H$62:$H$77>0)*Quesería!$F$62:$F$77*(1+Quesería!$I$62:$I$77)/(Quesería!$J$62:$J$77+(Quesería!$J$62:$J$77=0)))+SUMPRODUCT((Quesería!$C$62:$C$77=0)*(Quesería!$J$62:$J$77=0)*(F$43=0)*(Quesería!$H$62:$H$77>0)*Quesería!$F$62:$F$77*(1+Quesería!$I$62:$I$77)))*$B$47+(SUMPRODUCT((Quesería!$C$62:$C$77=1)*(Quesería!$J$62:$J$77>0)*(F$43>=2)*(F$43<=Quesería!$J$62:$J$77+1)*(Quesería!$H$62:$H$77>0)*Quesería!$F$62:$F$77*(1+Quesería!$I$62:$I$77)/(Quesería!$J$62:$J$77+(Quesería!$J$62:$J$77=0)))+SUMPRODUCT((Quesería!$C$62:$C$77=1)*(Quesería!$J$62:$J$77=0)*(F$43=1)*(Quesería!$H$62:$H$77>0)*Quesería!$F$62:$F$77*(1+Quesería!$I$62:$I$77)))*$C$47*$B$21,IF(AND(F$43>=1,F$43<=Quesería!$B$11),Quesería!$F$80/Quesería!$B$11,0)*$B$47+IF(AND(F$43>=2,F$43<=Quesería!$B$11+1),Quesería!$F$81/Quesería!$B$11,0)*$C$47*$B$21)*$B$11+IF(AND(F$43>=6,F$43<=10),$G51*$G47/5,0)+IF(AND(F$43>=7,F$43<=11),$H51*$H47/5,0))*F49 -> 107.60864 | G59: =(IF($B$19=1,(SUMPRODUCT((Quesería!$C$62:$C$77=0)*(Quesería!$J$62:$J$77>0)*(G$43>=1)*(G$43<=Quesería!$J$62:$J$77)*(Quesería!$H$62:$H$77>0)*Quesería!$F$62:$F$77*(1+Quesería!$I$62:$I$77)/(Quesería!$J$62:$J$77+(Quesería!$J$62:$J$77=0)))+SUMPRODUCT((Quesería!$C$62:$C$77=0)*(Quesería!$J$62:$J$77=0)*(G$43=0)*(Quesería!$H$62:$H$77>0)*Quesería!$F$62:$F$77*(1+Quesería!$I$62:$I$77)))*$B$47+(SUMPRODUCT((Quesería!$C$62:$C$77=1)*(Quesería!$J$62:$J$77>0)*(G$43>=2)*(G$43<=Quesería!$J$62:$J$77+1)*(Quesería!$H$62:$H$77>0)*Quesería!$F$62:$F$77*(1+Quesería!$I$62:$I$77)/(Quesería!$J$62:$J$77+(Quesería!$J$62:$J$77=0)))+SUMPRODUCT((Quesería!$C$62:$C$77=1)*(Quesería!$J$62:$J$77=0)*(G$43=1)*(Quesería!$H$62:$H$77>0)*Quesería!$F$62:$F$77*(1+Quesería!$I$62:$I$77)))*$C$47*$B$21,IF(AND(G$43>=1,G$43<=Quesería!$B$11),Quesería!$F$80/Quesería!$B$11,0)*$B$47+IF(AND(G$43>=2,G$43<=Quesería!$B$11+1),Quesería!$F$81/Quesería!$B$11,0)*$C$47*$B$21)*$B$11+IF(AND(G$43>=6,G$43<=10),$G51*$G47/5,0)+IF(AND(G$43>=7,G$43<=11),$H51*$H47/5,0))*G49 -> 103.46984 | H59: =(IF($B$19=1,(SUMPRODUCT((Quesería!$C$62:$C$77=0)*(Quesería!$J$62:$J$77>0)*(H$43>=1)*(H$43<=Quesería!$J$62:$J$77)*(Quesería!$H$62:$H$77>0)*Quesería!$F$62:$F$77*(1+Quesería!$I$62:$I$77)/(Quesería!$J$62:$J$77+(Quesería!$J$62:$J$77=0)))+SUMPRODUCT((Quesería!$C$62:$C$77=0)*(Quesería!$J$62:$J$77=0)*(H$43=0)*(Quesería!$H$62:$H$77>0)*Quesería!$F$62:$F$77*(1+Quesería!$I$62:$I$77)))*$B$47+(SUMPRODUCT((Quesería!$C$62:$C$77=1)*(Quesería!$J$62:$J$77>0)*(H$43>=2)*(H$43<=Quesería!$J$62:$J$77+1)*(Quesería!$H$62:$H$77>0)*Quesería!$F$62:$F$77*(1+Quesería!$I$62:$I$77)/(Quesería!$J$62:$J$77+(Quesería!$J$62:$J$77=0)))+SUMPRODUCT((Quesería!$C$62:$C$77=1)*(Quesería!$J$62:$J$77=0)*(H$43=1)*(Quesería!$H$62:$H$77>0)*Quesería!$F$62:$F$77*(1+Quesería!$I$62:$I$77)))*$C$47*$B$21,IF(AND(H$43>=1,H$43<=Quesería!$B$11),Quesería!$F$80/Quesería!$B$11,0)*$B$47+IF(AND(H$43>=2,H$43<=Quesería!$B$11+1),Quesería!$F$81/Quesería!$B$11,0)*$C$47*$B$21)*$B$11+IF(AND(H$43>=6,H$43<=10),$G51*$G47/5,0)+IF(AND(H$43>=7,H$43<=11),$H51*$H47/5,0))*H49 -> 92.673124 | I59: =(IF($B$19=1,(SUMPRODUCT((Quesería!$C$62:$C$77=0)*(Quesería!$J$62:$J$77>0)*(I$43>=1)*(I$43<=Quesería!$J$62:$J$77)*(Quesería!$H$62:$H$77>0)*Quesería!$F$62:$F$77*(1+Quesería!$I$62:$I$77)/(Quesería!$J$62:$J$77+(Quesería!$J$62:$J$77=0)))+SUMPRODUCT((Quesería!$C$62:$C$77=0)*(Quesería!$J$62:$J$77=0)*(I$43=0)*(Quesería!$H$62:$H$77>0)*Quesería!$F$62:$F$77*(1+Quesería!$I$62:$I$77)))*$B$47+(SUMPRODUCT((Quesería!$C$62:$C$77=1)*(Quesería!$J$62:$J$77>0)*(I$43>=2)*(I$43<=Quesería!$J$62:$J$77+1)*(Quesería!$H$62:$H$77>0)*Quesería!$F$62:$F$77*(1+Quesería!$I$62:$I$77)/(Quesería!$J$62:$J$77+(Quesería!$J$62:$J$77=0)))+SUMPRODUCT((Quesería!$C$62:$C$77=1)*(Quesería!$J$62:$J$77=0)*(I$43=1)*(Quesería!$H$62:$H$77>0)*Quesería!$F$62:$F$77*(1+Quesería!$I$62:$I$77)))*$C$47*$B$21,IF(AND(I$43>=1,I$43<=Quesería!$B$11),Quesería!$F$80/Quesería!$B$11,0)*$B$47+IF(AND(I$43>=2,I$43<=Quesería!$B$11+1),Quesería!$F$81/Quesería!$B$11,0)*$C$47*$B$21)*$B$11+IF(AND(I$43>=6,I$43<=10),$G51*$G47/5,0)+IF(AND(I$43>=7,I$43<=11),$H51*$H47/5,0))*I49 -> 95.89811 | ... L59: =(IF($B$19=1,(SUMPRODUCT((Quesería!$C$62:$C$77=0)*(Quesería!$J$62:$J$77>0)*(L$43>=1)*(L$43<=Quesería!$J$62:$J$77)*(Quesería!$H$62:$H$77>0)*Quesería!$F$62:$F$77*(1+Quesería!$I$62:$I$77)/(Quesería!$J$62:$J$77+(Quesería!$J$62:$J$77=0)))+SUMPRODUCT((Quesería!$C$62:$C$77=0)*(Quesería!$J$62:$J$77=0)*(L$43=0)*(Quesería!$H$62:$H$77>0)*Quesería!$F$62:$F$77*(1+Quesería!$I$62:$I$77)))*$B$47+(SUMPRODUCT((Quesería!$C$62:$C$77=1)*(Quesería!$J$62:$J$77>0)*(L$43>=2)*(L$43<=Quesería!$J$62:$J$77+1)*(Quesería!$H$62:$H$77>0)*Quesería!$F$62:$F$77*(1+Quesería!$I$62:$I$77)/(Quesería!$J$62:$J$77+(Quesería!$J$62:$J$77=0)))+SUMPRODUCT((Quesería!$C$62:$C$77=1)*(Quesería!$J$62:$J$77=0)*(L$43=1)*(Quesería!$H$62:$H$77>0)*Quesería!$F$62:$F$77*(1+Quesería!$I$62:$I$77)))*$C$47*$B$21,IF(AND(L$43>=1,L$43<=Quesería!$B$11),Quesería!$F$80/Quesería!$B$11,0)*$B$47+IF(AND(L$43>=2,L$43<=Quesería!$B$11+1),Quesería!$F$81/Quesería!$B$11,0)*$C$47*$B$21)*$B$11+IF(AND(L$43>=6,L$43<=10),$G51*$G47/5,0)+IF(AND(L$43>=7,L$43<=11),$H51*$H47/5,0))*L49 -> 85.253071
A60: Descuento tributario (art. 255) | B60: =IF(B$43=1,MIN($B$7*Quesería!$B$35*Quesería!$F$75*$B$11*$B$21,Quesería!$B$50*Quesería!$B$51),0) -> 0 | C60: =IF(C$43=1,MIN($B$7*Quesería!$B$35*Quesería!$F$75*$B$11*$B$21,Quesería!$B$50*Quesería!$B$51),0) -> 20 | D60: =IF(D$43=1,MIN($B$7*Quesería!$B$35*Quesería!$F$75*$B$11*$B$21,Quesería!$B$50*Quesería!$B$51),0) -> 0 | E60: =IF(E$43=1,MIN($B$7*Quesería!$B$35*Quesería!$F$75*$B$11*$B$21,Quesería!$B$50*Quesería!$B$51),0) -> 0 | F60: =IF(F$43=1,MIN($B$7*Quesería!$B$35*Quesería!$F$75*$B$11*$B$21,Quesería!$B$50*Quesería!$B$51),0) -> 0 | G60: =IF(G$43=1,MIN($B$7*Quesería!$B$35*Quesería!$F$75*$B$11*$B$21,Quesería!$B$50*Quesería!$B$51),0) -> 0 | H60: =IF(H$43=1,MIN($B$7*Quesería!$B$35*Quesería!$F$75*$B$11*$B$21,Quesería!$B$50*Quesería!$B$51),0) -> 0 | I60: =IF(I$43=1,MIN($B$7*Quesería!$B$35*Quesería!$F$75*$B$11*$B$21,Quesería!$B$50*Quesería!$B$51),0) -> 0 | ... L60: =IF(L$43=1,MIN($B$7*Quesería!$B$35*Quesería!$F$75*$B$11*$B$21,Quesería!$B$50*Quesería!$B$51),0) -> 0
A61: Crédito fiscal por innovación (art. 256-1) | B61: 0 | C61: =$B$20*Quesería!$B$52*Quesería!$F$86*$B$11*$B$47/C47 -> 166.87988 | D61: 0 | E61: 0 | F61: 0 | G61: 0 | H61: 0 | I61: 0 | J61: 0 | K61: 0 | L61: 0
A62: IVA recuperado como descuento de renta (art. 258-1) | B62: =0 -> 0 | C62: =B52*B47/C47 -> 94.617024 | D62: =C52*C47/D47 -> 117.32183 | E62: =D52*D47/E47 -> 0 | F62: =E52*E47/F47 -> 0 | G62: =F52*F47/G47 -> 0 | H62: =G52*G47/H47 -> 4.8717949 | I62: =H52*H47/I47 -> 6.4498703 | J62: =I52*I47/J47 -> 0 | ... L62: =K52*K47/L47 -> 0
A63: Impuesto de renta | B63: =$B$17*(B55-B56-B57-0.5*B58-B59)-B60-B61-B62 -> -19.308058 | C63: =$B$17*(C55-C56-C57-0.5*C58-C59)-C60-C61-C62 -> -273.44344 | D63: =$B$17*(D55-D56-D57-0.5*D58-D59)-D60-D61-D62 -> -55.927736 | E63: =$B$17*(E55-E56-E57-0.5*E58-E59)-E60-E61-E62 -> 75.793604 | F63: =$B$17*(F55-F56-F57-0.5*F58-F59)-F60-F61-F62 -> 77.473807 | G63: =$B$17*(G55-G56-G57-0.5*G58-G59)-G60-G61-G62 -> 79.074722 | H63: =$B$17*(H55-H56-H57-0.5*H58-H59)-H60-H61-H62 -> 78.150006 | I63: =$B$17*(I55-I56-I57-0.5*I58-I59)-I60-I61-I62 -> 75.648895 | ... L63: =$B$17*(L55-L56-L57-0.5*L58-L59)-L60-L61-L62 -> 86.358736
A64: Ventas adicionales | B64: =(IF(B$43>=1,Quesería!$G$107*IF(B$43=1,Quesería!$B$12,1),Quesería!$G$107*Quesería!$B$12*Quesería!$B$13/12*$B$23)+IF(B$43>=2,Quesería!$G$108*$B$21*IF(B$43=2,Quesería!$B$12,1),0))*$B$10 -> 26.851692 | C64: =(IF(C$43>=1,Quesería!$G$107*IF(C$43=1,Quesería!$B$12,1),Quesería!$G$107*Quesería!$B$12*Quesería!$B$13/12*$B$23)+IF(C$43>=2,Quesería!$G$108*$B$21*IF(C$43=2,Quesería!$B$12,1),0))*$B$10 -> 80.555075 | D64: =(IF(D$43>=1,Quesería!$G$107*IF(D$43=1,Quesería!$B$12,1),Quesería!$G$107*Quesería!$B$12*Quesería!$B$13/12*$B$23)+IF(D$43>=2,Quesería!$G$108*$B$21*IF(D$43=2,Quesería!$B$12,1),0))*$B$10 -> 189.65122 | E64: =(IF(E$43>=1,Quesería!$G$107*IF(E$43=1,Quesería!$B$12,1),Quesería!$G$107*Quesería!$B$12*Quesería!$B$13/12*$B$23)+IF(E$43>=2,Quesería!$G$108*$B$21*IF(E$43=2,Quesería!$B$12,1),0))*$B$10 -> 217.06604 | F64: =(IF(F$43>=1,Quesería!$G$107*IF(F$43=1,Quesería!$B$12,1),Quesería!$G$107*Quesería!$B$12*Quesería!$B$13/12*$B$23)+IF(F$43>=2,Quesería!$G$108*$B$21*IF(F$43=2,Quesería!$B$12,1),0))*$B$10 -> 217.06604 | G64: =(IF(G$43>=1,Quesería!$G$107*IF(G$43=1,Quesería!$B$12,1),Quesería!$G$107*Quesería!$B$12*Quesería!$B$13/12*$B$23)+IF(G$43>=2,Quesería!$G$108*$B$21*IF(G$43=2,Quesería!$B$12,1),0))*$B$10 -> 217.06604 | H64: =(IF(H$43>=1,Quesería!$G$107*IF(H$43=1,Quesería!$B$12,1),Quesería!$G$107*Quesería!$B$12*Quesería!$B$13/12*$B$23)+IF(H$43>=2,Quesería!$G$108*$B$21*IF(H$43=2,Quesería!$B$12,1),0))*$B$10 -> 217.06604 | I64: =(IF(I$43>=1,Quesería!$G$107*IF(I$43=1,Quesería!$B$12,1),Quesería!$G$107*Quesería!$B$12*Quesería!$B$13/12*$B$23)+IF(I$43>=2,Quesería!$G$108*$B$21*IF(I$43=2,Quesería!$B$12,1),0))*$B$10 -> 217.06604 | ... L64: =(IF(L$43>=1,Quesería!$G$107*IF(L$43=1,Quesería!$B$12,1),Quesería!$G$107*Quesería!$B$12*Quesería!$B$13/12*$B$23)+IF(L$43>=2,Quesería!$G$108*$B$21*IF(L$43=2,Quesería!$B$12,1),0))*$B$10 -> 217.06604
A65: Inversión en capital de trabajo | B65: =(B64*(Quesería!$B$23+Quesería!$B$25*Quesería!$B$24)/365-B56*Quesería!$B$26/365) -> 2.5086101 | C65: =(C64*(Quesería!$B$23+Quesería!$B$25*Quesería!$B$24)/365-C56*Quesería!$B$26/365)-(B64*(Quesería!$B$23+Quesería!$B$25*Quesería!$B$24)/365-B56*Quesería!$B$26/365)*B47/C47 -> 2.9130412 | D65: =(D64*(Quesería!$B$23+Quesería!$B$25*Quesería!$B$24)/365-D56*Quesería!$B$26/365)-(C64*(Quesería!$B$23+Quesería!$B$25*Quesería!$B$24)/365-C56*Quesería!$B$26/365)*C47/D47 -> 7.2915102 | E65: =(E64*(Quesería!$B$23+Quesería!$B$25*Quesería!$B$24)/365-E56*Quesería!$B$26/365)-(D64*(Quesería!$B$23+Quesería!$B$25*Quesería!$B$24)/365-D56*Quesería!$B$26/365)*D47/E47 -> 3.0368116 | F65: =(F64*(Quesería!$B$23+Quesería!$B$25*Quesería!$B$24)/365-F56*Quesería!$B$26/365)-(E64*(Quesería!$B$23+Quesería!$B$25*Quesería!$B$24)/365-E56*Quesería!$B$26/365)*E47/F47 -> 0.57409999 | G65: =(G64*(Quesería!$B$23+Quesería!$B$25*Quesería!$B$24)/365-G56*Quesería!$B$26/365)-(F64*(Quesería!$B$23+Quesería!$B$25*Quesería!$B$24)/365-F56*Quesería!$B$26/365)*F47/G47 -> 0.57409999 | H65: =(H64*(Quesería!$B$23+Quesería!$B$25*Quesería!$B$24)/365-H56*Quesería!$B$26/365)-(G64*(Quesería!$B$23+Quesería!$B$25*Quesería!$B$24)/365-G56*Quesería!$B$26/365)*G47/H47 -> 0.57409999 | I65: =(I64*(Quesería!$B$23+Quesería!$B$25*Quesería!$B$24)/365-I56*Quesería!$B$26/365)-(H64*(Quesería!$B$23+Quesería!$B$25*Quesería!$B$24)/365-H56*Quesería!$B$26/365)*H47/I47 -> 0.57409999 | J65: =(J64*(Quesería!$B$23+Quesería!$B$25*Quesería!$B$24)/365-J56*Quesería!$B$26/365)-(I64*(Quesería!$B$23+Quesería!$B$25*Quesería!$B$24)/365-I56*Quesería!$B$26/365)*I47/J47 -> 0.57409999 | K65: =(K64*(Quesería!$B$23+Quesería!$B$25*Quesería!$B$24)/365-K56*Quesería!$B$26/365)-(J64*(Quesería!$B$23+Quesería!$B$25*Quesería!$B$24)/365-J56*Quesería!$B$26/365)*J47/K47 -> 0.57409999 | L65: =-(K64*(Quesería!$B$23+Quesería!$B$25*Quesería!$B$24)/365-K56*Quesería!$B$26/365)*K47/L47 -> -14.3525
A66: Valor de los equipos al año 10, después de impuestos | B66: 0 | C66: 0 | D66: 0 | E66: 0 | F66: 0 | G66: 0 | H66: 0 | I66: 0 | J66: 0 | K66: 0 | L66: =$B$8*Quesería!$B$39*(Quesería!$F$82+Quesería!$F$83*$B$21)*$B$11*(1-$B$17) -> 56.050293
A67: Flujo de caja libre del proyecto | B67: =B55-B56-B57-B58-B63-B50-B51-B52-B65+B66 -> -662.04105 | C67: =C55-C56-C57-C58-C63-C50-C51-C52-C65+C66 -> -418.87765 | D67: =D55-D56-D57-D58-D63-D50-D51-D52-D65+D66 -> 340.25983 | E67: =E55-E56-E57-E58-E63-E50-E51-E52-E65+E66 -> 249.45811 | F67: =F55-F56-F57-F58-F63-F50-F51-F52-F65+F66 -> 250.73685 | G67: =G55-G56-G57-G58-G63-G50-G51-G52-G65+G66 -> 217.77439 | H67: =H55-H56-H57-H58-H63-H50-H51-H52-H65+H66 -> 208.88011 | I67: =I55-I56-I57-I58-I63-I50-I51-I52-I65+I66 -> 254.0654 | ... L67: =L55-L56-L57-L58-L63-L50-L51-L52-L65+L66 -> 315.85876
A68: Flujo de caja libre en pesos corrientes | B68: =B67*B47 -> -701.76351 | C68: =C67*C47 -> -466.21082 | D68: =D67*D47 -> 395.7511 | E68: =E67*E47 -> 301.74662 | F68: =F67*F47 -> 315.42514 | G68: =G67*G47 -> 284.91694 | H68: =H67*H47 -> 284.21166 | I68: =I67*I47 -> 359.52052 | ... L68: =L67*L47 -> 502.77201
A69: Flujo acumulado | B69: =B67 -> -662.04105 | C69: =B69+C67 -> -1080.9187 | D69: =C69+D67 -> -740.65887 | E69: =D69+E67 -> -491.20076 | F69: =E69+F67 -> -240.46391 | G69: =F69+G67 -> -22.689524 | H69: =G69+H67 -> 186.19058 | I69: =H69+I67 -> 440.25599 | J69: =I69+J67 -> 686.90963 | ... L69: =K69+L67 -> 1248.5115
A70: Recuperación (auxiliar) | B70: 0 | C70: =IF(AND(B69<0,C69>=0),B$43+(-B69)/C67,0) -> 0 | D70: =IF(AND(C69<0,D69>=0),C$43+(-C69)/D67,0) -> 0 | E70: =IF(AND(D69<0,E69>=0),D$43+(-D69)/E67,0) -> 0 | F70: =IF(AND(E69<0,F69>=0),E$43+(-E69)/F67,0) -> 0 | G70: =IF(AND(F69<0,G69>=0),F$43+(-F69)/G67,0) -> 0 | H70: =IF(AND(G69<0,H69>=0),G$43+(-G69)/H67,0) -> 5.1086246 | I70: =IF(AND(H69<0,I69>=0),H$43+(-H69)/I67,0) -> 0 | J70: =IF(AND(I69<0,J69>=0),I$43+(-I69)/J67,0) -> 0 | ... L70: =IF(AND(K69<0,L69>=0),K$43+(-K69)/L67,0) -> 0
A71: Factor de descuento del proyecto | B71: =(B47/$B$47)/(1+$B$25)^B$43 -> 1 | C71: =(C47/$B$47)/(1+$B$25)^C$43 -> 0.92173585 | D71: =(D47/$B$47)/(1+$B$25)^D$43 -> 0.84555127 | E71: =(E47/$B$47)/(1+$B$25)^E$43 -> 0.7719523 | F71: =(F47/$B$47)/(1+$B$25)^F$43 -> 0.70475958 | G71: =(G47/$B$47)/(1+$B$25)^G$43 -> 0.64341548 | H71: =(H47/$B$47)/(1+$B$25)^H$43 -> 0.58741093 | I71: =(I47/$B$47)/(1+$B$25)^I$43 -> 0.53628116 | ... L71: =(L47/$B$47)/(1+$B$25)^L$43 -> 0.40807886
A72: Flujo descontado | B72: =B67*B71 -> -662.04105 | C72: =C67*C71 -> -386.09455 | D72: =D67*D71 -> 287.70713 | E72: =E67*E71 -> 192.56976 | F72: =F67*F71 -> 176.7092 | G72: =G67*G71 -> 140.11941 | H72: =H67*H71 -> 122.69846 | I72: =I67*I71 -> 136.25049 | ... L72: =L67*L71 -> 128.89528
A73: Flujo descontado acumulado | B73: =B72 -> -662.04105 | C73: =B73+C72 -> -1048.1356 | D73: =C73+D72 -> -760.42846 | E73: =D73+E72 -> -567.8587 | F73: =E73+F72 -> -391.1495 | G73: =F73+G72 -> -251.03009 | H73: =G73+H72 -> -128.33164 | I73: =H73+I72 -> 7.9188536 | J73: =I73+J72 -> 128.68094 | ... L73: =K73+L72 -> 367.41984
A74: Recuperación descontada (auxiliar) | B74: 0 | C74: =IF(AND(B73<0,C73>=0),B$43+(-B73)/C72,0) -> 0 | D74: =IF(AND(C73<0,D73>=0),C$43+(-C73)/D72,0) -> 0 | E74: =IF(AND(D73<0,E73>=0),D$43+(-D73)/E72,0) -> 0 | F74: =IF(AND(E73<0,F73>=0),E$43+(-E73)/F72,0) -> 0 | G74: =IF(AND(F73<0,G73>=0),F$43+(-F73)/G72,0) -> 0 | H74: =IF(AND(G73<0,H73>=0),G$43+(-G73)/H72,0) -> 0 | I74: =IF(AND(H73<0,I73>=0),H$43+(-H73)/I72,0) -> 6.9418802 | J74: =IF(AND(I73<0,J73>=0),I$43+(-I73)/J72,0) -> 0 | ... L74: =IF(AND(K73<0,L73>=0),K$43+(-K73)/L72,0) -> 0
A75: Saldo del crédito al cierre del año, pesos corrientes | B75: =IF(B$43<0,0,(Quesería!$B$40*$B$50*$B$47)*(1-MAX(0,MIN(B$43-0-Quesería!$B$43,(Quesería!$B$42-Quesería!$B$43)))/(Quesería!$B$42-Quesería!$B$43)))+IF(B$43<1,0,(Quesería!$B$40*$C$50*$C$47)*(1-MAX(0,MIN(B$43-1-Quesería!$B$43,(Quesería!$B$42-Quesería!$B$43)))/(Quesería!$B$42-Quesería!$B$43))) -> 461.70477 | C75: =IF(C$43<0,0,(Quesería!$B$40*$B$50*$B$47)*(1-MAX(0,MIN(C$43-0-Quesería!$B$43,(Quesería!$B$42-Quesería!$B$43)))/(Quesería!$B$42-Quesería!$B$43)))+IF(C$43<1,0,(Quesería!$B$40*$C$50*$C$47)*(1-MAX(0,MIN(C$43-1-Quesería!$B$43,(Quesería!$B$42-Quesería!$B$43)))/(Quesería!$B$42-Quesería!$B$43))) -> 964.4347 | D75: =IF(D$43<0,0,(Quesería!$B$40*$B$50*$B$47)*(1-MAX(0,MIN(D$43-0-Quesería!$B$43,(Quesería!$B$42-Quesería!$B$43)))/(Quesería!$B$42-Quesería!$B$43)))+IF(D$43<1,0,(Quesería!$B$40*$C$50*$C$47)*(1-MAX(0,MIN(D$43-1-Quesería!$B$43,(Quesería!$B$42-Quesería!$B$43)))/(Quesería!$B$42-Quesería!$B$43))) -> 887.4839 | E75: =IF(E$43<0,0,(Quesería!$B$40*$B$50*$B$47)*(1-MAX(0,MIN(E$43-0-Quesería!$B$43,(Quesería!$B$42-Quesería!$B$43)))/(Quesería!$B$42-Quesería!$B$43)))+IF(E$43<1,0,(Quesería!$B$40*$C$50*$C$47)*(1-MAX(0,MIN(E$43-1-Quesería!$B$43,(Quesería!$B$42-Quesería!$B$43)))/(Quesería!$B$42-Quesería!$B$43))) -> 726.74478 | F75: =IF(F$43<0,0,(Quesería!$B$40*$B$50*$B$47)*(1-MAX(0,MIN(F$43-0-Quesería!$B$43,(Quesería!$B$42-Quesería!$B$43)))/(Quesería!$B$42-Quesería!$B$43)))+IF(F$43<1,0,(Quesería!$B$40*$C$50*$C$47)*(1-MAX(0,MIN(F$43-1-Quesería!$B$43,(Quesería!$B$42-Quesería!$B$43)))/(Quesería!$B$42-Quesería!$B$43))) -> 566.00567 | G75: =IF(G$43<0,0,(Quesería!$B$40*$B$50*$B$47)*(1-MAX(0,MIN(G$43-0-Quesería!$B$43,(Quesería!$B$42-Quesería!$B$43)))/(Quesería!$B$42-Quesería!$B$43)))+IF(G$43<1,0,(Quesería!$B$40*$C$50*$C$47)*(1-MAX(0,MIN(G$43-1-Quesería!$B$43,(Quesería!$B$42-Quesería!$B$43)))/(Quesería!$B$42-Quesería!$B$43))) -> 405.26655 | H75: =IF(H$43<0,0,(Quesería!$B$40*$B$50*$B$47)*(1-MAX(0,MIN(H$43-0-Quesería!$B$43,(Quesería!$B$42-Quesería!$B$43)))/(Quesería!$B$42-Quesería!$B$43)))+IF(H$43<1,0,(Quesería!$B$40*$C$50*$C$47)*(1-MAX(0,MIN(H$43-1-Quesería!$B$43,(Quesería!$B$42-Quesería!$B$43)))/(Quesería!$B$42-Quesería!$B$43))) -> 244.52744 | I75: =IF(I$43<0,0,(Quesería!$B$40*$B$50*$B$47)*(1-MAX(0,MIN(I$43-0-Quesería!$B$43,(Quesería!$B$42-Quesería!$B$43)))/(Quesería!$B$42-Quesería!$B$43)))+IF(I$43<1,0,(Quesería!$B$40*$C$50*$C$47)*(1-MAX(0,MIN(I$43-1-Quesería!$B$43,(Quesería!$B$42-Quesería!$B$43)))/(Quesería!$B$42-Quesería!$B$43))) -> 83.788321 | ... L75: =IF(L$43<0,0,(Quesería!$B$40*$B$50*$B$47)*(1-MAX(0,MIN(L$43-0-Quesería!$B$43,(Quesería!$B$42-Quesería!$B$43)))/(Quesería!$B$42-Quesería!$B$43)))+IF(L$43<1,0,(Quesería!$B$40*$C$50*$C$47)*(1-MAX(0,MIN(L$43-1-Quesería!$B$43,(Quesería!$B$42-Quesería!$B$43)))/(Quesería!$B$42-Quesería!$B$43))) -> 0
A76: Desembolso del crédito | B76: =Quesería!$B$40*B50 -> 435.57054 | C76: =Quesería!$B$40*C50 -> 451.68906 | D76: =Quesería!$B$40*D50 -> 0 | E76: =Quesería!$B$40*E50 -> 0 | F76: =Quesería!$B$40*F50 -> 0 | G76: =Quesería!$B$40*G50 -> 0 | H76: =Quesería!$B$40*H50 -> 0 | I76: =Quesería!$B$40*I50 -> 0 | ... L76: =Quesería!$B$40*L50 -> 0
A77: Intereses | B77: =(IF(AND(B$43>0,B$43<=0+Quesería!$B$42),($B$14+$B$24)*((Quesería!$B$40*$B$50*$B$47)-(Quesería!$B$40*$B$50*$B$47)/(Quesería!$B$42-Quesería!$B$43)*MAX(0,MIN(B$43-1-0-Quesería!$B$43,(Quesería!$B$42-Quesería!$B$43)))),0)+IF(AND(B$43>1,B$43<=1+Quesería!$B$42),($B$14+$B$24)*((Quesería!$B$40*$C$50*$C$47)-(Quesería!$B$40*$C$50*$C$47)/(Quesería!$B$42-Quesería!$B$43)*MAX(0,MIN(B$43-1-1-Quesería!$B$43,(Quesería!$B$42-Quesería!$B$43)))),0))*B49 -> 0 | C77: =(IF(AND(C$43>0,C$43<=0+Quesería!$B$42),($B$14+$B$24)*((Quesería!$B$40*$B$50*$B$47)-(Quesería!$B$40*$B$50*$B$47)/(Quesería!$B$42-Quesería!$B$43)*MAX(0,MIN(C$43-1-0-Quesería!$B$43,(Quesería!$B$42-Quesería!$B$43)))),0)+IF(AND(C$43>1,C$43<=1+Quesería!$B$42),($B$14+$B$24)*((Quesería!$B$40*$C$50*$C$47)-(Quesería!$B$40*$C$50*$C$47)/(Quesería!$B$42-Quesería!$B$43)*MAX(0,MIN(C$43-1-1-Quesería!$B$43,(Quesería!$B$42-Quesería!$B$43)))),0))*C49 -> 58.490901 | D77: =(IF(AND(D$43>0,D$43<=0+Quesería!$B$42),($B$14+$B$24)*((Quesería!$B$40*$B$50*$B$47)-(Quesería!$B$40*$B$50*$B$47)/(Quesería!$B$42-Quesería!$B$43)*MAX(0,MIN(D$43-1-0-Quesería!$B$43,(Quesería!$B$42-Quesería!$B$43)))),0)+IF(AND(D$43>1,D$43<=1+Quesería!$B$42),($B$14+$B$24)*((Quesería!$B$40*$C$50*$C$47)-(Quesería!$B$40*$C$50*$C$47)/(Quesería!$B$42-Quesería!$B$43)*MAX(0,MIN(D$43-1-1-Quesería!$B$43,(Quesería!$B$42-Quesería!$B$43)))),0))*D49 -> 116.91776 | E77: =(IF(AND(E$43>0,E$43<=0+Quesería!$B$42),($B$14+$B$24)*((Quesería!$B$40*$B$50*$B$47)-(Quesería!$B$40*$B$50*$B$47)/(Quesería!$B$42-Quesería!$B$43)*MAX(0,MIN(E$43-1-0-Quesería!$B$43,(Quesería!$B$42-Quesería!$B$43)))),0)+IF(AND(E$43>1,E$43<=1+Quesería!$B$42),($B$14+$B$24)*((Quesería!$B$40*$C$50*$C$47)-(Quesería!$B$40*$C$50*$C$47)/(Quesería!$B$42-Quesería!$B$43)*MAX(0,MIN(E$43-1-1-Quesería!$B$43,(Quesería!$B$42-Quesería!$B$43)))),0))*E49 -> 103.45103 | F77: =(IF(AND(F$43>0,F$43<=0+Quesería!$B$42),($B$14+$B$24)*((Quesería!$B$40*$B$50*$B$47)-(Quesería!$B$40*$B$50*$B$47)/(Quesería!$B$42-Quesería!$B$43)*MAX(0,MIN(F$43-1-0-Quesería!$B$43,(Quesería!$B$42-Quesería!$B$43)))),0)+IF(AND(F$43>1,F$43<=1+Quesería!$B$42),($B$14+$B$24)*((Quesería!$B$40*$C$50*$C$47)-(Quesería!$B$40*$C$50*$C$47)/(Quesería!$B$42-Quesería!$B$43)*MAX(0,MIN(F$43-1-1-Quesería!$B$43,(Quesería!$B$42-Quesería!$B$43)))),0))*F49 -> 81.455967 | G77: =(IF(AND(G$43>0,G$43<=0+Quesería!$B$42),($B$14+$B$24)*((Quesería!$B$40*$B$50*$B$47)-(Quesería!$B$40*$B$50*$B$47)/(Quesería!$B$42-Quesería!$B$43)*MAX(0,MIN(G$43-1-0-Quesería!$B$43,(Quesería!$B$42-Quesería!$B$43)))),0)+IF(AND(G$43>1,G$43<=1+Quesería!$B$42),($B$14+$B$24)*((Quesería!$B$40*$C$50*$C$47)-(Quesería!$B$40*$C$50*$C$47)/(Quesería!$B$42-Quesería!$B$43)*MAX(0,MIN(G$43-1-1-Quesería!$B$43,(Quesería!$B$42-Quesería!$B$43)))),0))*G49 -> 60.999801 | H77: =(IF(AND(H$43>0,H$43<=0+Quesería!$B$42),($B$14+$B$24)*((Quesería!$B$40*$B$50*$B$47)-(Quesería!$B$40*$B$50*$B$47)/(Quesería!$B$42-Quesería!$B$43)*MAX(0,MIN(H$43-1-0-Quesería!$B$43,(Quesería!$B$42-Quesería!$B$43)))),0)+IF(AND(H$43>1,H$43<=1+Quesería!$B$42),($B$14+$B$24)*((Quesería!$B$40*$C$50*$C$47)-(Quesería!$B$40*$C$50*$C$47)/(Quesería!$B$42-Quesería!$B$43)*MAX(0,MIN(H$43-1-1-Quesería!$B$43,(Quesería!$B$42-Quesería!$B$43)))),0))*H49 -> 41.99669 | I77: =(IF(AND(I$43>0,I$43<=0+Quesería!$B$42),($B$14+$B$24)*((Quesería!$B$40*$B$50*$B$47)-(Quesería!$B$40*$B$50*$B$47)/(Quesería!$B$42-Quesería!$B$43)*MAX(0,MIN(I$43-1-0-Quesería!$B$43,(Quesería!$B$42-Quesería!$B$43)))),0)+IF(AND(I$43>1,I$43<=1+Quesería!$B$42),($B$14+$B$24)*((Quesería!$B$40*$C$50*$C$47)-(Quesería!$B$40*$C$50*$C$47)/(Quesería!$B$42-Quesería!$B$43)*MAX(0,MIN(I$43-1-1-Quesería!$B$43,(Quesería!$B$42-Quesería!$B$43)))),0))*I49 -> 24.36512 | ... L77: =(IF(AND(L$43>0,L$43<=0+Quesería!$B$42),($B$14+$B$24)*((Quesería!$B$40*$B$50*$B$47)-(Quesería!$B$40*$B$50*$B$47)/(Quesería!$B$42-Quesería!$B$43)*MAX(0,MIN(L$43-1-0-Quesería!$B$43,(Quesería!$B$42-Quesería!$B$43)))),0)+IF(AND(L$43>1,L$43<=1+Quesería!$B$42),($B$14+$B$24)*((Quesería!$B$40*$C$50*$C$47)-(Quesería!$B$40*$C$50*$C$47)/(Quesería!$B$42-Quesería!$B$43)*MAX(0,MIN(L$43-1-1-Quesería!$B$43,(Quesería!$B$42-Quesería!$B$43)))),0))*L49 -> 0
A78: Abono a capital | B78: =(IF(AND(B$43>0+Quesería!$B$43,B$43<=0+Quesería!$B$42),(Quesería!$B$40*$B$50*$B$47)/(Quesería!$B$42-Quesería!$B$43),0)+IF(AND(B$43>1+Quesería!$B$43,B$43<=1+Quesería!$B$42),(Quesería!$B$40*$C$50*$C$47)/(Quesería!$B$42-Quesería!$B$43),0))*B49 -> 0 | C78: =(IF(AND(C$43>0+Quesería!$B$43,C$43<=0+Quesería!$B$42),(Quesería!$B$40*$B$50*$B$47)/(Quesería!$B$42-Quesería!$B$43),0)+IF(AND(C$43>1+Quesería!$B$43,C$43<=1+Quesería!$B$42),(Quesería!$B$40*$C$50*$C$47)/(Quesería!$B$42-Quesería!$B$43),0))*C49 -> 0 | D78: =(IF(AND(D$43>0+Quesería!$B$43,D$43<=0+Quesería!$B$42),(Quesería!$B$40*$B$50*$B$47)/(Quesería!$B$42-Quesería!$B$43),0)+IF(AND(D$43>1+Quesería!$B$43,D$43<=1+Quesería!$B$42),(Quesería!$B$40*$C$50*$C$47)/(Quesería!$B$42-Quesería!$B$43),0))*D49 -> 66.160938 | E78: =(IF(AND(E$43>0+Quesería!$B$43,E$43<=0+Quesería!$B$42),(Quesería!$B$40*$B$50*$B$47)/(Quesería!$B$42-Quesería!$B$43),0)+IF(AND(E$43>1+Quesería!$B$43,E$43<=1+Quesería!$B$42),(Quesería!$B$40*$C$50*$C$47)/(Quesería!$B$42-Quesería!$B$43),0))*E49 -> 132.88525 | F78: =(IF(AND(F$43>0+Quesería!$B$43,F$43<=0+Quesería!$B$42),(Quesería!$B$40*$B$50*$B$47)/(Quesería!$B$42-Quesería!$B$43),0)+IF(AND(F$43>1+Quesería!$B$43,F$43<=1+Quesería!$B$42),(Quesería!$B$40*$C$50*$C$47)/(Quesería!$B$42-Quesería!$B$43),0))*F49 -> 127.77428 | G78: =(IF(AND(G$43>0+Quesería!$B$43,G$43<=0+Quesería!$B$42),(Quesería!$B$40*$B$50*$B$47)/(Quesería!$B$42-Quesería!$B$43),0)+IF(AND(G$43>1+Quesería!$B$43,G$43<=1+Quesería!$B$42),(Quesería!$B$40*$C$50*$C$47)/(Quesería!$B$42-Quesería!$B$43),0))*G49 -> 122.85988 | H78: =(IF(AND(H$43>0+Quesería!$B$43,H$43<=0+Quesería!$B$42),(Quesería!$B$40*$B$50*$B$47)/(Quesería!$B$42-Quesería!$B$43),0)+IF(AND(H$43>1+Quesería!$B$43,H$43<=1+Quesería!$B$42),(Quesería!$B$40*$C$50*$C$47)/(Quesería!$B$42-Quesería!$B$43),0))*H49 -> 118.1345 | I78: =(IF(AND(I$43>0+Quesería!$B$43,I$43<=0+Quesería!$B$42),(Quesería!$B$40*$B$50*$B$47)/(Quesería!$B$42-Quesería!$B$43),0)+IF(AND(I$43>1+Quesería!$B$43,I$43<=1+Quesería!$B$42),(Quesería!$B$40*$C$50*$C$47)/(Quesería!$B$42-Quesería!$B$43),0))*I49 -> 113.59087 | ... L78: =(IF(AND(L$43>0+Quesería!$B$43,L$43<=0+Quesería!$B$42),(Quesería!$B$40*$B$50*$B$47)/(Quesería!$B$42-Quesería!$B$43),0)+IF(AND(L$43>1+Quesería!$B$43,L$43<=1+Quesería!$B$42),(Quesería!$B$40*$C$50*$C$47)/(Quesería!$B$42-Quesería!$B$43),0))*L49 -> 0
A79: Garantía del crédito | B79: =$B$13*Quesería!$B$44*(1+0.19)*B75*B49+(1-$B$13)*IF(B$43=0,Quesería!$B$53,0) -> 4 | C79: =$B$13*Quesería!$B$44*(1+0.19)*C75*C49+(1-$B$13)*IF(C$43=0,Quesería!$B$53,0) -> 0 | D79: =$B$13*Quesería!$B$44*(1+0.19)*D75*D49+(1-$B$13)*IF(D$43=0,Quesería!$B$53,0) -> 0 | E79: =$B$13*Quesería!$B$44*(1+0.19)*E75*E49+(1-$B$13)*IF(E$43=0,Quesería!$B$53,0) -> 0 | F79: =$B$13*Quesería!$B$44*(1+0.19)*F75*F49+(1-$B$13)*IF(F$43=0,Quesería!$B$53,0) -> 0 | G79: =$B$13*Quesería!$B$44*(1+0.19)*G75*G49+(1-$B$13)*IF(G$43=0,Quesería!$B$53,0) -> 0 | H79: =$B$13*Quesería!$B$44*(1+0.19)*H75*H49+(1-$B$13)*IF(H$43=0,Quesería!$B$53,0) -> 0 | I79: =$B$13*Quesería!$B$44*(1+0.19)*I75*I49+(1-$B$13)*IF(I$43=0,Quesería!$B$53,0) -> 0 | ... L79: =$B$13*Quesería!$B$44*(1+0.19)*L75*L49+(1-$B$13)*IF(L$43=0,Quesería!$B$53,0) -> 0
A80: GMF del servicio de la deuda | B80: =Quesería!$B$45*(B77+B78+B79) -> 0.016 | C80: =Quesería!$B$45*(C77+C78+C79) -> 0.2339636 | D80: =Quesería!$B$45*(D77+D78+D79) -> 0.73231479 | E80: =Quesería!$B$45*(E77+E78+E79) -> 0.94534511 | F80: =Quesería!$B$45*(F77+F78+F79) -> 0.83692099 | G80: =Quesería!$B$45*(G77+G78+G79) -> 0.73543874 | H80: =Quesería!$B$45*(H77+H78+H79) -> 0.64052478 | I80: =Quesería!$B$45*(I77+I78+I79) -> 0.55182396 | ... L80: =Quesería!$B$45*(L77+L78+L79) -> 0
A81: Ahorro de impuesto por los gastos financieros | B81: =$B$17*(B77+B79+0.5*B80) -> 1.4028 | C81: =$B$17*(C77+C79+0.5*C80) -> 20.512759 | D81: =$B$17*(D77+D79+0.5*D80) -> 41.049371 | E81: =$B$17*(E77+E79+0.5*E80) -> 36.373294 | F81: =$B$17*(F77+F79+0.5*F80) -> 28.65605 | G81: =$B$17*(G77+G79+0.5*G80) -> 21.478632 | H81: =$B$17*(H77+H79+0.5*H80) -> 14.810933 | I81: =$B$17*(I77+I79+0.5*I80) -> 8.6243612 | ... L81: =$B$17*(L77+L79+0.5*L80) -> 0
A82: Flujo del inversionista | B82: =B67+B76-B77-B78-B79-B80+B81 -> -229.08371 | C82: =C67+C76-C77-C78-C79-C80+C81 -> -5.4006931 | D82: =D67+D76-D77-D78-D79-D80+D81 -> 197.49818 | E82: =E67+E76-E77-E78-E79-E80+E81 -> 48.549781 | F82: =F67+F76-F77-F78-F79-F80+F81 -> 69.325734 | G82: =G67+G76-G77-G78-G79-G80+G81 -> 54.657893 | H82: =H67+H76-H77-H78-H79-H80+H81 -> 62.919322 | I82: =I67+I76-I77-I78-I79-I80+I81 -> 124.18195 | ... L82: =L67+L76-L77-L78-L79-L80+L81 -> 315.85876
A83: Flujo del inversionista en pesos corrientes | B83: =B82*B47 -> -242.82873 | C83: =C82*C47 -> -6.0109715 | D83: =D82*D47 -> 229.70717 | E83: =E82*E47 -> 58.726223 | F83: =F82*F47 -> 87.211269 | G83: =G82*G47 -> 71.509602 | H83: =H82*H47 -> 85.610858 | I83: =I82*I47 -> 175.72624 | ... L83: =L82*L47 -> 502.77201
A84: Factor de descuento del inversionista | B84: =(B47/$B$47)/(1+Quesería!$B$46+$B$24)^B$43 -> 1 | C84: =(C47/$B$47)/(1+Quesería!$B$46+$B$24)^C$43 -> 0.84 | D84: =(D47/$B$47)/(1+Quesería!$B$46+$B$24)^D$43 -> 0.70224 | E84: =(E47/$B$47)/(1+Quesería!$B$46+$B$24)^E$43 -> 0.58426368 | F84: =(F47/$B$47)/(1+Quesería!$B$46+$B$24)^F$43 -> 0.48610738 | G84: =(G47/$B$47)/(1+Quesería!$B$46+$B$24)^G$43 -> 0.40444134 | H84: =(H47/$B$47)/(1+Quesería!$B$46+$B$24)^H$43 -> 0.3364952 | I84: =(I47/$B$47)/(1+Quesería!$B$46+$B$24)^I$43 -> 0.279964 | ... L84: =(L47/$B$47)/(1+Quesería!$B$46+$B$24)^L$43 -> 0.16123977
A85: Flujo de la operación disponible para la deuda | B85: =B67+B50+B52+B81 -> 60.953255 | C85: =C67+C50+C52+C81 -> 369.50651 | D85: =D67+D50+D52+D81 -> 381.3092 | E85: =E67+E50+E52+E81 -> 285.8314 | F85: =F67+F50+F52+F81 -> 279.3929 | G85: =G67+G50+G52+G81 -> 244.31968 | H85: =H67+H50+H52+H81 -> 230.39891 | I85: =I67+I50+I52+I81 -> 262.68976 | ... L85: =L67+L50+L52+L81 -> 315.85876
A86: Cobertura del servicio de la deuda (veces) | B86: =IF(AND(B$43>=1,(B77+B78+B79)>0.001),B85/(B77+B78+B79),"") | C86: =IF(AND(C$43>=1,(C77+C78+C79)>0.001),C85/(C77+C78+C79),"") -> 6.3173333 | D86: =IF(AND(D$43>=1,(D77+D78+D79)>0.001),D85/(D77+D78+D79),"") -> 2.0827611 | E86: =IF(AND(E$43>=1,(E77+E78+E79)>0.001),E85/(E77+E78+E79),"") -> 1.2094267 | F86: =IF(AND(F$43>=1,(F77+F78+F79)>0.001),F85/(F77+F78+F79),"") -> 1.3353371 | G86: =IF(AND(G$43>=1,(G77+G78+G79)>0.001),G85/(G77+G78+G79),"") -> 1.3288377 | H86: =IF(AND(H$43>=1,(H77+H78+H79)>0.001),H85/(H77+H78+H79),"") -> 1.4388134 | I86: =IF(AND(I$43>=1,(I77+I78+I79)>0.001),I85/(I77+I78+I79),"") -> 1.9041563 | ... L86: =IF(AND(L$43>=1,(L77+L78+L79)>0.001),L85/(L77+L78+L79),"")
A88: Conservador
A89: Inflación del año | B89: =CHOOSE($C$15,Entorno!B$7,Entorno!B$8,Entorno!B$9) -> 0.06 | C89: =CHOOSE($C$15,Entorno!C$7,Entorno!C$8,Entorno!C$9) -> 0.05 | D89: =CHOOSE($C$15,Entorno!D$7,Entorno!D$8,Entorno!D$9) -> 0.045 | E89: =CHOOSE($C$15,Entorno!E$7,Entorno!E$8,Entorno!E$9) -> 0.04 | F89: =CHOOSE($C$15,Entorno!F$7,Entorno!F$8,Entorno!F$9) -> 0.04 | G89: =CHOOSE($C$15,Entorno!G$7,Entorno!G$8,Entorno!G$9) -> 0.04 | H89: =CHOOSE($C$15,Entorno!H$7,Entorno!H$8,Entorno!H$9) -> 0.04 | I89: =CHOOSE($C$15,Entorno!I$7,Entorno!I$8,Entorno!I$9) -> 0.04 | ... L89: =CHOOSE($C$15,Entorno!L$7,Entorno!L$8,Entorno!L$9) -> 0.04
A90: Índice de precios (2026 = 1) | B90: =1+B89 -> 1.06 | C90: =B90*(1+C89) -> 1.113 | D90: =C90*(1+D89) -> 1.163085 | E90: =D90*(1+E89) -> 1.2096084 | F90: =E90*(1+F89) -> 1.2579927 | G90: =F90*(1+G89) -> 1.3083124 | H90: =G90*(1+H89) -> 1.3606449 | I90: =H90*(1+I89) -> 1.4150707 | J90: =I90*(1+J89) -> 1.4716736 | ... L90: =K90*(1+L89) -> 1.5917621
A91: Salario mínimo real (2026 = 1) | B91: =(1+$C$16)/(1+B89) -> 1.0235849 | C91: =B91*(1+Entorno!$B$13) -> 1.0287028 | D91: =C91*(1+Entorno!$B$13) -> 1.0338463 | E91: =D91*(1+Entorno!$B$13) -> 1.0390156 | F91: =E91*(1+Entorno!$B$13) -> 1.0442107 | G91: =F91*(1+Entorno!$B$13) -> 1.0494317 | H91: =G91*(1+Entorno!$B$13) -> 1.0546789 | I91: =H91*(1+Entorno!$B$13) -> 1.0599523 | J91: =I91*(1+Entorno!$B$13) -> 1.065252 | ... L91: =K91*(1+Entorno!$B$13) -> 1.0759312
A92: Factor de pesos constantes | B92: =1/B90 -> 0.94339623 | C92: =1/C90 -> 0.8984726 | D92: =1/D90 -> 0.85978239 | E92: =1/E90 -> 0.82671384 | F92: =1/F90 -> 0.79491715 | G92: =1/G90 -> 0.76434341 | H92: =1/H90 -> 0.73494559 | I92: =1/I90 -> 0.70667845 | ... L92: =1/L90 -> 0.62823457
A93: Inversión | B93: =IF(B$43=0,Quesería!$F$80,IF(B$43=1,Quesería!$F$81*$C$21,0))*$C$11 -> 622.24362 | C93: =IF(C$43=0,Quesería!$F$80,IF(C$43=1,Quesería!$F$81*$C$21,0))*$C$11 -> 645.27009 | D93: =IF(D$43=0,Quesería!$F$80,IF(D$43=1,Quesería!$F$81*$C$21,0))*$C$11 -> 0 | E93: =IF(E$43=0,Quesería!$F$80,IF(E$43=1,Quesería!$F$81*$C$21,0))*$C$11 -> 0 | F93: =IF(F$43=0,Quesería!$F$80,IF(F$43=1,Quesería!$F$81*$C$21,0))*$C$11 -> 0 | G93: =IF(G$43=0,Quesería!$F$80,IF(G$43=1,Quesería!$F$81*$C$21,0))*$C$11 -> 0 | H93: =IF(H$43=0,Quesería!$F$80,IF(H$43=1,Quesería!$F$81*$C$21,0))*$C$11 -> 0 | I93: =IF(I$43=0,Quesería!$F$80,IF(I$43=1,Quesería!$F$81*$C$21,0))*$C$11 -> 0 | ... L93: =IF(L$43=0,Quesería!$F$80,IF(L$43=1,Quesería!$F$81*$C$21,0))*$C$11 -> 0
A94: Reposición de equipos | B94: =IF(B$43=5,Quesería!$F$87,IF(B$43=6,Quesería!$F$88,0))*$C$11 -> 0 | C94: =IF(C$43=5,Quesería!$F$87,IF(C$43=6,Quesería!$F$88,0))*$C$11 -> 0 | D94: =IF(D$43=5,Quesería!$F$87,IF(D$43=6,Quesería!$F$88,0))*$C$11 -> 0 | E94: =IF(E$43=5,Quesería!$F$87,IF(E$43=6,Quesería!$F$88,0))*$C$11 -> 0 | F94: =IF(F$43=5,Quesería!$F$87,IF(F$43=6,Quesería!$F$88,0))*$C$11 -> 0 | G94: =IF(G$43=5,Quesería!$F$87,IF(G$43=6,Quesería!$F$88,0))*$C$11 -> 26.666667 | H94: =IF(H$43=5,Quesería!$F$87,IF(H$43=6,Quesería!$F$88,0))*$C$11 -> 35.304553 | I94: =IF(I$43=5,Quesería!$F$87,IF(I$43=6,Quesería!$F$88,0))*$C$11 -> 0 | ... L94: =IF(L$43=5,Quesería!$F$87,IF(L$43=6,Quesería!$F$88,0))*$C$11 -> 0
A95: IVA de equipos y contratos | B95: =Quesería!$B$36*(IF(B$43=0,SUMPRODUCT((Quesería!$C$62:$C$77=0)*(Quesería!$H$62:$H$77>0)*(Quesería!$J$62:$J$77>0)*Quesería!$F$62:$F$77*(1+Quesería!$I$62:$I$77)),IF(B$43=1,SUMPRODUCT((Quesería!$C$62:$C$77=1)*(Quesería!$H$62:$H$77>0)*(Quesería!$J$62:$J$77>0)*Quesería!$F$62:$F$77*(1+Quesería!$I$62:$I$77))*$C$21,0))*$C$11+B94) -> 99.347875 | C95: =Quesería!$B$36*(IF(C$43=0,SUMPRODUCT((Quesería!$C$62:$C$77=0)*(Quesería!$H$62:$H$77>0)*(Quesería!$J$62:$J$77>0)*Quesería!$F$62:$F$77*(1+Quesería!$I$62:$I$77)),IF(C$43=1,SUMPRODUCT((Quesería!$C$62:$C$77=1)*(Quesería!$H$62:$H$77>0)*(Quesería!$J$62:$J$77>0)*Quesería!$F$62:$F$77*(1+Quesería!$I$62:$I$77))*$C$21,0))*$C$11+C94) -> 122.60132 | D95: =Quesería!$B$36*(IF(D$43=0,SUMPRODUCT((Quesería!$C$62:$C$77=0)*(Quesería!$H$62:$H$77>0)*(Quesería!$J$62:$J$77>0)*Quesería!$F$62:$F$77*(1+Quesería!$I$62:$I$77)),IF(D$43=1,SUMPRODUCT((Quesería!$C$62:$C$77=1)*(Quesería!$H$62:$H$77>0)*(Quesería!$J$62:$J$77>0)*Quesería!$F$62:$F$77*(1+Quesería!$I$62:$I$77))*$C$21,0))*$C$11+D94) -> 0 | E95: =Quesería!$B$36*(IF(E$43=0,SUMPRODUCT((Quesería!$C$62:$C$77=0)*(Quesería!$H$62:$H$77>0)*(Quesería!$J$62:$J$77>0)*Quesería!$F$62:$F$77*(1+Quesería!$I$62:$I$77)),IF(E$43=1,SUMPRODUCT((Quesería!$C$62:$C$77=1)*(Quesería!$H$62:$H$77>0)*(Quesería!$J$62:$J$77>0)*Quesería!$F$62:$F$77*(1+Quesería!$I$62:$I$77))*$C$21,0))*$C$11+E94) -> 0 | F95: =Quesería!$B$36*(IF(F$43=0,SUMPRODUCT((Quesería!$C$62:$C$77=0)*(Quesería!$H$62:$H$77>0)*(Quesería!$J$62:$J$77>0)*Quesería!$F$62:$F$77*(1+Quesería!$I$62:$I$77)),IF(F$43=1,SUMPRODUCT((Quesería!$C$62:$C$77=1)*(Quesería!$H$62:$H$77>0)*(Quesería!$J$62:$J$77>0)*Quesería!$F$62:$F$77*(1+Quesería!$I$62:$I$77))*$C$21,0))*$C$11+F94) -> 0 | G95: =Quesería!$B$36*(IF(G$43=0,SUMPRODUCT((Quesería!$C$62:$C$77=0)*(Quesería!$H$62:$H$77>0)*(Quesería!$J$62:$J$77>0)*Quesería!$F$62:$F$77*(1+Quesería!$I$62:$I$77)),IF(G$43=1,SUMPRODUCT((Quesería!$C$62:$C$77=1)*(Quesería!$H$62:$H$77>0)*(Quesería!$J$62:$J$77>0)*Quesería!$F$62:$F$77*(1+Quesería!$I$62:$I$77))*$C$21,0))*$C$11+G94) -> 5.0666667 | H95: =Quesería!$B$36*(IF(H$43=0,SUMPRODUCT((Quesería!$C$62:$C$77=0)*(Quesería!$H$62:$H$77>0)*(Quesería!$J$62:$J$77>0)*Quesería!$F$62:$F$77*(1+Quesería!$I$62:$I$77)),IF(H$43=1,SUMPRODUCT((Quesería!$C$62:$C$77=1)*(Quesería!$H$62:$H$77>0)*(Quesería!$J$62:$J$77>0)*Quesería!$F$62:$F$77*(1+Quesería!$I$62:$I$77))*$C$21,0))*$C$11+H94) -> 6.7078651 | I95: =Quesería!$B$36*(IF(I$43=0,SUMPRODUCT((Quesería!$C$62:$C$77=0)*(Quesería!$H$62:$H$77>0)*(Quesería!$J$62:$J$77>0)*Quesería!$F$62:$F$77*(1+Quesería!$I$62:$I$77)),IF(I$43=1,SUMPRODUCT((Quesería!$C$62:$C$77=1)*(Quesería!$H$62:$H$77>0)*(Quesería!$J$62:$J$77>0)*Quesería!$F$62:$F$77*(1+Quesería!$I$62:$I$77))*$C$21,0))*$C$11+I94) -> 0 | ... L95: =Quesería!$B$36*(IF(L$43=0,SUMPRODUCT((Quesería!$C$62:$C$77=0)*(Quesería!$H$62:$H$77>0)*(Quesería!$J$62:$J$77>0)*Quesería!$F$62:$F$77*(1+Quesería!$I$62:$I$77)),IF(L$43=1,SUMPRODUCT((Quesería!$C$62:$C$77=1)*(Quesería!$H$62:$H$77>0)*(Quesería!$J$62:$J$77>0)*Quesería!$F$62:$F$77*(1+Quesería!$I$62:$I$77))*$C$21,0))*$C$11+L94) -> 0
A96: Beneficio de las etapas 0 y 1 | B96: =IF(B$43=0,($C$22*Quesería!$J$109+(1-$C$22)*Quesería!$E$105)*Quesería!$B$12*Quesería!$B$13/12*$C$23,(($C$22*Quesería!$J$109+(1-$C$22)*Quesería!$E$105)+($C$22*Quesería!$J$92+(1-$C$22)*Quesería!$E$92)*(B91-1))*IF(B$43=1,Quesería!$B$12,1))*$C$10 -> 30.08018 | C96: =IF(C$43=0,($C$22*Quesería!$J$109+(1-$C$22)*Quesería!$E$105)*Quesería!$B$12*Quesería!$B$13/12*$C$23,(($C$22*Quesería!$J$109+(1-$C$22)*Quesería!$E$105)+($C$22*Quesería!$J$92+(1-$C$22)*Quesería!$E$92)*(C91-1))*IF(C$43=1,Quesería!$B$12,1))*$C$10 -> 90.430409 | D96: =IF(D$43=0,($C$22*Quesería!$J$109+(1-$C$22)*Quesería!$E$105)*Quesería!$B$12*Quesería!$B$13/12*$C$23,(($C$22*Quesería!$J$109+(1-$C$22)*Quesería!$E$105)+($C$22*Quesería!$J$92+(1-$C$22)*Quesería!$E$92)*(D91-1))*IF(D$43=1,Quesería!$B$12,1))*$C$10 -> 120.61924 | E96: =IF(E$43=0,($C$22*Quesería!$J$109+(1-$C$22)*Quesería!$E$105)*Quesería!$B$12*Quesería!$B$13/12*$C$23,(($C$22*Quesería!$J$109+(1-$C$22)*Quesería!$E$105)+($C$22*Quesería!$J$92+(1-$C$22)*Quesería!$E$92)*(E91-1))*IF(E$43=1,Quesería!$B$12,1))*$C$10 -> 120.66484 | F96: =IF(F$43=0,($C$22*Quesería!$J$109+(1-$C$22)*Quesería!$E$105)*Quesería!$B$12*Quesería!$B$13/12*$C$23,(($C$22*Quesería!$J$109+(1-$C$22)*Quesería!$E$105)+($C$22*Quesería!$J$92+(1-$C$22)*Quesería!$E$92)*(F91-1))*IF(F$43=1,Quesería!$B$12,1))*$C$10 -> 120.71066 | G96: =IF(G$43=0,($C$22*Quesería!$J$109+(1-$C$22)*Quesería!$E$105)*Quesería!$B$12*Quesería!$B$13/12*$C$23,(($C$22*Quesería!$J$109+(1-$C$22)*Quesería!$E$105)+($C$22*Quesería!$J$92+(1-$C$22)*Quesería!$E$92)*(G91-1))*IF(G$43=1,Quesería!$B$12,1))*$C$10 -> 120.75671 | H96: =IF(H$43=0,($C$22*Quesería!$J$109+(1-$C$22)*Quesería!$E$105)*Quesería!$B$12*Quesería!$B$13/12*$C$23,(($C$22*Quesería!$J$109+(1-$C$22)*Quesería!$E$105)+($C$22*Quesería!$J$92+(1-$C$22)*Quesería!$E$92)*(H91-1))*IF(H$43=1,Quesería!$B$12,1))*$C$10 -> 120.80299 | I96: =IF(I$43=0,($C$22*Quesería!$J$109+(1-$C$22)*Quesería!$E$105)*Quesería!$B$12*Quesería!$B$13/12*$C$23,(($C$22*Quesería!$J$109+(1-$C$22)*Quesería!$E$105)+($C$22*Quesería!$J$92+(1-$C$22)*Quesería!$E$92)*(I91-1))*IF(I$43=1,Quesería!$B$12,1))*$C$10 -> 120.8495 | ... L96: =IF(L$43=0,($C$22*Quesería!$J$109+(1-$C$22)*Quesería!$E$105)*Quesería!$B$12*Quesería!$B$13/12*$C$23,(($C$22*Quesería!$J$109+(1-$C$22)*Quesería!$E$105)+($C$22*Quesería!$J$92+(1-$C$22)*Quesería!$E$92)*(L91-1))*IF(L$43=1,Quesería!$B$12,1))*$C$10 -> 120.99043
A97: Beneficio de la etapa 2 | B97: =IF(B$43<=1,0,((($C$22*Quesería!$J$110+(1-$C$22)*Quesería!$E$106)-($C$22*Quesería!$J$99+(1-$C$22)*Quesería!$E$99)+$C$6*($C$22*Quesería!$J$99+(1-$C$22)*Quesería!$E$99)-(1-$C$9)*($C$22*Quesería!$J$102+(1-$C$22)*Quesería!$E$102))+($C$6*($C$22*Quesería!$J$99+(1-$C$22)*Quesería!$E$99)+$C$9*($C$22*Quesería!$J$102+(1-$C$22)*Quesería!$E$102))*(B91-1))*IF(B$43=2,Quesería!$B$12,1)+IF(B$43=2,Quesería!$B$14*$C$9*($C$22*Quesería!$J$102+(1-$C$22)*Quesería!$E$102)*B91,0))*$C$10*$C$21 -> 0 | C97: =IF(C$43<=1,0,((($C$22*Quesería!$J$110+(1-$C$22)*Quesería!$E$106)-($C$22*Quesería!$J$99+(1-$C$22)*Quesería!$E$99)+$C$6*($C$22*Quesería!$J$99+(1-$C$22)*Quesería!$E$99)-(1-$C$9)*($C$22*Quesería!$J$102+(1-$C$22)*Quesería!$E$102))+($C$6*($C$22*Quesería!$J$99+(1-$C$22)*Quesería!$E$99)+$C$9*($C$22*Quesería!$J$102+(1-$C$22)*Quesería!$E$102))*(C91-1))*IF(C$43=2,Quesería!$B$12,1)+IF(C$43=2,Quesería!$B$14*$C$9*($C$22*Quesería!$J$102+(1-$C$22)*Quesería!$E$102)*C91,0))*$C$10*$C$21 -> 0 | D97: =IF(D$43<=1,0,((($C$22*Quesería!$J$110+(1-$C$22)*Quesería!$E$106)-($C$22*Quesería!$J$99+(1-$C$22)*Quesería!$E$99)+$C$6*($C$22*Quesería!$J$99+(1-$C$22)*Quesería!$E$99)-(1-$C$9)*($C$22*Quesería!$J$102+(1-$C$22)*Quesería!$E$102))+($C$6*($C$22*Quesería!$J$99+(1-$C$22)*Quesería!$E$99)+$C$9*($C$22*Quesería!$J$102+(1-$C$22)*Quesería!$E$102))*(D91-1))*IF(D$43=2,Quesería!$B$12,1)+IF(D$43=2,Quesería!$B$14*$C$9*($C$22*Quesería!$J$102+(1-$C$22)*Quesería!$E$102)*D91,0))*$C$10*$C$21 -> 127.99694 | E97: =IF(E$43<=1,0,((($C$22*Quesería!$J$110+(1-$C$22)*Quesería!$E$106)-($C$22*Quesería!$J$99+(1-$C$22)*Quesería!$E$99)+$C$6*($C$22*Quesería!$J$99+(1-$C$22)*Quesería!$E$99)-(1-$C$9)*($C$22*Quesería!$J$102+(1-$C$22)*Quesería!$E$102))+($C$6*($C$22*Quesería!$J$99+(1-$C$22)*Quesería!$E$99)+$C$9*($C$22*Quesería!$J$102+(1-$C$22)*Quesería!$E$102))*(E91-1))*IF(E$43=2,Quesería!$B$12,1)+IF(E$43=2,Quesería!$B$14*$C$9*($C$22*Quesería!$J$102+(1-$C$22)*Quesería!$E$102)*E91,0))*$C$10*$C$21 -> 156.00688 | F97: =IF(F$43<=1,0,((($C$22*Quesería!$J$110+(1-$C$22)*Quesería!$E$106)-($C$22*Quesería!$J$99+(1-$C$22)*Quesería!$E$99)+$C$6*($C$22*Quesería!$J$99+(1-$C$22)*Quesería!$E$99)-(1-$C$9)*($C$22*Quesería!$J$102+(1-$C$22)*Quesería!$E$102))+($C$6*($C$22*Quesería!$J$99+(1-$C$22)*Quesería!$E$99)+$C$9*($C$22*Quesería!$J$102+(1-$C$22)*Quesería!$E$102))*(F91-1))*IF(F$43=2,Quesería!$B$12,1)+IF(F$43=2,Quesería!$B$14*$C$9*($C$22*Quesería!$J$102+(1-$C$22)*Quesería!$E$102)*F91,0))*$C$10*$C$21 -> 156.23972 | G97: =IF(G$43<=1,0,((($C$22*Quesería!$J$110+(1-$C$22)*Quesería!$E$106)-($C$22*Quesería!$J$99+(1-$C$22)*Quesería!$E$99)+$C$6*($C$22*Quesería!$J$99+(1-$C$22)*Quesería!$E$99)-(1-$C$9)*($C$22*Quesería!$J$102+(1-$C$22)*Quesería!$E$102))+($C$6*($C$22*Quesería!$J$99+(1-$C$22)*Quesería!$E$99)+$C$9*($C$22*Quesería!$J$102+(1-$C$22)*Quesería!$E$102))*(G91-1))*IF(G$43=2,Quesería!$B$12,1)+IF(G$43=2,Quesería!$B$14*$C$9*($C$22*Quesería!$J$102+(1-$C$22)*Quesería!$E$102)*G91,0))*$C$10*$C$21 -> 156.47373 | H97: =IF(H$43<=1,0,((($C$22*Quesería!$J$110+(1-$C$22)*Quesería!$E$106)-($C$22*Quesería!$J$99+(1-$C$22)*Quesería!$E$99)+$C$6*($C$22*Quesería!$J$99+(1-$C$22)*Quesería!$E$99)-(1-$C$9)*($C$22*Quesería!$J$102+(1-$C$22)*Quesería!$E$102))+($C$6*($C$22*Quesería!$J$99+(1-$C$22)*Quesería!$E$99)+$C$9*($C$22*Quesería!$J$102+(1-$C$22)*Quesería!$E$102))*(H91-1))*IF(H$43=2,Quesería!$B$12,1)+IF(H$43=2,Quesería!$B$14*$C$9*($C$22*Quesería!$J$102+(1-$C$22)*Quesería!$E$102)*H91,0))*$C$10*$C$21 -> 156.70891 | I97: =IF(I$43<=1,0,((($C$22*Quesería!$J$110+(1-$C$22)*Quesería!$E$106)-($C$22*Quesería!$J$99+(1-$C$22)*Quesería!$E$99)+$C$6*($C$22*Quesería!$J$99+(1-$C$22)*Quesería!$E$99)-(1-$C$9)*($C$22*Quesería!$J$102+(1-$C$22)*Quesería!$E$102))+($C$6*($C$22*Quesería!$J$99+(1-$C$22)*Quesería!$E$99)+$C$9*($C$22*Quesería!$J$102+(1-$C$22)*Quesería!$E$102))*(I91-1))*IF(I$43=2,Quesería!$B$12,1)+IF(I$43=2,Quesería!$B$14*$C$9*($C$22*Quesería!$J$102+(1-$C$22)*Quesería!$E$102)*I91,0))*$C$10*$C$21 -> 156.94526 | ... L97: =IF(L$43<=1,0,((($C$22*Quesería!$J$110+(1-$C$22)*Quesería!$E$106)-($C$22*Quesería!$J$99+(1-$C$22)*Quesería!$E$99)+$C$6*($C$22*Quesería!$J$99+(1-$C$22)*Quesería!$E$99)-(1-$C$9)*($C$22*Quesería!$J$102+(1-$C$22)*Quesería!$E$102))+($C$6*($C$22*Quesería!$J$99+(1-$C$22)*Quesería!$E$99)+$C$9*($C$22*Quesería!$J$102+(1-$C$22)*Quesería!$E$102))*(L91-1))*IF(L$43=2,Quesería!$B$12,1)+IF(L$43=2,Quesería!$B$14*$C$9*($C$22*Quesería!$J$102+(1-$C$22)*Quesería!$E$102)*L91,0))*$C$10*$C$21 -> 157.66144
A98: Beneficio total | B98: =B96+B97 -> 30.08018 | C98: =C96+C97 -> 90.430409 | D98: =D96+D97 -> 248.61618 | E98: =E96+E97 -> 276.67172 | F98: =F96+F97 -> 276.95038 | G98: =G96+G97 -> 277.23044 | H98: =H96+H97 -> 277.5119 | I98: =I96+I97 -> 277.79476 | ... L98: =L96+L97 -> 278.65187
A99: Costos operativos nuevos | B99: =(IF(B$43>=1,(Quesería!$B$21+Quesería!$B$54)*Quesería!$F$82*$C$11+Quesería!$B$22+'Beneficios y costos'!$B$118,0)+IF(B$43>=2,((Quesería!$B$21+Quesería!$B$54)*Quesería!$F$83*$C$11+'Beneficios y costos'!$C$118)*$C$21,0))*$C$12 -> 0 | C99: =(IF(C$43>=1,(Quesería!$B$21+Quesería!$B$54)*Quesería!$F$82*$C$11+Quesería!$B$22+'Beneficios y costos'!$B$118,0)+IF(C$43>=2,((Quesería!$B$21+Quesería!$B$54)*Quesería!$F$83*$C$11+'Beneficios y costos'!$C$118)*$C$21,0))*$C$12 -> 36.892153 | D99: =(IF(D$43>=1,(Quesería!$B$21+Quesería!$B$54)*Quesería!$F$82*$C$11+Quesería!$B$22+'Beneficios y costos'!$B$118,0)+IF(D$43>=2,((Quesería!$B$21+Quesería!$B$54)*Quesería!$F$83*$C$11+'Beneficios y costos'!$C$118)*$C$21,0))*$C$12 -> 88.806504 | E99: =(IF(E$43>=1,(Quesería!$B$21+Quesería!$B$54)*Quesería!$F$82*$C$11+Quesería!$B$22+'Beneficios y costos'!$B$118,0)+IF(E$43>=2,((Quesería!$B$21+Quesería!$B$54)*Quesería!$F$83*$C$11+'Beneficios y costos'!$C$118)*$C$21,0))*$C$12 -> 88.806504 | F99: =(IF(F$43>=1,(Quesería!$B$21+Quesería!$B$54)*Quesería!$F$82*$C$11+Quesería!$B$22+'Beneficios y costos'!$B$118,0)+IF(F$43>=2,((Quesería!$B$21+Quesería!$B$54)*Quesería!$F$83*$C$11+'Beneficios y costos'!$C$118)*$C$21,0))*$C$12 -> 88.806504 | G99: =(IF(G$43>=1,(Quesería!$B$21+Quesería!$B$54)*Quesería!$F$82*$C$11+Quesería!$B$22+'Beneficios y costos'!$B$118,0)+IF(G$43>=2,((Quesería!$B$21+Quesería!$B$54)*Quesería!$F$83*$C$11+'Beneficios y costos'!$C$118)*$C$21,0))*$C$12 -> 88.806504 | H99: =(IF(H$43>=1,(Quesería!$B$21+Quesería!$B$54)*Quesería!$F$82*$C$11+Quesería!$B$22+'Beneficios y costos'!$B$118,0)+IF(H$43>=2,((Quesería!$B$21+Quesería!$B$54)*Quesería!$F$83*$C$11+'Beneficios y costos'!$C$118)*$C$21,0))*$C$12 -> 88.806504 | I99: =(IF(I$43>=1,(Quesería!$B$21+Quesería!$B$54)*Quesería!$F$82*$C$11+Quesería!$B$22+'Beneficios y costos'!$B$118,0)+IF(I$43>=2,((Quesería!$B$21+Quesería!$B$54)*Quesería!$F$83*$C$11+'Beneficios y costos'!$C$118)*$C$21,0))*$C$12 -> 88.806504 | ... L99: =(IF(L$43>=1,(Quesería!$B$21+Quesería!$B$54)*Quesería!$F$82*$C$11+Quesería!$B$22+'Beneficios y costos'!$B$118,0)+IF(L$43>=2,((Quesería!$B$21+Quesería!$B$54)*Quesería!$F$83*$C$11+'Beneficios y costos'!$C$118)*$C$21,0))*$C$12 -> 88.806504
A100: Costo de la transición del personal | B100: =IF(B$43=1,2*Quesería!$B$33*Quesería!$B$34/12*B91,0)*$C$21 -> 0 | C100: =IF(C$43=1,2*Quesería!$B$33*Quesería!$B$34/12*C91,0)*$C$21 -> 18.516651 | D100: =IF(D$43=1,2*Quesería!$B$33*Quesería!$B$34/12*D91,0)*$C$21 -> 0 | E100: =IF(E$43=1,2*Quesería!$B$33*Quesería!$B$34/12*E91,0)*$C$21 -> 0 | F100: =IF(F$43=1,2*Quesería!$B$33*Quesería!$B$34/12*F91,0)*$C$21 -> 0 | G100: =IF(G$43=1,2*Quesería!$B$33*Quesería!$B$34/12*G91,0)*$C$21 -> 0 | H100: =IF(H$43=1,2*Quesería!$B$33*Quesería!$B$34/12*H91,0)*$C$21 -> 0 | I100: =IF(I$43=1,2*Quesería!$B$33*Quesería!$B$34/12*I91,0)*$C$21 -> 0 | ... L100: =IF(L$43=1,2*Quesería!$B$33*Quesería!$B$34/12*L91,0)*$C$21 -> 0
A101: GMF de los pagos del proyecto | B101: =Quesería!$B$45*(B93+B94+B95+B99+B100) -> 2.886366 | C101: =Quesería!$B$45*(C93+C94+C95+C99+C100) -> 3.2931208 | D101: =Quesería!$B$45*(D93+D94+D95+D99+D100) -> 0.35522602 | E101: =Quesería!$B$45*(E93+E94+E95+E99+E100) -> 0.35522602 | F101: =Quesería!$B$45*(F93+F94+F95+F99+F100) -> 0.35522602 | G101: =Quesería!$B$45*(G93+G94+G95+G99+G100) -> 0.48215935 | H101: =Quesería!$B$45*(H93+H94+H95+H99+H100) -> 0.52327569 | I101: =Quesería!$B$45*(I93+I94+I95+I99+I100) -> 0.35522602 | ... L101: =Quesería!$B$45*(L93+L94+L95+L99+L100) -> 0.35522602
A102: Depreciación fiscal en pesos constantes | B102: =(IF($C$19=1,(SUMPRODUCT((Quesería!$C$62:$C$77=0)*(Quesería!$J$62:$J$77>0)*(B$43>=1)*(B$43<=Quesería!$J$62:$J$77)*(Quesería!$H$62:$H$77>0)*Quesería!$F$62:$F$77*(1+Quesería!$I$62:$I$77)/(Quesería!$J$62:$J$77+(Quesería!$J$62:$J$77=0)))+SUMPRODUCT((Quesería!$C$62:$C$77=0)*(Quesería!$J$62:$J$77=0)*(B$43=0)*(Quesería!$H$62:$H$77>0)*Quesería!$F$62:$F$77*(1+Quesería!$I$62:$I$77)))*$B$90+(SUMPRODUCT((Quesería!$C$62:$C$77=1)*(Quesería!$J$62:$J$77>0)*(B$43>=2)*(B$43<=Quesería!$J$62:$J$77+1)*(Quesería!$H$62:$H$77>0)*Quesería!$F$62:$F$77*(1+Quesería!$I$62:$I$77)/(Quesería!$J$62:$J$77+(Quesería!$J$62:$J$77=0)))+SUMPRODUCT((Quesería!$C$62:$C$77=1)*(Quesería!$J$62:$J$77=0)*(B$43=1)*(Quesería!$H$62:$H$77>0)*Quesería!$F$62:$F$77*(1+Quesería!$I$62:$I$77)))*$C$90*$C$21,IF(AND(B$43>=1,B$43<=Quesería!$B$11),Quesería!$F$80/Quesería!$B$11,0)*$B$90+IF(AND(B$43>=2,B$43<=Quesería!$B$11+1),Quesería!$F$81/Quesería!$B$11,0)*$C$90*$C$21)*$C$11+IF(AND(B$43>=6,B$43<=10),$G94*$G90/5,0)+IF(AND(B$43>=7,B$43<=11),$H94*$H90/5,0))*B92 -> 99.360069 | C102: =(IF($C$19=1,(SUMPRODUCT((Quesería!$C$62:$C$77=0)*(Quesería!$J$62:$J$77>0)*(C$43>=1)*(C$43<=Quesería!$J$62:$J$77)*(Quesería!$H$62:$H$77>0)*Quesería!$F$62:$F$77*(1+Quesería!$I$62:$I$77)/(Quesería!$J$62:$J$77+(Quesería!$J$62:$J$77=0)))+SUMPRODUCT((Quesería!$C$62:$C$77=0)*(Quesería!$J$62:$J$77=0)*(C$43=0)*(Quesería!$H$62:$H$77>0)*Quesería!$F$62:$F$77*(1+Quesería!$I$62:$I$77)))*$B$90+(SUMPRODUCT((Quesería!$C$62:$C$77=1)*(Quesería!$J$62:$J$77>0)*(C$43>=2)*(C$43<=Quesería!$J$62:$J$77+1)*(Quesería!$H$62:$H$77>0)*Quesería!$F$62:$F$77*(1+Quesería!$I$62:$I$77)/(Quesería!$J$62:$J$77+(Quesería!$J$62:$J$77=0)))+SUMPRODUCT((Quesería!$C$62:$C$77=1)*(Quesería!$J$62:$J$77=0)*(C$43=1)*(Quesería!$H$62:$H$77>0)*Quesería!$F$62:$F$77*(1+Quesería!$I$62:$I$77)))*$C$90*$C$21,IF(AND(C$43>=1,C$43<=Quesería!$B$11),Quesería!$F$80/Quesería!$B$11,0)*$B$90+IF(AND(C$43>=2,C$43<=Quesería!$B$11+1),Quesería!$F$81/Quesería!$B$11,0)*$C$90*$C$21)*$C$11+IF(AND(C$43>=6,C$43<=10),$G94*$G90/5,0)+IF(AND(C$43>=7,C$43<=11),$H94*$H90/5,0))*C92 -> 57.100021 | D102: =(IF($C$19=1,(SUMPRODUCT((Quesería!$C$62:$C$77=0)*(Quesería!$J$62:$J$77>0)*(D$43>=1)*(D$43<=Quesería!$J$62:$J$77)*(Quesería!$H$62:$H$77>0)*Quesería!$F$62:$F$77*(1+Quesería!$I$62:$I$77)/(Quesería!$J$62:$J$77+(Quesería!$J$62:$J$77=0)))+SUMPRODUCT((Quesería!$C$62:$C$77=0)*(Quesería!$J$62:$J$77=0)*(D$43=0)*(Quesería!$H$62:$H$77>0)*Quesería!$F$62:$F$77*(1+Quesería!$I$62:$I$77)))*$B$90+(SUMPRODUCT((Quesería!$C$62:$C$77=1)*(Quesería!$J$62:$J$77>0)*(D$43>=2)*(D$43<=Quesería!$J$62:$J$77+1)*(Quesería!$H$62:$H$77>0)*Quesería!$F$62:$F$77*(1+Quesería!$I$62:$I$77)/(Quesería!$J$62:$J$77+(Quesería!$J$62:$J$77=0)))+SUMPRODUCT((Quesería!$C$62:$C$77=1)*(Quesería!$J$62:$J$77=0)*(D$43=1)*(Quesería!$H$62:$H$77>0)*Quesería!$F$62:$F$77*(1+Quesería!$I$62:$I$77)))*$C$90*$C$21,IF(AND(D$43>=1,D$43<=Quesería!$B$11),Quesería!$F$80/Quesería!$B$11,0)*$B$90+IF(AND(D$43>=2,D$43<=Quesería!$B$11+1),Quesería!$F$81/Quesería!$B$11,0)*$C$90*$C$21)*$C$11+IF(AND(D$43>=6,D$43<=10),$G94*$G90/5,0)+IF(AND(D$43>=7,D$43<=11),$H94*$H90/5,0))*D92 -> 116.3895 | E102: =(IF($C$19=1,(SUMPRODUCT((Quesería!$C$62:$C$77=0)*(Quesería!$J$62:$J$77>0)*(E$43>=1)*(E$43<=Quesería!$J$62:$J$77)*(Quesería!$H$62:$H$77>0)*Quesería!$F$62:$F$77*(1+Quesería!$I$62:$I$77)/(Quesería!$J$62:$J$77+(Quesería!$J$62:$J$77=0)))+SUMPRODUCT((Quesería!$C$62:$C$77=0)*(Quesería!$J$62:$J$77=0)*(E$43=0)*(Quesería!$H$62:$H$77>0)*Quesería!$F$62:$F$77*(1+Quesería!$I$62:$I$77)))*$B$90+(SUMPRODUCT((Quesería!$C$62:$C$77=1)*(Quesería!$J$62:$J$77>0)*(E$43>=2)*(E$43<=Quesería!$J$62:$J$77+1)*(Quesería!$H$62:$H$77>0)*Quesería!$F$62:$F$77*(1+Quesería!$I$62:$I$77)/(Quesería!$J$62:$J$77+(Quesería!$J$62:$J$77=0)))+SUMPRODUCT((Quesería!$C$62:$C$77=1)*(Quesería!$J$62:$J$77=0)*(E$43=1)*(Quesería!$H$62:$H$77>0)*Quesería!$F$62:$F$77*(1+Quesería!$I$62:$I$77)))*$C$90*$C$21,IF(AND(E$43>=1,E$43<=Quesería!$B$11),Quesería!$F$80/Quesería!$B$11,0)*$B$90+IF(AND(E$43>=2,E$43<=Quesería!$B$11+1),Quesería!$F$81/Quesería!$B$11,0)*$C$90*$C$21)*$C$11+IF(AND(E$43>=6,E$43<=10),$G94*$G90/5,0)+IF(AND(E$43>=7,E$43<=11),$H94*$H90/5,0))*E92 -> 111.91298 | F102: =(IF($C$19=1,(SUMPRODUCT((Quesería!$C$62:$C$77=0)*(Quesería!$J$62:$J$77>0)*(F$43>=1)*(F$43<=Quesería!$J$62:$J$77)*(Quesería!$H$62:$H$77>0)*Quesería!$F$62:$F$77*(1+Quesería!$I$62:$I$77)/(Quesería!$J$62:$J$77+(Quesería!$J$62:$J$77=0)))+SUMPRODUCT((Quesería!$C$62:$C$77=0)*(Quesería!$J$62:$J$77=0)*(F$43=0)*(Quesería!$H$62:$H$77>0)*Quesería!$F$62:$F$77*(1+Quesería!$I$62:$I$77)))*$B$90+(SUMPRODUCT((Quesería!$C$62:$C$77=1)*(Quesería!$J$62:$J$77>0)*(F$43>=2)*(F$43<=Quesería!$J$62:$J$77+1)*(Quesería!$H$62:$H$77>0)*Quesería!$F$62:$F$77*(1+Quesería!$I$62:$I$77)/(Quesería!$J$62:$J$77+(Quesería!$J$62:$J$77=0)))+SUMPRODUCT((Quesería!$C$62:$C$77=1)*(Quesería!$J$62:$J$77=0)*(F$43=1)*(Quesería!$H$62:$H$77>0)*Quesería!$F$62:$F$77*(1+Quesería!$I$62:$I$77)))*$C$90*$C$21,IF(AND(F$43>=1,F$43<=Quesería!$B$11),Quesería!$F$80/Quesería!$B$11,0)*$B$90+IF(AND(F$43>=2,F$43<=Quesería!$B$11+1),Quesería!$F$81/Quesería!$B$11,0)*$C$90*$C$21)*$C$11+IF(AND(F$43>=6,F$43<=10),$G94*$G90/5,0)+IF(AND(F$43>=7,F$43<=11),$H94*$H90/5,0))*F92 -> 107.60864 | G102: =(IF($C$19=1,(SUMPRODUCT((Quesería!$C$62:$C$77=0)*(Quesería!$J$62:$J$77>0)*(G$43>=1)*(G$43<=Quesería!$J$62:$J$77)*(Quesería!$H$62:$H$77>0)*Quesería!$F$62:$F$77*(1+Quesería!$I$62:$I$77)/(Quesería!$J$62:$J$77+(Quesería!$J$62:$J$77=0)))+SUMPRODUCT((Quesería!$C$62:$C$77=0)*(Quesería!$J$62:$J$77=0)*(G$43=0)*(Quesería!$H$62:$H$77>0)*Quesería!$F$62:$F$77*(1+Quesería!$I$62:$I$77)))*$B$90+(SUMPRODUCT((Quesería!$C$62:$C$77=1)*(Quesería!$J$62:$J$77>0)*(G$43>=2)*(G$43<=Quesería!$J$62:$J$77+1)*(Quesería!$H$62:$H$77>0)*Quesería!$F$62:$F$77*(1+Quesería!$I$62:$I$77)/(Quesería!$J$62:$J$77+(Quesería!$J$62:$J$77=0)))+SUMPRODUCT((Quesería!$C$62:$C$77=1)*(Quesería!$J$62:$J$77=0)*(G$43=1)*(Quesería!$H$62:$H$77>0)*Quesería!$F$62:$F$77*(1+Quesería!$I$62:$I$77)))*$C$90*$C$21,IF(AND(G$43>=1,G$43<=Quesería!$B$11),Quesería!$F$80/Quesería!$B$11,0)*$B$90+IF(AND(G$43>=2,G$43<=Quesería!$B$11+1),Quesería!$F$81/Quesería!$B$11,0)*$C$90*$C$21)*$C$11+IF(AND(G$43>=6,G$43<=10),$G94*$G90/5,0)+IF(AND(G$43>=7,G$43<=11),$H94*$H90/5,0))*G92 -> 103.46984 | H102: =(IF($C$19=1,(SUMPRODUCT((Quesería!$C$62:$C$77=0)*(Quesería!$J$62:$J$77>0)*(H$43>=1)*(H$43<=Quesería!$J$62:$J$77)*(Quesería!$H$62:$H$77>0)*Quesería!$F$62:$F$77*(1+Quesería!$I$62:$I$77)/(Quesería!$J$62:$J$77+(Quesería!$J$62:$J$77=0)))+SUMPRODUCT((Quesería!$C$62:$C$77=0)*(Quesería!$J$62:$J$77=0)*(H$43=0)*(Quesería!$H$62:$H$77>0)*Quesería!$F$62:$F$77*(1+Quesería!$I$62:$I$77)))*$B$90+(SUMPRODUCT((Quesería!$C$62:$C$77=1)*(Quesería!$J$62:$J$77>0)*(H$43>=2)*(H$43<=Quesería!$J$62:$J$77+1)*(Quesería!$H$62:$H$77>0)*Quesería!$F$62:$F$77*(1+Quesería!$I$62:$I$77)/(Quesería!$J$62:$J$77+(Quesería!$J$62:$J$77=0)))+SUMPRODUCT((Quesería!$C$62:$C$77=1)*(Quesería!$J$62:$J$77=0)*(H$43=1)*(Quesería!$H$62:$H$77>0)*Quesería!$F$62:$F$77*(1+Quesería!$I$62:$I$77)))*$C$90*$C$21,IF(AND(H$43>=1,H$43<=Quesería!$B$11),Quesería!$F$80/Quesería!$B$11,0)*$B$90+IF(AND(H$43>=2,H$43<=Quesería!$B$11+1),Quesería!$F$81/Quesería!$B$11,0)*$C$90*$C$21)*$C$11+IF(AND(H$43>=6,H$43<=10),$G94*$G90/5,0)+IF(AND(H$43>=7,H$43<=11),$H94*$H90/5,0))*H92 -> 92.673124 | I102: =(IF($C$19=1,(SUMPRODUCT((Quesería!$C$62:$C$77=0)*(Quesería!$J$62:$J$77>0)*(I$43>=1)*(I$43<=Quesería!$J$62:$J$77)*(Quesería!$H$62:$H$77>0)*Quesería!$F$62:$F$77*(1+Quesería!$I$62:$I$77)/(Quesería!$J$62:$J$77+(Quesería!$J$62:$J$77=0)))+SUMPRODUCT((Quesería!$C$62:$C$77=0)*(Quesería!$J$62:$J$77=0)*(I$43=0)*(Quesería!$H$62:$H$77>0)*Quesería!$F$62:$F$77*(1+Quesería!$I$62:$I$77)))*$B$90+(SUMPRODUCT((Quesería!$C$62:$C$77=1)*(Quesería!$J$62:$J$77>0)*(I$43>=2)*(I$43<=Quesería!$J$62:$J$77+1)*(Quesería!$H$62:$H$77>0)*Quesería!$F$62:$F$77*(1+Quesería!$I$62:$I$77)/(Quesería!$J$62:$J$77+(Quesería!$J$62:$J$77=0)))+SUMPRODUCT((Quesería!$C$62:$C$77=1)*(Quesería!$J$62:$J$77=0)*(I$43=1)*(Quesería!$H$62:$H$77>0)*Quesería!$F$62:$F$77*(1+Quesería!$I$62:$I$77)))*$C$90*$C$21,IF(AND(I$43>=1,I$43<=Quesería!$B$11),Quesería!$F$80/Quesería!$B$11,0)*$B$90+IF(AND(I$43>=2,I$43<=Quesería!$B$11+1),Quesería!$F$81/Quesería!$B$11,0)*$C$90*$C$21)*$C$11+IF(AND(I$43>=6,I$43<=10),$G94*$G90/5,0)+IF(AND(I$43>=7,I$43<=11),$H94*$H90/5,0))*I92 -> 95.89811 | ... L102: =(IF($C$19=1,(SUMPRODUCT((Quesería!$C$62:$C$77=0)*(Quesería!$J$62:$J$77>0)*(L$43>=1)*(L$43<=Quesería!$J$62:$J$77)*(Quesería!$H$62:$H$77>0)*Quesería!$F$62:$F$77*(1+Quesería!$I$62:$I$77)/(Quesería!$J$62:$J$77+(Quesería!$J$62:$J$77=0)))+SUMPRODUCT((Quesería!$C$62:$C$77=0)*(Quesería!$J$62:$J$77=0)*(L$43=0)*(Quesería!$H$62:$H$77>0)*Quesería!$F$62:$F$77*(1+Quesería!$I$62:$I$77)))*$B$90+(SUMPRODUCT((Quesería!$C$62:$C$77=1)*(Quesería!$J$62:$J$77>0)*(L$43>=2)*(L$43<=Quesería!$J$62:$J$77+1)*(Quesería!$H$62:$H$77>0)*Quesería!$F$62:$F$77*(1+Quesería!$I$62:$I$77)/(Quesería!$J$62:$J$77+(Quesería!$J$62:$J$77=0)))+SUMPRODUCT((Quesería!$C$62:$C$77=1)*(Quesería!$J$62:$J$77=0)*(L$43=1)*(Quesería!$H$62:$H$77>0)*Quesería!$F$62:$F$77*(1+Quesería!$I$62:$I$77)))*$C$90*$C$21,IF(AND(L$43>=1,L$43<=Quesería!$B$11),Quesería!$F$80/Quesería!$B$11,0)*$B$90+IF(AND(L$43>=2,L$43<=Quesería!$B$11+1),Quesería!$F$81/Quesería!$B$11,0)*$C$90*$C$21)*$C$11+IF(AND(L$43>=6,L$43<=10),$G94*$G90/5,0)+IF(AND(L$43>=7,L$43<=11),$H94*$H90/5,0))*L92 -> 85.253071
A103: Descuento tributario (art. 255) | B103: =IF(B$43=1,MIN($C$7*Quesería!$B$35*Quesería!$F$75*$C$11*$C$21,Quesería!$B$50*Quesería!$B$51),0) -> 0 | C103: =IF(C$43=1,MIN($C$7*Quesería!$B$35*Quesería!$F$75*$C$11*$C$21,Quesería!$B$50*Quesería!$B$51),0) -> 0 | D103: =IF(D$43=1,MIN($C$7*Quesería!$B$35*Quesería!$F$75*$C$11*$C$21,Quesería!$B$50*Quesería!$B$51),0) -> 0 | E103: =IF(E$43=1,MIN($C$7*Quesería!$B$35*Quesería!$F$75*$C$11*$C$21,Quesería!$B$50*Quesería!$B$51),0) -> 0 | F103: =IF(F$43=1,MIN($C$7*Quesería!$B$35*Quesería!$F$75*$C$11*$C$21,Quesería!$B$50*Quesería!$B$51),0) -> 0 | G103: =IF(G$43=1,MIN($C$7*Quesería!$B$35*Quesería!$F$75*$C$11*$C$21,Quesería!$B$50*Quesería!$B$51),0) -> 0 | H103: =IF(H$43=1,MIN($C$7*Quesería!$B$35*Quesería!$F$75*$C$11*$C$21,Quesería!$B$50*Quesería!$B$51),0) -> 0 | I103: =IF(I$43=1,MIN($C$7*Quesería!$B$35*Quesería!$F$75*$C$11*$C$21,Quesería!$B$50*Quesería!$B$51),0) -> 0 | ... L103: =IF(L$43=1,MIN($C$7*Quesería!$B$35*Quesería!$F$75*$C$11*$C$21,Quesería!$B$50*Quesería!$B$51),0) -> 0
A104: Crédito fiscal por innovación (art. 256-1) | B104: 0 | C104: =$C$20*Quesería!$B$52*Quesería!$F$86*$C$11*$B$90/C90 -> 0 | D104: 0 | E104: 0 | F104: 0 | G104: 0 | H104: 0 | I104: 0 | J104: 0 | K104: 0 | L104: 0
A105: IVA recuperado como descuento de renta (art. 258-1) | B105: =0 -> 0 | C105: =B95*B90/C90 -> 94.617024 | D105: =C95*C90/D90 -> 117.32183 | E105: =D95*D90/E90 -> 0 | F105: =E95*E90/F90 -> 0 | G105: =F95*F90/G90 -> 0 | H105: =G95*G90/H90 -> 4.8717949 | I105: =H95*H90/I90 -> 6.4498703 | J105: =I95*I90/J90 -> 0 | ... L105: =K95*K90/L90 -> 0
...

Sheet Riesgo
A1: Análisis de riesgo de la oferta
A2: Cuánto puede empeorar cada supuesto antes de que el proyecto deje de valer la pena, y qué supuestos pesan más. Se calcula con la hoja Escenarios.
A4: Punto de equilibrio: variación que deja el VPN en cero
A5: Supuesto | B5: Variación de equilibrio | C5: Valor de equilibrio | D5: Valor de la oferta | F5: Lectura
A6: Beneficios | B6: =-0.2*Escenarios!$B$33/(Escenarios!$B$33-Escenarios!$G$33) -> -0.23592488 | C6: =D6*(1+B6) -> 316.11582 | D6: =Quesería!$E$111 -> 413.72349 | F6: Los beneficios pueden caer esta fracción y el proyecto todavía devuelve su costo de capital.
A7: Inversión | B7: =0.2*Escenarios!$B$33/(Escenarios!$B$33-Escenarios!$I$33) -> 0.38670568 | C7: =D7*(1+B7) -> 1757.6685 | D7: =Quesería!$F$85 -> 1267.5137 | F7: La inversión puede subir esta fracción, además de los imprevistos que ya incluye.
A8: Costos operativos nuevos | B8: =0.3*Escenarios!$B$33/(Escenarios!$B$33-Escenarios!$K$33) -> 1.1002348 | C8: =D8*(1+B8) -> 186.51451 | D8: =Quesería!$E$112 -> 88.806504 | F8: Los costos nuevos pueden subir esta fracción.
A9: El VPN cambia en línea recta con cada factor; por eso basta un escenario para hallar el punto donde se hace cero. En ese punto la TIR en pesos corrientes iguala el costo de capital.
A11: Sensibilidad del VPN (gráfico de tornado)
A12: Supuesto | B12: VPN con el valor desfavorable | C12: VPN con el valor favorable | D12: Cambio desfavorable | E12: Cambio favorable | F12: Valores probados
A13: Beneficios | B13: =MIN(Escenarios!$G$33,Escenarios!$H$33) -> 55.947949 | C13: =MAX(Escenarios!$G$33,Escenarios!$H$33) -> 678.89173 | D13: =B13-Escenarios!$B$33 -> -311.47189 | E13: =C13-Escenarios!$B$33 -> 311.47189 | F13: −20 % / +20 %
A14: Relevo natural | B14: =MIN(Escenarios!$F$33,Escenarios!$B$33) -> 97.936235 | C14: =MAX(Escenarios!$F$33,Escenarios!$B$33) -> 367.41984 | D14: =B14-Escenarios!$B$33 -> -269.48361 | E14: =C14-Escenarios!$B$33 -> 0 | F14: Sin relevo / con relevo
A15: Inversión | B15: =MIN(Escenarios!$I$33,Escenarios!$J$33) -> 177.39427 | C15: =MAX(Escenarios!$I$33,Escenarios!$J$33) -> 557.44542 | D15: =B15-Escenarios!$B$33 -> -190.02557 | E15: =C15-Escenarios!$B$33 -> 190.02557 | F15: +20 % / −20 %
A16: Costos operativos nuevos | B16: =MIN(Escenarios!$K$33,Escenarios!$L$33) -> 267.23581 | C16: =MAX(Escenarios!$K$33,Escenarios!$L$33) -> 467.60387 | D16: =B16-Escenarios!$B$33 -> -100.18403 | E16: =C16-Escenarios!$B$33 -> 100.18403 | F16: +30 % / −30 %
A17: Supuestos del escenario conservador | B17: =MIN(Escenarios!$C$33,Escenarios!$B$33) -> -396.60213 | C17: =MAX(Escenarios!$C$33,Escenarios!$B$33) -> 367.41984 | D17: =B17-Escenarios!$B$33 -> -764.02197 | E17: =C17-Escenarios!$B$33 -> 0 | F17: Beneficios según su respaldo / oferta
A18: Inflación | B18: =MIN(Escenarios!$M$33,Escenarios!$N$33) -> 359.36482 | C18: =MAX(Escenarios!$M$33,Escenarios!$N$33) -> 391.67116 | D18: =B18-Escenarios!$B$33 -> -8.0550222 | E18: =C18-Escenarios!$B$33 -> 24.251319 | F18: Consenso de analistas / persistente
A19: Salario mínimo de 2027 | B19: =MIN(Escenarios!$O$33,Escenarios!$P$33) -> 362.58857 | C19: =MAX(Escenarios!$O$33,Escenarios!$P$33) -> 372.25111 | D19: =B19-Escenarios!$B$33 -> -4.8312716 | E19: =C19-Escenarios!$B$33 -> 4.8312716 | F19: 7 % / 10 %
A20: Gestiones de IntegraMotion (prenda y crédito fiscal) | B20: =MIN(Escenarios!$U$33,Escenarios!$B$33) -> 150.26438 | C20: =MAX(Escenarios!$U$33,Escenarios!$B$33) -> 367.41984 | D20: =B20-Escenarios!$B$33 -> -217.15547 | E20: =C20-Escenarios!$B$33 -> 0 | F20: Sin ellas / con ellas
A21: VPN de la oferta ($ M) | B21: =Escenarios!$B$33 -> 367.41984
A22: Inflación: las tasas nominales se mueven con la inflación de cada ruta, así que el cambio de VPN viene solo de lo pactado en pesos corrientes (deuda, depreciación fiscal, IVA y cartera). Salario mínimo: si sube más, valen más las horas extra y el relevo que se ahorran.
A41: Resultados por escenario
A42: Escenario | B42: TIR en pesos corrientes | C42: VPN ($ M) | D42: TIR del inversionista | E42: Cobertura mínima | F42: Lectura
A43: Oferta | B43: =Escenarios!$B$31 -> 0.21421387 | C43: =Escenarios!$B$33 -> 367.41984 | D43: =Escenarios!$B$37 -> 0.41220926 | E43: =Escenarios!$B$39 -> 1.2094267
A44: Conservador | B44: =Escenarios!$C$31 -> 0.062952682 | C44: =Escenarios!$C$33 -> -396.60213 | D44: =Escenarios!$C$37 -> 0.016139976 | E44: =Escenarios!$C$39 -> 0.79546539 | F44: Beneficios según su respaldo, haciendo la etapa 2 de todos modos.
A45: Conservador con compuerta | B45: =Escenarios!$D$31 -> 0.057937208 | C45: =Escenarios!$D$33 -> -209.22818 | D45: =Escenarios!$D$37 -> 0.0064963028 | E45: =Escenarios!$D$39 -> 0.5906165 | F45: Beneficios según su respaldo; la compuerta detiene la etapa 2.
A46: Adverso combinado | B46: =Escenarios!$V$31 -> 0.09300273 | C46: =Escenarios!$V$33 -> -240.57876 | D46: =Escenarios!$V$37 -> 0.092323305 | E46: =Escenarios!$V$39 -> 0.78943947 | F46: Tres supuestos malos a la vez: es la prueba más dura.
A47: Inflación persistente | B47: =Escenarios!$N$31 -> 0.23525123 | C47: =Escenarios!$N$33 -> 391.67116 | D47: =Escenarios!$N$37 -> 0.42760989 | E47: =Escenarios!$N$39 -> 1.1945178 | F47: La inflación se queda cerca del 6,5 % hasta 2037.
A48: Renta 30 % | B48: =Escenarios!$Q$31 -> 0.2250889 | C48: =Escenarios!$Q$33 -> 396.09283 | D48: =Escenarios!$Q$37 -> 0.42432534 | E48: =Escenarios!$Q$39 -> 1.2332549 | F48: Si prospera la reducción de impuestos anunciada.
A49: Crédito ordinario | B49: =Escenarios!$R$31 -> 0.21421387 | C49: =Escenarios!$R$33 -> 323.12592 | D49: =Escenarios!$R$37 -> 0.39182372 | E49: =Escenarios!$R$39 -> 1.1687911 | F49: Sin la línea de fomento.
A50: Garantía del FNG | B50: =Escenarios!$S$31 -> 0.21421387 | C50: =Escenarios!$S$33 -> 302.64226 | D50: =Escenarios!$S$37 -> 0.37457397 | E50: =Escenarios!$S$39 -> 1.1606656 | F50: Si el banco no acepta la prenda.
A51: Sin crédito fiscal por innovación | B51: =Escenarios!$T$31 -> 0.17926805 | C51: =Escenarios!$T$33 -> 213.60067 | D51: =Escenarios!$T$37 -> 0.28038084 | E51: =Escenarios!$T$39 -> 1.2094267 | F51: Si el CNBT no certifica la inversión.
A52: Sin las dos gestiones | B52: =Escenarios!$U$31 -> 0.17926805 | C52: =Escenarios!$U$33 -> 150.26438 | D52: =Escenarios!$U$37 -> 0.25681294 | E52: =Escenarios!$U$39 -> 1.1606656 | F52: Ninguna de las dos gestiones sale.
A53: Primera compuerta no superada: solo la etapa 0 | C53: =Herramientas!B36 -> 84.568705 | F53: La etapa 0 es organizacional, no compra equipos ni usa crédito. Positiva con los ahorros conservadores supuestos; su sensibilidad está en la hoja Herramientas.
A55: Riesgos principales y respuesta
A56: Riesgo | B56: Dónde pega en el modelo | F56: Respuesta
A57: El rendimiento o la grasa no mejoran lo esperado | B57: Beneficios de la etapa 1 | F57: La etapa 0 mide la línea base antes de comprar; la etapa 2 solo se aprueba si la etapa 1 cumple (compuerta).
A58: La hiladora cuesta más que el estimado | B58: Inversión del año 1 | F58: Cotización formal antes de la compuerta; los imprevistos de 15 % cubren parte; la etapa 2 se puede aplazar sin perder la etapa 1.
A59: Nadie compra el suero a $45/kg | B59: Beneficio del suero | F59: Dos cotizaciones de fábricas de alimento en la etapa 0; si no hay contrato, el enfriador no se compra.
A60: No se dan las vacantes del relevo natural | B60: Relevo natural | F60: Los operarios se forman y se reubican en yogur o UHT; el escenario Sin relevo natural muestra el efecto.
A61: Sube el gas o la energía (importaciones de gas, El Niño) | B61: Costos operativos nuevos | F61: El escenario Costos operativos +30 % y el punto de equilibrio muestran cuánto aguanta el proyecto.
A62: La inflación no baja y las tasas siguen altas | B62: Tasa del crédito y tasa real | F62: El crédito de fomento sigue la IBR; el escenario Crédito ordinario muestra 1,6 puntos más de tasa y el de inflación persistente, el otro lado.
A63: El salario mínimo de 2027 sube más de lo técnico | B63: Beneficios de mano de obra y precio de los contratos | F63: Sube el ahorro en horas extra y relevo; el contrato de IntegraMotion se reajusta con el salario mínimo, así que la integradora no pierde.
A64: Incertidumbre fiscal: presupuesto de 2027 por decreto | B64: Tasas de interés | F64: No toca la quesería directamente; se refleja en tasas que bajan más lento (ruta base por encima del consenso).
A65: El banco exige la garantía del FNG | B65: Garantía del crédito | F65: IntegraMotion negocia la prenda con el avalúo de los equipos y el balance de la empresa ($6.500 M en activos fijos, deuda de 0,8 veces el EBITDA); el escenario Garantía del FNG muestra el efecto.
A66: El CNBT no certifica la inversión en innovación | B66: Crédito fiscal por innovación | F66: Se postula antes de ejecutar, con el aval de un actor reconocido y solo con la parte de desarrollo; el escenario Sin crédito fiscal muestra el efecto y la etapa 2 no depende de él.

Sheet Herramientas
A1: Herramientas económicas de la oferta
A2: Lo que se hace con ingeniería económica, sin comprar equipos ni cambiar líneas, para que el valor de la propuesta no dependa de supuestos mal analizados. Se calcula con la hoja Escenarios.
A4: Herramientas, una sobre otra
A5: Paso | B5: Costo de capital | C5: VPN ($ M de 2026) | D5: TIR en pesos corrientes | E5: TIR del inversionista | F5: Cobertura mínima | G5: Estado y base
A6: Punto de partida: costo de capital de 16 %, todo depreciado a 10 años, garantía del FNG | B6: =Escenarios!$W$25 -> 0.16 | C6: =Escenarios!$W$33 -> 72.665882 | D6: =Escenarios!$W$31 -> 0.17427009 | E6: =Escenarios!$W$37 -> 0.24052487 | F6: =Escenarios!$W$39 -> 1.1634435 | G6: Referencia.
A7: + Costo de capital con la deuda que financia el proyecto | B7: =Escenarios!$X$25 -> 0.14992986 | C7: =Escenarios!$X$33 -> 128.42404 | D7: =Escenarios!$X$31 -> 0.17427009 | E7: =Escenarios!$X$37 -> 0.24052487 | F7: =Escenarios!$X$39 -> 1.1634435 | G7: El 16 % usaba el 18 % de la deuda actual de la empresa; el proyecto se financia con Bancóldex al 14,1 % más la garantía.
A8: + Depreciación por tipo de activo y gastos deducibles en el año | B8: =Escenarios!$U$25 -> 0.14992986 | C8: =Escenarios!$U$33 -> 150.26438 | D8: =Escenarios!$U$31 -> 0.17926805 | E8: =Escenarios!$U$37 -> 0.25681294 | F8: =Escenarios!$U$39 -> 1.1606656 | G8: Art. 137 ET: equipo de cómputo y redes al 20 % anual; el diagnóstico, la formación y el aval son gastos del año.
A9: + Prenda sobre los equipos en lugar de la garantía del FNG | B9: =Escenarios!$T$25 -> 0.139155 | C9: =Escenarios!$T$33 -> 213.60067 | D9: =Escenarios!$T$31 -> 0.17926805 | E9: =Escenarios!$T$37 -> 0.28038084 | F9: =Escenarios!$T$39 -> 1.2094267 | G9: Gestión de IntegraMotion ante el banco (Ley 1676 de 2013).
A10: + Crédito fiscal por innovación (art. 256-1 ET) | B10: =Escenarios!$B$25 -> 0.139155 | C10: =Escenarios!$B$33 -> 367.41984 | D10: =Escenarios!$B$31 -> 0.21421387 | E10: =Escenarios!$B$37 -> 0.41220926 | F10: =Escenarios!$B$39 -> 1.2094267 | G10: Gestión de IntegraMotion ante Minciencias y el CNBT: 50 % de la parte de desarrollo de la etapa 1.
A11: Cada fila suma la herramienta a las de arriba; todas están en la oferta. Las dos primeras corrigen el análisis; las dos últimas son gestiones que IntegraMotion hace por el cliente.
A13: Cómo se consiguen las dos gestiones
A14: • Prenda sobre los equipos: avalúo de los equipos financiados, contrato de garantía mobiliaria inscrito en el registro de Confecámaras (Ley 1676 de 2013) y póliza todo riesgo endosada al banco. Argumento ante el banco: $6.500 M en activos fijos y deuda de 0,8 veces el EBITDA. Costo: avalúo y registro, y la póliza dentro de los costos operativos.
A15: • Crédito fiscal por innovación (art. 256-1): Lácteos Fúquene es mediana empresa. Se formula el proyecto de innovación (corte del cuajo con sensor de coagulación y modelo de control, estandarización de grasa por balance de masa en línea y MES) y se postula en la convocatoria de beneficios tributarios de Minciencias antes de ejecutarlo, con el aval de un actor reconocido. El CNBT certifica la inversión y el crédito se compensa con impuestos nacionales en los dos años siguientes (o en títulos TIDIS si supera 1.000 UVT).
A16: • Base del crédito: solo la parte de desarrollo; la compra de equipos estándar (controladora de peso, medidor de grasa, tina básica) no califica. Responsable: ingeniero de gestión y finanzas, como entregable del contrato 1.
A18: Propuestas operativas y organizacionales que aseguran los beneficios
A19: Propuesta | B19: Efecto en el VPN ($ M) | G19: Qué asegura
A20: Arranque de la etapa 1 a mitad de 2027 | B20: =Escenarios!$B$33-Escenarios!$E$33 -> 29.35785 | G20: El contrato 1 dura 4 meses. Se ganan 4 meses de beneficio y la compuerta de diciembre se decide con datos medidos, no con promesas.
A21: Línea base medida con un protocolo de medida y verificación (etapa 0) | G21: Responsable: jefe de quesería con el ingeniero de procesos. Indicadores normalizados para que no se confundan con cambios de volumen o de mezcla: horas extra por tonelada, mantenimiento por hora de operación, merma y sobrepeso por producto y lote, rendimiento por litro y por receta; registro diario en el MES y revisión mensual.
A22: Relevo con la rotación normal de la planta | B22: =Quesería!$B$14*Quesería!$E$102 -> 21.6 | G22: Con unas 100 personas y 15 % o más de rotación hay unas 15 vacantes al año. Cubrir 2 con operarios ya formados ahorra además el costo de reemplazo (valor del año 2 en la columna).
A23: Contrato del suero antes de comprar el enfriador | G23: El beneficio del suero pasa a "contratado"; si no hay comprador, no se compra el equipo.
A24: Utilidad de IntegraMotion atada a los resultados | G24: Propuesta de contrato: la utilidad del AIU (unos $8 M del contrato 1) queda contingente. Se paga completa si el beneficio verificado a 12 meses llega al 80 % de la meta, en proporción entre 50 % y 80 %, y nada por debajo de 50 %. No está en el VPN de la quesería, que la paga completa.
A25: Bonificación del equipo de la quesería por metas | G25: Se paga solo de ahorro ya verificado en merma, sobrepeso y rendimiento; su monto se fija en la etapa 0. No está en el VPN: al definirlo se resta del beneficio.
A26: Caso conservador con la compuerta de la etapa 2 | B26: =Escenarios!$D$33 -> -209.22818 | G26: Si solo se cuenta lo respaldado y aun así se compra la etapa 1: por eso hace falta la primera compuerta.
A27: Caso conservador haciendo la etapa 2 de todos modos | B27: =Escenarios!$C$33 -> -396.60213 | G27: Sin ninguna compuerta.
A29: Si la primera compuerta no se supera: solo la etapa 0
A30: Si la línea base medida en la etapa 0 solo respalda el caso conservador, la etapa 1 no se compra. Queda la etapa 0, que es organizacional y no compra equipos: diagnóstico, orden del hilado, plan de mantenimiento preventivo y mantenimiento autónomo.
A31: $ M de 2026 | B31: Año 0 | C31: Año 1 | D31: Año 2 | E31: Año 3 | F31: Año 4 | G31: Año 5 | H31: Año 6 | I31: Año 7 | J31: Año 8 | K31: Año 9 | L31: Año 10
A32: Costo de la etapa 0 con imprevistos (diagnóstico y parte organizacional del contrato 1) | B32: =Quesería!$F$62*(1+Quesería!$I$62)+Quesería!$F$69*(1+Quesería!$I$69) -> 73.610069 | C32: 0 | D32: 0 | E32: 0 | F32: 0 | G32: 0 | H32: 0 | I32: 0 | J32: 0 | K32: 0 | L32: 0
A33: Ahorros, caso conservador (horas extra por el orden del hilado y mantenimiento preventivo) | B33: 0 | C33: =(Quesería!$J$92+Quesería!$J$96)*Quesería!$B$12*1 -> 25.1235 | D33: =(Quesería!$J$92+Quesería!$J$96)*1 -> 33.498 | E33: =(Quesería!$J$92+Quesería!$J$96)*1 -> 33.498 | F33: =(Quesería!$J$92+Quesería!$J$96)*1 -> 33.498 | G33: =(Quesería!$J$92+Quesería!$J$96)*1 -> 33.498 | H33: =(Quesería!$J$92+Quesería!$J$96)*1 -> 33.498 | I33: =(Quesería!$J$92+Quesería!$J$96)*1 -> 33.498 | J33: =(Quesería!$J$92+Quesería!$J$96)*1 -> 33.498 | K33: =(Quesería!$J$92+Quesería!$J$96)*1 -> 33.498 | L33: =(Quesería!$J$92+Quesería!$J$96)*1 -> 33.498
A34: Impuesto de renta, pagado al año siguiente (el costo es gasto deducible; el del año 10 se cierra en el año 10) | B34: 0 | C34: =Quesería!$B$10*(B33-B32)*Escenarios!B90/Escenarios!C90 -> -24.53669 | D34: =Quesería!$B$10*(C33-C32)*Escenarios!C90/Escenarios!D90 -> 8.4145694 | E34: =Quesería!$B$10*(D33-D32)*Escenarios!D90/Escenarios!E90 -> 11.273365 | F34: =Quesería!$B$10*(E33-E32)*Escenarios!E90/Escenarios!F90 -> 11.273365 | G34: =Quesería!$B$10*(F33-F32)*Escenarios!F90/Escenarios!G90 -> 11.273365 | H34: =Quesería!$B$10*(G33-G32)*Escenarios!G90/Escenarios!H90 -> 11.273365 | I34: =Quesería!$B$10*(H33-H32)*Escenarios!H90/Escenarios!I90 -> 11.273365 | J34: =Quesería!$B$10*(I33-I32)*Escenarios!I90/Escenarios!J90 -> 11.273365 | K34: =Quesería!$B$10*(J33-J32)*Escenarios!J90/Escenarios!K90 -> 11.273365 | L34: =Quesería!$B$10*(K33-K32)*Escenarios!K90/Escenarios!L90+Quesería!$B$10*(L33-L32) -> 22.997665
A35: Flujo de caja libre de la etapa 0 | B35: =B33-B32-B34 -> -73.610069 | C35: =C33-C32-C34 -> 49.66019 | D35: =D33-D32-D34 -> 25.083431 | E35: =E33-E32-E34 -> 22.224635 | F35: =F33-F32-F34 -> 22.224635 | G35: =G33-G32-G34 -> 22.224635 | H35: =H33-H32-H34 -> 22.224635 | I35: =I33-I32-I34 -> 22.224635 | ... L35: =L33-L32-L34 -> 10.500335
A36: VPN de la etapa 0 sola ($ M de 2026) | B36: =SUMPRODUCT(B35:L35,Escenarios!B114:L114) -> 84.568705 | G36: Descontado al costo de capital del caso conservador (con FNG). Con los ahorros conservadores y la deducción supuestos, la etapa 0 se paga sola; las filas de abajo prueban qué pasa si no.
A37: TIR de la etapa 0 sola, en pesos constantes | B37: =IRR(B35:L35) -> 0.40514521
A38: Si no se da el ahorro de mantenimiento | B38: =(-SUMPRODUCT(B32:L32,Escenarios!B114:L114)+Quesería!$B$10*SUMPRODUCT(B32:K32*Escenarios!B90:K90/Escenarios!C90:L90,Escenarios!C114:L114))+(SUMPRODUCT(B33:L33,Escenarios!B114:L114)-Quesería!$B$10*SUMPRODUCT(B33:K33*Escenarios!B90:K90/Escenarios!C90:L90,Escenarios!C114:L114)-Quesería!$B$10*L33*Escenarios!L114)*Quesería!$J$92/(Quesería!$J$92+Quesería!$J$96) -> -15.456348 | G38: El mantenimiento es cerca de tres cuartos del ahorro de la etapa 0: es lo primero que se mide.
A39: Si el ahorro neto de mantenimiento es 10 % del gasto y no 20 % | B39: =(-SUMPRODUCT(B32:L32,Escenarios!B114:L114)+Quesería!$B$10*SUMPRODUCT(B32:K32*Escenarios!B90:K90/Escenarios!C90:L90,Escenarios!C114:L114))+(SUMPRODUCT(B33:L33,Escenarios!B114:L114)-Quesería!$B$10*SUMPRODUCT(B33:K33*Escenarios!B90:K90/Escenarios!C90:L90,Escenarios!C114:L114)-Quesería!$B$10*L33*Escenarios!L114)*(Quesería!$J$92+0.5*Quesería!$J$96)/(Quesería!$J$92+Quesería!$J$96) -> 34.556178
A40: Si ambos ahorros son la mitad del caso conservador | B40: =(-SUMPRODUCT(B32:L32,Escenarios!B114:L114)+Quesería!$B$10*SUMPRODUCT(B32:K32*Escenarios!B90:K90/Escenarios!C90:L90,Escenarios!C114:L114))+0.5*(SUMPRODUCT(B33:L33,Escenarios!B114:L114)-Quesería!$B$10*SUMPRODUCT(B33:K33*Escenarios!B90:K90/Escenarios!C90:L90,Escenarios!C114:L114)-Quesería!$B$10*L33*Escenarios!L114) -> 16.681533
A41: Ahorro mínimo que deja el VPN en cero (% del caso conservador) | B41: =-(-SUMPRODUCT(B32:L32,Escenarios!B114:L114)+Quesería!$B$10*SUMPRODUCT(B32:K32*Escenarios!B90:K90/Escenarios!C90:L90,Escenarios!C114:L114))/(SUMPRODUCT(B33:L33,Escenarios!B114:L114)-Quesería!$B$10*SUMPRODUCT(B33:K33*Escenarios!B90:K90/Escenarios!C90:L90,Escenarios!C114:L114)-Quesería!$B$10*L33*Escenarios!L114) -> 0.37713781 | G41: Con menos de esta fracción del ahorro conservador, la etapa 0 no se paga.
A42: Si el costo de la etapa 0 no fuera deducible | B42: =(SUMPRODUCT(B33:L33,Escenarios!B114:L114)-Quesería!$B$10*SUMPRODUCT(B33:K33*Escenarios!B90:K90/Escenarios!C90:L90,Escenarios!C114:L114)-Quesería!$B$10*L33*Escenarios!L114)-SUMPRODUCT(B32:L32,Escenarios!B114:L114) -> 62.164274 | G42: El diagnóstico y la parte organizacional son servicios del año con relación de causalidad (art. 107 ET).
A44: Valor de cada etapa (análisis incremental)
B45: VPN ($ M de 2026) | C45: TIR en pesos corrientes | G45: Lectura
A46: Solo etapas 0 y 1 | B46: =Escenarios!$Y$33 -> 230.72914 | C46: =Escenarios!$Y$31 -> 0.24010284 | G46: Lo que vale el proyecto si se queda en la etapa 1.
A47: Etapa 2, incremental | B47: =Escenarios!$B$33-Escenarios!$Y$33 -> 136.6907 | C47: =IRR(B50:L50) -> 0.19071666 | G47: Lo que agrega la hiladora, el CIP y el suero sobre la etapa 1.
A48: Proyecto completo (oferta) | B48: =Escenarios!$B$33 -> 367.41984 | C48: =Escenarios!$B$31 -> 0.21421387
A49: Flujo incremental de la etapa 2 en pesos corrientes ($ M) | B49: Año 0 | C49: Año 1 | D49: Año 2 | E49: Año 3 | F49: Año 4 | G49: Año 5 | H49: Año 6 | I49: Año 7 | J49: Año 8 | K49: Año 9 | L49: Año 10
A50: Oferta − solo etapas 0 y 1 | B50: =Escenarios!B68-Escenarios!B1057 -> 0 | C50: =Escenarios!C68-Escenarios!C1057 -> -848.66507 | D50: =Escenarios!D68-Escenarios!D1057 -> 266.41404 | E50: =Escenarios!E68-Escenarios!E1057 -> 165.13079 | F50: =Escenarios!F68-Escenarios!F1057 -> 174.18445 | G50: =Escenarios!G68-Escenarios!G1057 -> 180.51826 | H50: =Escenarios!H68-Escenarios!H1057 -> 187.12223 | I50: =Escenarios!I68-Escenarios!I1057 -> 194.00794 | ... L50: =Escenarios!L68-Escenarios!L1057 -> 280.49636
A51: Primera compuerta, para comprar la etapa 1 (al cerrar la etapa 0): decide si la pérdida que se quiere atacar existe y es del tamaño supuesto.
A52: • Las pérdidas actuales están medidas con los registros históricos de la planta y un mes de medición: rendimiento por producto, variabilidad de grasa, merma, sobrepeso, horas extra y gasto de mantenimiento.
A53: • Con esas pérdidas medidas, el beneficio potencial recalculado deja la etapa 1 con VPN positivo en el caso conservador.
A54: • Prueba del sensor de coagulación en una tina con equipo de demostración del proveedor, antes de comprar los de las tres tinas.
A55: • El orden del hilado y el plan de mantenimiento ya están en marcha y muestran su ahorro.
A56: • El proyecto de innovación está postulado ante Minciencias y el banco aprobó el crédito con su garantía.
A57: Segunda compuerta, para aprobar la etapa 2 (diciembre de 2027): verifica que la automatización ya instalada logró la mejora, con al menos 4 meses de operación.
A58: • La etapa 1 cumple sus indicadores medidos contra la línea base de la etapa 0 (rendimiento, grasa, sobrepeso y merma).
A59: • Contrato de compra del suero firmado a $45/kg o más, con precio reajustado cada año por el IPC.
A60: • Plan de reasignación aprobado: los puestos de yogur o UHT que reciben a los 2 operarios, las competencias que piden, la formación y las fechas; así se confirma que esas 2 contrataciones se evitan.
A61: • Cotización formal de la hiladora dentro del presupuesto con sus imprevistos.
A62: Si alguna no se cumple, la empresa se queda en la etapa 1, que crea valor por sí sola, y no pierde lo ganado.
... A70: • Por evaluar: leasing financiero de fomento para los equipos de la etapa 2, que financia el 100 % y el IVA. Falta la tasa del leasing para compararlo con el crédito.

Sheet Empresa
A1: Efecto del proyecto en Lácteos Fúquene
A2: Estado de resultados y endeudamiento de la empresa con el proyecto. Sin el proyecto la empresa se mantiene igual a 2026, en pesos constantes (supuesto didáctico). $ M constantes de 2026.
A4: La empresa en 2026 (caso de estudio)
A5: Rubro | B5: Valor | C5: Fuente
A6: Ventas | B6: 30457 | C6: Estado de resultados y balance del caso.
A7: EBITDA | B7: 1806 | C7: Estado de resultados y balance del caso.
A8: Depreciación | B8: 600 | C8: Estado de resultados y balance del caso.
A9: Intereses | B9: 252 | C9: Estado de resultados y balance del caso.
A10: Utilidad neta | B10: 620 | C10: Estado de resultados y balance del caso.
A11: Deuda financiera | B11: 1400 | C11: Estado de resultados y balance del caso.
A12: Caja y bancos | B12: 1000 | C12: Estado de resultados y balance del caso.
A14: Con el proyecto (años 0 a 10)
A15: $ M | B15: Año 0 | C15: Año 1 | D15: Año 2 | E15: Año 3 | F15: Año 4 | G15: Año 5 | H15: Año 6 | I15: Año 7 | J15: Año 8 | K15: Año 9 | L15: Año 10
A16: Ventas sin el proyecto | B16: =$B$6 -> 30457 | C16: =$B$6 -> 30457 | D16: =$B$6 -> 30457 | E16: =$B$6 -> 30457 | F16: =$B$6 -> 30457 | G16: =$B$6 -> 30457 | H16: =$B$6 -> 30457 | I16: =$B$6 -> 30457 | ... L16: =$B$6 -> 30457
A17: Ventas adicionales del proyecto | B17: =Quesería!B135 -> 26.851692 | C17: =Quesería!C135 -> 80.555075 | D17: =Quesería!D135 -> 189.65122 | E17: =Quesería!E135 -> 217.06604 | F17: =Quesería!F135 -> 217.06604 | G17: =Quesería!G135 -> 217.06604 | H17: =Quesería!H135 -> 217.06604 | I17: =Quesería!I135 -> 217.06604 | ... L17: =Quesería!L135 -> 217.06604
A18: Ventas con el proyecto | B18: =B16+B17 -> 30483.852 | C18: =C16+C17 -> 30537.555 | D18: =D16+D17 -> 30646.651 | E18: =E16+E17 -> 30674.066 | F18: =F16+F17 -> 30674.066 | G18: =G16+G17 -> 30674.066 | H18: =H16+H17 -> 30674.066 | I18: =I16+I17 -> 30674.066 | ... L18: =L16+L17 -> 30674.066
A19: EBITDA sin el proyecto | B19: =$B$7 -> 1806 | C19: =$B$7 -> 1806 | D19: =$B$7 -> 1806 | E19: =$B$7 -> 1806 | F19: =$B$7 -> 1806 | G19: =$B$7 -> 1806 | H19: =$B$7 -> 1806 | I19: =$B$7 -> 1806 | ... L19: =$B$7 -> 1806
A20: EBITDA del proyecto | B20: =Quesería!B126-Quesería!B127-Quesería!B128 -> 45.637373 | C20: =Quesería!C126-Quesería!C127-Quesería!C128 -> 81.756475 | D20: =Quesería!D126-Quesería!D127-Quesería!D128 -> 291.97883 | E20: =Quesería!E126-Quesería!E127-Quesería!E128 -> 328.64375 | F20: =Quesería!F126-Quesería!F127-Quesería!F128 -> 329.13998 | G20: =Quesería!G126-Quesería!G127-Quesería!G128 -> 329.6387 | H20: =Quesería!H126-Quesería!H127-Quesería!H128 -> 330.13991 | I20: =Quesería!I126-Quesería!I127-Quesería!I128 -> 330.64362 | ... L20: =Quesería!L126-Quesería!L127-Quesería!L128 -> 332.16993
A21: EBITDA con el proyecto | B21: =B19+B20 -> 1851.6374 | C21: =C19+C20 -> 1887.7565 | D21: =D19+D20 -> 2097.9788 | E21: =E19+E20 -> 2134.6438 | F21: =F19+F20 -> 2135.14 | G21: =G19+G20 -> 2135.6387 | H21: =H19+H20 -> 2136.1399 | I21: =I19+I20 -> 2136.6436 | ... L21: =L19+L20 -> 2138.1699
A22: Margen EBITDA | B22: =B21/B18 -> 0.060741582 | C22: =C21/C18 -> 0.061817538 | D22: =D21/D18 -> 0.068457033 | E22: =E21/E18 -> 0.069591157 | F22: =F21/F18 -> 0.069607335 | G22: =G21/G18 -> 0.069623593 | H22: =H21/H18 -> 0.069639933 | I22: =I21/I18 -> 0.069656355 | ... L22: =L21/L18 -> 0.069706113
A23: Depreciación | B23: =$B$8+Quesería!B130 -> 699.36007 | C23: =$B$8+Quesería!C130 -> 657.10002 | D23: =$B$8+Quesería!D130 -> 716.3895 | E23: =$B$8+Quesería!E130 -> 711.91298 | F23: =$B$8+Quesería!F130 -> 707.60864 | G23: =$B$8+Quesería!G130 -> 703.46984 | H23: =$B$8+Quesería!H130 -> 692.67312 | I23: =$B$8+Quesería!I130 -> 695.89811 | ... L23: =$B$8+Quesería!L130 -> 685.25307
A24: Intereses, comisiones y GMF | B24: =$B$9+Quesería!B148+Quesería!B150+Quesería!B151+Quesería!B129 -> 258.90237 | C24: =$B$9+Quesería!C148+Quesería!C150+Quesería!C151+Quesería!C129 -> 314.01799 | D24: =$B$9+Quesería!D148+Quesería!D150+Quesería!D151+Quesería!D129 -> 370.0053 | E24: =$B$9+Quesería!E148+Quesería!E150+Quesería!E151+Quesería!E129 -> 356.7516 | F24: =$B$9+Quesería!F148+Quesería!F150+Quesería!F151+Quesería!F129 -> 334.64811 | G24: =$B$9+Quesería!G148+Quesería!G150+Quesería!G151+Quesería!G129 -> 314.2174 | H24: =$B$9+Quesería!H148+Quesería!H150+Quesería!H151+Quesería!H129 -> 295.16049 | I24: =$B$9+Quesería!I148+Quesería!I150+Quesería!I151+Quesería!I129 -> 277.27217 | ... L24: =$B$9+Quesería!L148+Quesería!L150+Quesería!L151+Quesería!L129 -> 252.35523
A25: Utilidad antes de impuestos | B25: =B21-B23-B24 -> 893.37494 | C25: =C21-C23-C24 -> 916.63847 | D25: =D21-D23-D24 -> 1011.584 | E25: =E21-E23-E24 -> 1065.9792 | F25: =F21-F23-F24 -> 1092.8832 | G25: =G21-G23-G24 -> 1117.9515 | H25: =H21-H23-H24 -> 1148.3063 | I25: =I21-I23-I24 -> 1163.4733 | ... L25: =L21-L23-L24 -> 1200.5616
A26: Impuesto antes de descuentos | B26: =Quesería!$B$10*(B25+0.5*(Quesería!B129+Quesería!B151)) -> 313.18914 | C26: =Quesería!$B$10*(C25+0.5*(Quesería!C129+Quesería!C151)) -> 321.4407 | D26: =Quesería!$B$10*(D25+0.5*(Quesería!D129+Quesería!D151)) -> 354.24473 | E26: =Quesería!$B$10*(E25+0.5*(Quesería!E129+Quesería!E151)) -> 373.32031 | F26: =Quesería!$B$10*(F25+0.5*(Quesería!F129+Quesería!F151)) -> 382.71776 | G26: =Quesería!$B$10*(G25+0.5*(Quesería!G129+Quesería!G151)) -> 391.49609 | H26: =Quesería!$B$10*(H25+0.5*(Quesería!H129+Quesería!H151)) -> 402.11087 | I26: =Quesería!$B$10*(I25+0.5*(Quesería!I129+Quesería!I151)) -> 407.3744 | ... L26: =Quesería!$B$10*(L25+0.5*(Quesería!L129+Quesería!L151)) -> 420.25874
A27: Descuentos de renta del proyecto (art. 255 y 258-1) | B27: =Quesería!B131+Quesería!B133 -> 0 | C27: =Quesería!C131+Quesería!C133 -> 114.61702 | D27: =Quesería!D131+Quesería!D133 -> 117.32183 | E27: =Quesería!E131+Quesería!E133 -> 0 | F27: =Quesería!F131+Quesería!F133 -> 0 | G27: =Quesería!G131+Quesería!G133 -> 0 | H27: =Quesería!H131+Quesería!H133 -> 4.8717949 | I27: =Quesería!I131+Quesería!I133 -> 6.4498703 | ... L27: =Quesería!L131+Quesería!L133 -> 0
A28: Crédito fiscal por innovación | B28: =Quesería!B132 -> 0 | C28: =Quesería!C132 -> 166.87988 | D28: =Quesería!D132 -> 0 | E28: =Quesería!E132 -> 0 | F28: =Quesería!F132 -> 0 | G28: =Quesería!G132 -> 0 | H28: =Quesería!H132 -> 0 | I28: =Quesería!I132 -> 0 | ... L28: =Quesería!L132 -> 0
A29: Impuesto de renta | B29: =B26-B27-B28 -> 313.18914 | C29: =C26-C27-C28 -> 39.943798 | D29: =D26-D27-D28 -> 236.92289 | E29: =E26-E27-E28 -> 373.32031 | F29: =F26-F27-F28 -> 382.71776 | G29: =G26-G27-G28 -> 391.49609 | H29: =H26-H27-H28 -> 397.23907 | I29: =I26-I27-I28 -> 400.92453 | ... L29: =L26-L27-L28 -> 420.25874
A30: Utilidad neta con el proyecto | B30: =B25-B29 -> 580.1858 | C30: =C25-C29 -> 876.69467 | D30: =D25-D29 -> 774.66113 | E30: =E25-E29 -> 692.65886 | F30: =F25-F29 -> 710.16548 | G30: =G25-G29 -> 726.45537 | H30: =H25-H29 -> 751.06722 | I30: =I25-I29 -> 762.54881 | ... L30: =L25-L29 -> 780.3029
A31: Cambio de la utilidad neta | B31: =B30-$B$10 -> -39.814204 | C31: =C30-$B$10 -> 256.69467 | D31: =D30-$B$10 -> 154.66113 | E31: =E30-$B$10 -> 72.658861 | F31: =F30-$B$10 -> 90.165476 | G31: =G30-$B$10 -> 106.45537 | H31: =H30-$B$10 -> 131.06722 | I31: =I30-$B$10 -> 142.54881 | ... L31: =L30-$B$10 -> 160.3029
A32: Deuda financiera actual | B32: =$B$11 -> 1400 | C32: =$B$11 -> 1400 | D32: =$B$11 -> 1400 | E32: =$B$11 -> 1400 | F32: =$B$11 -> 1400 | G32: =$B$11 -> 1400 | H32: =$B$11 -> 1400 | I32: =$B$11 -> 1400 | ... L32: =$B$11 -> 1400
A33: Saldo del crédito del proyecto | B33: =Quesería!B146*Quesería!B120 -> 435.57054 | C33: =Quesería!C146*Quesería!C120 -> 866.51814 | D33: =Quesería!D146*Quesería!D120 -> 763.04303 | E33: =Quesería!E146*Quesería!E120 -> 600.80997 | F33: =Quesería!F146*Quesería!F120 -> 449.92761 | G33: =Quesería!G146*Quesería!G120 -> 309.76282 | H33: =Quesería!H146*Quesería!H120 -> 179.71436 | I33: =Quesería!I146*Quesería!I120 -> 59.211401 | ... L33: =Quesería!L146*Quesería!L120 -> 0
A34: Deuda total / EBITDA (veces) | B34: =(B32+B33)/B21 -> 0.9913229 | C34: =(C32+C33)/C21 -> 1.2006412 | D34: =(D32+D33)/D21 -> 1.0310128 | E34: =(E32+E33)/E21 -> 0.93730393 | F34: =(F32+F33)/F21 -> 0.86641983 | G34: =(G32+G33)/G21 -> 0.80058618 | H34: =(H32+H33)/H21 -> 0.73951821 | I34: =(I32+I33)/I21 -> 0.68294562 | ... L34: =(L32+L33)/L21 -> 0.65476555
A35: EBITDA / gastos financieros (veces) | B35: =B21/B24 -> 7.1518751 | C35: =C21/C24 -> 6.011619 | D35: =D21/D24 -> 5.6701318 | E35: =E21/E24 -> 5.9835577 | F35: =F21/F24 -> 6.3802541 | G35: =G21/G24 -> 6.7966914 | H35: =H21/H24 -> 7.2372149 | I35: =I21/I24 -> 7.7059433 | ... L35: =L21/L24 -> 8.4728577
A36: Salida de caja de los socios en el año | B36: =MAX(0,-Quesería!B153) -> 229.08371 | C36: =MAX(0,-Quesería!C153) -> 5.4006931 | D36: =MAX(0,-Quesería!D153) -> 0 | E36: =MAX(0,-Quesería!E153) -> 0 | F36: =MAX(0,-Quesería!F153) -> 0 | G36: =MAX(0,-Quesería!G153) -> 0 | H36: =MAX(0,-Quesería!H153) -> 0 | I36: =MAX(0,-Quesería!I153) -> 0 | ... L36: =MAX(0,-Quesería!L153) -> 0
A37: Salida de caja / caja y bancos de 2026 | B37: =B36/$B$12 -> 0.22908371 | C37: =C36/$B$12 -> 0.0054006931 | D37: =D36/$B$12 -> 0 | E37: =E36/$B$12 -> 0 | F37: =F36/$B$12 -> 0 | G37: =G36/$B$12 -> 0 | H37: =H36/$B$12 -> 0 | I37: =I36/$B$12 -> 0 | ... L37: =L36/$B$12 -> 0
A38: Deuda actual: se supone que se refinancia y se mantiene. El crédito del proyecto se muestra en pesos constantes. La utilidad neta sin el proyecto es la de 2026.
A40: Lectura
A41: Deuda total / EBITDA más alta (los bancos suelen pedir 3 veces o menos) | B41: =MAX(B34:L34) -> 1.2006412
A42: Deuda / EBITDA de 2026, sin el proyecto | B42: =$B$11/$B$7 -> 0.7751938
A43: EBITDA / gastos financieros más bajo | B43: =MIN(B35:L35) -> 5.6701318
A44: Mayor salida de caja de los socios frente a la caja de 2026 | B44: =MAX(B37:L37) -> 0.22908371
A45: Cambio de la utilidad neta en el año 2 | B45: =D31 -> 154.66113
A46: Cambio de la utilidad neta en el año 5 | B46: =G31 -> 106.45537

Sheet IntegraMotion
A1: IntegraMotion S.A.S.: cuánto cobra por la quesería y cómo se reparte
A2: Cifras de la empresa integradora, no del cliente. Millones de pesos de 2026. Texto azul: datos de entrada; negro: fórmulas.
A4: Supuestos
A5: Supuesto | B5: Valor | C5: Unidad | D5: Fuente o criterio
A6: Salario mínimo mensual de 2026 | B6: 1.750905 | C6: $ M/mes | D6: Decreto 1469 de 2025.
A7: Horas de referencia al mes | B7: 182 | C7: h/mes | D7: Convierte un pago mensual en tarifa por hora (42 h × 52 semanas ÷ 12). Al director, con contrato laboral, le aplica la jornada de la Ley 2101 de 2021; a los socios por prestación de servicios no: es solo la unidad para estimar.
A8: Honorario de referencia de un socio, tiempo completo | B8: 3.6 | C8: SMMLV/mes | D8: SCI, honorarios de referencia: ingeniero con 0 a 2 años de experiencia, 3 a 4,2 SMMLV (punto medio).
A9: Salario del director (representante legal), tiempo completo | B9: 4 | C9: SMMLV/mes | D9: Contrato laboral; un poco por encima del tope de la misma categoría por la responsabilidad legal.
A10: Factor prestacional del salario | B10: 1.38 | C10: x | D10: Prima, cesantías e intereses, vacaciones, pensión, ARL y caja (exonerado de salud, SENA e ICBF por debajo de 10 SMMLV).
A11: Administración (A del AIU) | B11: 0.3 | C11: % costo directo | D11: Cubre los gastos de funcionamiento de IntegraMotion durante los 6 meses del proyecto, aunque no tenga otros clientes (detalle al final de esta hoja).
A12: Imprevistos (I del AIU) | B12: 0.05 | C12: % costo directo | D12: Reserva del contrato.
A13: Utilidad (U del AIU) | B13: 0.1 | C13: % costo directo | D13: Margen de la empresa; de ahí salen los dividendos.
A14: IVA sobre servicios de ingeniería | B14: 0.19 | C14: % | D14: Lo cobra IntegraMotion y lo paga a la DIAN; no es ingreso.
A15: Impuesto de renta de IntegraMotion | B15: 0.35 | C15: % | D15: Régimen ordinario de personas jurídicas.
A16: Aportes a seguridad social de un independiente | B16: 0.116088 | C16: % del honorario | D16: Sobre el 40 % del honorario: salud 12,5 %, pensión 16 % y ARL 0,522 %.
A17: Costo de un viaje Bogotá–Ubaté | B17: 0.35 | C17: $ M/viaje | D17: Transporte y viáticos del día.
A18: Socios | B18: 6 | C18: personas | D18: Los seis integrantes del Equipo 5, con acciones iguales. El director también es socio: recibe salario por su contrato laboral y dividendo como los demás. Los otros cinco cobran honorarios por entregables.
A20: Costo de cada hora para IntegraMotion
A21: Rol | B21: Vínculo | C21: Base ($ M/mes) | D21: Costo ($ M/mes) | E21: Costo por hora ($)
A22: Director de proyecto | B22: Contrato laboral | C22: =$B$9*$B$6 -> 7.00362 | D22: =C22*$B$10 -> 9.6649956 | E22: =D22/$B$7*1000000 -> 53104.371
A23: Ingeniero de procesos y producción | B23: Honorarios | C23: =$B$8*$B$6 -> 6.303258 | D23: =C23 -> 6.303258 | E23: =D23/$B$7*1000000 -> 34633.286
A24: Ingeniero de automatización y control (2) | B24: Honorarios | C24: =$B$8*$B$6 -> 6.303258 | D24: =C24 -> 6.303258 | E24: =D24/$B$7*1000000 -> 34633.286
A25: Ingeniero de robótica y simulación | B25: Honorarios | C25: =$B$8*$B$6 -> 6.303258 | D25: =C25 -> 6.303258 | E25: =D25/$B$7*1000000 -> 34633.286
A26: Ingeniero de gestión y finanzas | B26: Honorarios | C26: =$B$8*$B$6 -> 6.303258 | D26: =C26 -> 6.303258 | E26: =D26/$B$7*1000000 -> 34633.286
A27: Los cinco socios con honorarios tienen contrato de prestación de servicios: sin horario ni subordinación, se les paga por entregables del EDT del proyecto (valor = horas estimadas × tarifa) y pagan su propia seguridad social como independientes. El director, como empleado, la recibe en el factor prestacional.
A29: Contrato 1: ingeniería e integración de las etapas 0 y 1 (4 meses, año 0)
A30: Rol | B30: Personas | C30: Dedicación | D30: Meses | E30: Horas | F30: Costo ($ M)
A31: Director de proyecto | B31: 1 | C31: 0.45 | D31: 4 | E31: =B31*C31*D31*$B$7 -> 327.6 | F31: =E31*$E$22/1000000 -> 17.396992
A32: Ingeniero de procesos y producción | B32: 1 | C32: 0.45 | D32: 4 | E32: =B32*C32*D32*$B$7 -> 327.6 | F32: =E32*$E$23/1000000 -> 11.345864
A33: Ingeniero de automatización y control (2) | B33: 2 | C33: 0.45 | D33: 4 | E33: =B33*C33*D33*$B$7 -> 655.2 | F33: =E33*$E$24/1000000 -> 22.691729
A34: Ingeniero de robótica y simulación | B34: 1 | C34: 0.45 | D34: 4 | E34: =B34*C34*D34*$B$7 -> 327.6 | F34: =E34*$E$25/1000000 -> 11.345864
A35: Ingeniero de gestión y finanzas | B35: 1 | C35: 0.45 | D35: 4 | E35: =B35*C35*D35*$B$7 -> 327.6 | F35: =E35*$E$26/1000000 -> 11.345864
A36: Horas del equipo | F36: =SUM(E31:E35) -> 1965.6
A37: Personal ($ M) | F37: =SUM(F31:F35) -> 74.126314
A38: Viajes a planta | F38: =16*$B$17 -> 5.6
A39: Licencias de desarrollo, equipos e instrumentos de medición | F39: 10
A40: Costo directo | F40: =$F$37+$F$38+$F$39 -> 89.726314
A41: Administración | F41: =$B$11*$F$40 -> 26.917894
A42: Imprevistos | F42: =$B$12*$F$40 -> 4.4863157
A43: Utilidad | F43: =$B$13*$F$40 -> 8.9726314
A44: Precio sin IVA | F44: =$F$40+$F$41+$F$42+$F$43 -> 130.10316
A45: IVA | F45: =$B$14*$F$44 -> 24.7196
A46: Precio con IVA | F46: =$F$44+$F$45 -> 154.82275
A47: 16 viajes a planta.
A49: Contrato 2: integración de la etapa 2 (2 meses, año 1)
A50: Rol | B50: Personas | C50: Dedicación | D50: Meses | E50: Horas | F50: Costo ($ M)
A51: Director de proyecto | B51: 1 | C51: 0.25 | D51: 2 | E51: =B51*C51*D51*$B$7 -> 91 | F51: =E51*$E$22/1000000 -> 4.8324978
A52: Ingeniero de procesos y producción | B52: 1 | C52: 0.5 | D52: 2 | E52: =B52*C52*D52*$B$7 -> 182 | F52: =E52*$E$23/1000000 -> 6.303258
A53: Ingeniero de automatización y control (2) | B53: 2 | C53: 0.5 | D53: 2 | E53: =B53*C53*D53*$B$7 -> 364 | F53: =E53*$E$24/1000000 -> 12.606516
A54: Ingeniero de robótica y simulación | B54: 1 | C54: 0.25 | D54: 2 | E54: =B54*C54*D54*$B$7 -> 91 | F54: =E54*$E$25/1000000 -> 3.151629
A55: Ingeniero de gestión y finanzas | B55: 1 | C55: 0.1 | D55: 2 | E55: =B55*C55*D55*$B$7 -> 36.4 | F55: =E55*$E$26/1000000 -> 1.2606516
A56: Horas del equipo | F56: =SUM(E51:E55) -> 764.4
A57: Personal ($ M) | F57: =SUM(F51:F55) -> 28.154552
A58: Viajes a planta | F58: =8*$B$17 -> 2.8
A59: Licencias de desarrollo, equipos e instrumentos de medición | F59: 2
A60: Costo directo | F60: =$F$57+$F$58+$F$59 -> 32.954552
A61: Administración | F61: =$B$11*$F$60 -> 9.8863657
A62: Imprevistos | F62: =$B$12*$F$60 -> 1.6477276
A63: Utilidad | F63: =$B$13*$F$60 -> 3.2954552
A64: Precio sin IVA | F64: =$F$60+$F$61+$F$62+$F$63 -> 47.784101
A65: IVA | F65: =$B$14*$F$64 -> 9.0789792
A66: Precio con IVA | F66: =$F$64+$F$65 -> 56.86308
A67: 8 viajes a planta.
A69: Estado de resultados de IntegraMotion por el proyecto ($ M)
A70: Rubro | B70: Contrato 1 | C70: Contrato 2 | D70: Total
A71: Ingresos (precio sin IVA) | B71: =$F$44 -> 130.10316 | C71: =$F$64 -> 47.784101 | D71: =B71+C71 -> 177.88726
A72: − Honorarios de los socios | B72: =-($F$32+$F$33+$F$34+$F$35) -> -56.729322 | C72: =-($F$52+$F$53+$F$54+$F$55) -> -23.322055 | D72: =B72+C72 -> -80.051377
A73: − Salario del director, costo empresa | B73: =-$F$31 -> -17.396992 | C73: =-$F$51 -> -4.8324978 | D73: =B73+C73 -> -22.22949
A74: − Viajes | B74: =-$F$38 -> -5.6 | C74: =-$F$58 -> -2.8 | D74: =B74+C74 -> -8.4
A75: − Licencias, equipos e instrumentos | B75: =-$F$39 -> -10 | C75: =-$F$59 -> -2 | D75: =B75+C75 -> -12
A76: − Administración | B76: =-$F$41 -> -26.917894 | C76: =-$F$61 -> -9.8863657 | D76: =B76+C76 -> -36.80426
A77: − Imprevistos (se gastan) | B77: =-$F$42 -> -4.4863157 | C77: =-$F$62 -> -1.6477276 | D77: =B77+C77 -> -6.1340433
A78: Utilidad antes de impuestos | B78: =SUM(B71:B77) -> 8.9726314 | C78: =SUM(C71:C77) -> 3.2954552 | D78: =B78+C78 -> 12.268087
A79: − Impuesto de renta | B79: =-$B$15*B78 -> -3.140421 | C79: =-$B$15*C78 -> -1.1534093 | D79: =B79+C79 -> -4.2938303
A80: Utilidad neta = dividendos | B80: =B78+B79 -> 5.8322104 | C80: =C78+C79 -> 2.1420459 | D80: =B80+C80 -> 7.9742563
A81: Dividendo por socio | B81: =B80/$B$18 -> 0.97203507 | C81: =C80/$B$18 -> 0.35700765 | D81: =B81+C81 -> 1.3290427
A82: El IVA no es ingreso: se cobra al cliente y se paga a la DIAN. El cliente retiene en la fuente sobre los pagos; es un anticipo del impuesto de renta de IntegraMotion.
A84: Lo que recibe cada socio por el proyecto ($ M)
A85: Socio | B85: Horas | C85: Sueldo u honorarios | D85: Aportes propios | E85: Dividendo | F85: Total neto
A86: Director de proyecto | B86: =(E31+E51)/1 -> 418.6 | C86: =B86*$B$9*$B$6/$B$7 -> 16.108326 | D86: 0 | E86: =$D$81 -> 1.3290427 | F86: =C86+D86+E86 -> 17.437369
A87: Ingeniero de procesos y producción | B87: =(E32+E52)/1 -> 509.6 | C87: =(F32+F52)/1 -> 17.649122 | D87: =-$B$16*C87 -> -2.0488513 | E87: =$D$81 -> 1.3290427 | F87: =C87+D87+E87 -> 16.929314
A88: Ingeniero de automatización y control (2) — cada uno | B88: =(E33+E53)/2 -> 509.6 | C88: =(F33+F53)/2 -> 17.649122 | D88: =-$B$16*C88 -> -2.0488513 | E88: =$D$81 -> 1.3290427 | F88: =C88+D88+E88 -> 16.929314
A89: Ingeniero de robótica y simulación | B89: =(E34+E54)/1 -> 418.6 | C89: =(F34+F54)/1 -> 14.497493 | D89: =-$B$16*C89 -> -1.682985 | E89: =$D$81 -> 1.3290427 | F89: =C89+D89+E89 -> 14.143551
A90: Ingeniero de gestión y finanzas | B90: =(E35+E55)/1 -> 364 | C90: =(F35+F55)/1 -> 12.606516 | D90: =-$B$16*C90 -> -1.4634652 | E90: =$D$81 -> 1.3290427 | F90: =C90+D90+E90 -> 12.472093
A91: Director: sueldo con prestaciones, que la empresa paga aparte. Socios con honorarios: pagan su seguridad social sobre el 40 % del honorario. Dividendos por debajo de 1.090 UVT al año: sin retención en la fuente (art. 242 ET).
A93: Pagos de Lácteos Fúquene a IntegraMotion
A94: Hito | B94: % del contrato | C94: Sin IVA ($ M) | D94: Con IVA ($ M) | E94: Cuándo
A95: Contrato 1: anticipo a la firma | B95: 0.3 | C95: =B95*$F$44 -> 39.030947 | D95: =B95*$F$46 -> 46.446826 | E95: Año 0, mes 1
A96: Contrato 1: aprobación de la ingeniería de la etapa 1 | B96: 0.4 | C96: =B96*$F$44 -> 52.041262 | D96: =B96*$F$46 -> 61.929102 | E96: Año 0, mes 3
A97: Contrato 1: compuerta de la etapa 1 superada | B97: 0.3 | C97: =B97*$F$44 -> 39.030947 | D97: =B97*$F$46 -> 46.446826 | E97: Año 0, fin
A98: Contrato 2: inicio de la integración | B98: 0.5 | C98: =B98*$F$64 -> 23.89205 | D98: =B98*$F$66 -> 28.43154 | E98: Año 1
A99: Contrato 2: aceptación en sitio de la hiladora | B99: 0.5 | C99: =B99*$F$64 -> 23.89205 | D99: =B99*$F$66 -> 28.43154 | E99: Año 1
A101: Cómo se fijó el precio
A102: • Horas del equipo por tarifa: honorarios de referencia de la Sociedad Colombiana de Ingenieros para ingenieros con 0 a 2 años de experiencia, más viajes y licencias, más AIU.
A103: ="• Comprobación: la hora facturada, en promedio $"&FIXED(B156,0)&" sin IVA, es "&FIXED(B156/E23,1)&" veces el honorario por hora de un socio. Las firmas de consultoría cobran de 2,4 a 2,8 veces el salario, que incluye prestaciones; los socios por prestación de servicios no las reciben y la empresa trabaja con oficina virtual." -> • Comprobación: la hora facturada, en promedio $65,160 sin IVA, es 1.9 veces el honorario por hora de un socio. Las firmas de consultoría cobran de 2,4 a 2,8 veces el salario, que incluye prestaciones; los socios por prestación de servicios no las reciben y la empresa trabaja con oficina virtual.
A104: • Los programas del PLC, las pantallas del SCADA y la documentación se entregan al cliente; las licencias de producción quedan a su nombre.
A105: • Los precios están en pesos de 2026. Cada contrato se reajusta con el incremento del salario mínimo del año en que se ejecuta (2027 y 2028): así IntegraMotion no pierde valor si el mínimo sube más que la inflación.
A107: Gastos de funcionamiento de IntegraMotion durante el proyecto
A108: Lo que cuesta que la empresa funcione mientras dura el proyecto, sin contar con otros clientes. Precios de 2026; las cifras en azul son supuestos o referencias publicadas.
A109: Gasto | B109: $ M/mes | C109: Fuente o criterio
...

Sheet APU
A1: Análisis de precios unitarios (APU) de la ingeniería de IntegraMotion
A2: Cada hora de ingeniería se costea por componentes (mano de obra, licencias y herramientas, transporte). El presupuesto multiplica horas por precio unitario y suma el AIU. Debe dar lo mismo que la hoja IntegraMotion.
A4: Contrato 1: ingeniería e integración de las etapas 0 y 1
A5: APU por hora de ingeniería (pesos por hora)
A6: Rol | B6: Unidad | C6: Mano de obra | D6: Licencias y herramientas | E6: Transporte a planta | F6: Costo directo unitario | G6: Cómo se calcula
A7: Director de proyecto | B7: hora | C7: =IntegraMotion!$E$22 -> 53104.371 | D7: =IntegraMotion!$F$39*1000000/IntegraMotion!$F$36 -> 5087.5051 | E7: =IntegraMotion!$F$38*1000000/IntegraMotion!$F$36 -> 2849.0028 | F7: =C7+D7+E7 -> 61040.879 | G7: Mano de obra: salario o honorario mensual ÷ 182 horas de referencia (director con factor prestacional 1,38). Las horas son la unidad para estimar; a los socios se les paga por entregables. Licencias y transporte: total del contrato ÷ horas del equipo.
A8: Ingeniero de procesos y producción | B8: hora | C8: =IntegraMotion!$E$23 -> 34633.286 | D8: =IntegraMotion!$F$39*1000000/IntegraMotion!$F$36 -> 5087.5051 | E8: =IntegraMotion!$F$38*1000000/IntegraMotion!$F$36 -> 2849.0028 | F8: =C8+D8+E8 -> 42569.794
A9: Ingeniero de automatización y control (2) | B9: hora | C9: =IntegraMotion!$E$24 -> 34633.286 | D9: =IntegraMotion!$F$39*1000000/IntegraMotion!$F$36 -> 5087.5051 | E9: =IntegraMotion!$F$38*1000000/IntegraMotion!$F$36 -> 2849.0028 | F9: =C9+D9+E9 -> 42569.794
A10: Ingeniero de robótica y simulación | B10: hora | C10: =IntegraMotion!$E$25 -> 34633.286 | D10: =IntegraMotion!$F$39*1000000/IntegraMotion!$F$36 -> 5087.5051 | E10: =IntegraMotion!$F$38*1000000/IntegraMotion!$F$36 -> 2849.0028 | F10: =C10+D10+E10 -> 42569.794
A11: Ingeniero de gestión y finanzas | B11: hora | C11: =IntegraMotion!$E$26 -> 34633.286 | D11: =IntegraMotion!$F$39*1000000/IntegraMotion!$F$36 -> 5087.5051 | E11: =IntegraMotion!$F$38*1000000/IntegraMotion!$F$36 -> 2849.0028 | F11: =C11+D11+E11 -> 42569.794
A13: Presupuesto del contrato ($ M)
A14: Ítem | B14: Unidad | C14: Cantidad | D14: Valor unitario ($) | E14: Valor total ($ M)
A15: Director de proyecto | B15: h | C15: =IntegraMotion!$E$31 -> 327.6 | D15: =F7 -> 61040.879 | E15: =C15*D15/1000000 -> 19.996992
A16: Ingeniero de procesos y producción | B16: h | C16: =IntegraMotion!$E$32 -> 327.6 | D16: =F8 -> 42569.794 | E16: =C16*D16/1000000 -> 13.945864
A17: Ingeniero de automatización y control (2) | B17: h | C17: =IntegraMotion!$E$33 -> 655.2 | D17: =F9 -> 42569.794 | E17: =C17*D17/1000000 -> 27.891729
A18: Ingeniero de robótica y simulación | B18: h | C18: =IntegraMotion!$E$34 -> 327.6 | D18: =F10 -> 42569.794 | E18: =C18*D18/1000000 -> 13.945864
A19: Ingeniero de gestión y finanzas | B19: h | C19: =IntegraMotion!$E$35 -> 327.6 | D19: =F11 -> 42569.794 | E19: =C19*D19/1000000 -> 13.945864
A20: Costo directo | E20: =SUM(E15:E19) -> 89.726314
A21: Administración | E21: =E20*IntegraMotion!$B$11 -> 26.917894
A22: Imprevistos | E22: =E20*IntegraMotion!$B$12 -> 4.4863157
A23: Utilidad | E23: =E20*IntegraMotion!$B$13 -> 8.9726314
A24: Valor sin IVA | E24: =E20+E21+E22+E23 -> 130.10316
A25: IVA | E25: =E24*IntegraMotion!$B$14 -> 24.7196
A26: Valor con IVA | E26: =E24+E25 -> 154.82275
A27: Comprobación: diferencia con la hoja IntegraMotion ($ M) | E27: =E24-IntegraMotion!$F$44 -> 0
A29: Contrato 2: integración de la etapa 2
A30: APU por hora de ingeniería (pesos por hora)
A31: Rol | B31: Unidad | C31: Mano de obra | D31: Licencias y herramientas | E31: Transporte a planta | F31: Costo directo unitario | G31: Cómo se calcula
A32: Director de proyecto | B32: hora | C32: =IntegraMotion!$E$22 -> 53104.371 | D32: =IntegraMotion!$F$59*1000000/IntegraMotion!$F$56 -> 2616.4312 | E32: =IntegraMotion!$F$58*1000000/IntegraMotion!$F$56 -> 3663.0037 | F32: =C32+D32+E32 -> 59383.806 | G32: Mano de obra: salario o honorario mensual ÷ 182 horas de referencia (director con factor prestacional 1,38). Las horas son la unidad para estimar; a los socios se les paga por entregables. Licencias y transporte: total del contrato ÷ horas del equipo.
A33: Ingeniero de procesos y producción | B33: hora | C33: =IntegraMotion!$E$23 -> 34633.286 | D33: =IntegraMotion!$F$59*1000000/IntegraMotion!$F$56 -> 2616.4312 | E33: =IntegraMotion!$F$58*1000000/IntegraMotion!$F$56 -> 3663.0037 | F33: =C33+D33+E33 -> 40912.721
A34: Ingeniero de automatización y control (2) | B34: hora | C34: =IntegraMotion!$E$24 -> 34633.286 | D34: =IntegraMotion!$F$59*1000000/IntegraMotion!$F$56 -> 2616.4312 | E34: =IntegraMotion!$F$58*1000000/IntegraMotion!$F$56 -> 3663.0037 | F34: =C34+D34+E34 -> 40912.721
A35: Ingeniero de robótica y simulación | B35: hora | C35: =IntegraMotion!$E$25 -> 34633.286 | D35: =IntegraMotion!$F$59*1000000/IntegraMotion!$F$56 -> 2616.4312 | E35: =IntegraMotion!$F$58*1000000/IntegraMotion!$F$56 -> 3663.0037 | F35: =C35+D35+E35 -> 40912.721
A36: Ingeniero de gestión y finanzas | B36: hora | C36: =IntegraMotion!$E$26 -> 34633.286 | D36: =IntegraMotion!$F$59*1000000/IntegraMotion!$F$56 -> 2616.4312 | E36: =IntegraMotion!$F$58*1000000/IntegraMotion!$F$56 -> 3663.0037 | F36: =C36+D36+E36 -> 40912.721
A38: Presupuesto del contrato ($ M)
A39: Ítem | B39: Unidad | C39: Cantidad | D39: Valor unitario ($) | E39: Valor total ($ M)
A40: Director de proyecto | B40: h | C40: =IntegraMotion!$E$51 -> 91 | D40: =F32 -> 59383.806 | E40: =C40*D40/1000000 -> 5.4039264
A41: Ingeniero de procesos y producción | B41: h | C41: =IntegraMotion!$E$52 -> 182 | D41: =F33 -> 40912.721 | E41: =C41*D41/1000000 -> 7.4461151
A42: Ingeniero de automatización y control (2) | B42: h | C42: =IntegraMotion!$E$53 -> 364 | D42: =F34 -> 40912.721 | E42: =C42*D42/1000000 -> 14.89223
A43: Ingeniero de robótica y simulación | B43: h | C43: =IntegraMotion!$E$54 -> 91 | D43: =F35 -> 40912.721 | E43: =C43*D43/1000000 -> 3.7230576
A44: Ingeniero de gestión y finanzas | B44: h | C44: =IntegraMotion!$E$55 -> 36.4 | D44: =F36 -> 40912.721 | E44: =C44*D44/1000000 -> 1.489223
A45: Costo directo | E45: =SUM(E40:E44) -> 32.954552
A46: Administración | E46: =E45*IntegraMotion!$B$11 -> 9.8863657
A47: Imprevistos | E47: =E45*IntegraMotion!$B$12 -> 1.6477276
A48: Utilidad | E48: =E45*IntegraMotion!$B$13 -> 3.2954552
A49: Valor sin IVA | E49: =E45+E46+E47+E48 -> 47.784101
A50: IVA | E50: =E49*IntegraMotion!$B$14 -> 9.0789792
A51: Valor con IVA | E51: =E49+E50 -> 56.86308
A52: Comprobación: diferencia con la hoja IntegraMotion ($ M) | E52: =E49-IntegraMotion!$F$64 -> 0
A54: Los socios con honorarios pagan su propia seguridad social; por eso su mano de obra es el honorario por hora. El AIU se aplica sobre el costo directo, como en el resto del modelo.

Sheet Chequeos
A1: Chequeos del modelo
A2: Cada chequeo calcula una diferencia que debe ser cero. Si alguno dice Revisar, hay un error de fórmula o de enlace.
A4: Chequeos
A5: Chequeo | B5: Diferencia | C5: Estado | D5: Qué compara
A6: Empresa: descuentos de renta que superan el impuesto de algún año (capacidad tributaria) | B6: =SUMPRODUCT((Empresa!B27:L27+Empresa!B28:L28>Empresa!B26:L26)*1) -> 0 | C6: =IF(ABS(B6)<0.001,"OK","Revisar") -> OK | D6: La empresa paga suficiente renta cada año para usar los descuentos y el crédito fiscal.
A7: Inversión: suma de los componentes − (año 0 + año 1) | B7: =SUM(Quesería!F62:F77)-Quesería!$F$85 -> 0 | C7: =IF(ABS(B7)<0.001,"OK","Revisar") -> OK | D7: Tabla de inversión de la hoja Quesería.
A8: Beneficios: suma de la tabla − (etapas 0 y 1 + etapa 2) | B8: =SUM(Quesería!E92:E102)-Quesería!$E$111 -> 0 | C8: =IF(ABS(B8)<0.001,"OK","Revisar") -> OK | D8: Tabla de beneficios de la hoja Quesería.
A9: Beneficios: hoja Quesería − hoja Beneficios y costos (valor planta) | B9: =SUM(Quesería!C92:C102)-SUM('Beneficios y costos'!C73:C83) -> 0 | C9: =IF(ABS(B9)<0.001,"OK","Revisar") -> OK | D9: Que cada beneficio venga de su cálculo.
